Workbook

Sheet vendor_01_2023
A1: ASIN | B1: Numero del modello | C1: Codice marketplace | D1: Ricavi ordini | E1: Unità ordinate | F1: Ricavi spedizioni | G1: COGS spedizioni | H1: Unità spedite | I1: Resi cliente
A2: B07ZJQTGG8 | B2: 50.245 | C2: IT | D2: 36493.17 | E2: 2989 | F2: 36359.7 | G2: 20059.05 | H2: 2978 | I2: 27
A3: B01I497WWM | B3: 90.920R | C3: IT | D3: 34319.58 | E3: 2922 | F3: 33633.59 | G3: 25554.71 | H3: 2873 | I3: 100
A4: B096MX229M | B4: P102ROB050 | C4: DE | D4: 28799.28 | E4: 2322 | F4: 28859.41 | G4: 18118.2 | H4: 2326 | I4: 78
A5: B08GY7286R | B5: P203TFO001 | C5: IT | D5: 24665.9 | E5: 1095 | F5: 24321.95 | G5: 10523.55 | H5: 1073 | I5: 77
A6: B017IUJA50 | B6: 90.920G | C6: IT | D6: 19352.55 | E6: 1487 | F6: 19373.27 | G6: 13675.4 | H6: 1493 | I6: 72
A7: B08485QRVZ | B7: BC.261 | C7: IT | D7: 18144.49 | E7: 889 | F7: 17981.21 | G7: 14031 | H7: 881 | I7: 27
A8: B095PQJGKX | B8: C107UTT002 | C8: ES | D8: 17910.24 | E8: 2190 | F8: 18294.7 | G8: 11297.2 | H8: 2237 | I8: 61
A9: B01KMJ9OXW | B9: 90.590Y | C9: IT | D9: 17144.47 | E9: 597 | F9: 17773.89 | G9: 12407.85 | H9: 619 | I9: 34
A10: B01KMJ9OXW | B10: 90.590Y | C10: FR | D10: 16195.78 | E10: 536 | F10: 16304.03 | G10: 10315.46 | H10: 538 | I10: 33
A11: B0BHHV552D | B11: P203TER201 | C11: IT | D11: 15037.82 | E11: 922 | F11: 14793.17 | G11: 12784.2 | H11: 907 | I11: 94
A12: B09146GTKW | B12: P302VIS002 | C12: IT | D12: 14888.98 | E12: 1836 | F12: 15132.28 | G12: 11062.2 | H12: 1866 | I12: 63
A13: B06Y17FS6D | B13: 90.550 | C13: IT | D13: 14362.86 | E13: 586 | F13: 14583.45 | G13: 15228.65 | H13: 595 | I13: 14
... A46: B095PQJGKX | B46: C107UTT002 | C46: IT | D46: 4428.06 | E46: 546 | F46: 4403.73 | G46: 2885.07 | H46: 543 | I46: 10
A47: B00L5H5KUW | B47: 40.121 | C47: IT | D47: 4379.44 | E47: 258 | F47: 4219.78 | G47: 2616.4 | H47: 248
A48: B0BD4VX5JB | B48: P203PAN002 | C48: IT | D48: 4258.28 | E48: 52 | F48: 3603.16 | G48: 3346.8 | H48: 44 | I48: 6
A49: B0757TJRR9 | B49: 40.500 | C49: FR | D49: 4185.81 | E49: 166 | F49: 4279.89 | G49: 3128.39 | H49: 170 | I49: 6
A50: B08B66J4C3 | B50: P101PIA001 | C50: IT | D50: 4139.19 | E50: 339 | F50: 4163.61 | G50: 2790.26 | H50: 341 | I50: 8
A51: B095PQJGKX | B51: C107UTT002 | C51: FR | D51: 4106.42 | E51: 498 | F51: 4008.46 | G51: 2184.6 | H51: 486 | I51: 7
A52: B0B8DLSNJF | B52: P302VIS050 | C52: ES | D52: 3982 | E52: 220 | F52: 4072.5 | G52: 3319.72 | H52: 225 | I52: 4
A53: B07NQ2VYGD | B53: BT.710Y | C53: ES | D53: 3953.6 | E53: 160 | F53: 4324.25 | G53: 3325.18 | H53: 175 | I53: 14
A54: B097HRQNRG | B54: P101FRI100 | C54: DE | D54: 3943.22 | E54: 124 | F54: 3757.94 | G54: 2554.42 | H54: 118 | I54: 18
A55: B00L5H5KUW | B55: 40.121 | C55: ES | D55: 3651.87 | E55: 239 | F55: 3546.06 | G55: 2745.38 | H55: 232
A56: B07NQC6S9V | B56: BT.651Y | C56: ES | D56: 3636.78 | E56: 98 | F56: 4082.1 | G56: 3858.92 | H56: 110 | I56: 4
A57: B0823CVGHX | B57: BP.400 | C57: ES | D57: 3593.88 | E57: 67 | F57: 3701.16 | G57: 2918.08 | H57: 69 | I57: 7
A58: B06Y1997YH | B58: 90.883 | C58: IT | D58: 3560.59 | E58: 65 | F58: 3445.99 | G58: 2811.2 | H58: 63 | I58: 8
A59: B085R2GCKX | B59: 40.332 | C59: IT | D59: 3405.42 | E59: 229 | F59: 3425.2 | G59: 1878.04 | H59: 230 | I59: 3
A60: B08FDYW72J | B60: P101CUD100 | C60: DE | D60: 3394.09 | E60: 111 | F60: 3488.44 | G60: 1967.16 | H60: 114 | I60: 12
A61: B09ZBHJ91Q | B61: P201UTP100 | C61: IT | D61: 3392.48 | E61: 208 | F61: 3653.44 | G61: 2357.85 | H61: 224 | I61: 16
A62: B00FAJUDU8 | B62: 40.967N | C62: IT | D62: 3367.65 | E62: 165 | F62: 3388.06 | G62: 2356.93 | H62: 166 | I62: 3
A63: B07YZZZVXP | B63: MD.404 | C63: DE | D63: 3338.97 | E63: 52 | F63: 3210.97 | G63: 2213.03 | H63: 50 | I63: 7
A64: B084C3JTC2 | B64: 40.406 | C64: FR | D64: 3264.52 | E64: 131 | F64: 3289.44 | G64: 2841.87 | H64: 132 | I64: 4
A65: B091LRR67V | B65: P101FRI050 | C65: IT | D65: 3256.79 | E65: 51 | F65: 3188.1 | G65: 2726.4 | H65: 50 | I65: 50
A66: B08KYZ2FLN | B66: P101FRI001 | C66: FR | D66: 3248.25 | E66: 71 | F66: 3111 | G66: 2161.76 | H66: 68 | I66: 1
A67: B08LZN1PWY | B67: P101TEM001 | C67: FR | D67: 3200.33 | E67: 39 | F67: 2954.18 | G67: 1885.19 | H67: 36 | I67: 1
... A101: B085JJ81R7 | B101: RCO9003028 | C101: IT | D101: 1766.5 | E101: 242 | F101: 1766.5 | G101: 1043.76 | H101: 242 | I101: 1
A102: B09LHXJXQL | B102: P102SBA007 | C102: FR | D102: 1674.58 | E102: 101 | F102: 1658 | G102: 1296.76 | H102: 100
A103: B06Y17FS6D | B103: 90.550 | C103: FR | D103: 1562.75 | E103: 47 | F103: 1629.25 | G103: 1343.98 | H103: 49 | I103: 7
A104: B0823CVGHX | B104: BP.400 | C104: DE | D104: 1556.23 | E104: 29 | F104: 1710.88 | G104: 1372.04 | H104: 32 | I104: 1
A105: B01CNX6Z78 | B105: 90.820 | C105: FR | D105: 1499.04 | E105: 72 | F105: 1499.04 | G105: 1229.81 | H105: 72 | I105: 1
A106: B085R2GCKX | B106: 40.332 | C106: ES | D106: 1464.05 | E106: 89 | F106: 1546.3 | G106: 938.08 | H106: 94 | I106: 10
A107: B08HCT78N3 | B107: P202ASP400 | C107: IT | D107: 1386.35 | E107: 85 | F107: 1337.42 | G107: 532.29 | H107: 82 | I107: 38
A108: B09HMK8JDN | B108: P203TER001 | C108: IT | D108: 1386.05 | E108: 19 | F108: 1313.1 | G108: 1362.9 | H108: 18 | I108: 4
A109: B0B3N9ZNT2 | B109: P101CUD051 | C109: ES | D109: 1385.16 | E109: 42 | F109: 1681.98 | G109: 1223.08 | H109: 51 | I109: 1
A110: B0953R2W31 | B110: P102ACP001 | C110: IT | D110: 1355.31 | E110: 111 | F110: 1404.15 | G110: 672.39 | H110: 115 | I110: 4
A111: B0B6JPXDN6 | B111: P201UTP200 | C111: ES | D111: 1348.9 | E111: 82 | F111: 1579.2 | G111: 1338.55 | H111: 96 | I111: 9
A112: B08JYWF3PK | B112: C102COC101 | C112: FR | D112: 1344.75 | E112: 163 | F112: 1386 | G112: 928.26 | H112: 168
A113: B07V131F5W | B113: 40.490 | C113: FR | D113: 1343.2 | E113: 52 | F113: 1318.28 | G113: 851.27 | H113: 51
A114: B09L4SLDSZ | B114: P203TFO100 | C114: IT | D114: 1299.03 | E114: 53 | F114: 1348.05 | G114: 927.52 | H114: 55 | I114: 5
A115: B01M4O6145 | B115: 90.071 | C115: IT | D115: 1297.24 | E115: 60 | F115: 1360.93 | G115: 1031.24 | H115: 63 | I115: 5
A116: B0B6JPXDN6 | B116: P201UTP200 | C116: IT | D116: 1288.49 | E116: 79 | F116: 1239.56 | G116: 1010.5 | H116: 76 | I116: 12
A117: B084C3JTC2 | B117: 40.406 | C117: DE | D117: 1281.63 | E117: 51 | F117: 1257.67 | G117: 1094.38 | H117: 50 | I117: 4
A118: B0BBH12BYN | B118: P101COS001 | C118: IT | D118: 1278.33 | E118: 13 | F118: 1269.4 | G118: 944.71 | H118: 13
A119: B00L5H5KUW | B119: 40.121 | C119: FR | D119: 1260.08 | E119: 76 | F119: 1210.34 | G119: 1129.31 | H119: 73
A120: B017IUJA50 | B120: 90.920G | C120: FR | D120: 1245.5 | E120: 94 | F120: 1219 | G120: 863.97 | H120: 92 | I120: 5
A121: B08MX1SQKC | B121: P302VIS001 | C121: IT | D121: 1233.21 | E121: 101 | F121: 1306.47 | G121: 827.82 | H121: 107 | I121: 4
A122: B07YZZZVXP | B122: MD.404 | C122: ES | D122: 1212.25 | E122: 19 | F122: 1212.25 | G122: 934.96 | H122: 19 | I122: 2
A123: B08GS7XW73 | B123: P204FER250 | C123: FR | D123: 1211.56 | E123: 68 | F123: 1135.26 | G123: 723.54 | H123: 63 | I123: 1
A124: B0B39H1Z8J | B124: C106CAS001 | C124: ES | D124: 1210.64 | E124: 148 | F124: 1227 | G124: 874.5 | H124: 150 | I124: 5
A125: B08B66J4C3 | B125: P101PIA001 | C125: FR | D125: 1192.32 | E125: 96 | F125: 1229.58 | G125: 713.82 | H125: 99
A126: B09C2K1HQW | B126: P302MAS050 | C126: IT | D126: 1190.25 | E126: 11 | F126: 1405.3 | G126: 1173.9 | H126: 13 | I126: 3
A127: B097HRQNRG | B127: P101FRI100 | C127: FR | D127: 1179.99 | E127: 35 | F127: 1148.74 | G127: 799.9 | H127: 34 | I127: 1
A128: B0B6JPXDN6 | B128: P201UTP200 | C128: DE | D128: 1170.4 | E128: 70 | F128: 1120.24 | G128: 969.7 | H128: 67 | I128: 1
A129: B01I497WWM | B129: 90.920R | C129: ES | D129: 1120.85 | E129: 69 | F129: 1104 | G129: 671.69 | H129: 68 | I129: 10
A130: B07B9CPH62 | B130: BG.200Y | C130: IT | D130: 1118.2 | E130: 23 | F130: 1068.36 | G130: 794.53 | H130: 22 | I130: 3
A131: B09KYD9JGY | B131: P301PIS100 | C131: FR | D131: 1099.75 | E131: 53 | F131: 1037.5 | G131: 762.3 | H131: 50 | I131: 4
A132: B09KYD9JGY | B132: P301PIS100 | C132: ES | D132: 1090.74 | E132: 53 | F132: 1173.06 | G132: 849.25 | H132: 57 | I132: 13
A133: B09NBXYF5J | B133: P101TOS002 | C133: IT | D133: 1090.33 | E133: 55 | F133: 1109.86 | G133: 908.91 | H133: 56 | I133: 1
A134: B085JJFLGY | B134: RCO9003022 | C134: IT | D134: 1074.48 | E134: 222 | F134: 1084.16 | G134: 1048.29 | H134: 224 | I134: 2
A135: B09MFYXGV9 | B135: P101FRI012 | C135: IT | D135: 1073.63 | E135: 9 | F135: 1073.63 | G135: 1012.5 | H135: 9 | I135: 2
A136: B08JM7SZ36 | B136: C206UTI001 | C136: FR | D136: 1073.5 | E136: 37 | F136: 957.18 | G136: 672.53 | H136: 33 | I136: 1
A137: B07V131F5W | B137: 40.490 | C137: ES | D137: 1057.01 | E137: 43 | F137: 1081.72 | G137: 666.48 | H137: 44
A138: B0B3N9ZNT2 | B138: P101CUD051 | C138: IT | D138: 1046.4 | E138: 32 | F138: 1144.5 | G138: 811.46 | H138: 35 | I138: 3
A139: B095WCSSLC | B139: C301ABE101 | C139: IT | D139: 1042.15 | E139: 132 | F139: 1059.99 | G139: 554.79 | H139: 134 | I139: 4
A140: B076DCL19C | B140: BP.720 | C140: IT | D140: 1031.4 | E140: 18 | F140: 1088.7 | G140: 777.86 | H140: 19 | I140: 3
A141: B09B2NT2SV | B141: P102FRU150 | C141: FR | D141: 1030.75 | E141: 31 | F141: 1030.75 | G141: 783.14 | H141: 31 | I141: 6
A142: B07W7S9KYM | B142: BB.200 | C142: IT | D142: 998.34 | E142: 21 | F142: 998.34 | G142: 689.01 | H142: 21 | I142: 13
A143: B08NDZKNF5 | B143: P102CON001 | C143: ES | D143: 980.56 | E143: 34 | F143: 1153.6 | G143: 678.7 | H143: 40 | I143: 5
A144: B0B5XB4X2T | B144: P102ACP100 | C144: IT | D144: 978.6 | E144: 60 | F144: 897.05 | G144: 956.12 | H144: 55
A145: B07BB2DQ4V | B145: BT.150Y | C145: DE | D145: 968.24 | E145: 31 | F145: 968.24 | G145: 639.52 | H145: 31 | I145: 3
A146: B09B47S644 | B146: P101CUD501 | C146: DE | D146: 960.3 | E146: 34 | F146: 960.3 | G146: 654.89 | H146: 34 | I146: 3
A147: B07YBNPZPJ | B147: BP.552 | C147: IT | D147: 955.89 | E147: 39 | F147: 1004.91 | G147: 634.06 | H147: 41 | I147: 3
A148: B09B47S644 | B148: P101CUD501 | C148: ES | D148: 951.72 | E148: 33 | F148: 951.72 | G148: 659.86 | H148: 33 | I148: 3
A149: B076D74TC7 | B149: BT.700Y | C149: FR | D149: 951.16 | E149: 32 | F149: 951.16 | G149: 572.3 | H149: 32 | I149: 1
A150: B09Y9DBPK5 | B150: P101CUD300 | C150: IT | D150: 948.35 | E150: 13 | F150: 948.35 | G150: 1000.75 | H150: 13 | I150: 4
A151: B097HRQNRG | B151: P101FRI100 | C151: IT | D151: 944.13 | E151: 33 | F151: 915.52 | G151: 534.08 | H151: 32 | I151: 10
A152: B095WCSSLC | B152: C301ABE101 | C152: ES | D152: 930.8 | E152: 118 | F152: 926.72 | G152: 491.43 | H152: 117 | I152: 2
A153: B085R2GCKX | B153: 40.332 | C153: FR | D153: 928.48 | E153: 56 | F153: 945.06 | G153: 603.49 | H153: 57 | I153: 1
A154: B076Q7BR6F | B154: BC.041N | C154: FR | D154: 914.76 | E154: 22 | F154: 914.76 | G154: 665 | H154: 22 | I154: 3
A155: B0B2F48ZMP | B155: P102GEL100 | C155: IT | D155: 906.26 | E155: 23 | F155: 906.26 | G155: 689.66 | H155: 23 | I155: 5
A156: B08JYDDFZ2 | B156: C206UTI002 | C156: ES | D156: 896.69 | E156: 85 | F156: 918.01 | G156: 544.64 | H156: 87 | I156: 1
A157: B07KYWNC7Z | B157: 40.405 | C157: IT | D157: 878.32 | E157: 37 | F157: 905 | G157: 592.7 | H157: 38 | I157: 4
A158: B085JHTR6J | B158: BC.125 | C158: IT | D158: 862.16 | E158: 53 | F158: 862.16 | G158: 487 | H158: 53
A159: B08FMLPKY9 | B159: P201UTP004 | C159: FR | D159: 859.97 | E159: 46 | F159: 842.55 | G159: 521.6 | H159: 45
A160: B095X9KDJR | B160: P101BOL100 | C160: IT | D160: 859.53 | E160: 50 | F160: 859.53 | G160: 554.2 | H160: 50
A161: B08JM7SZ36 | B161: C206UTI001 | C161: DE | D161: 845.11 | E161: 29 | F161: 757.15 | G161: 544.34 | H161: 26 | I161: 3
A162: B085JHSWJH | B162: BP.802 | C162: IT | D162: 818.72 | E162: 52 | F162: 818.72 | G162: 534.87 | H162: 52
A163: B0953R2W31 | B163: P102ACP001 | C163: ES | D163: 811.62 | E163: 66 | F163: 822.05 | G163: 311.55 | H163: 67 | I163: 8
A164: B0B2F48ZMP | B164: P102GEL100 | C164: DE | D164: 798.28 | E164: 20 | F164: 798.28 | G164: 617.36 | H164: 20 | I164: 1
A165: B07N4C3H3V | B165: 40.405 | C165: IT | D165: 794.19 | E165: 68 | F165: 782.55 | G165: 399.6 | H165: 67 | I165: 4
...

Sheet vendor_01_2024
A1: ASIN | B1: Numero del modello | C1: Codice marketplace | D1: Ricavi ordini | E1: Unità ordinate | F1: Ricavi spedizioni | G1: COGS spedizioni | H1: Unità spedite | I1: Resi cliente
A2: B0BHHV552D | B2: P203TER201 | C2: IT | D2: 9074.87 | E2: 558 | F2: 8862.85 | G2: 6568.29 | H2: 545 | I2: 85
A3: B0050IHH4E | B3: 40.979 | C3: DE | D3: 8964.88 | E3: 634 | F3: 8911.52 | G3: 5696.78 | H3: 626 | I3: 45
A4: B0050IHH4E | B4: 40.979 | C4: IT | D4: 6983.03 | E4: 486 | F4: 6700.53 | G4: 4517.98 | H4: 466 | I4: 15
A5: B09146GTKW | B5: P302VIS002 | C5: IT | D5: 5723.45 | E5: 544 | F5: 5533.77 | G5: 3168 | H5: 528 | I5: 28
A6: B096MX229M | B6: P102ROB050 | C6: DE | D6: 5380.42 | E6: 431 | F6: 5105.68 | G6: 3225.2 | H6: 409 | I6: 31
A7: B0CLVS3FH6 | B7: P201UTP111 | C7: IT | D7: 5284.44 | E7: 324 | F7: 4990.86 | G7: 4284 | H7: 306 | I7: 24
A8: B00L5H5KUW | B8: 40.121 | C8: IT | D8: 5023.29 | E8: 275 | F8: 4969.44 | G8: 3229 | H8: 272
A9: B0BBH12BYN | B9: P101COS001 | C9: IT | D9: 5001.34 | E9: 57 | F9: 5079.94 | G9: 3342.7 | H9: 58 | I9: 16
A10: B07SSLRCT6 | B10: BP.304 | C10: FR | D10: 3652.58 | E10: 253 | F10: 3770.46 | G10: 2744.2 | H10: 262 | I10: 23
A11: B07Q38Z7CK | B11: BC.060 | C11: IT | D11: 3399.3 | E11: 168 | F11: 3460.53 | G11: 2565 | H11: 171 | I11: 34
A12: B09968BKDS | B12: P102FRU003 | C12: FR | D12: 2885.72 | E12: 203 | F12: 2835.81 | G12: 1745.72 | H12: 200 | I12: 20
A13: B07JGVMFY1 | B13: BP.581 | C13: FR | D13: 2760.2 | E13: 185 | F13: 2715.44 | G13: 1833.8 | H13: 182 | I13: 15
A14: B08GY7286R | B14: P203TFO001 | C14: IT | D14: 2651.93 | E14: 191 | F14: 2734.11 | G14: 1960.2 | H14: 198 | I14: 15
A15: B07V131F5W | B15: 40.490 | C15: IT | D15: 2591.61 | E15: 105 | F15: 2542.59 | G15: 1854 | H15: 103 | I15: 1
A16: B0B39H1Z8J | B16: C106CAS001 | C16: IT | D16: 2397.59 | E16: 222 | F16: 2343.81 | G16: 1140.12 | H16: 217 | I16: 30
A17: B0CLY2CF4T | B17: P201UTP113 | C17: IT | D17: 2234.47 | E17: 137 | F17: 2201.85 | G17: 1890 | H17: 135 | I17: 5
A18: B0BJ2TBPJW | B18: C206UTI004 | C18: IT | D18: 2224.23 | E18: 453 | F18: 2199.68 | G18: 950.98 | H18: 448 | I18: 1
A19: B076QCMZX1 | B19: 40.821 | C19: IT | D19: 1977.32 | E19: 162 | F19: 1989.53 | G19: 1371.9 | H19: 163 | I19: 13
A20: B0B8JVTQYQ | B20: P101CUD200 | C20: DE | D20: 1957.21 | E20: 42 | F20: 1957.21 | G20: 1438.29 | H20: 42 | I20: 21
... A63: B0BNNH9RZQ | B63: P302VIS060 | C63: ES | D63: 900.25 | E63: 72 | F63: 900.25 | G63: 502.92 | H63: 72 | I63: 37
A64: B07NQ2VYGD | B64: BT.710Y | C64: ES | D64: 864.85 | E64: 35 | F64: 1087.24 | G64: 765.6 | H64: 44
A65: B07NQ1T7YK | B65: BP.101H | C65: FR | D65: 856.06 | E65: 61 | F65: 980.44 | G65: 703.36 | H65: 72 | I65: 10
A66: B0CLVS3FH6 | B66: P201UTP111 | C66: DE | D66: 853.17 | E66: 45 | F66: 853.17 | G66: 630 | H66: 45 | I66: 3
A67: B09D8G2H7Q | B67: P102SBA500 | C67: IT | D67: 842.72 | E67: 8 | F67: 842.72 | G67: 646.4 | H67: 8 | I67: 11
A68: B07V131F5W | B68: 40.490 | C68: ES | D68: 819.64 | E68: 34 | F68: 716.59 | G68: 522 | H68: 29 | I68: 1
A69: B076DCL19C | B69: BP.720 | C69: IT | D69: 814.3 | E69: 17 | F69: 814.3 | G69: 670.85 | H69: 17 | I69: 6
A70: B09D8G2H7Q | B70: P102SBA500 | C70: FR | D70: 755.38 | E70: 7 | F70: 644.75 | G70: 484.8 | H70: 6
A71: B01M4O6145 | B71: 90.071 | C71: IT | D71: 755.17 | E71: 37 | F71: 693.94 | G71: 657.9 | H71: 34 | I71: 4
A72: B0B2F48ZMP | B72: P102GEL100 | C72: FR | D72: 723.25 | E72: 21 | F72: 689.72 | G72: 598.4 | H72: 20 | I72: 2
A73: B09BD8BG34 | B73: P301PIS001 | C73: DE | D73: 713.64 | E73: 57 | F73: 688.6 | G73: 484 | H73: 55 | I73: 8
A74: B08FMLPKY9 | B74: P201UTP004 | C74: FR | D74: 712.94 | E74: 43 | F74: 712.94 | G74: 580.5 | H74: 43 | I74: 8
A75: B085R2GCKX | B75: 40.332 | C75: IT | D75: 712.92 | E75: 43 | F75: 664.39 | G75: 450 | H75: 40 | I75: 14
A76: B07ZJMFB3R | B76: BC.510 | C76: IT | D76: 709.12 | E76: 12 | F76: 709.12 | G76: 556.8 | H76: 12 | I76: 6
A77: B0B8JVTQYQ | B77: P101CUD200 | C77: ES | D77: 701.68 | E77: 18 | F77: 712.34 | G77: 615.6 | H77: 18 | I77: 1
A78: B08JYWF3PK | B78: C102COC101 | C78: FR | D78: 701.25 | E78: 85 | F78: 726 | G78: 528 | H78: 88
A79: B0BD83RNDG | B79: C106CAS002 | C79: IT | D79: 690.53 | E79: 62 | F79: 722.24 | G79: 479.37 | H79: 65 | I79: 4
A80: B07R984VMS | B80: BI.505 | C80: FR | D80: 687.96 | E80: 93 | F80: 687.96 | G80: 587.76 | H80: 93 | I80: 1
A81: B011LFVLW8 | B81: 90.620 | C81: IT | D81: 686.19 | E81: 19 | F81: 751.59 | G81: 567 | H81: 21 | I81: 6
A82: B06Y1997YH | B82: 90.883 | C82: IT | D82: 685.1 | E82: 11 | F82: 742.4 | G82: 511.44 | H82: 12 | I82: 4
A83: B0CHFQXMZX | B83: P203PAN001 | C83: FR | D83: 677.25 | E83: 43 | F83: 693 | G83: 418 | H83: 44 | I83: 31
A84: B084C3JTC2 | B84: 40.406 | C84: IT | D84: 676.38 | E84: 28 | F84: 674.09 | G84: 563.27 | H84: 28 | I84: 5
A85: B085JHSWJH | B85: BP.802 | C85: IT | D85: 665.8 | E85: 51 | F85: 653.67 | G85: 485.8 | H85: 50
A86: B0CHWMFNNT | B86: P202ASP250 | C86: FR | D86: 665.28 | E86: 16 | F86: 582.12 | G86: 420 | H86: 14 | I86: 2
A87: B07B9CPH62 | B87: BG.200Y | C87: ES | D87: 643.5 | E87: 13 | F87: 643.5 | G87: 526.5 | H87: 13 | I87: 3
A88: B088V4DR59 | B88: P206ZAN040 | C88: IT | D88: 631.3 | E88: 12 | F88: 575.15 | G88: 450.49 | H88: 11
A89: B085JJ8RC6 | B89: BB.050 | C89: FR | D89: 627.89 | E89: 44 | F89: 667.19 | G89: 455.9 | H89: 47 | I89: 8
A90: B08GS7XW73 | B90: P204FER250 | C90: FR | D90: 626.08 | E90: 38 | F90: 495.42 | G90: 391.5 | H90: 30 | I90: 2
A91: B09BD8BG34 | B91: P301PIS001 | C91: FR | D91: 621 | E91: 50 | F91: 683.1 | G91: 484 | H91: 55 | I91: 4
A92: B0BTHSH5MK | B92: C103ACC001 | C92: FR | D92: 618.75 | E92: 75 | F92: 594 | G92: 390.08 | H92: 72 | I92: 3
A93: B09146GTKW | B93: P302VIS002 | C93: FR | D93: 618.75 | E93: 75 | F93: 577.5 | G93: 420 | H93: 70 | I93: 4
A94: B096MX229M | B94: P102ROB050 | C94: ES | D94: 615.5 | E94: 50 | F94: 590.88 | G94: 383.6 | H94: 48 | I94: 1
A95: B0BNNH9RZQ | B95: P302VIS060 | C95: DE | D95: 613.48 | E95: 49 | F95: 626 | G95: 375.66 | H95: 50 | I95: 48
A96: B085JHTR6Q | B96: BP.790 | C96: IT | D96: 612.75 | E96: 25 | F96: 612.75 | G96: 448.25 | H96: 25 | I96: 1
A97: B0B39H1Z8J | B97: C106CAS001 | C97: GB | D97: 606.35 | E97: 54 | F97: 573.37 | G97: 315.19 | H97: 51 | I97: 2
A98: B076QFRRZ5 | B98: 40.931 | C98: IT | D98: 573.31 | E98: 40 | F98: 569.68 | G98: 261.6 | H98: 40 | I98: 11
A99: B01CNX71NA | B99: 90.871 | C99: ES | D99: 572.74 | E99: 7 | F99: 572.74 | G99: 465.5 | H99: 7
A100: B085JHSWJH | B100: BP.802 | C100: FR | D100: 569.75 | E100: 43 | F100: 530 | G100: 356.8 | H100: 40 | I100: 2
A101: B08JYWF3PK | B101: C102COC101 | C101: IT | D101: 567.63 | E101: 63 | F101: 558.62 | G101: 372 | H101: 62
A102: B09KYD9JGY | B102: P301PIS100 | C102: IT | D102: 549.39 | E102: 21 | F102: 602.99 | G102: 344.08 | H102: 23 | I102: 4
A103: B0BVBY1RWS | B103: P206VEN550 | C103: DE | D103: 545.09 | E103: 13 | F103: 545.09 | G103: 455 | H103: 13 | I103: 1
A104: B07KYWNC7Z | B104: 40.405 | C104: IT | D104: 540.71 | E104: 25 | F104: 540.71 | G104: 416.25 | H104: 25 | I104: 3
A105: B0CPFRMPTM | B105: P101CAF001 | C105: ES | D105: 518.91 | E105: 21 | F105: 518.91 | G105: 556.5 | H105: 21 | I105: 1
A106: B09LHXJXQL | B106: P102SBA007 | C106: IT | D106: 516.37 | E106: 28 | F106: 479.06 | G106: 365.56 | H106: 26 | I106: 5
A107: B0CHFQXMZX | B107: P203PAN001 | C107: ES | D107: 498.28 | E107: 32 | F107: 498.28 | G107: 304 | H107: 32 | I107: 17
A108: B0CHF7YW6B | B108: P203PAN010 | C108: FR | D108: 493.56 | E108: 18 | F108: 493.56 | G108: 333 | H108: 18 | I108: 3
A109: B09L4SLDSZ | B109: P203TFO100 | C109: IT | D109: 490.2 | E109: 20 | F109: 514.71 | G109: 353.76 | H109: 21 | I109: 4
A110: B0C94Q6QZ9 | B110: P101TOS100 | C110: IT | D110: 489.7 | E110: 21 | F110: 489.7 | G110: 306.39 | H110: 21 | I110: 26
A111: B08GS7XW73 | B111: P204FER250 | C111: IT | D111: 488.1 | E111: 30 | F111: 358.82 | G111: 286.75 | H111: 22 | I111: 6
A112: B0BD83RNDG | B112: C106CAS002 | C112: FR | D112: 486.46 | E112: 40 | F112: 518.71 | G112: 324.76 | H112: 43 | I112: 5
A113: B0BJL1Z674 | B113: C102SPE001 | C113: FR | D113: 485.52 | E113: 77 | F113: 472.2 | G113: 232.54 | H113: 75 | I113: 3
A114: B07NQ1T7YK | B114: BP.101H | C114: ES | D114: 480.09 | E114: 39 | F114: 480.09 | G114: 412.04 | H114: 39 | I114: 1
A115: B08L9D9KR9 | B115: P202VAL001 | C115: FR | D115: 466 | E115: 8 | F115: 466 | G115: 360 | H115: 8
A116: B0BVZG7FPY | B116: P206VEN600 | C116: IT | D116: 464.74 | E116: 12 | F116: 464.74 | G116: 307.8 | H116: 12 | I116: 8
A117: B08Y6RJ69Y | B117: P204CAL001 | C117: ES | D117: 464.51 | E117: 8 | F117: 464.51 | G117: 288.64 | H117: 8 | I117: 1
A118: B07B9CPH62 | B118: BG.200Y | C118: FR | D118: 464.06 | E118: 5 | F118: 464.06 | G118: 202.5 | H118: 5 | I118: 1
A119: B08GSK6C18 | B119: P204FER200 | C119: ES | D119: 460.6 | E119: 28 | F119: 444.15 | G119: 351.03 | H119: 27
A120: B0B2F48ZMP | B120: P102GEL100 | C120: IT | D120: 451.55 | E120: 12 | F120: 412.05 | G120: 329.12 | H120: 11 | I120: 2
A121: B0050IHH4E | B121: 40.979 | C121: ES | D121: 444.71 | E121: 34 | F121: 444.71 | G121: 339.02 | H121: 34 | I121: 2
A122: B092QXCQ8K | B122: P205DIF001 | C122: FR | D122: 438.44 | E122: 32 | F122: 479.27 | G122: 343.79 | H122: 35 | I122: 2
A123: B09HMK8JDN | B123: P203TER001 | C123: ES | D123: 437.95 | E123: 5 | F123: 437.95 | G123: 365.75 | H123: 5 | I123: 1
A124: B073B67PLQ | B124: 90.884 | C124: ES | D124: 437.22 | E124: 7 | F124: 437.22 | G124: 472.5 | H124: 7 | I124: 1
A125: B097YTGFH7 | B125: P102ROB200 | C125: IT | D125: 433.99 | E125: 7 | F125: 433.99 | G125: 406 | H125: 7 | I125: 1
A126: B08C7YJB5N | B126: P201UTP001 | C126: IT | D126: 432.96 | E126: 33 | F126: 407.04 | G126: 145.5 | H126: 32
A127: B07V131F5W | B127: 40.490 | C127: DE | D127: 431.8 | E127: 20 | F127: 431.8 | G127: 361.21 | H127: 20 | I127: 1
A128: B08GY7286R | B128: P203TFO001 | C128: FR | D128: 429.83 | E128: 30 | F128: 443.8 | G128: 306.9 | H128: 31 | I128: 9
A129: B0050IHH4E | B129: 40.979 | C129: FR | D129: 429.59 | E129: 29 | F129: 542.57 | G129: 327.08 | H129: 36 | I129: 3
A130: B085R2GCKX | B130: 40.332 | C130: DE | D130: 418 | E130: 25 | F130: 351.12 | G130: 236.25 | H130: 21 | I130: 3
A131: B09B47S644 | B131: P101CUD501 | C131: DE | D131: 416.22 | E131: 13 | F131: 399.68 | G131: 271.7 | H131: 13 | I131: 4
A132: B091LRR67V | B132: P101FRI050 | C132: IT | D132: 415.55 | E132: 7 | F132: 415.55 | G132: 399.79 | H132: 7 | I132: 4
A133: B08FMLPKY9 | B133: P201UTP004 | C133: DE | D133: 413.53 | E133: 24 | F133: 413.53 | G133: 319.05 | H133: 24 | I133: 2
A134: B09LHXJXQL | B134: P102SBA007 | C134: FR | D134: 413.04 | E134: 18 | F134: 413.04 | G134: 253.08 | H134: 18 | I134: 1
A135: B0BJ2TBPJW | B135: C206UTI004 | C135: ES | D135: 405.65 | E135: 85 | F135: 387.35 | G135: 164 | H135: 82
A136: B08LZN1PWY | B136: P101TEM001 | C136: ES | D136: 404.39 | E136: 7 | F136: 462.16 | G136: 388.96 | H136: 8
A137: B088XJQ37J | B137: C301ABE001 | C137: IT | D137: 402.93 | E137: 33 | F137: 402.93 | G137: 214.35 | H137: 33 | I137: 3
A138: B0CHF7YW6B | B138: P203PAN010 | C138: DE | D138: 387.1 | E138: 14 | F138: 359.45 | G138: 240.5 | H138: 13 | I138: 2
A139: B0BD4VX5JB | B139: P203PAN002 | C139: IT | D139: 380.8 | E139: 4 | F139: 490.05 | G139: 280.55 | H139: 5
A140: B097YTGFH7 | B140: P102ROB200 | C140: DE | D140: 376.32 | E140: 9 | F140: 376.32 | G140: 522 | H140: 9 | I140: 2
A141: B07P7GGGQM | B141: BP.961 | C141: FR | D141: 374.22 | E141: 9 | F141: 374.22 | G141: 324 | H141: 9 | I141: 1
A142: B085JHTR6Q | B142: BP.790 | C142: FR | D142: 373.8 | E142: 15 | F142: 373.8 | G142: 268.95 | H142: 15
...

Sheet seller_01_2024
A1: amazon-order-id | B1: merchant-order-id | C1: purchase-date | D1: last-updated-date | E1: order-status | F1: fulfillment-channel | G1: sales-channel | H1: order-channel | I1: url | J1: ship-service-level | K1: product-name | L1: sku | M1: asin | N1: item-status | O1: quantity | P1: currency | Q1: item-price | R1: item-tax | S1: shipping-price | T1: shipping-tax | U1: gift-wrap-price | V1: gift-wrap-tax | W1: item-promotion-discount | X1: ship-promotion-discount | Y1: ship-city | Z1: ship-state | AA1: ship-postal-code | AB1: ship-country | AC1: promotion-ids | AD1: buyer-company-name | AE1: buyer-cst-number | AF1: buyer-vat-number | AG1: buyer-tax-registration-id | AH1: buyer-tax-registration-country | AI1: buyer-tax-registration-type
A2: 405-3843267-7979508 | B2: 405-3843267-7979508 | C2: 2024-01-31T22:55:05+00:00 | D2: 2024-02-02T12:04:06+00:00 | E2: Shipped | F2: Amazon | G2: Amazon.fr | J2: Standard | K2: BEPER BT.710Y Crêpière électrique avec poignée, 800 W, plaque en aluminium avec revêtement antiadhésif, rouge | L2: BT.710Y_FBA | M2: B07NQ2VYGD | N2: Shipped | O2: 1 | P2: EUR | Q2: 39.9 | S2: 1 | X2: 1 | Y2: clermont ferrand | AA2: 63000 | AB2: FR | AC2: Free Shipping 2017/10/17 17-17-37-677
A3: 402-3695688-5468327 | B3: 402-3695688-5468327 | C3: 2024-01-31T22:02:27+00:00 | D3: 2024-01-31T22:11:42+00:00 | E3: Cancelled | F3: Amazon | G3: Amazon.fr | J3: Expedited | K3: BEPER BT.710Y Crêpière électrique avec poignée, 800 W, plaque en aluminium avec revêtement antiadhésif, rouge | L3: BT.710Y_FBA | M3: B07NQ2VYGD | N3: Cancelled | O3: 0 | Y3: Bavilliers | AA3: 90800 | AB3: FR
A4: 406-8285919-0021116 | B4: 406-8285919-0021116 | C4: 2024-01-31T21:34:06+00:00 | D4: 2024-02-01T15:25:59+00:00 | E4: Shipped | F4: Amazon | G4: Amazon.fr | J4: Expedited | K4: BEPER BT.710Y Crêpière électrique avec poignée, 800 W, plaque en aluminium avec revêtement antiadhésif, rouge | L4: BT.710Y_FBA | M4: B07NQ2VYGD | N4: Shipped | O4: 1 | P4: EUR | Q4: 39.9 | Y4: Chateauneuf Les Martigues | AA4: 13220 | AB4: FR
A5: 408-3299766-2272353 | B5: 408-3299766-2272353 | C5: 2024-01-31T20:39:21+00:00 | D5: 2024-02-03T00:44:57+00:00 | E5: Shipped | F5: Amazon | G5: Amazon.fr | J5: Expedited | K5: BEPER BT.710Y Crêpière électrique avec poignée, 800 W, plaque en aluminium avec revêtement antiadhésif, rouge | L5: BT.710Y_FBA | M5: B07NQ2VYGD | N5: Shipped | O5: 1 | P5: EUR | Q5: 39.9 | Y5: Nanteuil Le Haudouin | AA5: 60440 | AB5: FR
A6: 406-4914578-1861133 | B6: 406-4914578-1861133 | C6: 2024-01-31T20:17:37+00:00 | D6: 2024-02-02T09:38:34+00:00 | E6: Shipped | F6: Amazon | G6: Amazon.fr | J6: Expedited | K6: BEPER BT.710Y Crêpière électrique avec poignée, 800 W, plaque en aluminium avec revêtement antiadhésif, rouge | L6: BT.710Y_FBA | M6: B07NQ2VYGD | N6: Shipped | O6: 1 | P6: EUR | Q6: 39.9 | Y6: Bruxelles Uccle | AA6: 1180 | AB6: BE
A7: 407-3888737-4981165 | B7: 407-3888737-4981165 | C7: 2024-01-31T20:03:34+00:00 | D7: 2024-02-01T15:44:28+00:00 | E7: Shipped | F7: Amazon | G7: Amazon.fr | J7: Expedited | K7: BEPER BT.710Y Crêpière électrique avec poignée, 800 W, plaque en aluminium avec revêtement antiadhésif, rouge | L7: BT.710Y_FBA | M7: B07NQ2VYGD | N7: Shipped | O7: 1 | P7: EUR | Q7: 39.9 | Y7: Mer | AA7: 41500 | AB7: FR
A8: 408-9077802-2293965 | B8: 408-9077802-2293965 | C8: 2024-01-31T19:52:59+00:00 | D8: 2024-02-01T00:25:13+00:00 | E8: Shipped | F8: Amazon | G8: Amazon.fr | J8: Expedited | K8: BEPER 40.405 Seche Cheveux de Voyage Pliable - Mini Seche Cheveux Silencieux, 2 Températures et 2 Vitesses | L8: 40.405_FBA | M8: B07N4C3H3V | N8: Shipped | O8: 1 | P8: EUR | Q8: 19.9 | Y8: BELLE ISLE EN TERRE | AA8: 22810 | AB8: FR
A9: 405-9171375-5879521 | B9: 405-9171375-5879521 | C9: 2024-01-31T17:48:58+00:00 | D9: 2024-02-01T00:32:57+00:00 | E9: Shipped | F9: Amazon | G9: Amazon.fr | J9: Expedited | K9: BEPER BT.710Y Crêpière électrique avec poignée, 800 W, plaque en aluminium avec revêtement antiadhésif, rouge | L9: BT.710Y_FBA | M9: B07NQ2VYGD | N9: Shipped | O9: 1 | P9: EUR | Q9: 39.9 | Y9: Maizieres | AA9: 14190 | AB9: FR
A10: 404-2179655-8359551 | B10: 404-2179655-8359551 | C10: 2024-01-31T17:21:55+00:00 | D10: 2024-01-31T17:50:06+00:00 | E10: Cancelled | F10: Amazon | G10: Amazon.fr | J10: Standard | K10: BEPER BT.710Y Crêpière électrique avec poignée, 800 W, plaque en aluminium avec revêtement antiadhésif, rouge | L10: BT.710Y_FBA | M10: B07NQ2VYGD | N10: Cancelled | O10: 0 | Y10: Nogent sur Oise | AA10: 60180 | AB10: FR
A11: 406-3733820-1731557 | B11: 406-3733820-1731557 | C11: 2024-01-31T16:02:50+00:00 | D11: 2024-01-31T21:02:08+00:00 | E11: Shipped | F11: Amazon | G11: Amazon.fr | J11: Expedited | K11: BEPER BT.710Y Crêpière électrique avec poignée, 800 W, plaque en aluminium avec revêtement antiadhésif, rouge | L11: BT.710Y_FBA | M11: B07NQ2VYGD | N11: Shipped | O11: 1 | P11: EUR | Q11: 39.9 | Y11: paris | AA11: 75013 | AB11: FR
A12: 408-9259204-7038733 | B12: 408-9259204-7038733 | C12: 2024-01-31T15:54:11+00:00 | D12: 2024-02-01T00:33:17+00:00 | E12: Shipped | F12: Amazon | G12: Amazon.fr | J12: Expedited | K12: BEPER BT.710Y Crêpière électrique avec poignée, 800 W, plaque en aluminium avec revêtement antiadhésif, rouge | L12: BT.710Y_FBA | M12: B07NQ2VYGD | N12: Shipped | O12: 1 | P12: EUR | Q12: 39.9 | S12: 2.99 | Y12: Liège | AA12: 4460 | AB12: BE
A13: 402-3114700-4349104 | B13: 402-3114700-4349104 | C13: 2024-01-31T13:39:35+00:00 | D13: 2024-01-31T16:38:23+00:00 | E13: Shipped | F13: Amazon | G13: Amazon.fr | J13: Expedited | K13: BEPER BT.710Y Crêpière électrique avec poignée, 800 W, plaque en aluminium avec revêtement antiadhésif, rouge | L13: BT.710Y_FBA | M13: B07NQ2VYGD | N13: Shipped | O13: 1 | P13: EUR | Q13: 39.9 | Y13: Castelnaudary | AA13: 11400 | AB13: FR
A14: 404-6584360-2083560 | B14: 404-6584360-2083560 | C14: 2024-01-31T13:36:10+00:00 | D14: 2024-02-01T00:33:16+00:00 | E14: Shipped | F14: Amazon | G14: Amazon.fr | J14: Expedited | K14: BEPER BT.710Y Crêpière électrique avec poignée, 800 W, plaque en aluminium avec revêtement antiadhésif, rouge | L14: BT.710Y_FBA | M14: B07NQ2VYGD | N14: Shipped | O14: 1 | P14: EUR | Q14: 39.9 | Y14: PLAISIR | AA14: 78370 | AB14: FR
A15: 404-1194761-5069908 | B15: 404-1194761-5069908 | C15: 2024-01-31T12:03:55+00:00 | D15: 2024-02-02T02:48:44+00:00 | E15: Shipped | F15: Amazon | G15: Amazon.fr | J15: Standard | K15: BEPER BT.710Y Crêpière électrique avec poignée, 800 W, plaque en aluminium avec revêtement antiadhésif, rouge | L15: BT.710Y_FBA | M15: B07NQ2VYGD | N15: Shipped | O15: 1 | P15: EUR | Q15: 39.9 | S15: 0.57 | X15: 0.57 | Y15: Nouilly | AA15: 57645 | AB15: FR | AC15: Free Shipping 2017/10/17 17-17-37-677
A16: 406-0575986-7234744 | B16: 406-0575986-7234744 | C16: 2024-01-31T09:45:23+00:00 | D16: 2024-02-01T04:01:47+00:00 | E16: Shipped | F16: Amazon | G16: Amazon.fr | J16: Expedited | K16: Beper - Machine à Pop-Corn, Pop-Corn en 3 Minutes, Sans Matières Grasses, Circulation d'Air Chaud, Puissance 1200W - Rouge [Classe d'efficacité én | L16: 90.590Y_FBA | M16: B01KMJ9OXW | N16: Shipped | O16: 1 | P16: EUR | Q16: 44.9 | Y16: Paris | AA16: 75015 | AB16: FR
A17: 407-3519396-5821109 | B17: 407-3519396-5821109 | C17: 2024-01-31T09:43:32+00:00 | D17: 2024-01-31T12:17:13+00:00 | E17: Shipped | F17: Amazon | G17: Amazon.fr | J17: Standard | K17: BEPER BT.710Y Crêpière électrique avec poignée, 800 W, plaque en aluminium avec revêtement antiadhésif, rouge | L17: BT.710Y_FBA | M17: B07NQ2VYGD | N17: Shipped | O17: 1 | P17: EUR | Q17: 39.9 | Y17: Chambly | AA17: 60230 | AB17: FR | AC17: Free Shipping 2017/10/17 17-17-37-677
A18: 402-5330354-4808345 | B18: 402-5330354-4808345 | C18: 2024-01-31T09:03:04+00:00 | D18: 2024-02-01T01:00:42+00:00 | E18: Shipped | F18: Amazon | G18: Amazon.fr | J18: Expedited | K18: BEPER BT.710Y Crêpière électrique avec poignée, 800 W, plaque en aluminium avec revêtement antiadhésif, rouge | L18: BT.710Y_FBA | M18: B07NQ2VYGD | N18: Shipped | O18: 1 | P18: EUR | Q18: 39.9 | Y18: Ahuy | AA18: 21121 | AB18: FR
A19: 402-2429105-0390756 | B19: 402-2429105-0390756 | C19: 2024-01-31T08:14:18+00:00 | D19: 2024-01-31T12:16:49+00:00 | E19: Shipped | F19: Amazon | G19: Amazon.fr | J19: Standard | K19: Beper - Machine à Pop-Corn, Pop-Corn en 3 Minutes, Sans Matières Grasses, Circulation d'Air Chaud, Puissance 1200W - Rouge [Classe d'efficacité én | L19: 90.590Y_FBA | M19: B01KMJ9OXW | N19: Shipped | O19: 1 | P19: EUR | Q19: 44.9 | Y19: Benfeld | AA19: 67230 | AB19: FR | AC19: Free Shipping 2017/10/17 17-17-37-677
A20: 402-6106346-5753960 | B20: 402-6106346-5753960 | C20: 2024-01-30T22:25:58+00:00 | D20: 2024-02-02T16:55:43+00:00 | E20: Shipped | F20: Amazon | G20: Amazon.fr | J20: Expedited | K20: BEPER BT.710Y Crêpière électrique avec poignée, 800 W, plaque en aluminium avec revêtement antiadhésif, rouge | L20: BT.710Y_FBA | M20: B07NQ2VYGD | N20: Shipped | O20: 1 | P20: EUR | Q20: 39.9 | Y20: jarnac | AA20: 16200 | AB20: FR
A21: 402-2680769-0229941 | B21: 402-2680769-0229941 | C21: 2024-01-30T21:15:36+00:00 | D21: 2024-01-31T04:58:38+00:00 | E21: Shipped | F21: Amazon | G21: Amazon.fr | J21: Standard | K21: Beper - Machine à Pop-Corn, Pop-Corn en 3 Minutes, Sans Matières Grasses, Circulation d'Air Chaud, Puissance 1200W - Rouge [Classe d'efficacité én | L21: 90.590Y_FBA | M21: B01KMJ9OXW | N21: Shipped | O21: 1 | P21: EUR | Q21: 44.9 | Y21: Sospel | AA21: 6380 | AB21: FR | AC21: Free Shipping 2017/10/17 17-17-37-677
A22: 407-2554927-9209102 | B22: 407-2554927-9209102 | C22: 2024-01-30T21:04:08+00:00 | D22: 2024-01-31T12:21:41+00:00 | E22: Shipped | F22: Amazon | G22: Amazon.fr | J22: Standard | K22: Beper - Machine à Pop-Corn, Pop-Corn en 3 Minutes, Sans Matières Grasses, Circulation d'Air Chaud, Puissance 1200W - Rouge [Classe d'efficacité én | L22: 90.590Y_FBA | M22: B01KMJ9OXW | N22: Shipped | O22: 1 | P22: EUR | Q22: 44.9 | Y22: pontcharra | AA22: 38530 | AB22: FR | AC22: Free Shipping 2017/10/17 17-17-37-677
A23: 408-5729419-0856354 | B23: 408-5729419-0856354 | C23: 2024-01-30T19:48:40+00:00 | D23: 2024-01-31T15:53:13+00:00 | E23: Shipped | F23: Amazon | G23: Amazon.fr | J23: Expedited | K23: BEPER BT.710Y Crêpière électrique avec poignée, 800 W, plaque en aluminium avec revêtement antiadhésif, rouge | L23: BT.710Y_FBA | M23: B07NQ2VYGD | N23: Shipped | O23: 1 | P23: EUR | Q23: 39.9 | Y23: PARIS | AA23: 75011 | AB23: FR
A24: 171-3066697-9063548 | B24: 171-3066697-9063548 | C24: 2024-01-30T18:52:31+00:00 | D24: 2024-01-31T12:19:21+00:00 | E24: Shipped | F24: Amazon | G24: Amazon.fr | J24: Standard | K24: BEPER BT.710Y Crêpière électrique avec poignée, 800 W, plaque en aluminium avec revêtement antiadhésif, rouge | L24: BT.710Y_FBA | M24: B07NQ2VYGD | N24: Shipped | O24: 1 | P24: EUR | Q24: 39.9 | Y24: Lapalud | AA24: 84840 | AB24: FR | AC24: Free Shipping 2017/10/17 17-17-37-677
A25: 402-2534146-1417125 | B25: 402-2534146-1417125 | C25: 2024-01-30T18:25:49+00:00 | D25: 2024-02-07T02:20:35+00:00 | E25: Shipped | F25: Amazon | G25: Amazon.fr | J25: Standard | K25: BEPER BT.710Y Crêpière électrique avec poignée, 800 W, plaque en aluminium avec revêtement antiadhésif, rouge | L25: BT.710Y_FBA | M25: B07NQ2VYGD | N25: Shipped | O25: 1 | P25: EUR | Q25: 39.9 | S25: 3.99 | X25: 3.99 | Y25: Paris | AA25: 75014 | AB25: FR | AC25: Free Shipping 2017/10/17 17-17-37-677
A26: 403-1560444-7321108 | B26: 403-1560444-7321108 | C26: 2024-01-30T18:00:18+00:00 | D26: 2024-02-01T18:46:24+00:00 | E26: Shipped | F26: Amazon | G26: Amazon.fr | J26: Standard | K26: BEPER BT.710Y Crêpière électrique avec poignée, 800 W, plaque en aluminium avec revêtement antiadhésif, rouge | L26: BT.710Y_FBA | M26: B07NQ2VYGD | N26: Shipped | O26: 1 | P26: EUR | Q26: 39.9 | S26: 2 | X26: 2 | Y26: PIGNY | Z26: Centre | AA26: 18110 | AB26: FR | AC26: Free Shipping 2017/10/17 17-17-37-677
A27: 407-3854702-0293935 | B27: 407-3854702-0293935 | C27: 2024-01-30T17:43:32+00:00 | D27: 2024-01-30T20:54:54+00:00 | E27: Shipped | F27: Amazon | G27: Amazon.fr | J27: Expedited | K27: BEPER BT.710Y Crêpière électrique avec poignée, 800 W, plaque en aluminium avec revêtement antiadhésif, rouge | L27: BT.710Y_FBA | M27: B07NQ2VYGD | N27: Shipped | O27: 1 | P27: EUR | Q27: 39.9 | Y27: St Soupplets | AA27: 77165 | AB27: FR
A28: 406-7573909-8095551 | B28: 406-7573909-8095551 | C28: 2024-01-30T17:42:03+00:00 | D28: 2024-01-31T08:59:35+00:00 | E28: Shipped | F28: Amazon | G28: Amazon.fr | J28: Expedited | K28: BEPER BT.710Y Crêpière électrique avec poignée, 800 W, plaque en aluminium avec revêtement antiadhésif, rouge | L28: BT.710Y_FBA | M28: B07NQ2VYGD | N28: Shipped | O28: 1 | P28: EUR | Q28: 39.9 | Y28: Sainte marie la mer | AA28: 66470 | AB28: FR
A29: 404-3092103-0753101 | B29: 404-3092103-0753101 | C29: 2024-01-30T17:26:39+00:00 | D29: 2024-01-31T12:51:59+00:00 | E29: Cancelled | F29: Amazon | G29: Amazon.fr | J29: Expedited | K29: BEPER BT.710Y Crêpière électrique avec poignée, 800 W, plaque en aluminium avec revêtement antiadhésif, rouge | L29: BT.710Y_FBA | M29: B07NQ2VYGD | N29: Cancelled | O29: 0 | Y29: ST SOUPPLETS | AA29: 77165 | AB29: FR
A30: 405-0174707-0062737 | B30: 405-0174707-0062737 | C30: 2024-01-30T16:15:58+00:00 | D30: 2024-01-30T20:55:26+00:00 | E30: Shipped | F30: Amazon | G30: Amazon.fr | J30: Standard | K30: Beper - Machine à Pop-Corn, Pop-Corn en 3 Minutes, Sans Matières Grasses, Circulation d'Air Chaud, Puissance 1200W - Rouge [Classe d'efficacité én | L30: 90.590Y_FBA | M30: B01KMJ9OXW | N30: Shipped | O30: 1 | P30: EUR | Q30: 44.9 | Y30: Le Cannet Rocheville | Z30: Sud | AA30: 6110 | AB30: FR | AC30: Free Shipping 2017/10/17 17-17-37-677
A31: 403-1958801-9690746 | B31: 403-1958801-9690746 | C31: 2024-01-30T15:10:38+00:00 | D31: 2024-01-31T05:02:33+00:00 | E31: Shipped | F31: Amazon | G31: Amazon.fr | J31: Standard | K31: BEPER BT.710Y Crêpière électrique avec poignée, 800 W, plaque en aluminium avec revêtement antiadhésif, rouge | L31: BT.710Y_FBA | M31: B07NQ2VYGD | N31: Shipped | O31: 1 | P31: EUR | Q31: 39.9 | Y31: LAVERNOSE lacasse | AA31: 31410 | AB31: FR | AC31: Free Shipping 2017/10/17 17-17-37-677
A32: 405-3145505-5999559 | B32: 405-3145505-5999559 | C32: 2024-01-30T14:53:57+00:00 | D32: 2024-01-31T00:33:17+00:00 | E32: Shipped | F32: Amazon | G32: Amazon.fr | J32: Expedited | K32: BEPER BT.710Y Crêpière électrique avec poignée, 800 W, plaque en aluminium avec revêtement antiadhésif, rouge | L32: BT.710Y_FBA | M32: B07NQ2VYGD | N32: Shipped | O32: 1 | P32: EUR | Q32: 39.9 | Y32: CHELLES | AA32: 77500 | AB32: FR
A33: 407-9216780-6296325 | B33: 407-9216780-6296325 | C33: 2024-01-30T14:39:19+00:00 | D33: 2024-01-31T00:33:18+00:00 | E33: Shipped | F33: Amazon | G33: Amazon.fr | J33: Expedited | K33: BEPER BT.710Y Crêpière électrique avec poignée, 800 W, plaque en aluminium avec revêtement antiadhésif, rouge | L33: BT.710Y_FBA | M33: B07NQ2VYGD | N33: Shipped | O33: 1 | P33: EUR | Q33: 39.9 | Y33: Caudebec Lès Elbeuf | AA33: 76320 | AB33: FR
A34: 406-8231380-3077109 | B34: 406-8231380-3077109 | C34: 2024-01-30T13:57:20+00:00 | D34: 2024-01-31T01:47:16+00:00 | E34: Shipped | F34: Amazon | G34: Amazon.fr | J34: Expedited | K34: BEPER BT.710Y Crêpière électrique avec poignée, 800 W, plaque en aluminium avec revêtement antiadhésif, rouge | L34: BT.710Y_FBA | M34: B07NQ2VYGD | N34: Shipped | O34: 1 | P34: EUR | Q34: 39.9 | Y34: RESTIGNE | AA34: 37140 | AB34: FR
A35: 406-1070790-2301149 | B35: 406-1070790-2301149 | C35: 2024-01-30T13:11:48+00:00 | D35: 2024-01-31T00:33:17+00:00 | E35: Shipped | F35: Amazon | G35: Amazon.fr | J35: Expedited | K35: BEPER BT.710Y Crêpière électrique avec poignée, 800 W, plaque en aluminium avec revêtement antiadhésif, rouge | L35: BT.710Y_FBA | M35: B07NQ2VYGD | N35: Shipped | O35: 1 | P35: EUR | Q35: 39.9 | Y35: Linselles | AA35: 59126 | AB35: FR
A36: 402-8553313-3173166 | B36: 402-8553313-3173166 | C36: 2024-01-30T12:21:36+00:00 | D36: 2024-02-12T08:04:09+00:00 | E36: Shipped | F36: Amazon | G36: Amazon.fr | J36: Standard | K36: Beper - Machine à Pop-Corn, Pop-Corn en 3 Minutes, Sans Matières Grasses, Circulation d'Air Chaud, Puissance 1200W - Rouge [Classe d'efficacité én | L36: 90.590Y_FBA | M36: B01KMJ9OXW | N36: Shipped | O36: 2 | P36: EUR | Q36: 89.8 | S36: 3.99 | X36: 3.99 | Y36: St Pierre Montlimart | AA36: 49110 | AB36: FR | AC36: Free Shipping 2017/10/17 17-17-37-677
A37: 405-3363135-7459552 | B37: 405-3363135-7459552 | C37: 2024-01-30T12:18:04+00:00 | D37: 2024-01-30T20:55:30+00:00 | E37: Shipped | F37: Amazon | G37: Amazon.fr | J37: Expedited | K37: BEPER BT.710Y Crêpière électrique avec poignée, 800 W, plaque en aluminium avec revêtement antiadhésif, rouge | L37: BT.710Y_FBA | M37: B07NQ2VYGD | N37: Shipped | O37: 1 | P37: EUR | Q37: 39.9 | Y37: Draveil | AA37: 91210 | AB37: FR
A38: 405-7404889-1469149 | B38: 405-7404889-1469149 | C38: 2024-01-30T10:32:57+00:00 | D38: 2024-02-01T15:07:39+00:00 | E38: Shipped | F38: Amazon | G38: Amazon.fr | J38: Expedited | K38: BEPER BT.710Y Crêpière électrique avec poignée, 800 W, plaque en aluminium avec revêtement antiadhésif, rouge | L38: BT.710Y_FBA | M38: B07NQ2VYGD | N38: Shipped | O38: 1 | P38: EUR | Q38: 39.9 | Y38: Fos-sur-Mer | AA38: 13270 | AB38: FR
A39: 402-2190183-7726739 | B39: 402-2190183-7726739 | C39: 2024-01-30T10:15:59+00:00 | D39: 2024-02-04T10:19:29+00:00 | E39: Cancelled | F39: Amazon | G39: Amazon.fr | J39: Expedited | K39: BEPER BT.710Y Crêpière électrique avec poignée, 800 W, plaque en aluminium avec revêtement antiadhésif, rouge | L39: BT.710Y_FBA | M39: B07NQ2VYGD | N39: Cancelled | O39: 0 | Y39: WALDOLWISHEIM | AA39: 67700 | AB39: FR
A40: 171-9571645-3937903 | B40: 171-9571645-3937903 | C40: 2024-01-30T09:42:23+00:00 | D40: 2024-01-31T00:38:18+00:00 | E40: Shipped | F40: Amazon | G40: Amazon.fr | J40: Expedited | K40: BEPER BT.710Y Crêpière électrique avec poignée, 800 W, plaque en aluminium avec revêtement antiadhésif, rouge | L40: BT.710Y_FBA | M40: B07NQ2VYGD | N40: Shipped | O40: 1 | P40: EUR | Q40: 39.9 | Y40: rimbach pres masevaux | AA40: 68290 | AB40: FR
A41: 406-6833685-4361110 | B41: 406-6833685-4361110 | C41: 2024-01-30T09:14:53+00:00 | D41: 2024-01-30T20:57:27+00:00 | E41: Shipped | F41: Amazon | G41: Amazon.fr | J41: Expedited | K41: BEPER BT.710Y Crêpière électrique avec poignée, 800 W, plaque en aluminium avec revêtement antiadhésif, rouge | L41: BT.710Y_FBA | M41: B07NQ2VYGD | N41: Shipped | O41: 1 | P41: EUR | Q41: 39.9 | Y41: Noaillac | AA41: 33190 | AB41: FR
A42: 408-3542924-7539510 | B42: 408-3542924-7539510 | C42: 2024-01-30T07:31:47+00:00 | D42: 2024-01-31T04:58:44+00:00 | E42: Shipped | F42: Amazon | G42: Amazon.fr | J42: Standard | K42: Beper - Machine à Pop-Corn, Pop-Corn en 3 Minutes, Sans Matières Grasses, Circulation d'Air Chaud, Puissance 1200W - Rouge [Classe d'efficacité én | L42: 90.590Y_FBA | M42: B01KMJ9OXW | N42: Shipped | O42: 1 | P42: EUR | Q42: 44.9 | Y42: Blagnac | Z42: Sud Ouest | AA42: 31700 | AB42: FR | AC42: Free Shipping 2017/10/17 17-17-37-677
A43: 402-0837085-9839568 | B43: 402-0837085-9839568 | C43: 2024-01-30T00:50:29+00:00 | D43: 2024-01-30T12:06:59+00:00 | E43: Shipped | F43: Amazon | G43: Amazon.fr | J43: Standard | K43: Beper - Machine à Pop-Corn, Pop-Corn en 3 Minutes, Sans Matières Grasses, Circulation d'Air Chaud, Puissance 1200W - Rouge [Classe d'efficacité én | L43: 90.590Y_FBA | M43: B01KMJ9OXW | N43: Shipped | O43: 1 | P43: EUR | Q43: 44.9 | Y43: Aubagne | Z43: Sud | AA43: 13400 | AB43: FR | AC43: Free Shipping 2017/10/17 17-17-37-677
A44: 408-2465957-3177117 | B44: 408-2465957-3177117 | C44: 2024-01-30T00:24:09+00:00 | D44: 2024-01-30T16:35:54+00:00 | E44: Shipped | F44: Amazon | G44: Amazon.fr | J44: Expedited | K44: BEPER BT.710Y Crêpière électrique avec poignée, 800 W, plaque en aluminium avec revêtement antiadhésif, rouge | L44: BT.710Y_FBA | M44: B07NQ2VYGD | N44: Shipped | O44: 1 | P44: EUR | Q44: 39.9 | Y44: Toulouse | AA44: 31200 | AB44: FR
A45: 404-4967350-3455514 | B45: 404-4967350-3455514 | C45: 2024-01-30T00:13:21+00:00 | D45: 2024-01-30T04:21:27+00:00 | E45: Shipped | F45: Amazon | G45: Amazon.fr | J45: Expedited | K45: Beper - Machine à Pop-Corn, Pop-Corn en 3 Minutes, Sans Matières Grasses, Circulation d'Air Chaud, Puissance 1200W - Rouge [Classe d'efficacité én | L45: 90.590Y_FBA | M45: B01KMJ9OXW | N45: Shipped | O45: 1 | P45: EUR | Q45: 44.9 | Y45: Les Ponts-de-Cé | AA45: 49130 | AB45: FR
A46: 408-9181995-9055510 | B46: 408-9181995-9055510 | C46: 2024-01-29T21:43:40+00:00 | D46: 2024-01-30T12:07:44+00:00 | E46: Shipped | F46: Amazon | G46: Amazon.fr | J46: Expedited | K46: BEPER BT.710Y Crêpière électrique avec poignée, 800 W, plaque en aluminium avec revêtement antiadhésif, rouge | L46: BT.710Y_FBA | M46: B07NQ2VYGD | N46: Shipped | O46: 1 | P46: EUR | Q46: 39.9 | Y46: Lyon | AA46: 69006 | AB46: FR
A47: 408-9884586-8157912 | B47: 408-9884586-8157912 | C47: 2024-01-29T21:30:11+00:00 | D47: 2024-01-31T02:34:52+00:00 | E47: Shipped | F47: Amazon | G47: Amazon.fr | J47: Expedited | K47: Beper - Machine à Pop-Corn, Pop-Corn en 3 Minutes, Sans Matières Grasses, Circulation d'Air Chaud, Puissance 1200W - Rouge [Classe d'efficacité én | L47: 90.590Y_FBA | M47: B01KMJ9OXW | N47: Shipped | O47: 1 | P47: EUR | Q47: 44.9 | Y47: MARSEILLE | AA47: 13008 | AB47: FR
A48: 402-7904381-9030763 | B48: 402-7904381-9030763 | C48: 2024-01-29T20:15:54+00:00 | D48: 2024-01-30T00:35:17+00:00 | E48: Shipped | F48: Amazon | G48: Amazon.fr | J48: Expedited | K48: BEPER BT.710Y Crêpière électrique avec poignée, 800 W, plaque en aluminium avec revêtement antiadhésif, rouge | L48: BT.710Y_FBA | M48: B07NQ2VYGD | N48: Shipped | O48: 1 | P48: EUR | Q48: 39.9 | Y48: Charleville Mezieres | AA48: 8000 | AB48: FR
A49: 402-1582164-3300309 | B49: 402-1582164-3300309 | C49: 2024-01-29T19:55:24+00:00 | D49: 2024-01-30T00:35:15+00:00 | E49: Shipped | F49: Amazon | G49: Amazon.fr | J49: Expedited | K49: BEPER BT.710Y Crêpière électrique avec poignée, 800 W, plaque en aluminium avec revêtement antiadhésif, rouge | L49: BT.710Y_FBA | M49: B07NQ2VYGD | N49: Shipped | O49: 1 | P49: EUR | Q49: 39.9 | Y49: Caen | AA49: 14000 | AB49: FR
A50: 408-2028799-3096326 | B50: 408-2028799-3096326 | C50: 2024-01-29T19:54:28+00:00 | D50: 2024-01-30T12:07:44+00:00 | E50: Shipped | F50: Amazon | G50: Amazon.fr | J50: Standard | K50: BEPER BT.710Y Crêpière électrique avec poignée, 800 W, plaque en aluminium avec revêtement antiadhésif, rouge | L50: BT.710Y_FBA | M50: B07NQ2VYGD | N50: Shipped | O50: 1 | P50: EUR | Q50: 39.9 | Y50: GARDANNE | AA50: 13120 | AB50: FR | AC50: Free Shipping 2017/10/17 17-17-37-677
A51: 407-1957420-2940324 | B51: 407-1957420-2940324 | C51: 2024-01-29T19:35:03+00:00 | D51: 2024-01-30T12:07:32+00:00 | E51: Shipped | F51: Amazon | G51: Amazon.fr | J51: Expedited | K51: BEPER BT.710Y Crêpière électrique avec poignée, 800 W, plaque en aluminium avec revêtement antiadhésif, rouge | L51: BT.710Y_FBA | M51: B07NQ2VYGD | N51: Shipped | O51: 1 | P51: EUR | Q51: 39.9 | Y51: villaines les prevotes | AA51: 21500 | AB51: FR
A52: 402-9498380-7261919 | B52: 402-9498380-7261919 | C52: 2024-01-29T19:01:04+00:00 | D52: 2024-01-30T12:17:06+00:00 | E52: Shipped | F52: Amazon | G52: Amazon.fr | J52: Standard | K52: BEPER BT.710Y Crêpière électrique avec poignée, 800 W, plaque en aluminium avec revêtement antiadhésif, rouge | L52: BT.710Y_FBA | M52: B07NQ2VYGD | N52: Shipped | O52: 1 | P52: EUR | Q52: 39.9 | Y52: Aubigny Sur Nere | AA52: 18700 | AB52: FR | AC52: Free Shipping 2017/10/17 17-17-37-677
A53: 403-3783802-9499522 | B53: 403-3783802-9499522 | C53: 2024-01-29T17:40:14+00:00 | D53: 2024-01-30T05:49:55+00:00 | E53: Shipped | F53: Amazon | G53: Amazon.fr | J53: Expedited | K53: BEPER BT.710Y Crêpière électrique avec poignée, 800 W, plaque en aluminium avec revêtement antiadhésif, rouge | L53: BT.710Y_FBA | M53: B07NQ2VYGD | N53: Shipped | O53: 1 | P53: EUR | Q53: 39.9 | Y53: Tassin La Demi Lune | AA53: 69160 | AB53: FR
A54: 408-7736349-1761101 | B54: 408-7736349-1761101 | C54: 2024-01-29T16:58:31+00:00 | D54: 2024-02-13T17:53:38+00:00 | E54: Shipped | F54: Amazon | G54: Amazon.fr | J54: Standard | K54: BEPER BT.710Y Crêpière électrique avec poignée, 800 W, plaque en aluminium avec revêtement antiadhésif, rouge | L54: BT.710Y_FBA | M54: B07NQ2VYGD | N54: Shipped | O54: 1 | P54: EUR | Q54: 39.9 | Y54: FEURS | AA54: 42110 | AB54: FR | AC54: Free Shipping 2017/10/17 17-17-37-677
A55: 403-8060264-5916303 | B55: 403-8060264-5916303 | C55: 2024-01-29T15:44:13+00:00 | D55: 2024-01-30T00:47:24+00:00 | E55: Shipped | F55: Amazon | G55: Amazon.fr | J55: Expedited | K55: Beper - Machine à Pop-Corn, Pop-Corn en 3 Minutes, Sans Matières Grasses, Circulation d'Air Chaud, Puissance 1200W - Rouge [Classe d'efficacité én | L55: 90.590Y_FBA | M55: B01KMJ9OXW | N55: Shipped | O55: 1 | P55: EUR | Q55: 44.9 | Y55: Chanteloup-Les-Vignes | AA55: 78570 | AB55: FR
A56: 406-9457504-3646728 | B56: 406-9457504-3646728 | C56: 2024-01-29T15:32:48+00:00 | D56: 2024-01-29T21:05:35+00:00 | E56: Shipped | F56: Amazon | G56: Amazon.fr | J56: Standard | K56: BEPER BT.710Y Crêpière électrique avec poignée, 800 W, plaque en aluminium avec revêtement antiadhésif, rouge | L56: BT.710Y_FBA | M56: B07NQ2VYGD | N56: Shipped | O56: 1 | P56: EUR | Q56: 39.9 | Y56: Strasbourg | AA56: 67000 | AB56: FR | AC56: Free Shipping 2017/10/17 17-17-37-677
A57: 402-8585425-2188343 | B57: 402-8585425-2188343 | C57: 2024-01-29T15:27:15+00:00 | D57: 2024-01-30T00:39:19+00:00 | E57: Shipped | F57: Amazon | G57: Amazon.fr | J57: Expedited | K57: Beper - Machine à Pop-Corn, Pop-Corn en 3 Minutes, Sans Matières Grasses, Circulation d'Air Chaud, Puissance 1200W - Rouge [Classe d'efficacité én | L57: 90.590Y_FBA | M57: B01KMJ9OXW | N57: Shipped | O57: 1 | P57: EUR | Q57: 44.9 | Y57: Paris | AA57: 75014 | AB57: FR
A58: 405-8457661-8961954 | B58: 405-8457661-8961954 | C58: 2024-01-29T15:02:21+00:00 | D58: 2024-01-30T22:24:21+00:00 | E58: Shipped | F58: Amazon | G58: Amazon.fr | J58: Standard | K58: BEPER BT.710Y Crêpière électrique avec poignée, 800 W, plaque en aluminium avec revêtement antiadhésif, rouge | L58: BT.710Y_FBA | M58: B07NQ2VYGD | N58: Shipped | O58: 1 | P58: EUR | Q58: 39.9 | S58: 0.6 | X58: 0.6 | Y58: Maurage | AA58: 7110 | AB58: BE | AC58: Free Shipping 2017/10/17 17-17-37-677
A59: 406-7484648-8952363 | B59: 406-7484648-8952363 | C59: 2024-01-29T14:21:26+00:00 | D59: 2024-01-30T00:36:31+00:00 | E59: Shipped | F59: Amazon | G59: Amazon.fr | J59: Expedited | K59: BEPER BT.710Y Crêpière électrique avec poignée, 800 W, plaque en aluminium avec revêtement antiadhésif, rouge | L59: BT.710Y_FBA | M59: B07NQ2VYGD | N59: Shipped | O59: 1 | P59: EUR | Q59: 39.9 | Y59: Paris | AA59: 75008 | AB59: FR
A60: 405-2778255-3151560 | B60: 405-2778255-3151560 | C60: 2024-01-29T14:19:51+00:00 | D60: 2024-01-29T21:07:01+00:00 | E60: Shipped | F60: Amazon | G60: Amazon.fr | J60: Standard | K60: BEPER BT.710Y Crêpière électrique avec poignée, 800 W, plaque en aluminium avec revêtement antiadhésif, rouge | L60: BT.710Y_FBA | M60: B07NQ2VYGD | N60: Shipped | O60: 1 | P60: EUR | Q60: 39.9 | Y60: Malataverne | AA60: 26780 | AB60: FR | AC60: Free Shipping 2017/10/17 17-17-37-677
A61: 407-6614282-1973100 | B61: 407-6614282-1973100 | C61: 2024-01-29T13:53:56+00:00 | D61: 2024-01-30T00:36:28+00:00 | E61: Shipped | F61: Amazon | G61: Amazon.fr | J61: Expedited | K61: BEPER BT.710Y Crêpière électrique avec poignée, 800 W, plaque en aluminium avec revêtement antiadhésif, rouge | L61: BT.710Y_FBA | M61: B07NQ2VYGD | N61: Shipped | O61: 1 | P61: EUR | Q61: 39.9 | Y61: Villiers sur marne | AA61: 94350 | AB61: FR
A62: 405-9776344-5603504 | B62: 405-9776344-5603504 | C62: 2024-01-29T13:37:47+00:00 | D62: 2024-02-06T15:24:18+00:00 | E62: Shipped | F62: Amazon | G62: Amazon.fr | J62: Expedited | K62: Beper - Machine à Pop-Corn, Pop-Corn en 3 Minutes, Sans Matières Grasses, Circulation d'Air Chaud, Puissance 1200W - Rouge [Classe d'efficacité én | L62: 90.590Y_FBA | M62: B01KMJ9OXW | N62: Shipped | O62: 1 | P62: EUR | Q62: 44.9 | Y62: Sollies Toucas | AA62: 83210 | AB62: FR
A63: 171-1700949-8625129 | B63: 171-1700949-8625129 | C63: 2024-01-29T13:30:24+00:00 | D63: 2024-01-30T01:58:37+00:00 | E63: Shipped | F63: Amazon | G63: Amazon.fr | J63: Expedited | K63: Beper - Machine à Pop-Corn, Pop-Corn en 3 Minutes, Sans Matières Grasses, Circulation d'Air Chaud, Puissance 1200W - Rouge [Classe d'efficacité én | L63: 90.590Y_FBA | M63: B01KMJ9OXW | N63: Shipped | O63: 1 | P63: EUR | Q63: 44.9 | Y63: Marseille | AA63: 13011 | AB63: FR
A64: 407-9083625-8677153 | B64: 407-9083625-8677153 | C64: 2024-01-29T13:11:27+00:00 | D64: 2024-01-29T21:04:10+00:00 | E64: Shipped | F64: Amazon | G64: Amazon.fr | J64: Expedited | K64: BEPER BT.710Y Crêpière électrique avec poignée, 800 W, plaque en aluminium avec revêtement antiadhésif, rouge | L64: BT.710Y_FBA | M64: B07NQ2VYGD | N64: Shipped | O64: 1 | P64: EUR | Q64: 39.9 | Y64: LAMANON | AA64: 13113 | AB64: FR
A65: 406-1728854-8564338 | B65: 406-1728854-8564338 | C65: 2024-01-29T12:14:20+00:00 | D65: 2024-01-29T12:18:51+00:00 | E65: Cancelled | F65: Amazon | G65: Amazon.fr | J65: Standard | K65: BEPER BT.710Y Crêpière électrique avec poignée, 800 W, plaque en aluminium avec revêtement antiadhésif, rouge | L65: BT.710Y_FBA | M65: B07NQ2VYGD | N65: Cancelled | O65: 0 | Y65: GOURNAY EN BRAY | AA65: 76220 | AB65: FR
A66: 408-7807528-2215511 | B66: 408-7807528-2215511 | C66: 2024-01-29T11:05:33+00:00 | D66: 2024-01-29T21:07:04+00:00 | E66: Shipped | F66: Amazon | G66: Amazon.fr | J66: Expedited | K66: BEPER BT.710Y Crêpière électrique avec poignée, 800 W, plaque en aluminium avec revêtement antiadhésif, rouge | L66: BT.710Y_FBA | M66: B07NQ2VYGD | N66: Shipped | O66: 1 | P66: EUR | Q66: 39.9 | Y66: Lyon | AA66: 69004 | AB66: FR
A67: 403-8110519-9474757 | B67: 403-8110519-9474757 | C67: 2024-01-29T10:20:19+00:00 | D67: 2024-01-29T21:04:09+00:00 | E67: Shipped | F67: Amazon | G67: Amazon.fr | J67: Standard | K67: BEPER BT.710Y Crêpière électrique avec poignée, 800 W, plaque en aluminium avec revêtement antiadhésif, rouge | L67: BT.710Y_FBA | M67: B07NQ2VYGD | N67: Shipped | O67: 1 | P67: EUR | Q67: 39.9 | Y67: roquefort la Bedoule | AA67: 13830 | AB67: FR | AC67: Free Shipping 2017/10/17 17-17-37-677
A68: 403-6624575-4861131 | B68: 403-6624575-4861131 | C68: 2024-01-29T10:10:05+00:00 | D68: 2024-01-29T22:44:01+00:00 | E68: Shipped | F68: Amazon | G68: Amazon.fr | J68: Expedited | K68: Beper - Cuiseur à Vapeur Multicombustion de 5L, Économiseur d'Espace, Minuterie de 60 minutes, Cuisson à la Vapeur Saine, Puissance 400-500W - Arge | L68: BC.261_FBA | M68: B08485QRVZ | N68: Shipped | O68: 1 | P68: EUR | Q68: 39.9 | Y68: PARCIEUX | AA68: 1600 | AB68: FR
A69: 402-9902156-4904360 | B69: 402-9902156-4904360 | C69: 2024-01-29T10:03:40+00:00 | D69: 2024-01-30T00:36:29+00:00 | E69: Shipped | F69: Amazon | G69: Amazon.fr | J69: Expedited | K69: BEPER BT.710Y Crêpière électrique avec poignée, 800 W, plaque en aluminium avec revêtement antiadhésif, rouge | L69: BT.710Y_FBA | M69: B07NQ2VYGD | N69: Shipped | O69: 1 | P69: EUR | Q69: 39.9 | Y69: Paris | AA69: 75017 | AB69: FR
A70: 405-3692450-1421158 | B70: 405-3692450-1421158 | C70: 2024-01-29T09:16:08+00:00 | D70: 2024-03-01T10:40:19+00:00 | E70: Shipped | F70: Amazon | G70: Amazon.fr | J70: Standard | K70: BEPER P102ROB001 Hachoir en verre, récipient en verre, corps Abs, double paire de lames en acier, 2 vitesses, base antidérapante, capacité 1,5 L, g | L70: P102ROB001_FBA | M70: B08KSBDTQD | N70: Shipped | O70: 1 | P70: EUR | Q70: 49.9 | S70: 1.33 | X70: 1.33 | Y70: Luçon | Z70: France | AA70: 85400 | AB70: FR | AC70: Free Shipping 2017/10/17 17-17-37-677
A71: 408-9188321-0836360 | B71: 408-9188321-0836360 | C71: 2024-01-29T09:16:05+00:00 | D71: 2024-01-29T12:21:17+00:00 | E71: Shipped | F71: Amazon | G71: Amazon.fr | J71: Expedited | K71: BEPER BT.710Y Crêpière électrique avec poignée, 800 W, plaque en aluminium avec revêtement antiadhésif, rouge | L71: BT.710Y_FBA | M71: B07NQ2VYGD | N71: Shipped | O71: 1 | P71: EUR | Q71: 39.9 | Y71: Samoens | AA71: 74340 | AB71: FR
A72: 404-1648665-2689169 | B72: 404-1648665-2689169 | C72: 2024-01-29T07:42:57+00:00 | D72: 2024-01-29T12:21:36+00:00 | E72: Shipped | F72: Amazon | G72: Amazon.fr | J72: Standard | K72: Beper - Machine à Pop-Corn, Pop-Corn en 3 Minutes, Sans Matières Grasses, Circulation d'Air Chaud, Puissance 1200W - Rouge [Classe d'efficacité én | L72: 90.590Y_FBA | M72: B01KMJ9OXW | N72: Shipped | O72: 1 | P72: EUR | Q72: 44.9 | S72: 2.99 | X72: 2.99 | Y72: capellen | AA72: 8313 | AB72: LU | AC72: Free Shipping 2017/10/17 17-17-37-677
A73: 406-0359279-6618700 | B73: 406-0359279-6618700 | C73: 2024-01-28T21:36:25+00:00 | D73: 2024-01-29T04:32:40+00:00 | E73: Shipped | F73: Amazon | G73: Amazon.fr | J73: Standard | K73: BEPER BT.710Y Crêpière électrique avec poignée, 800 W, plaque en aluminium avec revêtement antiadhésif, rouge | L73: BT.710Y_FBA | M73: B07NQ2VYGD | N73: Shipped | O73: 1 | P73: EUR | Q73: 39.9 | S73: 3.99 | X73: 3.99 | Y73: St Maur Des Fosses | AA73: 94210 | AB73: FR | AC73: Free Shipping 2017/10/17 17-17-37-677
A74: 403-6154612-6626757 | B74: 403-6154612-6626757 | C74: 2024-01-28T20:18:39+00:00 | D74: 2024-01-29T12:19:29+00:00 | E74: Shipped | F74: Amazon | G74: Amazon.fr | J74: Standard | K74: Beper - Machine à Pop-Corn, Pop-Corn en 3 Minutes, Sans Matières Grasses, Circulation d'Air Chaud, Puissance 1200W - Rouge [Classe d'efficacité én | L74: 90.590Y_FBA | M74: B01KMJ9OXW | N74: Shipped | O74: 1 | P74: EUR | Q74: 44.9 | S74: 3.99 | X74: 3.99 | Y74: MARSANEIX | AA74: 24750 | AB74: FR | AC74: Free Shipping 2017/10/17 17-17-37-677
A75: 404-7721453-4273900 | B75: 404-7721453-4273900 | C75: 2024-01-28T20:06:45+00:00 | D75: 2024-01-29T02:23:21+00:00 | E75: Shipped | F75: Amazon | G75: Amazon.fr | J75: Standard | K75: BEPER BT.150Y Machine à Hot Dog, 750W, 5 levels de Cuissons, Design Vintage, Rouge | L75: BT.150Y_FBA | M75: B07BB2DQ4V | N75: Shipped | O75: 1 | P75: EUR | Q75: 49.9 | U75: 2.99 | Y75: Brignais | AA75: 69530 | AB75: FR | AC75: Free Shipping 2017/10/17 17-17-37-677
A76: 405-5722633-9685956 | B76: 405-5722633-9685956 | C76: 2024-01-28T20:01:20+00:00 | D76: 2024-01-30T02:35:26+00:00 | E76: Shipped | F76: Amazon | G76: Amazon.fr | J76: Standard | K76: Beper - Machine à Pop-Corn, Pop-Corn en 3 Minutes, Sans Matières Grasses, Circulation d'Air Chaud, Puissance 1200W - Rouge [Classe d'efficacité én | L76: 90.590Y_FBA | M76: B01KMJ9OXW | N76: Shipped | O76: 1 | P76: EUR | Q76: 44.9 | S76: 2 | X76: 2 | Y76: FAMECK | AA76: 57290 | AB76: FR | AC76: Free Shipping 2017/10/17 17-17-37-677
A77: 402-2794699-0975559 | B77: 402-2794699-0975559 | C77: 2024-01-28T19:46:34+00:00 | D77: 2024-01-28T22:56:24+00:00 | E77: Shipped | F77: Amazon | G77: Amazon.fr | J77: Standard | K77: BEPER BT.710Y Crêpière électrique avec poignée, 800 W, plaque en aluminium avec revêtement antiadhésif, rouge | L77: BT.710Y_FBA | M77: B07NQ2VYGD | N77: Shipped | O77: 1 | P77: EUR | Q77: 39.9 | Y77: VIDAUBAN | AA77: 83550 | AB77: FR | AC77: Free Shipping 2017/10/17 17-17-37-677
A78: 403-9336058-0719531 | B78: 403-9336058-0719531 | C78: 2024-01-28T19:09:30+00:00 | D78: 2024-01-29T16:38:10+00:00 | E78: Shipped | F78: Amazon | G78: Amazon.fr | J78: Expedited | K78: Beper BF.640 - Four ventilé multifonction 12L Anneau de rallonge pour capacité totale 18L Minuterie 60 minutes Température réglable jusqu'à 250° | L78: BF.640_FBA | M78: B07YBN2FS3 | N78: Shipped | O78: 1 | P78: EUR | Q78: 99 | Y78: Ste Alauzie | Z78: Castelnau montratier | AA78: 46170 | AB78: FR
A79: 405-4908837-3059524 | B79: 405-4908837-3059524 | C79: 2024-01-28T18:38:41+00:00 | D79: 2024-01-29T04:33:53+00:00 | E79: Shipped | F79: Amazon | G79: Amazon.fr | J79: Standard | K79: BEPER BT.710Y Crêpière électrique avec poignée, 800 W, plaque en aluminium avec revêtement antiadhésif, rouge | L79: BT.710Y_FBA | M79: B07NQ2VYGD | N79: Shipped | O79: 1 | P79: EUR | Q79: 39.9 | S79: 3.99 | X79: 3.99 | Y79: Aix-en-Provence | AA79: 13080 | AB79: FR | AC79: Free Shipping 2017/10/17 17-17-37-677
A80: 405-7551949-6333926 | B80: 405-7551949-6333926 | C80: 2024-01-28T17:47:59+00:00 | D80: 2024-01-29T12:25:43+00:00 | E80: Shipped | F80: Amazon | G80: Amazon.fr | J80: Expedited | K80: Beper - Machine à Pop-Corn, Pop-Corn en 3 Minutes, Sans Matières Grasses, Circulation d'Air Chaud, Puissance 1200W - Rouge [Classe d'efficacité én | L80: 90.590Y_FBA | M80: B01KMJ9OXW | N80: Shipped | O80: 1 | P80: EUR | Q80: 44.9 | Y80: Coudun | AA80: 60150 | AB80: FR
A81: 406-7828393-6015543 | B81: 406-7828393-6015543 | C81: 2024-01-28T17:34:37+00:00 | D81: 2024-01-29T04:35:26+00:00 | E81: Shipped | F81: Amazon | G81: Amazon.fr | J81: Expedited | K81: BEPER BT.710Y Crêpière électrique avec poignée, 800 W, plaque en aluminium avec revêtement antiadhésif, rouge | L81: BT.710Y_FBA | M81: B07NQ2VYGD | N81: Shipped | O81: 1 | P81: EUR | Q81: 39.9 | Y81: Mornant | AA81: 69440 | AB81: FR
A82: 171-4382994-1810756 | B82: 171-4382994-1810756 | C82: 2024-01-28T17:24:42+00:00 | D82: 2024-01-29T05:03:59+00:00 | E82: Shipped | F82: Amazon | G82: Amazon.fr | J82: Expedited | K82: BEPER BT.710Y Crêpière électrique avec poignée, 800 W, plaque en aluminium avec revêtement antiadhésif, rouge | L82: BT.710Y_FBA | M82: B07NQ2VYGD | N82: Shipped | O82: 1 | P82: EUR | Q82: 39.9 | Y82: MONCAUT | AA82: 47310 | AB82: FR
A83: 405-0753049-2877900 | B83: 405-0753049-2877900 | C83: 2024-01-28T16:43:09+00:00 | D83: 2024-01-29T00:32:52+00:00 | E83: Shipped | F83: Amazon | G83: Amazon.fr | J83: Expedited | K83: BEPER BT.710Y Crêpière électrique avec poignée, 800 W, plaque en aluminium avec revêtement antiadhésif, rouge | L83: BT.710Y_FBA | M83: B07NQ2VYGD | N83: Shipped | O83: 1 | P83: EUR | Q83: 39.9 | Y83: Coignieres | Z83: Yvelines | AA83: 78310 | AB83: FR
A84: 407-9231546-8774749 | B84: 407-9231546-8774749 | C84: 2024-01-28T16:01:21+00:00 | D84: 2024-01-29T12:19:58+00:00 | E84: Shipped | F84: Amazon | G84: Amazon.fr | J84: Standard | K84: BEPER BT.710Y Crêpière électrique avec poignée, 800 W, plaque en aluminium avec revêtement antiadhésif, rouge | L84: BT.710Y_FBA | M84: B07NQ2VYGD | N84: Shipped | O84: 1 | P84: EUR | Q84: 39.9 | Y84: Olivet | AA84: 45160 | AB84: FR | AC84: Free Shipping 2017/10/17 17-17-37-677
A85: 406-7141477-0919520 | B85: 406-7141477-0919520 | C85: 2024-01-28T14:15:31+00:00 | D85: 2024-01-28T22:54:45+00:00 | E85: Shipped | F85: Amazon | G85: Amazon.fr | J85: Expedited | K85: BEPER BT.710Y Crêpière électrique avec poignée, 800 W, plaque en aluminium avec revêtement antiadhésif, rouge | L85: BT.710Y_FBA | M85: B07NQ2VYGD | N85: Shipped | O85: 1 | P85: EUR | Q85: 39.9 | Y85: Thorigny Sur Oreuse | AA85: 89260 | AB85: FR
A86: 402-8785122-7117929 | B86: 402-8785122-7117929 | C86: 2024-01-28T14:12:25+00:00 | D86: 2024-01-28T22:56:23+00:00 | E86: Shipped | F86: Amazon | G86: Amazon.fr | J86: Expedited | K86: BEPER BT.710Y Crêpière électrique avec poignée, 800 W, plaque en aluminium avec revêtement antiadhésif, rouge | L86: BT.710Y_FBA | M86: B07NQ2VYGD | N86: Shipped | O86: 1 | P86: EUR | Q86: 39.9 | Y86: baron | AA86: 33750 | AB86: FR
A87: 405-3271429-6253166 | B87: 405-3271429-6253166 | C87: 2024-01-28T14:11:28+00:00 | D87: 2024-01-30T20:58:03+00:00 | E87: Shipped | F87: Amazon | G87: Amazon.fr | J87: Standard | K87: BEPER BT.710Y Crêpière électrique avec poignée, 800 W, plaque en aluminium avec revêtement antiadhésif, rouge | L87: BT.710Y_FBA | M87: B07NQ2VYGD | N87: Shipped | O87: 1 | P87: EUR | Q87: 39.9 | Y87: FRENEUSE | AA87: 78840 | AB87: FR | AC87: Free Shipping 2017/10/17 17-17-37-677
A88: 404-6442413-2764368 | B88: 404-6442413-2764368 | C88: 2024-01-28T13:57:02+00:00 | D88: 2024-01-29T12:19:58+00:00 | E88: Shipped | F88: Amazon | G88: Amazon.fr | J88: Standard | K88: BEPER BT.710Y Crêpière électrique avec poignée, 800 W, plaque en aluminium avec revêtement antiadhésif, rouge | L88: BT.710Y_FBA | M88: B07NQ2VYGD | N88: Shipped | O88: 1 | P88: EUR | Q88: 39.9 | Y88: Le Mans | AA88: 72000 | AB88: FR | AC88: Free Shipping 2017/10/17 17-17-37-677
A89: 407-5249642-5201168 | B89: 407-5249642-5201168 | C89: 2024-01-28T12:17:57+00:00 | D89: 2024-01-29T00:32:22+00:00 | E89: Shipped | F89: Amazon | G89: Amazon.fr | J89: Expedited | K89: BEPER BT.710Y Crêpière électrique avec poignée, 800 W, plaque en aluminium avec revêtement antiadhésif, rouge | L89: BT.710Y_FBA | M89: B07NQ2VYGD | N89: Shipped | O89: 1 | P89: EUR | Q89: 39.9 | Y89: COUME | AA89: 57220 | AB89: FR
A90: 403-8062366-8746710 | B90: 403-8062366-8746710 | C90: 2024-01-28T12:12:34+00:00 | D90: 2024-01-29T09:30:48+00:00 | E90: Shipped | F90: Amazon | G90: Amazon.fr | J90: Expedited | K90: Beper - Machine à Pop-Corn, Pop-Corn en 3 Minutes, Sans Matières Grasses, Circulation d'Air Chaud, Puissance 1200W - Rouge [Classe d'efficacité én | L90: 90.590Y_FBA | M90: B01KMJ9OXW | N90: Shipped | O90: 1 | P90: EUR | Q90: 44.9 | Y90: ST PIERRE D IRUBE | AA90: 64990 | AB90: FR
A91: 403-4838167-0769155 | B91: 403-4838167-0769155 | C91: 2024-01-28T12:05:58+00:00 | D91: 2024-01-28T17:04:42+00:00 | E91: Cancelled | F91: Amazon | G91: Amazon.fr | J91: Expedited | K91: BEPER BT.710Y Crêpière électrique avec poignée, 800 W, plaque en aluminium avec revêtement antiadhésif, rouge | L91: BT.710Y_FBA | M91: B07NQ2VYGD | N91: Cancelled | O91: 0 | Y91: Nogent sur marne | AA91: 94130 | AB91: FR
A92: 171-4176070-2405914 | B92: 171-4176070-2405914 | C92: 2024-01-28T10:43:07+00:00 | D92: 2024-01-29T00:34:30+00:00 | E92: Shipped | F92: Amazon | G92: Amazon.fr | J92: Expedited | K92: Beper - Cuiseur à Vapeur Multicombustion de 5L, Économiseur d'Espace, Minuterie de 60 minutes, Cuisson à la Vapeur Saine, Puissance 400-500W - Arge | L92: BC.261_FBA | M92: B08485QRVZ | N92: Shipped | O92: 1 | P92: EUR | Q92: 39.9 | Y92: Vieux Conde | AA92: 59690 | AB92: FR
A93: 403-9827706-8451539 | B93: 403-9827706-8451539 | C93: 2024-01-28T10:16:12+00:00 | D93: 2024-01-28T21:56:02+00:00 | E93: Shipped | F93: Amazon | G93: Amazon.fr | J93: Expedited | K93: BEPER BT.710Y Crêpière électrique avec poignée, 800 W, plaque en aluminium avec revêtement antiadhésif, rouge | L93: BT.710Y_FBA | M93: B07NQ2VYGD | N93: Shipped | O93: 1 | P93: EUR | Q93: 39.9 | Y93: Cogolin | AA93: 83310 | AB93: FR
A94: 404-9727000-2441923 | B94: 404-9727000-2441923 | C94: 2024-01-28T09:33:58+00:00 | D94: 2024-01-29T00:36:38+00:00 | E94: Shipped | F94: Amazon | G94: Amazon.fr | J94: Expedited | K94: BEPER BT.710Y Crêpière électrique avec poignée, 800 W, plaque en aluminium avec revêtement antiadhésif, rouge | L94: BT.710Y_FBA | M94: B07NQ2VYGD | N94: Shipped | O94: 1 | P94: EUR | Q94: 39.9 | Y94: Goussainville | AA94: 95190 | AB94: FR
A95: 408-9767081-4783515 | B95: 408-9767081-4783515 | C95: 2024-01-28T09:08:57+00:00 | D95: 2024-01-29T12:20:08+00:00 | E95: Shipped | F95: Amazon | G95: Amazon.fr | J95: Expedited | K95: BEPER BT.710Y Crêpière électrique avec poignée, 800 W, plaque en aluminium avec revêtement antiadhésif, rouge | L95: BT.710Y_FBA | M95: B07NQ2VYGD | N95: Shipped | O95: 1 | P95: EUR | Q95: 39.9 | Y95: ISLE | AA95: 87170 | AB95: FR
A96: 402-5714183-9694725 | B96: 402-5714183-9694725 | C96: 2024-01-28T08:15:08+00:00 | D96: 2024-01-28T16:19:34+00:00 | E96: Shipped | F96: Amazon | G96: Amazon.fr | J96: Expedited | K96: BEPER BT.710Y Crêpière électrique avec poignée, 800 W, plaque en aluminium avec revêtement antiadhésif, rouge | L96: BT.710Y_FBA | M96: B07NQ2VYGD | N96: Shipped | O96: 1 | P96: EUR | Q96: 39.9 | Y96: Saint lys | AA96: 31470 | AB96: FR
A97: 406-2852817-8193917 | B97: 406-2852817-8193917 | C97: 2024-01-27T22:41:53+00:00 | D97: 2024-01-28T22:56:11+00:00 | E97: Shipped | F97: Amazon | G97: Amazon.fr | J97: Expedited | K97: BEPER BT.710Y Crêpière électrique avec poignée, 800 W, plaque en aluminium avec revêtement antiadhésif, rouge | L97: BT.710Y_FBA | M97: B07NQ2VYGD | N97: Shipped | O97: 1 | P97: EUR | Q97: 39.9 | Y97: Consac | Z97: France | AA97: 17150 | AB97: FR
A98: 404-7281320-2313163 | B98: 404-7281320-2313163 | C98: 2024-01-27T22:37:31+00:00 | D98: 2024-01-28T04:53:46+00:00 | E98: Shipped | F98: Amazon | G98: Amazon.fr | J98: Standard | K98: BEPER BT.710Y Crêpière électrique avec poignée, 800 W, plaque en aluminium avec revêtement antiadhésif, rouge | L98: BT.710Y_FBA | M98: B07NQ2VYGD | N98: Shipped | O98: 1 | P98: EUR | Q98: 39.9 | Y98: Mezens | Z98: Occitanie | AA98: 81800 | AB98: FR | AC98: Free Shipping 2017/10/17 17-17-37-677
A99: 405-6521990-4162751 | B99: 405-6521990-4162751 | C99: 2024-01-27T22:25:52+00:00 | D99: 2024-01-28T22:54:50+00:00 | E99: Shipped | F99: Amazon | G99: Amazon.fr | J99: Expedited | K99: BEPER BT.710Y Crêpière électrique avec poignée, 800 W, plaque en aluminium avec revêtement antiadhésif, rouge | L99: BT.710Y_FBA | M99: B07NQ2VYGD | N99: Shipped | O99: 1 | P99: EUR | Q99: 39.9 | Y99: LANDAUL | AA99: 56690 | AB99: FR
A100: 408-4010216-7086751 | B100: 408-4010216-7086751 | C100: 2024-01-27T20:56:49+00:00 | D100: 2024-01-28T22:56:12+00:00 | E100: Shipped | F100: Amazon | G100: Amazon.fr | J100: Standard | K100: BEPER BT.710Y Crêpière électrique avec poignée, 800 W, plaque en aluminium avec revêtement antiadhésif, rouge | L100: BT.710Y_FBA | M100: B07NQ2VYGD | N100: Shipped | O100: 1 | P100: EUR | Q100: 39.9 | Y100: Massy | Z100: Essonne | AA100: 91300 | AB100: FR | AC100: Free Shipping 2017/10/17 17-17-37-677
...

Sheet v_2023
A1: Codice marketplace | B1: (Tutto) | F1: Codice marketplace | G1: IT
A3: ASIN | B3: Numero del modello | C3: Somma di Unità ordinate | D3: Somma di Ricavi ordini | F3: ASIN | G3: Numero del modello | H3: Somma di Unità ordinate | I3: Somma di Ricavi ordini
A4: B0050IHH4E | B4: 40.979 | C4: 14 | D4: 182.42 | F4: B0050IHH4E | G4: 40.979 | H4: 14 | I4: 182.42
A5: B00BH202XK | B5: 40.808A | C5: 1 | D5: 20.59 | F5: B00BH202XK | G5: 40.808A | H5: 1 | I5: 20.59
A6: B00C5CCJP0 | B6: 40.993 | C6: 8 | D6: 121.8 | F6: B00CMAD2FG | G6: HK-NV009W | H6: 1 | I6: 19.69
A7: B00CMAD2FG | B7: HK-NV009W | C7: 2 | D7: 34.18 | F7: B00EYDRS1I | G7: 90.349 | H7: 109 | I7: 755.85
A8: B00EYDRS1I | B8: 90.349 | C8: 119 | D8: 828.55 | F8: B00EYF02AU | G8: 90.502 | H8: 0 | I8: 0
A9: B00EYF02AU | B9: 90.502 | C9: 0 | D9: 0 | F9: B00FAJUDU8 | G9: 40.967N | H9: 165 | I9: 3367.65
A10: B00EZ4185S | B10: RI.501SL | C10: 1 | D10: 119.51 | F10: B00FFBFVG2 | G10: 40.100 | H10: 9 | I10: 71.49
A11: B00FAJUDU8 | B11: 40.967N | C11: 302 | D11: 6543.96 | F11: B00L5GPWFG | G11: 40.120 | H11: 20 | I11: 325.84
A12: B00FFBED98 | B12: 40.11 | C12: 1 | D12: 28.03 | F12: B00L5H5KUW | G12: 40.121 | H12: 258 | I12: 4379.44
A13: B00FFBFVG2 | B13: 40.100 | C13: 13 | D13: 104.24 | F13: B00NSNZSLM | G13: 90.602 | H13: 388 | I13: 7919.08
A14: B00J7MNQFS | B14: 40.994 | C14: 0 | D14: 0 | F14: B00OKE4RTM | G14: 90.386 | H14: 7 | I14: 364.33
A15: B00L5GPWFG | B15: 40.120 | C15: 20 | D15: 325.84 | F15: B00OLZPU5K | G15: 40.947 | H15: 7 | I15: 71.13
... A207: B08MM2VK11 | B207: P302MAS001 | C207: 13 | D207: 376.61 | F207: B0BRQB2J4B | G207: PET005 | H207: 9 | I207: 36.18
A208: B08MX1SQKC | B208: P302VIS001 | C208: 154 | D208: 1887.5 | F208: Totale complessivo | H208: 31233 | I208: 477924.76
A209: B08NDZKNF5 | B209: P102CON001 | C209: 35 | D209: 1010.82
A210: B08NF8TQKT | B210: P102FRU100 | C210: 9 | D210: 220.59
A211: B08NTD853X | B211: P102SBA006 | C211: 21 | D211: 172.9
A212: B08V4VTTQN | B212: C107UTT001 | C212: 27 | D212: 191.08
A213: B08X4VZV3S | B213: P303BIP001 | C213: 1 | D213: 10.57
A214: B08XQT9P5C | B214: P102GEL001 | C214: 5 | D214: 194.29
A215: B08XVV3PVK | B215: P303MED001 | C215: 4 | D215: 45
A216: B09146GTKW | B216: P302VIS002 | C216: 4056 | D216: 33322.03
A217: B091C5XQZN | B217: P202ASP001 | C217: 3 | D217: 168.63
A218: B091LRR67V | B218: P101FRI050 | C218: 66 | D218: 4251.64
A219: B091VSY78C | B219: P303BIP050 | C219: 0 | D219: 0
A220: B09251R9RJ | B220: P304CAP001 | C220: 5 | D220: 81.96
... A295: B0BRQB2J4B | B295: PET005 | C295: 13 | D295: 52.36
A296: Totale complessivo | C296: 51985 | D296: 814456.16

Sheet v_2024
A1: Codice marketplace | B1: (Tutto) | F1: Codice marketplace | G1: IT
A3: ASIN | B3: Numero del modello | C3: Somma di Unità ordinate | D3: Somma di Ricavi ordini | F3: ASIN | G3: Numero del modello | H3: Somma di Unità ordinate | I3: Somma di Ricavi ordini
A4: B0050IHH4E | B4: 40.979 | C4: 1183 | D4: 16822.21 | F4: B0050IHH4E | G4: 40.979 | H4: 486 | I4: 6983.03
A5: B009O92WU4 | B5: 40.999 | C5: 1 | D5: 5.03 | F5: B00BH202XK | G5: 40.808A | H5: 6 | I5: 83.1
A6: B00BH202XK | B6: 40.808A | C6: 10 | D6: 127.35 | F6: B00EYDRS1I | G6: 90.349 | H6: 36 | I6: 211.74
A7: B00CMAD2FG | B7: HK-NV009W | C7: 1 | D7: 15.18 | F7: B00FFBFVG2 | G7: 40.100 | H7: 0 | I7: 0
A8: B00EYDRS1I | B8: 90.349 | C8: 48 | D8: 271.81 | F8: B00L5GPWFG | G8: 40.120 | H8: 6 | I8: 147.9
A9: B00FFBFVG2 | B9: 40.100 | C9: 0 | D9: 0 | F9: B00L5H5KUW | G9: 40.121 | H9: 275 | I9: 5023.29
A10: B00FMZ2VW8 | B10: HK-HQ601C PINK | C10: 0 | D10: 0 | F10: B00NSNZSLM | G10: 90.602 | H10: 1 | I10: 20.41
A11: B00L5GPWFG | B11: 40.120 | C11: 6 | D11: 147.9 | F11: B00OKE4RTM | G11: 90.386 | H11: 2 | I11: 98.08
A12: B00L5H5KUW | B12: 40.121 | C12: 275 | D12: 5023.29 | F12: B00YH3FRV8 | G12: 40.998 | H12: 1 | I12: 7.43
A13: B00NSNZSLM | B13: 90.602 | C13: 1 | D13: 20.41 | F13: B011LFM60E | G13: 40.948T | H13: 2 | I13: 12.96
A14: B00OKE4RTM | B14: 90.386 | C14: 2 | D14: 98.08 | F14: B011LFVLW8 | G14: 90.620 | H14: 19 | I14: 686.19
A15: B00YH3FRV8 | B15: 40.998 | C15: 1 | D15: 7.43 | F15: B017IUJA50 | G15: 90.920G | H15: 15 | I15: 209.45
... A201: B097785V2V | B201: P202VAL110 | C201: 1 | D201: 5.42 | F201: B0CXJCJF5B | G201: P101PIA003 | H201: 8 | I201: 117.36
A202: B0978ZKW4S | B202: P205DIF100 | C202: 35 | D202: 428.14 | F202: Totale complessivo | H202: 6632 | I202: 104761.64
A203: B097F45J2B | B203: P102FRU500 | C203: 2 | D203: 65.4
A204: B097HRQNRG | B204: P101FRI100 | C204: 5 | D204: 150.29
A205: B097YTGFH7 | B205: P102ROB200 | C205: 22 | D205: 1103.13
A206: B098F33WBD | B206: RCO4091819 | C206: 21 | D206: 2.93
A207: B098QM485T | B207: P101CUD050 | C207: 5 | D207: 208.96
A208: B09968BKDS | B208: P102FRU003 | C208: 243 | D208: 3443.57
A209: B09B15P5H1 | B209: P102FRU200 | C209: 6 | D209: 91.74
A210: B09B2NT2SV | B210: P102FRU150 | C210: 9 | D210: 194.04
A211: B09B47S644 | B211: P101CUD501 | C211: 79 | D211: 2302.19
A212: B09BBFTDLJ | B212: P101TOS501 | C212: 1 | D212: 61.57
A213: B09BD8BG34 | B213: P301PIS001 | C213: 188 | D213: 2349.32
A214: B09BG1GGSM | B214: P204FER003 | C214: 0 | D214: 0
... A284: B0CXJCJF5B | B284: P101PIA003 | C284: 13 | D284: 191.49
A285: Totale complessivo | C285: 13774 | D285: 219396.13

Sheet s_2024
A1: sales-channel | B1: (Tutto) | E1: sales-channel | F1: Amazon.it
A3: Etichette di riga | B3: Somma di quantity | C3: Somma di item-price | E3: Etichette di riga | F3: Somma di quantity | G3: Somma di item-price
A4: B0050IHH4E | B4: 3 | C4: 60.7 | E4: B0050IHH4E | F4: 3 | G4: 60.7
A5: B00FAJUDU8 | B5: 27 | C5: 822.3 | E5: B00FAJUDU8 | F5: 27 | G5: 822.3
A6: B00NSNZSLM | B6: 48 | C6: 1440.2 | E6: B00NSNZSLM | F6: 48 | G6: 1440.2
A7: B01CNX704K | B7: 6 | C7: 281.4 | E7: B01CNX704K | F7: 6 | G7: 281.4
A8: B01I497WWM | B8: 534 | C8: 10674.53 | E8: B01I497WWM | F8: 534 | G8: 10674.53
A9: B01KMJ9OXW | B9: 394 | C9: 14503.53 | E9: B01KMJ9OXW | F9: 317 | G9: 11062.43
A10: B01MTSEGF9 | B10: 8 | C10: 432.8 | E10: B01MTSEGF9 | F10: 8 | G10: 432.8
A11: B06Y17FS6D | B11: 1 | E11: B06Y195DJN | F11: 18 | G11: 898.2
A12: B06Y195DJN | B12: 18 | C12: 898.2 | E12: B0757TJRR9 | F12: 385 | G12: 12660.57
A13: B0757TJRR9 | B13: 388 | C13: 12795.27 | E13: B076D74TC7 | F13: 1 | G13: 36.99
A14: B076D74TC7 | B14: 1 | C14: 36.99 | E14: B076DCKSTJ | F14: 35 | G14: 871.5
A15: B076DCKSTJ | B15: 36 | C15: 906.4 | E15: B07BB2DQ4V | F15: 8 | G15: 377.4
A16: B07BB2DQ4V | B16: 13 | C16: 626.9 | E16: B07HM7P6MP | F16: 17 | G16: 542.99
A17: B07HM7P6MP | B17: 17 | C17: 542.99 | E17: B07N4C3H3V | F17: 44 | G17: 652.91
A18: B07N4C3H3V | B18: 45 | C18: 672.81 | E18: B07NQ2VYGD | F18: 229 | G18: 6838.12
A19: B07NQ2VYGD | B19: 365 | C19: 12257.32 | E19: B07NQC6S9V | F19: 16 | G19: 798.4
A20: B07NQC6S9V | B20: 20 | C20: 1038 | E20: B07P7GGGQM | F20: 19 | G20: 1138.1
A21: B07P7GGGQM | B21: 19 | C21: 1138.1 | E21: B07TVSJDCL | F21: 1 | G21: 15.9
A22: B07TVSJDCL | B22: 1 | C22: 15.9 | E22: B07V131F5W | F22: 104 | G22: 3109.6
A23: B07V131F5W | B23: 104 | C23: 3109.6 | E23: B07YBN2FS3 | F23: 26 | G23: 2077.4
... A40: B0B8DLSNJF | B40: 17 | C40: 418.81 | E40: Totale complessivo | F40: 2257 | G40: 67095.84
A41: Totale complessivo | B41: 2497 | C41: 77269.54

Sheet pivot
A3: ASIN | B3: SKU | C3: Somma di Ordini Vendor 24 | D3: Somma di Valori ordini Vendor 24 | E3: Somma di Ordini Seller 24 | F3: Somma di Valori ordini Seller 24 | G3: Somma di Ordini Complessivi 24 | H3: Somma di Valori ordini Complessivi 24 | I3: Somma di Ordini Vendor 23 | J3: Somma di Valori ordini Vendor 23
A4: B0050IHH4E | B4: 40.979 | C4: 1183 | D4: 16822.21 | E4: 3 | F4: 60.7 | G4: 1186 | H4: 16882.91 | I4: 14 | J4: 182.42
A5: B009O92WU4 | B5: 40.999 | C5: 1 | D5: 5.03 | E5: 0 | F5: 0 | G5: 1 | H5: 5.03 | I5: 0 | J5: 0
A6: B00BH202XK | B6: 40.808A | C6: 10 | D6: 127.35 | E6: 0 | F6: 0 | G6: 10 | H6: 127.35 | I6: 1 | J6: 20.59
A7: B00C5CCJP0 | B7: 40.993 | C7: 0 | D7: 0 | E7: 0 | F7: 0 | G7: 0 | H7: 0 | I7: 8 | J7: 121.8
A8: B00CMAD2FG | B8: HK-NV009W | C8: 1 | D8: 15.18 | E8: 0 | F8: 0 | G8: 1 | H8: 15.18 | I8: 2 | J8: 34.18
A9: B00EYDRS1I | B9: 90.349 | C9: 48 | D9: 271.81 | E9: 0 | F9: 0 | G9: 48 | H9: 271.81 | I9: 119 | J9: 828.55
A10: B00EYF02AU | B10: 90.502 | C10: 0 | D10: 0 | E10: 0 | F10: 0 | G10: 0 | H10: 0 | I10: 0 | J10: 0
A11: B00EZ4185S | B11: RI.501SL | C11: 0 | D11: 0 | E11: 0 | F11: 0 | G11: 0 | H11: 0 | I11: 1 | J11: 119.51
A12: B00FAJUDU8 | B12: 40.967N | C12: 0 | D12: 0 | E12: 27 | F12: 822.3 | G12: 27 | H12: 822.3 | I12: 302 | J12: 6543.96
A13: B00FFBED98 | B13: 40.11 | C13: 0 | D13: 0 | E13: 0 | F13: 0 | G13: 0 | H13: 0 | I13: 1 | J13: 28.03
A14: B00FFBFVG2 | B14: 40.100 | C14: 0 | D14: 0 | E14: 0 | F14: 0 | G14: 0 | H14: 0 | I14: 13 | J14: 104.24
A15: B00FMZ2VW8 | B15: HK-HQ601C PINK | C15: 0 | D15: 0 | E15: 0 | F15: 0 | G15: 0 | H15: 0 | I15: 0 | J15: 0
... A362: Totale complessivo | B362: Totale complessivo | C362: 13774 | D362: 219396.13 | E362: 2497 | F362: 77269.54 | G362: 16271 | H362: 296665.67 | I362: 51985 | J362: 814456.16
A363: Totale complessivo | C363: 27548 | D363: 438792.26 | E363: 4994 | F363: 154539.08 | G363: 32542 | H363: 593331.34 | I363: 103970 | J363: 1628912.3

Sheet IT
A1: ASIN | B1: SKU | C1: Ordini Vendor 24 | D1: Valori ordini Vendor 24 | E1: Ordini Seller 24 | F1: Valori ordini Seller 24 | G1: % seller / totale | H1: Ordini Complessivi 24 | I1: Valori ordini Complessivi 24 | J1: Ordini Vendor 23 | K1: Valori ordini Vendor 23 | L1: Differenza Ordini | M1: Differenza Valore | N1: Differenza Valore %
A2: B0050IHH4E | B2: 40.979 | C2: =VLOOKUP(A2,v_2024!F:I,3,FALSE) -> 486 | D2: =VLOOKUP(A2,v_2024!F:I,4,FALSE) -> 6983.03 | E2: =VLOOKUP(A2,s_2024!E:G,2,FALSE) -> 3 | F2: =VLOOKUP(A2,s_2024!E:G,3,FALSE) -> 60.7 | G2: =F2/I2 -> 0.0086175932 | H2: =E2+C2 -> 489 | I2: =F2+D2 -> 7043.73 | J2: =VLOOKUP(A2,v_2023!F:I,3,FALSE) -> 14 | K2: =VLOOKUP(A2,v_2023!F:I,4,FALSE) -> 182.42 | L2: =H2-J2 -> 475 | M2: =I2-K2 -> 6861.31 | N2: =M2/K2 -> 37.612707
A3: B009O92WU4 | B3: 40.999 | C3: 0 | D3: 0 | E3: 0 | F3: 0 | H3: =E3+C3 -> 0 | I3: =F3+D3 -> 0 | J3: 0 | K3: 0 | L3: =H3-J3 -> 0 | M3: =I3-K3 -> 0
A4: B00BH202XK | B4: 40.808A | C4: =VLOOKUP(A4,v_2024!F:I,3,FALSE) -> 6 | D4: =VLOOKUP(A4,v_2024!F:I,4,FALSE) -> 83.1 | E4: 0 | F4: 0 | G4: =F4/I4 -> 0 | H4: =E4+C4 -> 6 | I4: =F4+D4 -> 83.1 | J4: =VLOOKUP(A4,v_2023!F:I,3,FALSE) -> 1 | K4: =VLOOKUP(A4,v_2023!F:I,4,FALSE) -> 20.59 | L4: =H4-J4 -> 5 | M4: =I4-K4 -> 62.51 | N4: =M4/K4 -> 3.0359398
A5: B00CMAD2FG | B5: HK-NV009W | C5: 0 | D5: 0 | E5: 0 | F5: 0 | H5: =E5+C5 -> 0 | I5: =F5+D5 -> 0 | J5: =VLOOKUP(A5,v_2023!F:I,3,FALSE) -> 1 | K5: =VLOOKUP(A5,v_2023!F:I,4,FALSE) -> 19.69 | L5: =H5-J5 -> -1 | M5: =I5-K5 -> -19.69 | N5: =M5/K5 -> -1
A6: B00EYDRS1I | B6: 90.349 | C6: =VLOOKUP(A6,v_2024!F:I,3,FALSE) -> 36 | D6: =VLOOKUP(A6,v_2024!F:I,4,FALSE) -> 211.74 | E6: 0 | F6: 0 | G6: =F6/I6 -> 0 | H6: =E6+C6 -> 36 | I6: =F6+D6 -> 211.74 | J6: =VLOOKUP(A6,v_2023!F:I,3,FALSE) -> 109 | K6: =VLOOKUP(A6,v_2023!F:I,4,FALSE) -> 755.85 | L6: =H6-J6 -> -73 | M6: =I6-K6 -> -544.11 | N6: =M6/K6 -> -0.71986505
A7: B00FFBFVG2 | B7: 40.100 | C7: =VLOOKUP(A7,v_2024!F:I,3,FALSE) -> 0 | D7: =VLOOKUP(A7,v_2024!F:I,4,FALSE) -> 0 | E7: 0 | F7: 0 | H7: =E7+C7 -> 0 | I7: =F7+D7 -> 0 | J7: =VLOOKUP(A7,v_2023!F:I,3,FALSE) -> 9 | K7: =VLOOKUP(A7,v_2023!F:I,4,FALSE) -> 71.49 | L7: =H7-J7 -> -9 | M7: =I7-K7 -> -71.49 | N7: =M7/K7 -> -1
A8: B00FMZ2VW8 | B8: HK-HQ601C PINK | C8: 0 | D8: 0 | E8: 0 | F8: 0 | H8: =E8+C8 -> 0 | I8: =F8+D8 -> 0 | J8: 0 | K8: 0 | L8: =H8-J8 -> 0 | M8: =I8-K8 -> 0
A9: B00L5GPWFG | B9: 40.120 | C9: =VLOOKUP(A9,v_2024!F:I,3,FALSE) -> 6 | D9: =VLOOKUP(A9,v_2024!F:I,4,FALSE) -> 147.9 | E9: 0 | F9: 0 | G9: =F9/I9 -> 0 | H9: =E9+C9 -> 6 | I9: =F9+D9 -> 147.9 | J9: =VLOOKUP(A9,v_2023!F:I,3,FALSE) -> 20 | K9: =VLOOKUP(A9,v_2023!F:I,4,FALSE) -> 325.84 | L9: =H9-J9 -> -14 | M9: =I9-K9 -> -177.94 | N9: =M9/K9 -> -0.54609624
A10: B00L5H5KUW | B10: 40.121 | C10: =VLOOKUP(A10,v_2024!F:I,3,FALSE) -> 275 | D10: =VLOOKUP(A10,v_2024!F:I,4,FALSE) -> 5023.29 | E10: 0 | F10: 0 | G10: =F10/I10 -> 0 | H10: =E10+C10 -> 275 | I10: =F10+D10 -> 5023.29 | J10: =VLOOKUP(A10,v_2023!F:I,3,FALSE) -> 258 | K10: =VLOOKUP(A10,v_2023!F:I,4,FALSE) -> 4379.44 | L10: =H10-J10 -> 17 | M10: =I10-K10 -> 643.85 | N10: =M10/K10 -> 0.14701651
A11: B00NSNZSLM | B11: 90.602 | C11: =VLOOKUP(A11,v_2024!F:I,3,FALSE) -> 1 | D11: =VLOOKUP(A11,v_2024!F:I,4,FALSE) -> 20.41 | E11: =VLOOKUP(A11,s_2024!E:G,2,FALSE) -> 48 | F11: =VLOOKUP(A11,s_2024!E:G,3,FALSE) -> 1440.2 | G11: =F11/I11 -> 0.98602639 | H11: =E11+C11 -> 49 | I11: =F11+D11 -> 1460.61 | J11: =VLOOKUP(A11,v_2023!F:I,3,FALSE) -> 388 | K11: =VLOOKUP(A11,v_2023!F:I,4,FALSE) -> 7919.08 | L11: =H11-J11 -> -339 | M11: =I11-K11 -> -6458.47 | N11: =M11/K11 -> -0.81555812
A12: B00OKE4RTM | B12: 90.386 | C12: =VLOOKUP(A12,v_2024!F:I,3,FALSE) -> 2 | D12: =VLOOKUP(A12,v_2024!F:I,4,FALSE) -> 98.08 | E12: 0 | F12: 0 | G12: =F12/I12 -> 0 | H12: =E12+C12 -> 2 | I12: =F12+D12 -> 98.08 | J12: =VLOOKUP(A12,v_2023!F:I,3,FALSE) -> 7 | K12: =VLOOKUP(A12,v_2023!F:I,4,FALSE) -> 364.33 | L12: =H12-J12 -> -5 | M12: =I12-K12 -> -266.25 | N12: =M12/K12 -> -0.73079351
A13: B00YH3FRV8 | B13: 40.998 | C13: =VLOOKUP(A13,v_2024!F:I,3,FALSE) -> 1 | D13: =VLOOKUP(A13,v_2024!F:I,4,FALSE) -> 7.43 | E13: 0 | F13: 0 | G13: =F13/I13 -> 0 | H13: =E13+C13 -> 1 | I13: =F13+D13 -> 7.43 | J13: 0 | K13: 0 | L13: =H13-J13 -> 1 | M13: =I13-K13 -> 7.43
A14: B011LFM60E | B14: 40.948T | C14: =VLOOKUP(A14,v_2024!F:I,3,FALSE) -> 2 | D14: =VLOOKUP(A14,v_2024!F:I,4,FALSE) -> 12.96 | E14: 0 | F14: 0 | G14: =F14/I14 -> 0 | H14: =E14+C14 -> 2 | I14: =F14+D14 -> 12.96 | J14: 0 | K14: 0 | L14: =H14-J14 -> 2 | M14: =I14-K14 -> 12.96
A15: B011LFVLW8 | B15: 90.620 | C15: =VLOOKUP(A15,v_2024!F:I,3,FALSE) -> 19 | D15: =VLOOKUP(A15,v_2024!F:I,4,FALSE) -> 686.19 | E15: 0 | F15: 0 | G15: =F15/I15 -> 0 | H15: =E15+C15 -> 19 | I15: =F15+D15 -> 686.19 | J15: =VLOOKUP(A15,v_2023!F:I,3,FALSE) -> 99 | K15: =VLOOKUP(A15,v_2023!F:I,4,FALSE) -> 2832.39 | L15: =H15-J15 -> -80 | M15: =I15-K15 -> -2146.2 | N15: =M15/K15 -> -0.75773463
A16: B017IUJA50 | B16: 90.920G | C16: =VLOOKUP(A16,v_2024!F:I,3,FALSE) -> 15 | D16: =VLOOKUP(A16,v_2024!F:I,4,FALSE) -> 209.45 | E16: 0 | F16: 0 | G16: =F16/I16 -> 0 | H16: =E16+C16 -> 15 | I16: =F16+D16 -> 209.45 | J16: =VLOOKUP(A16,v_2023!F:I,3,FALSE) -> 1487 | K16: =VLOOKUP(A16,v_2023!F:I,4,FALSE) -> 19352.55 | L16: =H16-J16 -> -1472 | M16: =I16-K16 -> -19143.1 | N16: =M16/K16 -> -0.98917714
A17: B01CHW1L88 | B17: PE.001 | C17: =VLOOKUP(A17,v_2024!F:I,3,FALSE) -> 1 | D17: =VLOOKUP(A17,v_2024!F:I,4,FALSE) -> 15.05 | E17: 0 | F17: 0 | G17: =F17/I17 -> 0 | H17: =E17+C17 -> 1 | I17: =F17+D17 -> 15.05 | J17: 0 | K17: 0 | L17: =H17-J17 -> 1 | M17: =I17-K17 -> 15.05
A18: B01CNX6T10 | B18: PE.165 | C18: 0 | D18: 0 | E18: 0 | F18: 0 | H18: =E18+C18 -> 0 | I18: =F18+D18 -> 0 | J18: 0 | K18: 0 | L18: =H18-J18 -> 0 | M18: =I18-K18 -> 0
A19: B01CNX6UIM | B19: PE.300 | C19: =VLOOKUP(A19,v_2024!F:I,3,FALSE) -> 0 | D19: =VLOOKUP(A19,v_2024!F:I,4,FALSE) -> 0 | E19: 0 | F19: 0 | H19: =E19+C19 -> 0 | I19: =F19+D19 -> 0 | J19: 0 | K19: 0 | L19: =H19-J19 -> 0 | M19: =I19-K19 -> 0
A20: B01CNX6Z78 | B20: 90.820 | C20: 0 | D20: 0 | E20: 0 | F20: 0 | H20: =E20+C20 -> 0 | I20: =F20+D20 -> 0 | J20: 0 | K20: 0 | L20: =H20-J20 -> 0 | M20: =I20-K20 -> 0
A21: B01CNX704K | B21: 90.825 | C21: 0 | D21: 0 | E21: =VLOOKUP(A21,s_2024!E:G,2,FALSE) -> 6 | F21: =VLOOKUP(A21,s_2024!E:G,3,FALSE) -> 281.4 | G21: =F21/I21 -> 1 | H21: =E21+C21 -> 6 | I21: =F21+D21 -> 281.4 | J21: 0 | K21: 0 | L21: =H21-J21 -> 6 | M21: =I21-K21 -> 281.4
A22: B01CNX71NA | B22: 90.871 | C22: =VLOOKUP(A22,v_2024!F:I,3,FALSE) -> 1 | D22: =VLOOKUP(A22,v_2024!F:I,4,FALSE) -> 86.86 | E22: 0 | F22: 0 | G22: =F22/I22 -> 0 | H22: =E22+C22 -> 1 | I22: =F22+D22 -> 86.86 | J22: =VLOOKUP(A22,v_2023!F:I,3,FALSE) -> 3 | K22: =VLOOKUP(A22,v_2023!F:I,4,FALSE) -> 238.42 | L22: =H22-J22 -> -2 | M22: =I22-K22 -> -151.56 | N22: =M22/K22 -> -0.63568493
A23: B01HM47LF8 | B23: MD.004 | C23: =VLOOKUP(A23,v_2024!F:I,3,FALSE) -> 2 | D23: =VLOOKUP(A23,v_2024!F:I,4,FALSE) -> 7.25 | E23: 0 | F23: 0 | G23: =F23/I23 -> 0 | H23: =E23+C23 -> 2 | I23: =F23+D23 -> 7.25 | J23: =VLOOKUP(A23,v_2023!F:I,3,FALSE) -> 13 | K23: =VLOOKUP(A23,v_2023!F:I,4,FALSE) -> 44.07 | L23: =H23-J23 -> -11 | M23: =I23-K23 -> -36.82 | N23: =M23/K23 -> -0.83548899
A24: B01I497WWM | B24: 90.920R | C24: =VLOOKUP(A24,v_2024!F:I,3,FALSE) -> 14 | D24: =VLOOKUP(A24,v_2024!F:I,4,FALSE) -> 260.2 | E24: =VLOOKUP(A24,s_2024!E:G,2,FALSE) -> 534 | F24: =VLOOKUP(A24,s_2024!E:G,3,FALSE) -> 10674.53 | G24: =F24/I24 -> 0.97620426 | H24: =E24+C24 -> 548 | I24: =F24+D24 -> 10934.73 | J24: =VLOOKUP(A24,v_2023!F:I,3,FALSE) -> 2922 | K24: =VLOOKUP(A24,v_2023!F:I,4,FALSE) -> 34319.58 | L24: =H24-J24 -> -2374 | M24: =I24-K24 -> -23384.85 | N24: =M24/K24 -> -0.68138509
A25: B01IHGX2HQ | B25: MD.104 | C25: =VLOOKUP(A25,v_2024!F:I,3,FALSE) -> 14 | D25: =VLOOKUP(A25,v_2024!F:I,4,FALSE) -> 58.41 | E25: 0 | F25: 0 | G25: =F25/I25 -> 0 | H25: =E25+C25 -> 14 | I25: =F25+D25 -> 58.41 | J25: =VLOOKUP(A25,v_2023!F:I,3,FALSE) -> 9 | K25: =VLOOKUP(A25,v_2023!F:I,4,FALSE) -> 37.22 | L25: =H25-J25 -> 5 | M25: =I25-K25 -> 21.19 | N25: =M25/K25 -> 0.56931757
A26: B01II7S968 | B26: MD.217 | C26: 0 | D26: 0 | E26: 0 | F26: 0 | H26: =E26+C26 -> 0 | I26: =F26+D26 -> 0 | J26: =VLOOKUP(A26,v_2023!F:I,3,FALSE) -> 7 | K26: =VLOOKUP(A26,v_2023!F:I,4,FALSE) -> 42.76 | L26: =H26-J26 -> -7 | M26: =I26-K26 -> -42.76 | N26: =M26/K26 -> -1
A27: B01KMJ9OXW | B27: 90.590Y | C27: =VLOOKUP(A27,v_2024!F:I,3,FALSE) -> 1 | D27: =VLOOKUP(A27,v_2024!F:I,4,FALSE) -> 35.32 | E27: =VLOOKUP(A27,s_2024!E:G,2,FALSE) -> 317 | F27: =VLOOKUP(A27,s_2024!E:G,3,FALSE) -> 11062.43 | G27: =F27/I27 -> 0.99681737 | H27: =E27+C27 -> 318 | I27: =F27+D27 -> 11097.75 | J27: =VLOOKUP(A27,v_2023!F:I,3,FALSE) -> 597 | K27: =VLOOKUP(A27,v_2023!F:I,4,FALSE) -> 17144.47 | L27: =H27-J27 -> -279 | M27: =I27-K27 -> -6046.72 | N27: =M27/K27 -> -0.35269215
A28: B01M4O6145 | B28: 90.071 | C28: =VLOOKUP(A28,v_2024!F:I,3,FALSE) -> 37 | D28: =VLOOKUP(A28,v_2024!F:I,4,FALSE) -> 755.17 | E28: 0 | F28: 0 | G28: =F28/I28 -> 0 | H28: =E28+C28 -> 37 | I28: =F28+D28 -> 755.17 | J28: =VLOOKUP(A28,v_2023!F:I,3,FALSE) -> 60 | K28: =VLOOKUP(A28,v_2023!F:I,4,FALSE) -> 1297.24 | L28: =H28-J28 -> -23 | M28: =I28-K28 -> -542.07 | N28: =M28/K28 -> -0.41786408
A29: B01MTSEGF9 | B29: 50.700 | C29: =VLOOKUP(A29,v_2024!F:I,3,FALSE) -> 0 | D29: =VLOOKUP(A29,v_2024!F:I,4,FALSE) -> 0 | E29: =VLOOKUP(A29,s_2024!E:G,2,FALSE) -> 8 | F29: =VLOOKUP(A29,s_2024!E:G,3,FALSE) -> 432.8 | G29: =F29/I29 -> 1 | H29: =E29+C29 -> 8 | I29: =F29+D29 -> 432.8 | J29: =VLOOKUP(A29,v_2023!F:I,3,FALSE) -> 266 | K29: =VLOOKUP(A29,v_2023!F:I,4,FALSE) -> 7610.26 | L29: =H29-J29 -> -258 | M29: =I29-K29 -> -7177.46 | N29: =M29/K29 -> -0.94312941
A30: B01N12PI05 | B30: PE.301 | C30: 0 | D30: 0 | E30: 0 | F30: 0 | H30: =E30+C30 -> 0 | I30: =F30+D30 -> 0 | J30: 0 | K30: 0 | L30: =H30-J30 -> 0 | M30: =I30-K30 -> 0
A31: B06WGS8ZVG | B31: 90.131 | C31: =VLOOKUP(A31,v_2024!F:I,3,FALSE) -> 2 | D31: =VLOOKUP(A31,v_2024!F:I,4,FALSE) -> 27.28 | E31: 0 | F31: 0 | G31: =F31/I31 -> 0 | H31: =E31+C31 -> 2 | I31: =F31+D31 -> 27.28 | J31: =VLOOKUP(A31,v_2023!F:I,3,FALSE) -> 8 | K31: =VLOOKUP(A31,v_2023!F:I,4,FALSE) -> 100.16 | L31: =H31-J31 -> -6 | M31: =I31-K31 -> -72.88 | N31: =M31/K31 -> -0.72763578
A32: B06XPK3BTC | B32: 40.450GO | C32: =VLOOKUP(A32,v_2024!F:I,3,FALSE) -> 2 | D32: =VLOOKUP(A32,v_2024!F:I,4,FALSE) -> 31.65 | E32: 0 | F32: 0 | G32: =F32/I32 -> 0 | H32: =E32+C32 -> 2 | I32: =F32+D32 -> 31.65 | J32: =VLOOKUP(A32,v_2023!F:I,3,FALSE) -> 3 | K32: =VLOOKUP(A32,v_2023!F:I,4,FALSE) -> 48.93 | L32: =H32-J32 -> -1 | M32: =I32-K32 -> -17.28 | N32: =M32/K32 -> -0.35315757
A33: B06XPYSCGJ | B33: 40.939 | C33: =VLOOKUP(A33,v_2024!F:I,3,FALSE) -> 0 | D33: =VLOOKUP(A33,v_2024!F:I,4,FALSE) -> 0 | E33: 0 | F33: 0 | H33: =E33+C33 -> 0 | I33: =F33+D33 -> 0 | J33: =VLOOKUP(A33,v_2023!F:I,3,FALSE) -> 1 | K33: =VLOOKUP(A33,v_2023!F:I,4,FALSE) -> 6.89 | L33: =H33-J33 -> -1 | M33: =I33-K33 -> -6.89 | N33: =M33/K33 -> -1
A34: B06XQ25NLB | B34: 40.220 | C34: 0 | D34: 0 | E34: 0 | F34: 0 | H34: =E34+C34 -> 0 | I34: =F34+D34 -> 0 | J34: 0 | K34: 0 | L34: =H34-J34 -> 0 | M34: =I34-K34 -> 0
A35: B06XSJPGR9 | B35: 50.130 | C35: =VLOOKUP(A35,v_2024!F:I,3,FALSE) -> 0 | D35: =VLOOKUP(A35,v_2024!F:I,4,FALSE) -> 0 | E35: 0 | F35: 0 | H35: =E35+C35 -> 0 | I35: =F35+D35 -> 0 | J35: 0 | K35: 0 | L35: =H35-J35 -> 0 | M35: =I35-K35 -> 0
A36: B06XYMCV3W | B36: 90.485H | C36: =VLOOKUP(A36,v_2024!F:I,3,FALSE) -> 0 | D36: =VLOOKUP(A36,v_2024!F:I,4,FALSE) -> 0 | E36: 0 | F36: 0 | H36: =E36+C36 -> 0 | I36: =F36+D36 -> 0 | J36: 0 | K36: 0 | L36: =H36-J36 -> 0 | M36: =I36-K36 -> 0
A37: B06Y17FS6D | B37: 90.550 | C37: =VLOOKUP(A37,v_2024!F:I,3,FALSE) -> 49 | D37: =VLOOKUP(A37,v_2024!F:I,4,FALSE) -> 1395.95 | E37: 0 | F37: 0 | G37: =F37/I37 -> 0 | H37: =E37+C37 -> 49 | I37: =F37+D37 -> 1395.95 | J37: =VLOOKUP(A37,v_2023!F:I,3,FALSE) -> 586 | K37: =VLOOKUP(A37,v_2023!F:I,4,FALSE) -> 14362.86 | L37: =H37-J37 -> -537 | M37: =I37-K37 -> -12966.91 | N37: =M37/K37 -> -0.90280835
A38: B06Y195DJN | B38: 90.882 | C38: 0 | D38: 0 | E38: =VLOOKUP(A38,s_2024!E:G,2,FALSE) -> 18 | F38: =VLOOKUP(A38,s_2024!E:G,3,FALSE) -> 898.2 | G38: =F38/I38 -> 1 | H38: =E38+C38 -> 18 | I38: =F38+D38 -> 898.2 | J38: 0 | K38: 0 | L38: =H38-J38 -> 18 | M38: =I38-K38 -> 898.2
A39: B06Y1997YH | B39: 90.883 | C39: =VLOOKUP(A39,v_2024!F:I,3,FALSE) -> 11 | D39: =VLOOKUP(A39,v_2024!F:I,4,FALSE) -> 685.1 | E39: 0 | F39: 0 | G39: =F39/I39 -> 0 | H39: =E39+C39 -> 11 | I39: =F39+D39 -> 685.1 | J39: =VLOOKUP(A39,v_2023!F:I,3,FALSE) -> 65 | K39: =VLOOKUP(A39,v_2023!F:I,4,FALSE) -> 3560.59 | L39: =H39-J39 -> -54 | M39: =I39-K39 -> -2875.49 | N39: =M39/K39 -> -0.80758807
A40: B06Y1P6DPZ | B40: VE.112 | C40: 0 | D40: 0 | E40: 0 | F40: 0 | H40: =E40+C40 -> 0 | I40: =F40+D40 -> 0 | J40: 0 | K40: 0 | L40: =H40-J40 -> 0 | M40: =I40-K40 -> 0
A41: B073B67PLQ | B41: 90.884 | C41: =VLOOKUP(A41,v_2024!F:I,3,FALSE) -> 14 | D41: =VLOOKUP(A41,v_2024!F:I,4,FALSE) -> 1136.27 | E41: 0 | F41: 0 | G41: =F41/I41 -> 0 | H41: =E41+C41 -> 14 | I41: =F41+D41 -> 1136.27 | J41: =VLOOKUP(A41,v_2023!F:I,3,FALSE) -> 38 | K41: =VLOOKUP(A41,v_2023!F:I,4,FALSE) -> 2800.22 | L41: =H41-J41 -> -24 | M41: =I41-K41 -> -1663.95 | N41: =M41/K41 -> -0.59422117
A42: B0757TJRR9 | B42: 40.500 | C42: =VLOOKUP(A42,v_2024!F:I,3,FALSE) -> 1 | D42: =VLOOKUP(A42,v_2024!F:I,4,FALSE) -> 26.97 | E42: =VLOOKUP(A42,s_2024!E:G,2,FALSE) -> 385 | F42: =VLOOKUP(A42,s_2024!E:G,3,FALSE) -> 12660.57 | G42: =F42/I42 -> 0.99787429 | H42: =E42+C42 -> 386 | I42: =F42+D42 -> 12687.54 | J42: =VLOOKUP(A42,v_2023!F:I,3,FALSE) -> 304 | K42: =VLOOKUP(A42,v_2023!F:I,4,FALSE) -> 8435.04 | L42: =H42-J42 -> 82 | M42: =I42-K42 -> 4252.5 | N42: =M42/K42 -> 0.50414699
A43: B075FX6RFP | B43: BC.040N | C43: 0 | D43: 0 | E43: 0 | F43: 0 | H43: =E43+C43 -> 0 | I43: =F43+D43 -> 0 | J43: 0 | K43: 0 | L43: =H43-J43 -> 0 | M43: =I43-K43 -> 0
A44: B075K5C2QG | B44: RI.201 | C44: =VLOOKUP(A44,v_2024!F:I,3,FALSE) -> 2 | D44: =VLOOKUP(A44,v_2024!F:I,4,FALSE) -> 40.82 | E44: 0 | F44: 0 | G44: =F44/I44 -> 0 | H44: =E44+C44 -> 2 | I44: =F44+D44 -> 40.82 | J44: =VLOOKUP(A44,v_2023!F:I,3,FALSE) -> -1 | K44: =VLOOKUP(A44,v_2023!F:I,4,FALSE) -> -14.75 | L44: =H44-J44 -> 3 | M44: =I44-K44 -> 55.57 | N44: =M44/K44 -> -3.7674576
A45: B075RF5S3N | B45: BC.160A | C45: =VLOOKUP(A45,v_2024!F:I,3,FALSE) -> 5 | D45: =VLOOKUP(A45,v_2024!F:I,4,FALSE) -> 129.21 | E45: 0 | F45: 0 | G45: =F45/I45 -> 0 | H45: =E45+C45 -> 5 | I45: =F45+D45 -> 129.21 | J45: =VLOOKUP(A45,v_2023!F:I,3,FALSE) -> 19 | K45: =VLOOKUP(A45,v_2023!F:I,4,FALSE) -> 465.69 | L45: =H45-J45 -> -14 | M45: =I45-K45 -> -336.48 | N45: =M45/K45 -> -0.72254075
A46: B075RF8FM9 | B46: BC.160G | C46: =VLOOKUP(A46,v_2024!F:I,3,FALSE) -> 0 | D46: =VLOOKUP(A46,v_2024!F:I,4,FALSE) -> 0 | E46: 0 | F46: 0 | H46: =E46+C46 -> 0 | I46: =F46+D46 -> 0 | J46: =VLOOKUP(A46,v_2023!F:I,3,FALSE) -> 2 | K46: =VLOOKUP(A46,v_2023!F:I,4,FALSE) -> 49.02 | L46: =H46-J46 -> -2 | M46: =I46-K46 -> -49.02 | N46: =M46/K46 -> -1
A47: B075XR3T8V | B47: BT.600Y | C47: 0 | D47: 0 | E47: 0 | F47: 0 | H47: =E47+C47 -> 0 | I47: =F47+D47 -> 0 | J47: 0 | K47: 0 | L47: =H47-J47 -> 0 | M47: =I47-K47 -> 0
A48: B076D74TC7 | B48: BT.700Y | C48: 0 | D48: 0 | E48: =VLOOKUP(A48,s_2024!E:G,2,FALSE) -> 1 | F48: =VLOOKUP(A48,s_2024!E:G,3,FALSE) -> 36.99 | G48: =F48/I48 -> 1 | H48: =E48+C48 -> 1 | I48: =F48+D48 -> 36.99 | J48: 0 | K48: 0 | L48: =H48-J48 -> 1 | M48: =I48-K48 -> 36.99
A49: B076DC4VWG | B49: 40.501 | C49: =VLOOKUP(A49,v_2024!F:I,3,FALSE) -> 0 | D49: =VLOOKUP(A49,v_2024!F:I,4,FALSE) -> 0 | E49: 0 | F49: 0 | H49: =E49+C49 -> 0 | I49: =F49+D49 -> 0 | J49: =VLOOKUP(A49,v_2023!F:I,3,FALSE) -> 2 | K49: =VLOOKUP(A49,v_2023!F:I,4,FALSE) -> 45.58 | L49: =H49-J49 -> -2 | M49: =I49-K49 -> -45.58 | N49: =M49/K49 -> -1
A50: B076DCKSTJ | B50: BT.602H | C50: =VLOOKUP(A50,v_2024!F:I,3,FALSE) -> 3 | D50: =VLOOKUP(A50,v_2024!F:I,4,FALSE) -> 62.39 | E50: =VLOOKUP(A50,s_2024!E:G,2,FALSE) -> 35 | F50: =VLOOKUP(A50,s_2024!E:G,3,FALSE) -> 871.5 | G50: =F50/I50 -> 0.93319342 | H50: =E50+C50 -> 38 | I50: =F50+D50 -> 933.89 | J50: =VLOOKUP(A50,v_2023!F:I,3,FALSE) -> 417 | K50: =VLOOKUP(A50,v_2023!F:I,4,FALSE) -> 8510.97 | L50: =H50-J50 -> -379 | M50: =I50-K50 -> -7577.08 | N50: =M50/K50 -> -0.8902722
A51: B076DCL19C | B51: BP.720 | C51: =VLOOKUP(A51,v_2024!F:I,3,FALSE) -> 17 | D51: =VLOOKUP(A51,v_2024!F:I,4,FALSE) -> 814.3 | E51: 0 | F51: 0 | G51: =F51/I51 -> 0 | H51: =E51+C51 -> 17 | I51: =F51+D51 -> 814.3 | J51: =VLOOKUP(A51,v_2023!F:I,3,FALSE) -> 18 | K51: =VLOOKUP(A51,v_2023!F:I,4,FALSE) -> 1031.4 | L51: =H51-J51 -> -1 | M51: =I51-K51 -> -217.1 | N51: =M51/K51 -> -0.2104906
A52: B076DCX3JH | B52: BB.103 | C52: 0 | D52: 0 | E52: 0 | F52: 0 | H52: =E52+C52 -> 0 | I52: =F52+D52 -> 0 | J52: 0 | K52: 0 | L52: =H52-J52 -> 0 | M52: =I52-K52 -> 0
A53: B076DD26WW | B53: CA.010 | C53: =VLOOKUP(A53,v_2024!F:I,3,FALSE) -> -1 | D53: =VLOOKUP(A53,v_2024!F:I,4,FALSE) -> -5.12 | E53: 0 | F53: 0 | G53: =F53/I53 -> 0 | H53: =E53+C53 -> -1 | I53: =F53+D53 -> -5.12 | J53: 0 | K53: 0 | L53: =H53-J53 -> -1 | M53: =I53-K53 -> -5.12
A54: B076DD35DZ | B54: BC.002 | C54: 0 | D54: 0 | E54: 0 | F54: 0 | H54: =E54+C54 -> 0 | I54: =F54+D54 -> 0 | J54: 0 | K54: 0 | L54: =H54-J54 -> 0 | M54: =I54-K54 -> 0
A55: B076Q7BR6F | B55: BC.041N | C55: =VLOOKUP(A55,v_2024!F:I,3,FALSE) -> 34 | D55: =VLOOKUP(A55,v_2024!F:I,4,FALSE) -> 1525.2 | E55: 0 | F55: 0 | G55: =F55/I55 -> 0 | H55: =E55+C55 -> 34 | I55: =F55+D55 -> 1525.2 | J55: =VLOOKUP(A55,v_2023!F:I,3,FALSE) -> 222 | K55: =VLOOKUP(A55,v_2023!F:I,4,FALSE) -> 9036.6 | L55: =H55-J55 -> -188 | M55: =I55-K55 -> -7511.4 | N55: =M55/K55 -> -0.83121971
A56: B076QCMZX1 | B56: 40.821 | C56: =VLOOKUP(A56,v_2024!F:I,3,FALSE) -> 162 | D56: =VLOOKUP(A56,v_2024!F:I,4,FALSE) -> 1977.32 | E56: 0 | F56: 0 | G56: =F56/I56 -> 0 | H56: =E56+C56 -> 162 | I56: =F56+D56 -> 1977.32 | J56: =VLOOKUP(A56,v_2023!F:I,3,FALSE) -> 2 | K56: =VLOOKUP(A56,v_2023!F:I,4,FALSE) -> 33.9 | L56: =H56-J56 -> 160 | M56: =I56-K56 -> 1943.42 | N56: =M56/K56 -> 57.328024
A57: B076QFRRZ5 | B57: 40.931 | C57: =VLOOKUP(A57,v_2024!F:I,3,FALSE) -> 40 | D57: =VLOOKUP(A57,v_2024!F:I,4,FALSE) -> 573.31 | E57: 0 | F57: 0 | G57: =F57/I57 -> 0 | H57: =E57+C57 -> 40 | I57: =F57+D57 -> 573.31 | J57: =VLOOKUP(A57,v_2023!F:I,3,FALSE) -> 181 | K57: =VLOOKUP(A57,v_2023!F:I,4,FALSE) -> 2670.84 | L57: =H57-J57 -> -141 | M57: =I57-K57 -> -2097.53 | N57: =M57/K57 -> -0.78534469
A58: B079SB5VJZ | B58: 50451 | C58: =VLOOKUP(A58,v_2024!F:I,3,FALSE) -> 2 | D58: =VLOOKUP(A58,v_2024!F:I,4,FALSE) -> 91.63 | E58: 0 | F58: 0 | G58: =F58/I58 -> 0 | H58: =E58+C58 -> 2 | I58: =F58+D58 -> 91.63 | J58: =VLOOKUP(A58,v_2023!F:I,3,FALSE) -> 400 | K58: =VLOOKUP(A58,v_2023!F:I,4,FALSE) -> 13080 | L58: =H58-J58 -> -398 | M58: =I58-K58 -> -12988.37 | N58: =M58/K58 -> -0.99299465
A59: B07B9CBD91 | B59: VE.550 | C59: 0 | D59: 0 | E59: 0 | F59: 0 | H59: =E59+C59 -> 0 | I59: =F59+D59 -> 0 | J59: 0 | K59: 0 | L59: =H59-J59 -> 0 | M59: =I59-K59 -> 0
A60: B07B9CPH62 | B60: BG.200Y | C60: =VLOOKUP(A60,v_2024!F:I,3,FALSE) -> 6 | D60: =VLOOKUP(A60,v_2024!F:I,4,FALSE) -> 294.6 | E60: 0 | F60: 0 | G60: =F60/I60 -> 0 | H60: =E60+C60 -> 6 | I60: =F60+D60 -> 294.6 | J60: =VLOOKUP(A60,v_2023!F:I,3,FALSE) -> 23 | K60: =VLOOKUP(A60,v_2023!F:I,4,FALSE) -> 1118.2 | L60: =H60-J60 -> -17 | M60: =I60-K60 -> -823.6 | N60: =M60/K60 -> -0.73654087
A61: B07BB2DQ4V | B61: BT.150Y | C61: =VLOOKUP(A61,v_2024!F:I,3,FALSE) -> 1 | D61: =VLOOKUP(A61,v_2024!F:I,4,FALSE) -> 33.14 | E61: =VLOOKUP(A61,s_2024!E:G,2,FALSE) -> 8 | F61: =VLOOKUP(A61,s_2024!E:G,3,FALSE) -> 377.4 | G61: =F61/I61 -> 0.91927705 | H61: =E61+C61 -> 9 | I61: =F61+D61 -> 410.54 | J61: =VLOOKUP(A61,v_2023!F:I,3,FALSE) -> 20 | K61: =VLOOKUP(A61,v_2023!F:I,4,FALSE) -> 490.2 | L61: =H61-J61 -> -11 | M61: =I61-K61 -> -79.66 | N61: =M61/K61 -> -0.1625051
A62: B07BHCZR84 | B62: BA.200Y | C62: =VLOOKUP(A62,v_2024!F:I,3,FALSE) -> 22 | D62: =VLOOKUP(A62,v_2024!F:I,4,FALSE) -> 266.22 | E62: 0 | F62: 0 | G62: =F62/I62 -> 0 | H62: =E62+C62 -> 22 | I62: =F62+D62 -> 266.22 | J62: =VLOOKUP(A62,v_2023!F:I,3,FALSE) -> 2 | K62: =VLOOKUP(A62,v_2023!F:I,4,FALSE) -> 26.88 | L62: =H62-J62 -> 20 | M62: =I62-K62 -> 239.34 | N62: =M62/K62 -> 8.9040179
A63: B07BHTW4WV | B63: VE.210 | C63: 0 | D63: 0 | E63: 0 | F63: 0 | H63: =E63+C63 -> 0 | I63: =F63+D63 -> 0 | J63: 0 | K63: 0 | L63: =H63-J63 -> 0 | M63: =I63-K63 -> 0
A64: B07CZ4WMB8 | B64: 40.330 | C64: 0 | D64: 0 | E64: 0 | F64: 0 | H64: =E64+C64 -> 0 | I64: =F64+D64 -> 0 | J64: 0 | K64: 0 | L64: =H64-J64 -> 0 | M64: =I64-K64 -> 0
A65: B07F187NFQ | B65: 50.900 | C65: =VLOOKUP(A65,v_2024!F:I,3,FALSE) -> 1 | D65: =VLOOKUP(A65,v_2024!F:I,4,FALSE) -> 3.77 | E65: 0 | F65: 0 | G65: =F65/I65 -> 0 | H65: =E65+C65 -> 1 | I65: =F65+D65 -> 3.77 | J65: 0 | K65: 0 | L65: =H65-J65 -> 1 | M65: =I65-K65 -> 3.77
A66: B07FN14FSN | B66: 50.160 | C66: 0 | D66: 0 | E66: 0 | F66: 0 | H66: =E66+C66 -> 0 | I66: =F66+D66 -> 0 | J66: 0 | K66: 0 | L66: =H66-J66 -> 0 | M66: =I66-K66 -> 0
A67: B07HFPYL56 | B67: BC.353 | C67: 0 | D67: 0 | E67: 0 | F67: 0 | H67: =E67+C67 -> 0 | I67: =F67+D67 -> 0 | J67: 0 | K67: 0 | L67: =H67-J67 -> 0 | M67: =I67-K67 -> 0
A68: B07HFQH172 | B68: BC.250 | C68: 0 | D68: 0 | E68: 0 | F68: 0 | H68: =E68+C68 -> 0 | I68: =F68+D68 -> 0 | J68: 0 | K68: 0 | L68: =H68-J68 -> 0 | M68: =I68-K68 -> 0
A69: B07HHDSJHM | B69: BI.504 | C69: 0 | D69: 0 | E69: 0 | F69: 0 | H69: =E69+C69 -> 0 | I69: =F69+D69 -> 0 | J69: 0 | K69: 0 | L69: =H69-J69 -> 0 | M69: =I69-K69 -> 0
A70: B07HM7P6MP | B70: RI.080 | C70: =VLOOKUP(A70,v_2024!F:I,3,FALSE) -> 10 | D70: =VLOOKUP(A70,v_2024!F:I,4,FALSE) -> 253.92 | E70: =VLOOKUP(A70,s_2024!E:G,2,FALSE) -> 17 | F70: =VLOOKUP(A70,s_2024!E:G,3,FALSE) -> 542.99 | G70: =F70/I70 -> 0.68136929 | H70: =E70+C70 -> 27 | I70: =F70+D70 -> 796.91 | J70: =VLOOKUP(A70,v_2023!F:I,3,FALSE) -> 91 | K70: =VLOOKUP(A70,v_2023!F:I,4,FALSE) -> 2230.41 | L70: =H70-J70 -> -64 | M70: =I70-K70 -> -1433.5 | N70: =M70/K70 -> -0.64270695
A71: B07JGVMFY1 | B71: BP.581 | C71: =VLOOKUP(A71,v_2024!F:I,3,FALSE) -> 2 | D71: =VLOOKUP(A71,v_2024!F:I,4,FALSE) -> 34.38 | E71: 0 | F71: 0 | G71: =F71/I71 -> 0 | H71: =E71+C71 -> 2 | I71: =F71+D71 -> 34.38 | J71: =VLOOKUP(A71,v_2023!F:I,3,FALSE) -> 13 | K71: =VLOOKUP(A71,v_2023!F:I,4,FALSE) -> 199.11 | L71: =H71-J71 -> -11 | M71: =I71-K71 -> -164.73 | N71: =M71/K71 -> -0.82733163
A72: B07KYWNC7Z | B72: 40.405 | C72: =VLOOKUP(A72,v_2024!F:I,3,FALSE) -> 25 | D72: =VLOOKUP(A72,v_2024!F:I,4,FALSE) -> 540.71 | E72: 0 | F72: 0 | G72: =F72/I72 -> 0 | H72: =E72+C72 -> 25 | I72: =F72+D72 -> 540.71 | J72: =VLOOKUP(A72,v_2023!F:I,3,FALSE) -> 37 | K72: =VLOOKUP(A72,v_2023!F:I,4,FALSE) -> 878.32 | L72: =H72-J72 -> -12 | M72: =I72-K72 -> -337.61 | N72: =M72/K72 -> -0.38438155
A73: B07MC8ZVRM | B73: 40.452 | C73: 0 | D73: 0 | E73: 0 | F73: 0 | H73: =E73+C73 -> 0 | I73: =F73+D73 -> 0 | J73: 0 | K73: 0 | L73: =H73-J73 -> 0 | M73: =I73-K73 -> 0
A74: B07N4C3H3V | B74: 40.405 | C74: =VLOOKUP(A74,v_2024!F:I,3,FALSE) -> 2 | D74: =VLOOKUP(A74,v_2024!F:I,4,FALSE) -> 22.14 | E74: =VLOOKUP(A74,s_2024!E:G,2,FALSE) -> 44 | F74: =VLOOKUP(A74,s_2024!E:G,3,FALSE) -> 652.91 | G74: =F74/I74 -> 0.96720243 | H74: =E74+C74 -> 46 | I74: =F74+D74 -> 675.05 | J74: =VLOOKUP(A74,v_2023!F:I,3,FALSE) -> 68 | K74: =VLOOKUP(A74,v_2023!F:I,4,FALSE) -> 794.19 | L74: =H74-J74 -> -22 | M74: =I74-K74 -> -119.14 | N74: =M74/K74 -> -0.15001448
A75: B07NNZSW1W | B75: BT.110 | C75: =VLOOKUP(A75,v_2024!F:I,3,FALSE) -> 1 | D75: =VLOOKUP(A75,v_2024!F:I,4,FALSE) -> 19.72 | E75: 0 | F75: 0 | G75: =F75/I75 -> 0 | H75: =E75+C75 -> 1 | I75: =F75+D75 -> 19.72 | J75: 0 | K75: 0 | L75: =H75-J75 -> 1 | M75: =I75-K75 -> 19.72
A76: B07NP6YY5W | B76: BP.200 | C76: 0 | D76: 0 | E76: 0 | F76: 0 | H76: =E76+C76 -> 0 | I76: =F76+D76 -> 0 | J76: 0 | K76: 0 | L76: =H76-J76 -> 0 | M76: =I76-K76 -> 0
A77: B07NQ1T7YK | B77: BP.101H | C77: =VLOOKUP(A77,v_2024!F:I,3,FALSE) -> 13 | D77: =VLOOKUP(A77,v_2024!F:I,4,FALSE) -> 182.92 | E77: 0 | F77: 0 | G77: =F77/I77 -> 0 | H77: =E77+C77 -> 13 | I77: =F77+D77 -> 182.92 | J77: =VLOOKUP(A77,v_2023!F:I,3,FALSE) -> 161 | K77: =VLOOKUP(A77,v_2023!F:I,4,FALSE) -> 1965.81 | L77: =H77-J77 -> -148 | M77: =I77-K77 -> -1782.89 | N77: =M77/K77 -> -0.9069493
A78: B07NQ2VYGD | B78: BT.710Y | C78: 0 | D78: 0 | E78: =VLOOKUP(A78,s_2024!E:G,2,FALSE) -> 229 | F78: =VLOOKUP(A78,s_2024!E:G,3,FALSE) -> 6838.12 | G78: =F78/I78 -> 1 | H78: =E78+C78 -> 229 | I78: =F78+D78 -> 6838.12 | J78: 0 | K78: 0 | L78: =H78-J78 -> 229 | M78: =I78-K78 -> 6838.12
A79: B07NQC6S9V | B79: BT.651Y | C79: =VLOOKUP(A79,v_2024!F:I,3,FALSE) -> 1 | D79: =VLOOKUP(A79,v_2024!F:I,4,FALSE) -> 36.8 | E79: =VLOOKUP(A79,s_2024!E:G,2,FALSE) -> 16 | F79: =VLOOKUP(A79,s_2024!E:G,3,FALSE) -> 798.4 | G79: =F79/I79 -> 0.9559387 | H79: =E79+C79 -> 17 | I79: =F79+D79 -> 835.2 | J79: =VLOOKUP(A79,v_2023!F:I,3,FALSE) -> 135 | K79: =VLOOKUP(A79,v_2023!F:I,4,FALSE) -> 4968 | L79: =H79-J79 -> -118 | M79: =I79-K79 -> -4132.8 | N79: =M79/K79 -> -0.83188406
A80: B07P7GGGQM | B80: BP.961 | C80: 0 | D80: 0 | E80: =VLOOKUP(A80,s_2024!E:G,2,FALSE) -> 19 | F80: =VLOOKUP(A80,s_2024!E:G,3,FALSE) -> 1138.1 | G80: =F80/I80 -> 1 | H80: =E80+C80 -> 19 | I80: =F80+D80 -> 1138.1 | J80: 0 | K80: 0 | L80: =H80-J80 -> 19 | M80: =I80-K80 -> 1138.1
A81: B07P7L18T9 | B81: 40.102 | C81: =VLOOKUP(A81,v_2024!F:I,3,FALSE) -> 1 | D81: =VLOOKUP(A81,v_2024!F:I,4,FALSE) -> 13.81 | E81: 0 | F81: 0 | G81: =F81/I81 -> 0 | H81: =E81+C81 -> 1 | I81: =F81+D81 -> 13.81 | J81: 0 | K81: 0 | L81: =H81-J81 -> 1 | M81: =I81-K81 -> 13.81
A82: B07PCQJ1P8 | B82: BT.410 | C82: 0 | D82: 0 | E82: 0 | F82: 0 | H82: =E82+C82 -> 0 | I82: =F82+D82 -> 0 | J82: 0 | K82: 0 | L82: =H82-J82 -> 0 | M82: =I82-K82 -> 0
A83: B07PTQPT16 | B83: BF.570 | C83: 0 | D83: 0 | E83: 0 | F83: 0 | H83: =E83+C83 -> 0 | I83: =F83+D83 -> 0 | J83: 0 | K83: 0 | L83: =H83-J83 -> 0 | M83: =I83-K83 -> 0
A84: B07Q38Z7CK | B84: BC.060 | C84: =VLOOKUP(A84,v_2024!F:I,3,FALSE) -> 168 | D84: =VLOOKUP(A84,v_2024!F:I,4,FALSE) -> 3399.3 | E84: 0 | F84: 0 | G84: =F84/I84 -> 0 | H84: =E84+C84 -> 168 | I84: =F84+D84 -> 3399.3 | J84: =VLOOKUP(A84,v_2023!F:I,3,FALSE) -> 472 | K84: =VLOOKUP(A84,v_2023!F:I,4,FALSE) -> 9633.52 | L84: =H84-J84 -> -304 | M84: =I84-K84 -> -6234.22 | N84: =M84/K84 -> -0.64713833
A85: B07QX1RJRH | B85: 40.742 | C85: =VLOOKUP(A85,v_2024!F:I,3,FALSE) -> 2 | D85: =VLOOKUP(A85,v_2024!F:I,4,FALSE) -> 48.17 | E85: 0 | F85: 0 | G85: =F85/I85 -> 0 | H85: =E85+C85 -> 2 | I85: =F85+D85 -> 48.17 | J85: =VLOOKUP(A85,v_2023!F:I,3,FALSE) -> 5 | K85: =VLOOKUP(A85,v_2023!F:I,4,FALSE) -> 104.95 | L85: =H85-J85 -> -3 | M85: =I85-K85 -> -56.78 | N85: =M85/K85 -> -0.54101953
A86: B07QZ89PLH | B86: 40.403 | C86: 0 | D86: 0 | E86: 0 | F86: 0 | H86: =E86+C86 -> 0 | I86: =F86+D86 -> 0 | J86: 0 | K86: 0 | L86: =H86-J86 -> 0 | M86: =I86-K86 -> 0
A87: B07R984VMS | B87: BI.505 | C87: 0 | D87: 0 | E87: 0 | F87: 0 | H87: =E87+C87 -> 0 | I87: =F87+D87 -> 0 | J87: 0 | K87: 0 | L87: =H87-J87 -> 0 | M87: =I87-K87 -> 0
A88: B07RN75ZFL | B88: 50.401 | C88: 0 | D88: 0 | E88: 0 | F88: 0 | H88: =E88+C88 -> 0 | I88: =F88+D88 -> 0 | J88: 0 | K88: 0 | L88: =H88-J88 -> 0 | M88: =I88-K88 -> 0
A89: B07RRBP1YR | B89: VE.502 | C89: =VLOOKUP(A89,v_2024!F:I,3,FALSE) -> 0 | D89: =VLOOKUP(A89,v_2024!F:I,4,FALSE) -> 0 | E89: 0 | F89: 0 | H89: =E89+C89 -> 0 | I89: =F89+D89 -> 0 | J89: =VLOOKUP(A89,v_2023!F:I,3,FALSE) -> 2 | K89: =VLOOKUP(A89,v_2023!F:I,4,FALSE) -> 162.3 | L89: =H89-J89 -> -2 | M89: =I89-K89 -> -162.3 | N89: =M89/K89 -> -1
A90: B07RRBS54G | B90: BP.620 | C90: 0 | D90: 0 | E90: 0 | F90: 0 | H90: =E90+C90 -> 0 | I90: =F90+D90 -> 0 | J90: 0 | K90: 0 | L90: =H90-J90 -> 0 | M90: =I90-K90 -> 0
A91: B07SSLRCT6 | B91: BP.304 | C91: =VLOOKUP(A91,v_2024!F:I,3,FALSE) -> 99 | D91: =VLOOKUP(A91,v_2024!F:I,4,FALSE) -> 1371.15 | E91: 0 | F91: 0 | G91: =F91/I91 -> 0 | H91: =E91+C91 -> 99 | I91: =F91+D91 -> 1371.15 | J91: =VLOOKUP(A91,v_2023!F:I,3,FALSE) -> 43 | K91: =VLOOKUP(A91,v_2023!F:I,4,FALSE) -> 701.33 | L91: =H91-J91 -> 56 | M91: =I91-K91 -> 669.82 | N91: =M91/K91 -> 0.95507108
A92: B07TJGZNPN | B92: BP.654 | C92: 0 | D92: 0 | E92: 0 | F92: 0 | H92: =E92+C92 -> 0 | I92: =F92+D92 -> 0 | J92: =VLOOKUP(A92,v_2023!F:I,3,FALSE) -> 2 | K92: =VLOOKUP(A92,v_2023!F:I,4,FALSE) -> 32.66 | L92: =H92-J92 -> -2 | M92: =I92-K92 -> -32.66 | N92: =M92/K92 -> -1
A93: B07TQVD94L | B93: BP.690 | C93: =VLOOKUP(A93,v_2024!F:I,3,FALSE) -> 6 | D93: =VLOOKUP(A93,v_2024!F:I,4,FALSE) -> 147.06 | E93: 0 | F93: 0 | G93: =F93/I93 -> 0 | H93: =E93+C93 -> 6 | I93: =F93+D93 -> 147.06 | J93: =VLOOKUP(A93,v_2023!F:I,3,FALSE) -> 16 | K93: =VLOOKUP(A93,v_2023!F:I,4,FALSE) -> 392.16 | L93: =H93-J93 -> -10 | M93: =I93-K93 -> -245.1 | N93: =M93/K93 -> -0.625
A94: B07TSNB5WG | B94: BP.102 | C94: =VLOOKUP(A94,v_2024!F:I,3,FALSE) -> 0 | D94: =VLOOKUP(A94,v_2024!F:I,4,FALSE) -> 0 | E94: 0 | F94: 0 | H94: =E94+C94 -> 0 | I94: =F94+D94 -> 0 | J94: =VLOOKUP(A94,v_2023!F:I,3,FALSE) -> 794 | K94: =VLOOKUP(A94,v_2023!F:I,4,FALSE) -> 9694.74 | L94: =H94-J94 -> -794 | M94: =I94-K94 -> -9694.74 | N94: =M94/K94 -> -1
A95: B07TSNCJ5J | B95: BP.800 | C95: =VLOOKUP(A95,v_2024!F:I,3,FALSE) -> 16 | D95: =VLOOKUP(A95,v_2024!F:I,4,FALSE) -> 167.52 | E95: 0 | F95: 0 | G95: =F95/I95 -> 0 | H95: =E95+C95 -> 16 | I95: =F95+D95 -> 167.52 | J95: =VLOOKUP(A95,v_2023!F:I,3,FALSE) -> 52 | K95: =VLOOKUP(A95,v_2023!F:I,4,FALSE) -> 596.63 | L95: =H95-J95 -> -36 | M95: =I95-K95 -> -429.11 | N95: =M95/K95 -> -0.71922297
A96: B07TTJQDC2 | B96: 70.404 | C96: 0 | D96: 0 | E96: 0 | F96: 0 | H96: =E96+C96 -> 0 | I96: =F96+D96 -> 0 | J96: 0 | K96: 0 | L96: =H96-J96 -> 0 | M96: =I96-K96 -> 0
A97: B07TVSJDCL | B97: MD.500 | C97: 0 | D97: 0 | E97: =VLOOKUP(A97,s_2024!E:G,2,FALSE) -> 1 | F97: =VLOOKUP(A97,s_2024!E:G,3,FALSE) -> 15.9 | G97: =F97/I97 -> 1 | H97: =E97+C97 -> 1 | I97: =F97+D97 -> 15.9 | J97: 0 | K97: 0 | L97: =H97-J97 -> 1 | M97: =I97-K97 -> 15.9
A98: B07TWX2L8N | B98: 40.361 | C98: 0 | D98: 0 | E98: 0 | F98: 0 | H98: =E98+C98 -> 0 | I98: =F98+D98 -> 0 | J98: =VLOOKUP(A98,v_2023!F:I,3,FALSE) -> 23 | K98: =VLOOKUP(A98,v_2023!F:I,4,FALSE) -> 171.89 | L98: =H98-J98 -> -23 | M98: =I98-K98 -> -171.89 | N98: =M98/K98 -> -1
A99: B07V131F5W | B99: 40.490 | C99: =VLOOKUP(A99,v_2024!F:I,3,FALSE) -> 105 | D99: =VLOOKUP(A99,v_2024!F:I,4,FALSE) -> 2591.61 | E99: =VLOOKUP(A99,s_2024!E:G,2,FALSE) -> 104 | F99: =VLOOKUP(A99,s_2024!E:G,3,FALSE) -> 3109.6 | G99: =F99/I99 -> 0.54542808 | H99: =E99+C99 -> 209 | I99: =F99+D99 -> 5701.21 | J99: =VLOOKUP(A99,v_2023!F:I,3,FALSE) -> 247 | K99: =VLOOKUP(A99,v_2023!F:I,4,FALSE) -> 5658.63 | L99: =H99-J99 -> -38 | M99: =I99-K99 -> 42.58 | N99: =M99/K99 -> 0.0075247896
A100: B07W7S9KYM | B100: BB.200 | C100: =VLOOKUP(A100,v_2024!F:I,3,FALSE) -> 25 | D100: =VLOOKUP(A100,v_2024!F:I,4,FALSE) -> 993.72 | E100: 0 | F100: 0 | G100: =F100/I100 -> 0 | H100: =E100+C100 -> 25 | I100: =F100+D100 -> 993.72 | J100: =VLOOKUP(A100,v_2023!F:I,3,FALSE) -> 21 | K100: =VLOOKUP(A100,v_2023!F:I,4,FALSE) -> 998.34 | L100: =H100-J100 -> 4 | M100: =I100-K100 -> -4.62 | N100: =M100/K100 -> -0.004627682
...

Sheet complessivo
A1: ASIN | B1: SKU | C1: Ordini Vendor 24 | D1: Valori ordini Vendor 24 | E1: Ordini Seller 24 | F1: Valori ordini Seller 24 | G1: % seller / totale | H1: Ordini Complessivi 24 | I1: Valori ordini Complessivi 24 | J1: Ordini Vendor 23 | K1: Valori ordini Vendor 23 | L1: Differenza Ordini | M1: Differenza Valore | N1: Differenza Valore %
A2: B0050IHH4E | B2: 40.979 | C2: 1183 | D2: 16822.21 | E2: =VLOOKUP(A2,s_2024!A:C,2,FALSE) -> 3 | F2: =VLOOKUP(A2,s_2024!A:C,3,FALSE) -> 60.7 | G2: =F2/I2 -> 0.0035953517 | H2: =E2+C2 -> 1186 | I2: =F2+D2 -> 16882.91 | J2: =VLOOKUP(A2,v_2023!A:D,3,FALSE) -> 14 | K2: =VLOOKUP(A2,v_2023!A:D,4,FALSE) -> 182.42 | L2: =H2-J2 -> 1172 | M2: =I2-K2 -> 16700.49 | N2: =M2/K2 -> 91.549666
A3: B009O92WU4 | B3: 40.999 | C3: 1 | D3: 5.03 | E3: 0 | F3: 0 | G3: =F3/I3 -> 0 | H3: =E3+C3 -> 1 | I3: =F3+D3 -> 5.03 | J3: 0 | K3: 0 | L3: =H3-J3 -> 1 | M3: =I3-K3 -> 5.03
A4: B00BH202XK | B4: 40.808A | C4: 10 | D4: 127.35 | E4: 0 | F4: 0 | G4: =F4/I4 -> 0 | H4: =E4+C4 -> 10 | I4: =F4+D4 -> 127.35 | J4: =VLOOKUP(A4,v_2023!A:D,3,FALSE) -> 1 | K4: =VLOOKUP(A4,v_2023!A:D,4,FALSE) -> 20.59 | L4: =H4-J4 -> 9 | M4: =I4-K4 -> 106.76 | N4: =M4/K4 -> 5.1850413
A5: B00CMAD2FG | B5: HK-NV009W | C5: 1 | D5: 15.18 | E5: 0 | F5: 0 | G5: =F5/I5 -> 0 | H5: =E5+C5 -> 1 | I5: =F5+D5 -> 15.18 | J5: =VLOOKUP(A5,v_2023!A:D,3,FALSE) -> 2 | K5: =VLOOKUP(A5,v_2023!A:D,4,FALSE) -> 34.18 | L5: =H5-J5 -> -1 | M5: =I5-K5 -> -19 | N5: =M5/K5 -> -0.55588063
A6: B00EYDRS1I | B6: 90.349 | C6: 48 | D6: 271.81 | E6: 0 | F6: 0 | G6: =F6/I6 -> 0 | H6: =E6+C6 -> 48 | I6: =F6+D6 -> 271.81 | J6: =VLOOKUP(A6,v_2023!A:D,3,FALSE) -> 119 | K6: =VLOOKUP(A6,v_2023!A:D,4,FALSE) -> 828.55 | L6: =H6-J6 -> -71 | M6: =I6-K6 -> -556.74 | N6: =M6/K6 -> -0.67194496
A7: B00FFBFVG2 | B7: 40.100 | C7: 0 | D7: 0 | E7: 0 | F7: 0 | H7: =E7+C7 -> 0 | I7: =F7+D7 -> 0 | J7: =VLOOKUP(A7,v_2023!A:D,3,FALSE) -> 13 | K7: =VLOOKUP(A7,v_2023!A:D,4,FALSE) -> 104.24 | L7: =H7-J7 -> -13 | M7: =I7-K7 -> -104.24 | N7: =M7/K7 -> -1
A8: B00FMZ2VW8 | B8: HK-HQ601C PINK | C8: 0 | D8: 0 | E8: 0 | F8: 0 | H8: =E8+C8 -> 0 | I8: =F8+D8 -> 0 | J8: 0 | K8: 0 | L8: =H8-J8 -> 0 | M8: =I8-K8 -> 0
A9: B00L5GPWFG | B9: 40.120 | C9: 6 | D9: 147.9 | E9: 0 | F9: 0 | G9: =F9/I9 -> 0 | H9: =E9+C9 -> 6 | I9: =F9+D9 -> 147.9 | J9: =VLOOKUP(A9,v_2023!A:D,3,FALSE) -> 20 | K9: =VLOOKUP(A9,v_2023!A:D,4,FALSE) -> 325.84 | L9: =H9-J9 -> -14 | M9: =I9-K9 -> -177.94 | N9: =M9/K9 -> -0.54609624
A10: B00L5H5KUW | B10: 40.121 | C10: 275 | D10: 5023.29 | E10: 0 | F10: 0 | G10: =F10/I10 -> 0 | H10: =E10+C10 -> 275 | I10: =F10+D10 -> 5023.29 | J10: =VLOOKUP(A10,v_2023!A:D,3,FALSE) -> 573 | K10: =VLOOKUP(A10,v_2023!A:D,4,FALSE) -> 9291.39 | L10: =H10-J10 -> -298 | M10: =I10-K10 -> -4268.1 | N10: =M10/K10 -> -0.45936076
A11: B00NSNZSLM | B11: 90.602 | C11: 1 | D11: 20.41 | E11: =VLOOKUP(A11,s_2024!A:C,2,FALSE) -> 48 | F11: =VLOOKUP(A11,s_2024!A:C,3,FALSE) -> 1440.2 | G11: =F11/I11 -> 0.98602639 | H11: =E11+C11 -> 49 | I11: =F11+D11 -> 1460.61 | J11: =VLOOKUP(A11,v_2023!A:D,3,FALSE) -> 400 | K11: =VLOOKUP(A11,v_2023!A:D,4,FALSE) -> 8213.58 | L11: =H11-J11 -> -351 | M11: =I11-K11 -> -6752.97 | N11: =M11/K11 -> -0.82217133
A12: B00OKE4RTM | B12: 90.386 | C12: 2 | D12: 98.08 | E12: 0 | F12: 0 | G12: =F12/I12 -> 0 | H12: =E12+C12 -> 2 | I12: =F12+D12 -> 98.08 | J12: =VLOOKUP(A12,v_2023!A:D,3,FALSE) -> 8 | K12: =VLOOKUP(A12,v_2023!A:D,4,FALSE) -> 425.01 | L12: =H12-J12 -> -6 | M12: =I12-K12 -> -326.93 | N12: =M12/K12 -> -0.76922896
A13: B00YH3FRV8 | B13: 40.998 | C13: 1 | D13: 7.43 | E13: 0 | F13: 0 | G13: =F13/I13 -> 0 | H13: =E13+C13 -> 1 | I13: =F13+D13 -> 7.43 | J13: 0 | K13: 0 | L13: =H13-J13 -> 1 | M13: =I13-K13 -> 7.43
A14: B011LFM60E | B14: 40.948T | C14: 2 | D14: 12.96 | E14: 0 | F14: 0 | G14: =F14/I14 -> 0 | H14: =E14+C14 -> 2 | I14: =F14+D14 -> 12.96 | J14: 0 | K14: 0 | L14: =H14-J14 -> 2 | M14: =I14-K14 -> 12.96
A15: B011LFVLW8 | B15: 90.620 | C15: 19 | D15: 686.19 | E15: 0 | F15: 0 | G15: =F15/I15 -> 0 | H15: =E15+C15 -> 19 | I15: =F15+D15 -> 686.19 | J15: =VLOOKUP(A15,v_2023!A:D,3,FALSE) -> 99 | K15: =VLOOKUP(A15,v_2023!A:D,4,FALSE) -> 2832.39 | L15: =H15-J15 -> -80 | M15: =I15-K15 -> -2146.2 | N15: =M15/K15 -> -0.75773463
A16: B017IUJA50 | B16: 90.920G | C16: 15 | D16: 209.45 | E16: 0 | F16: 0 | G16: =F16/I16 -> 0 | H16: =E16+C16 -> 15 | I16: =F16+D16 -> 209.45 | J16: =VLOOKUP(A16,v_2023!A:D,3,FALSE) -> 1584 | K16: =VLOOKUP(A16,v_2023!A:D,4,FALSE) -> 20644.51 | L16: =H16-J16 -> -1569 | M16: =I16-K16 -> -20435.06 | N16: =M16/K16 -> -0.98985445
A17: B01CHW1L88 | B17: PE.001 | C17: 1 | D17: 15.05 | E17: 0 | F17: 0 | G17: =F17/I17 -> 0 | H17: =E17+C17 -> 1 | I17: =F17+D17 -> 15.05 | J17: 0 | K17: 0 | L17: =H17-J17 -> 1 | M17: =I17-K17 -> 15.05
A18: B01CNX6T10 | B18: PE.165 | C18: 1 | D18: 18.03 | E18: 0 | F18: 0 | G18: =F18/I18 -> 0 | H18: =E18+C18 -> 1 | I18: =F18+D18 -> 18.03 | J18: 0 | K18: 0 | L18: =H18-J18 -> 1 | M18: =I18-K18 -> 18.03
A19: B01CNX6UIM | B19: PE.300 | C19: 3 | D19: 17.19 | E19: 0 | F19: 0 | G19: =F19/I19 -> 0 | H19: =E19+C19 -> 3 | I19: =F19+D19 -> 17.19 | J19: 0 | K19: 0 | L19: =H19-J19 -> 3 | M19: =I19-K19 -> 17.19
A20: B01CNX6Z78 | B20: 90.820 | C20: 9 | D20: 199.98 | E20: 0 | F20: 0 | G20: =F20/I20 -> 0 | H20: =E20+C20 -> 9 | I20: =F20+D20 -> 199.98 | J20: =VLOOKUP(A20,v_2023!A:D,3,FALSE) -> 75 | K20: =VLOOKUP(A20,v_2023!A:D,4,FALSE) -> 1575.73 | L20: =H20-J20 -> -66 | M20: =I20-K20 -> -1375.75 | N20: =M20/K20 -> -0.87308739
A21: B01CNX704K | B21: 90.825 | C21: 1 | D21: 22.97 | E21: =VLOOKUP(A21,s_2024!A:C,2,FALSE) -> 6 | F21: =VLOOKUP(A21,s_2024!A:C,3,FALSE) -> 281.4 | G21: =F21/I21 -> 0.92453264 | H21: =E21+C21 -> 7 | I21: =F21+D21 -> 304.37 | J21: =VLOOKUP(A21,v_2023!A:D,3,FALSE) -> 8 | K21: =VLOOKUP(A21,v_2023!A:D,4,FALSE) -> 319.22 | L21: =H21-J21 -> -1 | M21: =I21-K21 -> -14.85 | N21: =M21/K21 -> -0.046519642
A22: B01CNX71NA | B22: 90.871 | C22: 12 | D22: 1075.69 | E22: 0 | F22: 0 | G22: =F22/I22 -> 0 | H22: =E22+C22 -> 12 | I22: =F22+D22 -> 1075.69 | J22: =VLOOKUP(A22,v_2023!A:D,3,FALSE) -> 13 | K22: =VLOOKUP(A22,v_2023!A:D,4,FALSE) -> 973.92 | L22: =H22-J22 -> -1 | M22: =I22-K22 -> 101.77 | N22: =M22/K22 -> 0.10449524
A23: B01HM47LF8 | B23: MD.004 | C23: 3 | D23: 10.49 | E23: 0 | F23: 0 | G23: =F23/I23 -> 0 | H23: =E23+C23 -> 3 | I23: =F23+D23 -> 10.49 | J23: =VLOOKUP(A23,v_2023!A:D,3,FALSE) -> 13 | K23: =VLOOKUP(A23,v_2023!A:D,4,FALSE) -> 44.07 | L23: =H23-J23 -> -10 | M23: =I23-K23 -> -33.58 | N23: =M23/K23 -> -0.76196959
A24: B01I497WWM | B24: 90.920R | C24: 23 | D24: 410.8 | E24: =VLOOKUP(A24,s_2024!A:C,2,FALSE) -> 534 | F24: =VLOOKUP(A24,s_2024!A:C,3,FALSE) -> 10674.53 | G24: =F24/I24 -> 0.96294201 | H24: =E24+C24 -> 557 | I24: =F24+D24 -> 11085.33 | J24: =VLOOKUP(A24,v_2023!A:D,3,FALSE) -> 3002 | K24: =VLOOKUP(A24,v_2023!A:D,4,FALSE) -> 35627.11 | L24: =H24-J24 -> -2445 | M24: =I24-K24 -> -24541.78 | N24: =M24/K24 -> -0.68885127
A25: B01IHGX2HQ | B25: MD.104 | C25: 14 | D25: 58.41 | E25: 0 | F25: 0 | G25: =F25/I25 -> 0 | H25: =E25+C25 -> 14 | I25: =F25+D25 -> 58.41 | J25: =VLOOKUP(A25,v_2023!A:D,3,FALSE) -> 9 | K25: =VLOOKUP(A25,v_2023!A:D,4,FALSE) -> 37.22 | L25: =H25-J25 -> 5 | M25: =I25-K25 -> 21.19 | N25: =M25/K25 -> 0.56931757
A26: B01II7S968 | B26: MD.217 | C26: 6 | D26: 36.93 | E26: 0 | F26: 0 | G26: =F26/I26 -> 0 | H26: =E26+C26 -> 6 | I26: =F26+D26 -> 36.93 | J26: =VLOOKUP(A26,v_2023!A:D,3,FALSE) -> 9 | K26: =VLOOKUP(A26,v_2023!A:D,4,FALSE) -> 54.1 | L26: =H26-J26 -> -3 | M26: =I26-K26 -> -17.17 | N26: =M26/K26 -> -0.31737523
A27: B01KMJ9OXW | B27: 90.590Y | C27: 9 | D27: 267.96 | E27: =VLOOKUP(A27,s_2024!A:C,2,FALSE) -> 394 | F27: =VLOOKUP(A27,s_2024!A:C,3,FALSE) -> 14503.53 | G27: =F27/I27 -> 0.98185965 | H27: =E27+C27 -> 403 | I27: =F27+D27 -> 14771.49 | J27: =VLOOKUP(A27,v_2023!A:D,3,FALSE) -> 1143 | K27: =VLOOKUP(A27,v_2023!A:D,4,FALSE) -> 33655.87 | L27: =H27-J27 -> -740 | M27: =I27-K27 -> -18884.38 | N27: =M27/K27 -> -0.56110212
A28: B01M4O6145 | B28: 90.071 | C28: 66 | D28: 1357.87 | E28: 0 | F28: 0 | G28: =F28/I28 -> 0 | H28: =E28+C28 -> 66 | I28: =F28+D28 -> 1357.87 | J28: =VLOOKUP(A28,v_2023!A:D,3,FALSE) -> 72 | K28: =VLOOKUP(A28,v_2023!A:D,4,FALSE) -> 1646.1 | L28: =H28-J28 -> -6 | M28: =I28-K28 -> -288.23 | N28: =M28/K28 -> -0.17509872
A29: B01MTSEGF9 | B29: 50.700 | C29: 0 | D29: 0 | E29: =VLOOKUP(A29,s_2024!A:C,2,FALSE) -> 8 | F29: =VLOOKUP(A29,s_2024!A:C,3,FALSE) -> 432.8 | G29: =F29/I29 -> 1 | H29: =E29+C29 -> 8 | I29: =F29+D29 -> 432.8 | J29: =VLOOKUP(A29,v_2023!A:D,3,FALSE) -> 266 | K29: =VLOOKUP(A29,v_2023!A:D,4,FALSE) -> 7610.26 | L29: =H29-J29 -> -258 | M29: =I29-K29 -> -7177.46 | N29: =M29/K29 -> -0.94312941
A30: B01N12PI05 | B30: PE.301 | C30: 11 | D30: 45.74 | E30: 0 | F30: 0 | G30: =F30/I30 -> 0 | H30: =E30+C30 -> 11 | I30: =F30+D30 -> 45.74 | J30: 0 | K30: 0 | L30: =H30-J30 -> 11 | M30: =I30-K30 -> 45.74
A31: B06WGS8ZVG | B31: 90.131 | C31: 2 | D31: 27.28 | E31: 0 | F31: 0 | G31: =F31/I31 -> 0 | H31: =E31+C31 -> 2 | I31: =F31+D31 -> 27.28 | J31: =VLOOKUP(A31,v_2023!A:D,3,FALSE) -> 8 | K31: =VLOOKUP(A31,v_2023!A:D,4,FALSE) -> 100.16 | L31: =H31-J31 -> -6 | M31: =I31-K31 -> -72.88 | N31: =M31/K31 -> -0.72763578
A32: B06XPK3BTC | B32: 40.450GO | C32: 4 | D32: 51.29 | E32: 0 | F32: 0 | G32: =F32/I32 -> 0 | H32: =E32+C32 -> 4 | I32: =F32+D32 -> 51.29 | J32: =VLOOKUP(A32,v_2023!A:D,3,FALSE) -> 6 | K32: =VLOOKUP(A32,v_2023!A:D,4,FALSE) -> 98.39 | L32: =H32-J32 -> -2 | M32: =I32-K32 -> -47.1 | N32: =M32/K32 -> -0.47870719
A33: B06XPYSCGJ | B33: 40.939 | C33: 36 | D33: 3.64 | E33: 0 | F33: 0 | G33: =F33/I33 -> 0 | H33: =E33+C33 -> 36 | I33: =F33+D33 -> 3.64 | J33: =VLOOKUP(A33,v_2023!A:D,3,FALSE) -> 17 | K33: =VLOOKUP(A33,v_2023!A:D,4,FALSE) -> 72.96 | L33: =H33-J33 -> 19 | M33: =I33-K33 -> -69.32 | N33: =M33/K33 -> -0.95010965
A34: B06XQ25NLB | B34: 40.220 | C34: 0 | D34: 0 | E34: 0 | F34: 0 | H34: =E34+C34 -> 0 | I34: =F34+D34 -> 0 | J34: =VLOOKUP(A34,v_2023!A:D,3,FALSE) -> 0 | K34: =VLOOKUP(A34,v_2023!A:D,4,FALSE) -> 0 | L34: =H34-J34 -> 0 | M34: =I34-K34 -> 0
A35: B06XSJPGR9 | B35: 50.130 | C35: 0 | D35: 0 | E35: 0 | F35: 0 | H35: =E35+C35 -> 0 | I35: =F35+D35 -> 0 | J35: 0 | K35: 0 | L35: =H35-J35 -> 0 | M35: =I35-K35 -> 0
A36: B06XYMCV3W | B36: 90.485H | C36: 0 | D36: 0 | E36: 0 | F36: 0 | H36: =E36+C36 -> 0 | I36: =F36+D36 -> 0 | J36: 0 | K36: 0 | L36: =H36-J36 -> 0 | M36: =I36-K36 -> 0
A37: B06Y17FS6D | B37: 90.550 | C37: 49 | D37: 1395.95 | E37: =VLOOKUP(A37,s_2024!A:C,2,FALSE) -> 1 | F37: =VLOOKUP(A37,s_2024!A:C,3,FALSE) -> 0 | G37: =F37/I37 -> 0 | H37: =E37+C37 -> 50 | I37: =F37+D37 -> 1395.95 | J37: =VLOOKUP(A37,v_2023!A:D,3,FALSE) -> 633 | K37: =VLOOKUP(A37,v_2023!A:D,4,FALSE) -> 15925.61 | L37: =H37-J37 -> -583 | M37: =I37-K37 -> -14529.66 | N37: =M37/K37 -> -0.91234559
A38: B06Y195DJN | B38: 90.882 | C38: 1 | D38: 31.06 | E38: =VLOOKUP(A38,s_2024!A:C,2,FALSE) -> 18 | F38: =VLOOKUP(A38,s_2024!A:C,3,FALSE) -> 898.2 | G38: =F38/I38 -> 0.96657555 | H38: =E38+C38 -> 19 | I38: =F38+D38 -> 929.26 | J38: =VLOOKUP(A38,v_2023!A:D,3,FALSE) -> 17 | K38: =VLOOKUP(A38,v_2023!A:D,4,FALSE) -> 651.91 | L38: =H38-J38 -> 2 | M38: =I38-K38 -> 277.35 | N38: =M38/K38 -> 0.42544216
A39: B06Y1997YH | B39: 90.883 | C39: 15 | D39: 942.38 | E39: 0 | F39: 0 | G39: =F39/I39 -> 0 | H39: =E39+C39 -> 15 | I39: =F39+D39 -> 942.38 | J39: =VLOOKUP(A39,v_2023!A:D,3,FALSE) -> 68 | K39: =VLOOKUP(A39,v_2023!A:D,4,FALSE) -> 3790.13 | L39: =H39-J39 -> -53 | M39: =I39-K39 -> -2847.75 | N39: =M39/K39 -> -0.75135945
A40: B06Y1P6DPZ | B40: VE.112 | C40: 1 | D40: 66.58 | E40: 0 | F40: 0 | G40: =F40/I40 -> 0 | H40: =E40+C40 -> 1 | I40: =F40+D40 -> 66.58 | J40: 0 | K40: 0 | L40: =H40-J40 -> 1 | M40: =I40-K40 -> 66.58
A41: B073B67PLQ | B41: 90.884 | C41: 25 | D41: 1858.24 | E41: 0 | F41: 0 | G41: =F41/I41 -> 0 | H41: =E41+C41 -> 25 | I41: =F41+D41 -> 1858.24 | J41: =VLOOKUP(A41,v_2023!A:D,3,FALSE) -> 43 | K41: =VLOOKUP(A41,v_2023!A:D,4,FALSE) -> 3112.52 | L41: =H41-J41 -> -18 | M41: =I41-K41 -> -1254.28 | N41: =M41/K41 -> -0.40297894
A42: B0757TJRR9 | B42: 40.500 | C42: 1 | D42: 26.97 | E42: =VLOOKUP(A42,s_2024!A:C,2,FALSE) -> 388 | F42: =VLOOKUP(A42,s_2024!A:C,3,FALSE) -> 12795.27 | G42: =F42/I42 -> 0.99789662 | H42: =E42+C42 -> 389 | I42: =F42+D42 -> 12822.24 | J42: =VLOOKUP(A42,v_2023!A:D,3,FALSE) -> 803 | K42: =VLOOKUP(A42,v_2023!A:D,4,FALSE) -> 20999.62 | L42: =H42-J42 -> -414 | M42: =I42-K42 -> -8177.38 | N42: =M42/K42 -> -0.38940609
A43: B075FX6RFP | B43: BC.040N | C43: 3 | D43: 101.14 | E43: 0 | F43: 0 | G43: =F43/I43 -> 0 | H43: =E43+C43 -> 3 | I43: =F43+D43 -> 101.14 | J43: =VLOOKUP(A43,v_2023!A:D,3,FALSE) -> 4 | K43: =VLOOKUP(A43,v_2023!A:D,4,FALSE) -> 139.68 | L43: =H43-J43 -> -1 | M43: =I43-K43 -> -38.54 | N43: =M43/K43 -> -0.27591638
A44: B075K5C2QG | B44: RI.201 | C44: 2 | D44: 40.82 | E44: 0 | F44: 0 | G44: =F44/I44 -> 0 | H44: =E44+C44 -> 2 | I44: =F44+D44 -> 40.82 | J44: =VLOOKUP(A44,v_2023!A:D,3,FALSE) -> -1 | K44: =VLOOKUP(A44,v_2023!A:D,4,FALSE) -> -14.75 | L44: =H44-J44 -> 3 | M44: =I44-K44 -> 55.57 | N44: =M44/K44 -> -3.7674576
A45: B075RF5S3N | B45: BC.160A | C45: 5 | D45: 129.21 | E45: 0 | F45: 0 | G45: =F45/I45 -> 0 | H45: =E45+C45 -> 5 | I45: =F45+D45 -> 129.21 | J45: =VLOOKUP(A45,v_2023!A:D,3,FALSE) -> 19 | K45: =VLOOKUP(A45,v_2023!A:D,4,FALSE) -> 465.69 | L45: =H45-J45 -> -14 | M45: =I45-K45 -> -336.48 | N45: =M45/K45 -> -0.72254075
A46: B075RF8FM9 | B46: BC.160G | C46: 0 | D46: 0 | E46: 0 | F46: 0 | H46: =E46+C46 -> 0 | I46: =F46+D46 -> 0 | J46: =VLOOKUP(A46,v_2023!A:D,3,FALSE) -> 2 | K46: =VLOOKUP(A46,v_2023!A:D,4,FALSE) -> 49.02 | L46: =H46-J46 -> -2 | M46: =I46-K46 -> -49.02 | N46: =M46/K46 -> -1
A47: B075XR3T8V | B47: BT.600Y | C47: 7 | D47: 257.01 | E47: 0 | F47: 0 | G47: =F47/I47 -> 0 | H47: =E47+C47 -> 7 | I47: =F47+D47 -> 257.01 | J47: =VLOOKUP(A47,v_2023!A:D,3,FALSE) -> 11 | K47: =VLOOKUP(A47,v_2023!A:D,4,FALSE) -> 311.01 | L47: =H47-J47 -> -4 | M47: =I47-K47 -> -54 | N47: =M47/K47 -> -0.17362786
A48: B076D74TC7 | B48: BT.700Y | C48: 4 | D48: 156.28 | E48: =VLOOKUP(A48,s_2024!A:C,2,FALSE) -> 1 | F48: =VLOOKUP(A48,s_2024!A:C,3,FALSE) -> 36.99 | G48: =F48/I48 -> 0.19139028 | H48: =E48+C48 -> 5 | I48: =F48+D48 -> 193.27 | J48: =VLOOKUP(A48,v_2023!A:D,3,FALSE) -> 43 | K48: =VLOOKUP(A48,v_2023!A:D,4,FALSE) -> 1264.96 | L48: =H48-J48 -> -38 | M48: =I48-K48 -> -1071.69 | N48: =M48/K48 -> -0.84721256
A49: B076DC4VWG | B49: 40.501 | C49: 6 | D49: 150.78 | E49: 0 | F49: 0 | G49: =F49/I49 -> 0 | H49: =E49+C49 -> 6 | I49: =F49+D49 -> 150.78 | J49: =VLOOKUP(A49,v_2023!A:D,3,FALSE) -> 7 | K49: =VLOOKUP(A49,v_2023!A:D,4,FALSE) -> 169.26 | L49: =H49-J49 -> -1 | M49: =I49-K49 -> -18.48 | N49: =M49/K49 -> -0.10918114
A50: B076DCKSTJ | B50: BT.602H | C50: 5 | D50: 103.55 | E50: =VLOOKUP(A50,s_2024!A:C,2,FALSE) -> 36 | F50: =VLOOKUP(A50,s_2024!A:C,3,FALSE) -> 906.4 | G50: =F50/I50 -> 0.89747017 | H50: =E50+C50 -> 41 | I50: =F50+D50 -> 1009.95 | J50: =VLOOKUP(A50,v_2023!A:D,3,FALSE) -> 573 | K50: =VLOOKUP(A50,v_2023!A:D,4,FALSE) -> 11649.88 | L50: =H50-J50 -> -532 | M50: =I50-K50 -> -10639.93 | N50: =M50/K50 -> -0.91330812
A51: B076DCL19C | B51: BP.720 | C51: 19 | D51: 922.48 | E51: 0 | F51: 0 | G51: =F51/I51 -> 0 | H51: =E51+C51 -> 19 | I51: =F51+D51 -> 922.48 | J51: =VLOOKUP(A51,v_2023!A:D,3,FALSE) -> 23 | K51: =VLOOKUP(A51,v_2023!A:D,4,FALSE) -> 1319.95 | L51: =H51-J51 -> -4 | M51: =I51-K51 -> -397.47 | N51: =M51/K51 -> -0.30112504
A52: B076DCX3JH | B52: BB.103 | C52: 1 | D52: 19.59 | E52: 0 | F52: 0 | G52: =F52/I52 -> 0 | H52: =E52+C52 -> 1 | I52: =F52+D52 -> 19.59 | J52: =VLOOKUP(A52,v_2023!A:D,3,FALSE) -> 2 | K52: =VLOOKUP(A52,v_2023!A:D,4,FALSE) -> 49.42 | L52: =H52-J52 -> -1 | M52: =I52-K52 -> -29.83 | N52: =M52/K52 -> -0.60360178
A53: B076DD26WW | B53: CA.010 | C53: -1 | D53: -5.12 | E53: 0 | F53: 0 | G53: =F53/I53 -> 0 | H53: =E53+C53 -> -1 | I53: =F53+D53 -> -5.12 | J53: 0 | K53: 0 | L53: =H53-J53 -> -1 | M53: =I53-K53 -> -5.12
A54: B076DD35DZ | B54: BC.002 | C54: 3 | D54: 130.44 | E54: 0 | F54: 0 | G54: =F54/I54 -> 0 | H54: =E54+C54 -> 3 | I54: =F54+D54 -> 130.44 | J54: =VLOOKUP(A54,v_2023!A:D,3,FALSE) -> 4 | K54: =VLOOKUP(A54,v_2023!A:D,4,FALSE) -> 167.39 | L54: =H54-J54 -> -1 | M54: =I54-K54 -> -36.95 | N54: =M54/K54 -> -0.22074198
A55: B076Q7BR6F | B55: BC.041N | C55: 43 | D55: 1896.1 | E55: 0 | F55: 0 | G55: =F55/I55 -> 0 | H55: =E55+C55 -> 43 | I55: =F55+D55 -> 1896.1 | J55: =VLOOKUP(A55,v_2023!A:D,3,FALSE) -> 244 | K55: =VLOOKUP(A55,v_2023!A:D,4,FALSE) -> 9958.31 | L55: =H55-J55 -> -201 | M55: =I55-K55 -> -8062.21 | N55: =M55/K55 -> -0.80959621
A56: B076QCMZX1 | B56: 40.821 | C56: 170 | D56: 2082.7 | E56: 0 | F56: 0 | G56: =F56/I56 -> 0 | H56: =E56+C56 -> 170 | I56: =F56+D56 -> 2082.7 | J56: =VLOOKUP(A56,v_2023!A:D,3,FALSE) -> 4 | K56: =VLOOKUP(A56,v_2023!A:D,4,FALSE) -> 67.51 | L56: =H56-J56 -> 166 | M56: =I56-K56 -> 2015.19 | N56: =M56/K56 -> 29.850244
A57: B076QFRRZ5 | B57: 40.931 | C57: 52 | D57: 763.71 | E57: 0 | F57: 0 | G57: =F57/I57 -> 0 | H57: =E57+C57 -> 52 | I57: =F57+D57 -> 763.71 | J57: =VLOOKUP(A57,v_2023!A:D,3,FALSE) -> 212 | K57: =VLOOKUP(A57,v_2023!A:D,4,FALSE) -> 3204.1 | L57: =H57-J57 -> -160 | M57: =I57-K57 -> -2440.39 | N57: =M57/K57 -> -0.76164602
A58: B079SB5VJZ | B58: 50451 | C58: 7 | D58: 325.84 | E58: 0 | F58: 0 | G58: =F58/I58 -> 0 | H58: =E58+C58 -> 7 | I58: =F58+D58 -> 325.84 | J58: =VLOOKUP(A58,v_2023!A:D,3,FALSE) -> 401 | K58: =VLOOKUP(A58,v_2023!A:D,4,FALSE) -> 13128.1 | L58: =H58-J58 -> -394 | M58: =I58-K58 -> -12802.26 | N58: =M58/K58 -> -0.97517996
A59: B07B9CBD91 | B59: VE.550 | C59: 1 | D59: 117.41 | E59: 0 | F59: 0 | G59: =F59/I59 -> 0 | H59: =E59+C59 -> 1 | I59: =F59+D59 -> 117.41 | J59: 0 | K59: 0 | L59: =H59-J59 -> 1 | M59: =I59-K59 -> 117.41
A60: B07B9CPH62 | B60: BG.200Y | C60: 46 | D60: 2537.23 | E60: 0 | F60: 0 | G60: =F60/I60 -> 0 | H60: =E60+C60 -> 46 | I60: =F60+D60 -> 2537.23 | J60: =VLOOKUP(A60,v_2023!A:D,3,FALSE) -> 30 | K60: =VLOOKUP(A60,v_2023!A:D,4,FALSE) -> 1541.34 | L60: =H60-J60 -> 16 | M60: =I60-K60 -> 995.89 | N60: =M60/K60 -> 0.64611961
A61: B07BB2DQ4V | B61: BT.150Y | C61: 47 | D61: 1409.65 | E61: =VLOOKUP(A61,s_2024!A:C,2,FALSE) -> 13 | F61: =VLOOKUP(A61,s_2024!A:C,3,FALSE) -> 626.9 | G61: =F61/I61 -> 0.30782451 | H61: =E61+C61 -> 60 | I61: =F61+D61 -> 2036.55 | J61: =VLOOKUP(A61,v_2023!A:D,3,FALSE) -> 67 | K61: =VLOOKUP(A61,v_2023!A:D,4,FALSE) -> 1995.43 | L61: =H61-J61 -> -7 | M61: =I61-K61 -> 41.12 | N61: =M61/K61 -> 0.020607087
A62: B07BHCZR84 | B62: BA.200Y | C62: 32 | D62: 372.1 | E62: 0 | F62: 0 | G62: =F62/I62 -> 0 | H62: =E62+C62 -> 32 | I62: =F62+D62 -> 372.1 | J62: =VLOOKUP(A62,v_2023!A:D,3,FALSE) -> 32 | K62: =VLOOKUP(A62,v_2023!A:D,4,FALSE) -> 241.24 | L62: =H62-J62 -> 0 | M62: =I62-K62 -> 130.86 | N62: =M62/K62 -> 0.54244736
A63: B07BHTW4WV | B63: VE.210 | C63: 0 | D63: 0 | E63: 0 | F63: 0 | H63: =E63+C63 -> 0 | I63: =F63+D63 -> 0 | J63: 0 | K63: 0 | L63: =H63-J63 -> 0 | M63: =I63-K63 -> 0
A64: B07CZ4WMB8 | B64: 40.330 | C64: 9 | D64: 206.62 | E64: 0 | F64: 0 | G64: =F64/I64 -> 0 | H64: =E64+C64 -> 9 | I64: =F64+D64 -> 206.62 | J64: 0 | K64: 0 | L64: =H64-J64 -> 9 | M64: =I64-K64 -> 206.62
A65: B07F187NFQ | B65: 50.900 | C65: 3 | D65: 14.35 | E65: 0 | F65: 0 | G65: =F65/I65 -> 0 | H65: =E65+C65 -> 3 | I65: =F65+D65 -> 14.35 | J65: 0 | K65: 0 | L65: =H65-J65 -> 3 | M65: =I65-K65 -> 14.35
A66: B07FN14FSN | B66: 50.160 | C66: 1 | D66: 29.03 | E66: 0 | F66: 0 | G66: =F66/I66 -> 0 | H66: =E66+C66 -> 1 | I66: =F66+D66 -> 29.03 | J66: =VLOOKUP(A66,v_2023!A:D,3,FALSE) -> 0 | K66: =VLOOKUP(A66,v_2023!A:D,4,FALSE) -> 0 | L66: =H66-J66 -> 1 | M66: =I66-K66 -> 29.03
A67: B07HFPYL56 | B67: BC.353 | C67: 1 | D67: 55.62 | E67: 0 | F67: 0 | G67: =F67/I67 -> 0 | H67: =E67+C67 -> 1 | I67: =F67+D67 -> 55.62 | J67: 0 | K67: 0 | L67: =H67-J67 -> 1 | M67: =I67-K67 -> 55.62
A68: B07HFQH172 | B68: BC.250 | C68: 1 | D68: 41.58 | E68: 0 | F68: 0 | G68: =F68/I68 -> 0 | H68: =E68+C68 -> 1 | I68: =F68+D68 -> 41.58 | J68: =VLOOKUP(A68,v_2023!A:D,3,FALSE) -> 15 | K68: =VLOOKUP(A68,v_2023!A:D,4,FALSE) -> 623.7 | L68: =H68-J68 -> -14 | M68: =I68-K68 -> -582.12 | N68: =M68/K68 -> -0.93333333
A69: B07HHDSJHM | B69: BI.504 | C69: 0 | D69: 0 | E69: 0 | F69: 0 | H69: =E69+C69 -> 0 | I69: =F69+D69 -> 0 | J69: 0 | K69: 0 | L69: =H69-J69 -> 0 | M69: =I69-K69 -> 0
A70: B07HM7P6MP | B70: RI.080 | C70: 10 | D70: 253.92 | E70: =VLOOKUP(A70,s_2024!A:C,2,FALSE) -> 17 | F70: =VLOOKUP(A70,s_2024!A:C,3,FALSE) -> 542.99 | G70: =F70/I70 -> 0.68136929 | H70: =E70+C70 -> 27 | I70: =F70+D70 -> 796.91 | J70: =VLOOKUP(A70,v_2023!A:D,3,FALSE) -> 100 | K70: =VLOOKUP(A70,v_2023!A:D,4,FALSE) -> 2466.4 | L70: =H70-J70 -> -73 | M70: =I70-K70 -> -1669.49 | N70: =M70/K70 -> -0.67689345
A71: B07JGVMFY1 | B71: BP.581 | C71: 199 | D71: 2973.83 | E71: 0 | F71: 0 | G71: =F71/I71 -> 0 | H71: =E71+C71 -> 199 | I71: =F71+D71 -> 2973.83 | J71: =VLOOKUP(A71,v_2023!A:D,3,FALSE) -> 17 | K71: =VLOOKUP(A71,v_2023!A:D,4,FALSE) -> 261.65 | L71: =H71-J71 -> 182 | M71: =I71-K71 -> 2712.18 | N71: =M71/K71 -> 10.365679
A72: B07KYWNC7Z | B72: 40.405 | C72: 30 | D72: 665.8 | E72: 0 | F72: 0 | G72: =F72/I72 -> 0 | H72: =E72+C72 -> 30 | I72: =F72+D72 -> 665.8 | J72: =VLOOKUP(A72,v_2023!A:D,3,FALSE) -> 37 | K72: =VLOOKUP(A72,v_2023!A:D,4,FALSE) -> 878.32 | L72: =H72-J72 -> -7 | M72: =I72-K72 -> -212.52 | N72: =M72/K72 -> -0.24196193
A73: B07MC8ZVRM | B73: 40.452 | C73: 8 | D73: 196.7 | E73: 0 | F73: 0 | G73: =F73/I73 -> 0 | H73: =E73+C73 -> 8 | I73: =F73+D73 -> 196.7 | J73: 0 | K73: 0 | L73: =H73-J73 -> 8 | M73: =I73-K73 -> 196.7
A74: B07N4C3H3V | B74: 40.405 | C74: 2 | D74: 22.14 | E74: =VLOOKUP(A74,s_2024!A:C,2,FALSE) -> 45 | F74: =VLOOKUP(A74,s_2024!A:C,3,FALSE) -> 672.81 | G74: =F74/I74 -> 0.96814159 | H74: =E74+C74 -> 47 | I74: =F74+D74 -> 694.95 | J74: =VLOOKUP(A74,v_2023!A:D,3,FALSE) -> 85 | K74: =VLOOKUP(A74,v_2023!A:D,4,FALSE) -> 1021.69 | L74: =H74-J74 -> -38 | M74: =I74-K74 -> -326.74 | N74: =M74/K74 -> -0.31980346
A75: B07NNZSW1W | B75: BT.110 | C75: 4 | D75: 64.51 | E75: 0 | F75: 0 | G75: =F75/I75 -> 0 | H75: =E75+C75 -> 4 | I75: =F75+D75 -> 64.51 | J75: 0 | K75: 0 | L75: =H75-J75 -> 4 | M75: =I75-K75 -> 64.51
A76: B07NP6YY5W | B76: BP.200 | C76: 1 | D76: 91.6 | E76: 0 | F76: 0 | G76: =F76/I76 -> 0 | H76: =E76+C76 -> 1 | I76: =F76+D76 -> 91.6 | J76: =VLOOKUP(A76,v_2023!A:D,3,FALSE) -> 0 | K76: =VLOOKUP(A76,v_2023!A:D,4,FALSE) -> 0 | L76: =H76-J76 -> 1 | M76: =I76-K76 -> 91.6
A77: B07NQ1T7YK | B77: BP.101H | C77: 203 | D77: 2645.87 | E77: 0 | F77: 0 | G77: =F77/I77 -> 0 | H77: =E77+C77 -> 203 | I77: =F77+D77 -> 2645.87 | J77: =VLOOKUP(A77,v_2023!A:D,3,FALSE) -> 164 | K77: =VLOOKUP(A77,v_2023!A:D,4,FALSE) -> 2010.57 | L77: =H77-J77 -> 39 | M77: =I77-K77 -> 635.3 | N77: =M77/K77 -> 0.31598005
A78: B07NQ2VYGD | B78: BT.710Y | C78: 72 | D78: 2028.94 | E78: =VLOOKUP(A78,s_2024!A:C,2,FALSE) -> 365 | F78: =VLOOKUP(A78,s_2024!A:C,3,FALSE) -> 12257.32 | G78: =F78/I78 -> 0.85797963 | H78: =E78+C78 -> 437 | I78: =F78+D78 -> 14286.26 | J78: =VLOOKUP(A78,v_2023!A:D,3,FALSE) -> 375 | K78: =VLOOKUP(A78,v_2023!A:D,4,FALSE) -> 11812.32 | L78: =H78-J78 -> 62 | M78: =I78-K78 -> 2473.94 | N78: =M78/K78 -> 0.20943727
A79: B07NQC6S9V | B79: BT.651Y | C79: 5 | D79: 186.48 | E79: =VLOOKUP(A79,s_2024!A:C,2,FALSE) -> 20 | F79: =VLOOKUP(A79,s_2024!A:C,3,FALSE) -> 1038 | G79: =F79/I79 -> 0.84770678 | H79: =E79+C79 -> 25 | I79: =F79+D79 -> 1224.48 | J79: =VLOOKUP(A79,v_2023!A:D,3,FALSE) -> 287 | K79: =VLOOKUP(A79,v_2023!A:D,4,FALSE) -> 10625.77 | L79: =H79-J79 -> -262 | M79: =I79-K79 -> -9401.29 | N79: =M79/K79 -> -0.88476317
A80: B07P7GGGQM | B80: BP.961 | C80: 62 | D80: 2621.26 | E80: =VLOOKUP(A80,s_2024!A:C,2,FALSE) -> 19 | F80: =VLOOKUP(A80,s_2024!A:C,3,FALSE) -> 1138.1 | G80: =F80/I80 -> 0.3027377 | H80: =E80+C80 -> 81 | I80: =F80+D80 -> 3759.36 | J80: =VLOOKUP(A80,v_2023!A:D,3,FALSE) -> 62 | K80: =VLOOKUP(A80,v_2023!A:D,4,FALSE) -> 2954.3 | L80: =H80-J80 -> 19 | M80: =I80-K80 -> 805.06 | N80: =M80/K80 -> 0.27250448
A81: B07P7L18T9 | B81: 40.102 | C81: 1 | D81: 13.81 | E81: 0 | F81: 0 | G81: =F81/I81 -> 0 | H81: =E81+C81 -> 1 | I81: =F81+D81 -> 13.81 | J81: =VLOOKUP(A81,v_2023!A:D,3,FALSE) -> 1 | K81: =VLOOKUP(A81,v_2023!A:D,4,FALSE) -> 18.24 | L81: =H81-J81 -> 0 | M81: =I81-K81 -> -4.43 | N81: =M81/K81 -> -0.24287281
A82: B07PCQJ1P8 | B82: BT.410 | C82: 1 | D82: 33.25 | E82: 0 | F82: 0 | G82: =F82/I82 -> 0 | H82: =E82+C82 -> 1 | I82: =F82+D82 -> 33.25 | J82: =VLOOKUP(A82,v_2023!A:D,3,FALSE) -> 2 | K82: =VLOOKUP(A82,v_2023!A:D,4,FALSE) -> 71.1 | L82: =H82-J82 -> -1 | M82: =I82-K82 -> -37.85 | N82: =M82/K82 -> -0.5323488
A83: B07PTQPT16 | B83: BF.570 | C83: 1 | D83: 54.9 | E83: 0 | F83: 0 | G83: =F83/I83 -> 0 | H83: =E83+C83 -> 1 | I83: =F83+D83 -> 54.9 | J83: 0 | K83: 0 | L83: =H83-J83 -> 1 | M83: =I83-K83 -> 54.9
A84: B07Q38Z7CK | B84: BC.060 | C84: 178 | D84: 3604.56 | E84: 0 | F84: 0 | G84: =F84/I84 -> 0 | H84: =E84+C84 -> 178 | I84: =F84+D84 -> 3604.56 | J84: =VLOOKUP(A84,v_2023!A:D,3,FALSE) -> 491 | K84: =VLOOKUP(A84,v_2023!A:D,4,FALSE) -> 10102.95 | L84: =H84-J84 -> -313 | M84: =I84-K84 -> -6498.39 | N84: =M84/K84 -> -0.64321708
A85: B07QX1RJRH | B85: 40.742 | C85: 3 | D85: 72.88 | E85: 0 | F85: 0 | G85: =F85/I85 -> 0 | H85: =E85+C85 -> 3 | I85: =F85+D85 -> 72.88 | J85: =VLOOKUP(A85,v_2023!A:D,3,FALSE) -> 6 | K85: =VLOOKUP(A85,v_2023!A:D,4,FALSE) -> 134.09 | L85: =H85-J85 -> -3 | M85: =I85-K85 -> -61.21 | N85: =M85/K85 -> -0.45648445
A86: B07QZ89PLH | B86: 40.403 | C86: 1 | D86: 17.07 | E86: 0 | F86: 0 | G86: =F86/I86 -> 0 | H86: =E86+C86 -> 1 | I86: =F86+D86 -> 17.07 | J86: 0 | K86: 0 | L86: =H86-J86 -> 1 | M86: =I86-K86 -> 17.07
A87: B07R984VMS | B87: BI.505 | C87: 93 | D87: 687.96 | E87: 0 | F87: 0 | G87: =F87/I87 -> 0 | H87: =E87+C87 -> 93 | I87: =F87+D87 -> 687.96 | J87: =VLOOKUP(A87,v_2023!A:D,3,FALSE) -> 31 | K87: =VLOOKUP(A87,v_2023!A:D,4,FALSE) -> 255.24 | L87: =H87-J87 -> 62 | M87: =I87-K87 -> 432.72 | N87: =M87/K87 -> 1.6953456
A88: B07RN75ZFL | B88: 50.401 | C88: 24 | D88: 339.75 | E88: 0 | F88: 0 | G88: =F88/I88 -> 0 | H88: =E88+C88 -> 24 | I88: =F88+D88 -> 339.75 | J88: =VLOOKUP(A88,v_2023!A:D,3,FALSE) -> 3 | K88: =VLOOKUP(A88,v_2023!A:D,4,FALSE) -> 86.73 | L88: =H88-J88 -> 21 | M88: =I88-K88 -> 253.02 | N88: =M88/K88 -> 2.9173296
A89: B07RRBP1YR | B89: VE.502 | C89: 2 | D89: 151.86 | E89: 0 | F89: 0 | G89: =F89/I89 -> 0 | H89: =E89+C89 -> 2 | I89: =F89+D89 -> 151.86 | J89: =VLOOKUP(A89,v_2023!A:D,3,FALSE) -> 2 | K89: =VLOOKUP(A89,v_2023!A:D,4,FALSE) -> 162.3 | L89: =H89-J89 -> 0 | M89: =I89-K89 -> -10.44 | N89: =M89/K89 -> -0.064325323
A90: B07RRBS54G | B90: BP.620 | C90: 7 | D90: 332.73 | E90: 0 | F90: 0 | G90: =F90/I90 -> 0 | H90: =E90+C90 -> 7 | I90: =F90+D90 -> 332.73 | J90: =VLOOKUP(A90,v_2023!A:D,3,FALSE) -> 11 | K90: =VLOOKUP(A90,v_2023!A:D,4,FALSE) -> 525.08 | L90: =H90-J90 -> -4 | M90: =I90-K90 -> -192.35 | N90: =M90/K90 -> -0.36632513
A91: B07SSLRCT6 | B91: BP.304 | C91: 361 | D91: 5152.88 | E91: 0 | F91: 0 | G91: =F91/I91 -> 0 | H91: =E91+C91 -> 361 | I91: =F91+D91 -> 5152.88 | J91: =VLOOKUP(A91,v_2023!A:D,3,FALSE) -> 187 | K91: =VLOOKUP(A91,v_2023!A:D,4,FALSE) -> 2564.2 | L91: =H91-J91 -> 174 | M91: =I91-K91 -> 2588.68 | N91: =M91/K91 -> 1.0095468
A92: B07TJGZNPN | B92: BP.654 | C92: 5 | D92: 97.62 | E92: 0 | F92: 0 | G92: =F92/I92 -> 0 | H92: =E92+C92 -> 5 | I92: =F92+D92 -> 97.62 | J92: =VLOOKUP(A92,v_2023!A:D,3,FALSE) -> 2 | K92: =VLOOKUP(A92,v_2023!A:D,4,FALSE) -> 32.66 | L92: =H92-J92 -> 3 | M92: =I92-K92 -> 64.96 | N92: =M92/K92 -> 1.9889773
A93: B07TQVD94L | B93: BP.690 | C93: 8 | D93: 198.65 | E93: 0 | F93: 0 | G93: =F93/I93 -> 0 | H93: =E93+C93 -> 8 | I93: =F93+D93 -> 198.65 | J93: =VLOOKUP(A93,v_2023!A:D,3,FALSE) -> 22 | K93: =VLOOKUP(A93,v_2023!A:D,4,FALSE) -> 544.95 | L93: =H93-J93 -> -14 | M93: =I93-K93 -> -346.3 | N93: =M93/K93 -> -0.63547114
A94: B07TSNB5WG | B94: BP.102 | C94: 0 | D94: 0 | E94: 0 | F94: 0 | H94: =E94+C94 -> 0 | I94: =F94+D94 -> 0 | J94: =VLOOKUP(A94,v_2023!A:D,3,FALSE) -> 835 | K94: =VLOOKUP(A94,v_2023!A:D,4,FALSE) -> 10271.71 | L94: =H94-J94 -> -835 | M94: =I94-K94 -> -10271.71 | N94: =M94/K94 -> -1
A95: B07TSNCJ5J | B95: BP.800 | C95: 40 | D95: 465.02 | E95: 0 | F95: 0 | G95: =F95/I95 -> 0 | H95: =E95+C95 -> 40 | I95: =F95+D95 -> 465.02 | J95: =VLOOKUP(A95,v_2023!A:D,3,FALSE) -> 54 | K95: =VLOOKUP(A95,v_2023!A:D,4,FALSE) -> 620.82 | L95: =H95-J95 -> -14 | M95: =I95-K95 -> -155.8 | N95: =M95/K95 -> -0.25095841
A96: B07TTJQDC2 | B96: 70.404 | C96: 8 | D96: 198.73 | E96: 0 | F96: 0 | G96: =F96/I96 -> 0 | H96: =E96+C96 -> 8 | I96: =F96+D96 -> 198.73 | J96: =VLOOKUP(A96,v_2023!A:D,3,FALSE) -> 10 | K96: =VLOOKUP(A96,v_2023!A:D,4,FALSE) -> 245.4 | L96: =H96-J96 -> -2 | M96: =I96-K96 -> -46.67 | N96: =M96/K96 -> -0.1901793
A97: B07TVSJDCL | B97: MD.500 | C97: 0 | D97: 0 | E97: =VLOOKUP(A97,s_2024!A:C,2,FALSE) -> 1 | F97: =VLOOKUP(A97,s_2024!A:C,3,FALSE) -> 15.9 | G97: =F97/I97 -> 1 | H97: =E97+C97 -> 1 | I97: =F97+D97 -> 15.9 | J97: =VLOOKUP(A97,v_2023!A:D,3,FALSE) -> 0 | K97: =VLOOKUP(A97,v_2023!A:D,4,FALSE) -> 0 | L97: =H97-J97 -> 1 | M97: =I97-K97 -> 15.9
A98: B07TWX2L8N | B98: 40.361 | C98: 0 | D98: 0 | E98: 0 | F98: 0 | H98: =E98+C98 -> 0 | I98: =F98+D98 -> 0 | J98: =VLOOKUP(A98,v_2023!A:D,3,FALSE) -> 24 | K98: =VLOOKUP(A98,v_2023!A:D,4,FALSE) -> 184.5 | L98: =H98-J98 -> -24 | M98: =I98-K98 -> -184.5 | N98: =M98/K98 -> -1
A99: B07V131F5W | B99: 40.490 | C99: 172 | D99: 4167.01 | E99: =VLOOKUP(A99,s_2024!A:C,2,FALSE) -> 104 | F99: =VLOOKUP(A99,s_2024!A:C,3,FALSE) -> 3109.6 | G99: =F99/I99 -> 0.42734185 | H99: =E99+C99 -> 276 | I99: =F99+D99 -> 7276.61 | J99: =VLOOKUP(A99,v_2023!A:D,3,FALSE) -> 352 | K99: =VLOOKUP(A99,v_2023!A:D,4,FALSE) -> 8344.1 | L99: =H99-J99 -> -76 | M99: =I99-K99 -> -1067.49 | N99: =M99/K99 -> -0.12793351
A100: B07W7S9KYM | B100: BB.200 | C100: 25 | D100: 993.72 | E100: 0 | F100: 0 | G100: =F100/I100 -> 0 | H100: =E100+C100 -> 25 | I100: =F100+D100 -> 993.72 | J100: =VLOOKUP(A100,v_2023!A:D,3,FALSE) -> 21 | K100: =VLOOKUP(A100,v_2023!A:D,4,FALSE) -> 998.34 | L100: =H100-J100 -> 4 | M100: =I100-K100 -> -4.62 | N100: =M100/K100 -> -0.004627682
...
