Workbook

Sheet vendor_03_2023
A1: ASIN | B1: Numero del modello | C1: Codice marketplace | D1: Ricavi ordini | E1: Unità ordinate | F1: Ricavi spedizioni | G1: COGS spedizioni | H1: Unità spedite | I1: Resi cliente
A2: B07ZJQTGG8 | B2: 50.245 | C2: IT | D2: 22600.71 | E2: 1851 | F2: 22771.65 | G2: 14348.16 | H2: 1865 | I2: 55
A3: B01I497WWM | B3: 90.920R | C3: IT | D3: 18280.61 | E3: 1296 | F3: 18359.33 | G3: 11024.15 | H3: 1296 | I3: 115
A4: B096MX229M | B4: P102ROB050 | C4: DE | D4: 15499.76 | E4: 1238 | F4: 15850.32 | G4: 9798.32 | H4: 1266 | I4: 151
A5: B0757TJRR9 | B5: 40.500 | C5: IT | D5: 15132.43 | E5: 545 | F5: 14923.23 | G5: 9971.57 | H5: 537 | I5: 24
A6: B096MX229M | B6: P102ROB050 | C6: FR | D6: 13834.25 | E6: 1287 | F6: 13759 | G6: 9989.6 | H6: 1280 | I6: 63
A7: B0B8DLSNJF | B7: P302VIS050 | C7: IT | D7: 13374.2 | E7: 820 | F7: 13488.37 | G7: 11805.12 | H7: 827 | I7: 28
A8: B01KMJ9OXW | B8: 90.590Y | C8: FR | D8: 13050.89 | E8: 403 | F8: 13063.25 | G8: 8525.16 | H8: 403 | I8: 20
A9: B095PQJGKX | B9: C107UTT002 | C9: FR | D9: 12802.96 | E9: 1552 | F9: 12679.21 | G9: 8385.3 | H9: 1537 | I9: 14
A10: B095PQJGKX | B10: C107UTT002 | C10: ES | D10: 10264.25 | E10: 1255 | F10: 10583.27 | G10: 7059.84 | H10: 1294 | I10: 56
A11: B00NSNZSLM | B11: 90.602 | C11: IT | D11: 10082.54 | E11: 494 | F11: 10347.87 | G11: 8850.36 | H11: 507 | I11: 15
A12: B09146GTKW | B12: P302VIS002 | C12: IT | D12: 9561.69 | E12: 1179 | F12: 9537.36 | G12: 6878.4 | H12: 1176 | I12: 42
A13: B07ZJQTGG8 | B13: 50.245 | C13: FR | D13: 9041.76 | E13: 728 | F13: 9066.6 | G13: 6083.02 | H13: 730 | I13: 26
... A43: B085R2GCKX | B43: 40.332 | C43: IT | D43: 3828.87 | E43: 261 | F43: 3916.89 | G43: 2152.1 | H43: 267 | I43: 16
A44: B0050IHH4E | B44: 40.979 | C44: IT | D44: 3824.22 | E44: 294 | F44: 3516.1 | G44: 2750.5 | H44: 270
A45: B07N4C3H3V | B45: 40.405 | C45: DE | D45: 3741.4 | E45: 373 | F45: 3763.11 | G45: 2412.72 | H45: 375 | I45: 11
A46: B085JJ8RC6 | B46: BB.050 | C46: FR | D46: 3674.54 | E46: 269 | F46: 3783.82 | G46: 2907.52 | H46: 277 | I46: 18
A47: B0757TJRR9 | B47: 40.500 | C47: FR | D47: 3633.84 | E47: 132 | F47: 3559.08 | G47: 2427.48 | H47: 129 | I47: 9
A48: B096MX229M | B48: P102ROB050 | C48: ES | D48: 3631.45 | E48: 295 | F48: 3656.07 | G48: 2265.6 | H48: 297 | I48: 42
A49: B0BJ2TBPJW | B49: C206UTI004 | C49: IT | D49: 3594.46 | E49: 879 | F49: 3545.38 | G49: 2336.74 | H49: 867 | I49: 1
A50: B08GY7286R | B50: P203TFO001 | C50: IT | D50: 3586.73 | E50: 199 | F50: 3680.72 | G50: 2055.59 | H50: 204 | I50: 31
A51: B08L9D9KR9 | B51: P202VAL001 | C51: IT | D51: 3502.16 | E51: 71 | F51: 3598.9 | G51: 3244.7 | H51: 73 | I51: 11
A52: B07NQ2VYGD | B52: BT.710Y | C52: FR | D52: 3496.67 | E52: 97 | F52: 3618.23 | G52: 1786.7 | H52: 100 | I52: 6
A53: B07NQC6S9V | B53: BT.651Y | C53: FR | D53: 3480.06 | E53: 93 | F53: 3517.48 | G53: 3172.5 | H53: 94 | I53: 2
A54: B097HRQNRG | B54: P101FRI100 | C54: DE | D54: 3436.04 | E54: 110 | F54: 3343.01 | G54: 1996.44 | H54: 107 | I54: 26
A55: B06Y195DJN | B55: 90.882 | C55: FR | D55: 3207.82 | E55: 77 | F55: 3082.84 | G55: 2278.9 | H55: 74 | I55: 13
A56: B088XJQ37J | B56: C301ABE001 | C56: IT | D56: 3202.71 | E56: 303 | F56: 3266.13 | G56: 2111.52 | H56: 309 | I56: 29
... A60: B095X9KDJR | B60: P101BOL100 | C60: FR | D60: 2865.04 | E60: 173 | F60: 2815.3 | G60: 2284.5 | H60: 170 | I60: 12
A61: B08LZN1PWY | B61: P101TEM001 | C61: FR | D61: 2840.19 | E61: 33 | F61: 2580.48 | G61: 1385.22 | H61: 30
A62: B08B66J4C3 | B62: P101PIA001 | C62: DE | D62: 2817.35 | E62: 224 | F62: 2804.83 | G62: 1480.67 | H62: 223 | I62: 13
A63: B084C3JTC2 | B63: 40.406 | C63: IT | D63: 2745.12 | E63: 112 | F63: 2549.04 | G63: 1965.39 | H63: 104 | I63: 8
A64: B085JHTR6Q | B64: BP.790 | C64: IT | D64: 2653.39 | E64: 129 | F64: 2641.18 | G64: 2101.28 | H64: 128 | I64: 7
A65: B09B47S644 | B65: P101CUD501 | C65: FR | D65: 2594.99 | E65: 89 | F65: 2567.29 | G65: 1743.4 | H65: 88 | I65: 5
A66: B0B8DLSNJF | B66: P302VIS050 | C66: ES | D66: 2549.75 | E66: 155 | F66: 2516.85 | G66: 2210.83 | H66: 153 | I66: 5
A67: B07NQ1T7YK | B67: BP.101H | C67: IT | D67: 2539.68 | E67: 208 | F67: 2637.36 | G67: 2303.04 | H67: 216 | I67: 11
A68: B07KYWNC7Z | B68: 40.405 | C68: IT | D68: 2535.71 | E68: 129 | F68: 2358.64 | G68: 1998 | H68: 120 | I68: 4
A69: B07NQ2VYGD | B69: BT.710Y | C69: ES | D69: 2446.29 | E69: 99 | F69: 2495.71 | G69: 1815.68 | H69: 101 | I69: 16
A70: B07HM7P6MP | B70: RI.080 | C70: IT | D70: 2439.18 | E70: 112 | F70: 2456.68 | G70: 1976.48 | H70: 113 | I70: 7
A71: B0BD83RNDG | B71: C106CAS002 | C71: IT | D71: 2420.53 | E71: 229 | F71: 2441.67 | G71: 1997.1 | H71: 231 | I71: 1
A72: B076QFRRZ5 | B72: 40.931 | C72: IT | D72: 2411.94 | E72: 178 | F72: 2412.83 | G72: 1199.32 | H72: 178 | I72: 25
A73: B08GS7XW73 | B73: P204FER250 | C73: DE | D73: 2354.37 | E73: 135 | F73: 2490.45 | G73: 1841 | H73: 143 | I73: 11
... A80: B07N4C3H3V | B80: 40.405 | C80: IT | D80: 2181.9 | E80: 225 | F80: 2146.57 | G80: 1473.12 | H80: 222 | I80: 8
A81: B08JZDZTPG | B81: BP.803 | C81: FR | D81: 2161.5 | E81: 262 | F81: 2186.25 | G81: 1460.15 | H81: 265
A82: B09LHXJXQL | B82: P102SBA007 | C82: FR | D82: 1826.82 | E82: 104 | F82: 1824.32 | G82: 1459.4 | H82: 104 | I82: 5
A83: B085R2GCKX | B83: 40.332 | C83: ES | D83: 1815.58 | E83: 112 | F83: 1815.58 | G83: 903.1 | H83: 112 | I83: 5
A84: B06Y17FS6D | B84: 90.550 | C84: FR | D84: 1815.19 | E84: 54 | F84: 1781.94 | G84: 1187.37 | H84: 53 | I84: 5
A85: B0BD83RNDG | B85: C106CAS002 | C85: DE | D85: 1810.28 | E85: 167 | F85: 1810.28 | G85: 1453.24 | H85: 167 | I85: 3
A86: B07YZZZVXP | B86: MD.404 | C86: IT | D86: 1780.31 | E86: 29 | F86: 1718.92 | G86: 1392.64 | H86: 28 | I86: 5
A87: B08FDYW72J | B87: P101CUD100 | C87: DE | D87: 1718.03 | E87: 55 | F87: 1725.67 | G87: 919.05 | H87: 55 | I87: 14
A88: B00FAJUDU8 | B88: 40.967N | C88: FR | D88: 1717.34 | E88: 80 | F88: 1705.08 | G88: 1084.38 | H88: 80 | I88: 3
A89: B08KSBDTQD | B89: P102ROB001 | C89: FR | D89: 1715.72 | E89: 59 | F89: 1657.56 | G89: 1273.77 | H89: 57 | I89: 1
A90: B08GY7286R | B90: P203TFO001 | C90: DE | D90: 1710.08 | E90: 128 | F90: 1696.72 | G90: 1309.13 | H90: 127 | I90: 28
A91: B09D8G2H7Q | B91: P102SBA500 | C91: IT | D91: 1705.28 | E91: 18 | F91: 1797.3 | G91: 1422.7 | H91: 19 | I91: 4
A92: B07ZJMFB3R | B92: BC.510 | C92: IT | D92: 1694.4 | E92: 30 | F92: 1637.92 | G92: 1147.49 | H92: 29 | I92: 1
A93: B0BD83RNDG | B93: C106CAS002 | C93: ES | D93: 1673.62 | E93: 157 | F93: 1726.92 | G93: 1408.52 | H93: 162 | I93: 3
... A102: B07JGVMFY1 | B102: BP.581 | C102: IT | D102: 1504.64 | E102: 123 | F102: 1480.22 | G102: 1218.47 | H102: 121 | I102: 4
A103: B08JYWF3PK | B103: C102COC101 | C103: FR | D103: 1468.5 | E103: 178 | F103: 1460.25 | G103: 1023.57 | H103: 177
A104: B085JHTR6Q | B104: BP.790 | C104: FR | D104: 1449.05 | E104: 59 | F104: 1454.2 | G104: 950.03 | H104: 59 | I104: 4
A105: B09495C38F | B105: P204FER002 | C105: ES | D105: 1437.7 | E105: 88 | F105: 1454.15 | G105: 1112.5 | H105: 89 | I105: 3
A106: B076DCL19C | B106: BP.720 | C106: IT | D106: 1436.05 | E106: 24 | F106: 1436.05 | G106: 943.92 | H106: 24 | I106: 3
A107: B09146GTKW | B107: P302VIS002 | C107: FR | D107: 1402.5 | E107: 170 | F107: 1460.25 | G107: 1026.9 | H107: 177 | I107: 4
A108: B0823CVGHX | B108: BP.400 | C108: DE | D108: 1371.12 | E108: 24 | F108: 1428.25 | G108: 1101.49 | H108: 25 | I108: 7
A109: B09NBXYF5J | B109: P101TOS002 | C109: IT | D109: 1361.47 | E109: 71 | F109: 1396.87 | G109: 1174.86 | H109: 73 | I109: 3
A110: B09BD8BG34 | B110: P301PIS001 | C110: IT | D110: 1322.11 | E110: 115 | F110: 1359.39 | G110: 1047.2 | H110: 119 | I110: 7
A111: B08GS7XW73 | B111: P204FER250 | C111: FR | D111: 1311.94 | E111: 77 | F111: 1382.46 | G111: 1046.88 | H111: 81 | I111: 7
A112: B00L5H5KUW | B112: 40.121 | C112: ES | D112: 1291.94 | E112: 63 | F112: 1291.94 | G112: 819.78 | H112: 63
A113: B01CNX6Z78 | B113: 90.820 | C113: FR | D113: 1270.02 | E113: 61 | F113: 1249.2 | G113: 957.81 | H113: 60 | I113: 4
A114: B09LHXJXQL | B114: P102SBA007 | C114: DE | D114: 1254 | E114: 75 | F114: 1254 | G114: 1048.32 | H114: 75 | I114: 1
A115: B07V131F5W | B115: 40.490 | C115: FR | D115: 1248.65 | E115: 51 | F115: 1271.9 | G115: 903.55 | H115: 52 | I115: 4
A116: B076Q7BR6F | B116: BC.041N | C116: FR | D116: 1247.4 | E116: 30 | F116: 1205.82 | G116: 855 | H116: 29
A117: B08485QRVZ | B117: BC.261 | C117: FR | D117: 1241.71 | E117: 39 | F117: 1216.24 | G117: 683.4 | H117: 38 | I117: 1
A118: B09BD8BG34 | B118: P301PIS001 | C118: ES | D118: 1215.24 | E118: 114 | F118: 1300.52 | G118: 1073.6 | H118: 122 | I118: 11
A119: B07YBNB2QY | B119: 50161 | C119: FR | D119: 1205.82 | E119: 29 | F119: 1081.08 | G119: 768.57 | H119: 26 | I119: 1
A120: B09KYD9JGY | B120: P301PIS100 | C120: ES | D120: 1204.75 | E120: 61 | F120: 1244.25 | G120: 979.69 | H120: 63 | I120: 20
A121: B00FAJUDU8 | B121: 40.967N | C121: ES | D121: 1188.11 | E121: 51 | F121: 1161.09 | G121: 619.84 | H121: 50 | I121: 2
A122: B073B57HQH | B122: 90.886 | C122: IT | D122: 1182.82 | E122: 12 | F122: 1182.82 | G122: 848.28 | H122: 12 | I122: 1
A123: B09KYD9JGY | B123: P301PIS100 | C123: FR | D123: 1182.75 | E123: 57 | F123: 1245 | G123: 933.15 | H123: 60 | I123: 12
A124: B07P7GGGQM | B124: BP.961 | C124: DE | D124: 1169.2 | E124: 26 | F124: 1254.86 | G124: 796.14 | H124: 27 | I124: 12
A125: B07YZZZVXP | B125: MD.404 | C125: DE | D125: 1160.53 | E125: 19 | F125: 1224.61 | G125: 1004.85 | H125: 20 | I125: 9
A126: B0757TJRR9 | B126: 40.500 | C126: GB | D126: 1151.77 | E126: 40 | F126: 1236.74 | G126: 958.77 | H126: 43 | I126: 4
A127: B08C7YJB5N | B127: P201UTP001 | C127: IT | D127: 1143.04 | E127: 128 | F127: 1143.04 | G127: 870.01 | H127: 128 | I127: 9
A128: B0B2F48ZMP | B128: P102GEL100 | C128: IT | D128: 1121.43 | E128: 32 | F128: 1085.43 | G128: 927.52 | H128: 31 | I128: 3
A129: B08JYWF3PK | B129: C102COC101 | C129: ES | D129: 1111.36 | E129: 151 | F129: 1155.52 | G129: 812.85 | H129: 157
A130: B085R2GCKX | B130: 40.332 | C130: DE | D130: 1103.52 | E130: 66 | F130: 1120.24 | G130: 607.77 | H130: 67 | I130: 5
A131: B096MX229M | B131: P102ROB050 | C131: GB | D131: 1101.18 | E131: 115 | F131: 1120.21 | G131: 917.72 | H131: 117 | I131: 4
A132: B07RRBS54G | B132: BP.620 | C132: DE | D132: 1092.56 | E132: 29 | F132: 1101.74 | G132: 2668 | H132: 29 | I132: 4
A133: B01M4O6145 | B133: 90.071 | C133: IT | D133: 1090.75 | E133: 53 | F133: 1070.34 | G133: 754.52 | H133: 52 | I133: 6
A134: B08KSBDTQD | B134: P102ROB001 | C134: ES | D134: 1087.24 | E134: 44 | F134: 1062.53 | G134: 1085.54 | H134: 43 | I134: 2
A135: B08B66J4C3 | B135: P101PIA001 | C135: FR | D135: 1068.98 | E135: 85 | F135: 1088.84 | G135: 584.54 | H135: 87 | I135: 4
A136: B097HRQNRG | B136: P101FRI100 | C136: FR | D136: 1051.66 | E136: 26 | F136: 1051.66 | G136: 468.78 | H136: 26 | I136: 3
A137: B0B39H1Z8J | B137: C106CAS001 | C137: ES | D137: 1047.04 | E137: 128 | F137: 1038.86 | G137: 740.74 | H137: 127 | I137: 5
A138: B09D8G2H7Q | B138: P102SBA500 | C138: FR | D138: 1041.93 | E138: 11 | F138: 1041.93 | G138: 791.07 | H138: 11 | I138: 4
A139: B085R2GCKX | B139: 40.332 | C139: FR | D139: 1031.6 | E139: 70 | F139: 1048.18 | G139: 742.17 | H139: 71 | I139: 4
A140: B01I497WWM | B140: 90.920R | C140: ES | D140: 1031.4 | E140: 66 | F140: 1064.3 | G140: 567.8 | H140: 68 | I140: 5
A141: B097HRQNRG | B141: P101FRI100 | C141: IT | D141: 1029.96 | E141: 36 | F141: 1029.96 | G141: 591.48 | H141: 36 | I141: 8
... A149: B07JGVMFY1 | B149: BP.581 | C149: FR | D149: 916.81 | E149: 73 | F149: 867.13 | G149: 704.9 | H149: 69 | I149: 2
A150: B0B5XB4X2T | B150: P102ACP100 | C150: IT | D150: 913.36 | E150: 56 | F150: 897.05 | G150: 928.4 | H150: 55
A151: B01CNX71NA | B151: 90.871 | C151: IT | D151: 903.8 | E151: 11 | F151: 903.8 | G151: 699.64 | H151: 11
A152: B08B66J4C3 | B152: P101PIA001 | C152: ES | D152: 896.28 | E152: 72 | F152: 920.9 | G152: 494.93 | H152: 74 | I152: 2
A153: B0B2F48ZMP | B153: P102GEL100 | C153: DE | D153: 893.53 | E153: 23 | F153: 854.12 | G153: 667.72 | H153: 22 | I153: 3
...

Sheet vendor_03_2024
A1: ASIN | B1: Numero del modello | C1: Codice marketplace | D1: Ricavi ordini | E1: Unità ordinate | F1: Ricavi spedizioni | G1: COGS spedizioni | H1: Unità spedite | I1: Resi cliente
A2: B0BHHV552D | B2: P203TER201 | C2: IT | D2: 9074.87 | E2: 558 | F2: 8862.85 | G2: 6568.29 | H2: 545 | I2: 85
A3: B0050IHH4E | B3: 40.979 | C3: DE | D3: 8964.88 | E3: 634 | F3: 8911.52 | G3: 5696.78 | H3: 626 | I3: 45
A4: B0050IHH4E | B4: 40.979 | C4: IT | D4: 6983.03 | E4: 486 | F4: 6700.53 | G4: 4517.98 | H4: 466 | I4: 15
A5: B09146GTKW | B5: P302VIS002 | C5: IT | D5: 5723.45 | E5: 544 | F5: 5533.77 | G5: 3168 | H5: 528 | I5: 28
A6: B096MX229M | B6: P102ROB050 | C6: DE | D6: 5380.42 | E6: 431 | F6: 5105.68 | G6: 3225.2 | H6: 409 | I6: 31
A7: B0CLVS3FH6 | B7: P201UTP111 | C7: IT | D7: 5284.44 | E7: 324 | F7: 4990.86 | G7: 4284 | H7: 306 | I7: 24
A8: B00L5H5KUW | B8: 40.121 | C8: IT | D8: 5023.29 | E8: 275 | F8: 4969.44 | G8: 3229 | H8: 272
A9: B0BBH12BYN | B9: P101COS001 | C9: IT | D9: 5001.34 | E9: 57 | F9: 5079.94 | G9: 3342.7 | H9: 58 | I9: 16
A10: B07SSLRCT6 | B10: BP.304 | C10: FR | D10: 3652.58 | E10: 253 | F10: 3770.46 | G10: 2744.2 | H10: 262 | I10: 23
A11: B07Q38Z7CK | B11: BC.060 | C11: IT | D11: 3399.3 | E11: 168 | F11: 3460.53 | G11: 2565 | H11: 171 | I11: 34
A12: B09968BKDS | B12: P102FRU003 | C12: FR | D12: 2885.72 | E12: 203 | F12: 2835.81 | G12: 1745.72 | H12: 200 | I12: 20
A13: B07JGVMFY1 | B13: BP.581 | C13: FR | D13: 2760.2 | E13: 185 | F13: 2715.44 | G13: 1833.8 | H13: 182 | I13: 15
A14: B08GY7286R | B14: P203TFO001 | C14: IT | D14: 2651.93 | E14: 191 | F14: 2734.11 | G14: 1960.2 | H14: 198 | I14: 15
A15: B07V131F5W | B15: 40.490 | C15: IT | D15: 2591.61 | E15: 105 | F15: 2542.59 | G15: 1854 | H15: 103 | I15: 1
A16: B0B39H1Z8J | B16: C106CAS001 | C16: IT | D16: 2397.59 | E16: 222 | F16: 2343.81 | G16: 1140.12 | H16: 217 | I16: 30
A17: B0CLY2CF4T | B17: P201UTP113 | C17: IT | D17: 2234.47 | E17: 137 | F17: 2201.85 | G17: 1890 | H17: 135 | I17: 5
A18: B0BJ2TBPJW | B18: C206UTI004 | C18: IT | D18: 2224.23 | E18: 453 | F18: 2199.68 | G18: 950.98 | H18: 448 | I18: 1
A19: B076QCMZX1 | B19: 40.821 | C19: IT | D19: 1977.32 | E19: 162 | F19: 1989.53 | G19: 1371.9 | H19: 163 | I19: 13
A20: B0B8JVTQYQ | B20: P101CUD200 | C20: DE | D20: 1957.21 | E20: 42 | F20: 1957.21 | G20: 1438.29 | H20: 42 | I20: 21
... A63: B0BNNH9RZQ | B63: P302VIS060 | C63: ES | D63: 900.25 | E63: 72 | F63: 900.25 | G63: 502.92 | H63: 72 | I63: 37
A64: B07NQ2VYGD | B64: BT.710Y | C64: ES | D64: 864.85 | E64: 35 | F64: 1087.24 | G64: 765.6 | H64: 44
A65: B07NQ1T7YK | B65: BP.101H | C65: FR | D65: 856.06 | E65: 61 | F65: 980.44 | G65: 703.36 | H65: 72 | I65: 10
A66: B0CLVS3FH6 | B66: P201UTP111 | C66: DE | D66: 853.17 | E66: 45 | F66: 853.17 | G66: 630 | H66: 45 | I66: 3
A67: B09D8G2H7Q | B67: P102SBA500 | C67: IT | D67: 842.72 | E67: 8 | F67: 842.72 | G67: 646.4 | H67: 8 | I67: 11
A68: B07V131F5W | B68: 40.490 | C68: ES | D68: 819.64 | E68: 34 | F68: 716.59 | G68: 522 | H68: 29 | I68: 1
A69: B076DCL19C | B69: BP.720 | C69: IT | D69: 814.3 | E69: 17 | F69: 814.3 | G69: 670.85 | H69: 17 | I69: 6
A70: B09D8G2H7Q | B70: P102SBA500 | C70: FR | D70: 755.38 | E70: 7 | F70: 644.75 | G70: 484.8 | H70: 6
A71: B01M4O6145 | B71: 90.071 | C71: IT | D71: 755.17 | E71: 37 | F71: 693.94 | G71: 657.9 | H71: 34 | I71: 4
A72: B0B2F48ZMP | B72: P102GEL100 | C72: FR | D72: 723.25 | E72: 21 | F72: 689.72 | G72: 598.4 | H72: 20 | I72: 2
A73: B09BD8BG34 | B73: P301PIS001 | C73: DE | D73: 713.64 | E73: 57 | F73: 688.6 | G73: 484 | H73: 55 | I73: 8
A74: B08FMLPKY9 | B74: P201UTP004 | C74: FR | D74: 712.94 | E74: 43 | F74: 712.94 | G74: 580.5 | H74: 43 | I74: 8
A75: B085R2GCKX | B75: 40.332 | C75: IT | D75: 712.92 | E75: 43 | F75: 664.39 | G75: 450 | H75: 40 | I75: 14
A76: B07ZJMFB3R | B76: BC.510 | C76: IT | D76: 709.12 | E76: 12 | F76: 709.12 | G76: 556.8 | H76: 12 | I76: 6
A77: B0B8JVTQYQ | B77: P101CUD200 | C77: ES | D77: 701.68 | E77: 18 | F77: 712.34 | G77: 615.6 | H77: 18 | I77: 1
A78: B08JYWF3PK | B78: C102COC101 | C78: FR | D78: 701.25 | E78: 85 | F78: 726 | G78: 528 | H78: 88
A79: B0BD83RNDG | B79: C106CAS002 | C79: IT | D79: 690.53 | E79: 62 | F79: 722.24 | G79: 479.37 | H79: 65 | I79: 4
A80: B07R984VMS | B80: BI.505 | C80: FR | D80: 687.96 | E80: 93 | F80: 687.96 | G80: 587.76 | H80: 93 | I80: 1
A81: B011LFVLW8 | B81: 90.620 | C81: IT | D81: 686.19 | E81: 19 | F81: 751.59 | G81: 567 | H81: 21 | I81: 6
A82: B06Y1997YH | B82: 90.883 | C82: IT | D82: 685.1 | E82: 11 | F82: 742.4 | G82: 511.44 | H82: 12 | I82: 4
A83: B0CHFQXMZX | B83: P203PAN001 | C83: FR | D83: 677.25 | E83: 43 | F83: 693 | G83: 418 | H83: 44 | I83: 31
A84: B084C3JTC2 | B84: 40.406 | C84: IT | D84: 676.38 | E84: 28 | F84: 674.09 | G84: 563.27 | H84: 28 | I84: 5
A85: B085JHSWJH | B85: BP.802 | C85: IT | D85: 665.8 | E85: 51 | F85: 653.67 | G85: 485.8 | H85: 50
A86: B0CHWMFNNT | B86: P202ASP250 | C86: FR | D86: 665.28 | E86: 16 | F86: 582.12 | G86: 420 | H86: 14 | I86: 2
A87: B07B9CPH62 | B87: BG.200Y | C87: ES | D87: 643.5 | E87: 13 | F87: 643.5 | G87: 526.5 | H87: 13 | I87: 3
A88: B088V4DR59 | B88: P206ZAN040 | C88: IT | D88: 631.3 | E88: 12 | F88: 575.15 | G88: 450.49 | H88: 11
A89: B085JJ8RC6 | B89: BB.050 | C89: FR | D89: 627.89 | E89: 44 | F89: 667.19 | G89: 455.9 | H89: 47 | I89: 8
A90: B08GS7XW73 | B90: P204FER250 | C90: FR | D90: 626.08 | E90: 38 | F90: 495.42 | G90: 391.5 | H90: 30 | I90: 2
A91: B09BD8BG34 | B91: P301PIS001 | C91: FR | D91: 621 | E91: 50 | F91: 683.1 | G91: 484 | H91: 55 | I91: 4
A92: B09146GTKW | B92: P302VIS002 | C92: FR | D92: 618.75 | E92: 75 | F92: 577.5 | G92: 420 | H92: 70 | I92: 4
A93: B0BTHSH5MK | B93: C103ACC001 | C93: FR | D93: 618.75 | E93: 75 | F93: 594 | G93: 390.08 | H93: 72 | I93: 3
A94: B096MX229M | B94: P102ROB050 | C94: ES | D94: 615.5 | E94: 50 | F94: 590.88 | G94: 383.6 | H94: 48 | I94: 1
A95: B0BNNH9RZQ | B95: P302VIS060 | C95: DE | D95: 613.48 | E95: 49 | F95: 626 | G95: 375.66 | H95: 50 | I95: 48
A96: B085JHTR6Q | B96: BP.790 | C96: IT | D96: 612.75 | E96: 25 | F96: 612.75 | G96: 448.25 | H96: 25 | I96: 1
A97: B0B39H1Z8J | B97: C106CAS001 | C97: GB | D97: 606.35 | E97: 54 | F97: 573.37 | G97: 315.19 | H97: 51 | I97: 2
A98: B076QFRRZ5 | B98: 40.931 | C98: IT | D98: 573.31 | E98: 40 | F98: 569.68 | G98: 261.6 | H98: 40 | I98: 11
A99: B01CNX71NA | B99: 90.871 | C99: ES | D99: 572.74 | E99: 7 | F99: 572.74 | G99: 465.5 | H99: 7
A100: B085JHSWJH | B100: BP.802 | C100: FR | D100: 569.75 | E100: 43 | F100: 530 | G100: 356.8 | H100: 40 | I100: 2
A101: B08JYWF3PK | B101: C102COC101 | C101: IT | D101: 567.63 | E101: 63 | F101: 558.62 | G101: 372 | H101: 62
A102: B09KYD9JGY | B102: P301PIS100 | C102: IT | D102: 549.39 | E102: 21 | F102: 602.99 | G102: 344.08 | H102: 23 | I102: 4
A103: B0BVBY1RWS | B103: P206VEN550 | C103: DE | D103: 545.09 | E103: 13 | F103: 545.09 | G103: 455 | H103: 13 | I103: 1
A104: B07KYWNC7Z | B104: 40.405 | C104: IT | D104: 540.71 | E104: 25 | F104: 540.71 | G104: 416.25 | H104: 25 | I104: 3
A105: B0CPFRMPTM | B105: P101CAF001 | C105: ES | D105: 518.91 | E105: 21 | F105: 518.91 | G105: 556.5 | H105: 21 | I105: 1
A106: B09LHXJXQL | B106: P102SBA007 | C106: IT | D106: 516.37 | E106: 28 | F106: 479.06 | G106: 365.56 | H106: 26 | I106: 5
A107: B0CHFQXMZX | B107: P203PAN001 | C107: ES | D107: 498.28 | E107: 32 | F107: 498.28 | G107: 304 | H107: 32 | I107: 17
A108: B0CHF7YW6B | B108: P203PAN010 | C108: FR | D108: 493.56 | E108: 18 | F108: 493.56 | G108: 333 | H108: 18 | I108: 3
A109: B09L4SLDSZ | B109: P203TFO100 | C109: IT | D109: 490.2 | E109: 20 | F109: 514.71 | G109: 353.76 | H109: 21 | I109: 4
A110: B0C94Q6QZ9 | B110: P101TOS100 | C110: IT | D110: 489.7 | E110: 21 | F110: 489.7 | G110: 306.39 | H110: 21 | I110: 26
A111: B08GS7XW73 | B111: P204FER250 | C111: IT | D111: 488.1 | E111: 30 | F111: 358.82 | G111: 286.75 | H111: 22 | I111: 6
A112: B0BD83RNDG | B112: C106CAS002 | C112: FR | D112: 486.46 | E112: 40 | F112: 518.71 | G112: 324.76 | H112: 43 | I112: 5
A113: B0BJL1Z674 | B113: C102SPE001 | C113: FR | D113: 485.52 | E113: 77 | F113: 472.2 | G113: 232.54 | H113: 75 | I113: 3
A114: B07NQ1T7YK | B114: BP.101H | C114: ES | D114: 480.09 | E114: 39 | F114: 480.09 | G114: 412.04 | H114: 39 | I114: 1
A115: B08L9D9KR9 | B115: P202VAL001 | C115: FR | D115: 466 | E115: 8 | F115: 466 | G115: 360 | H115: 8
A116: B0BVZG7FPY | B116: P206VEN600 | C116: IT | D116: 464.74 | E116: 12 | F116: 464.74 | G116: 307.8 | H116: 12 | I116: 8
A117: B08Y6RJ69Y | B117: P204CAL001 | C117: ES | D117: 464.51 | E117: 8 | F117: 464.51 | G117: 288.64 | H117: 8 | I117: 1
A118: B07B9CPH62 | B118: BG.200Y | C118: FR | D118: 464.06 | E118: 5 | F118: 464.06 | G118: 202.5 | H118: 5 | I118: 1
A119: B08GSK6C18 | B119: P204FER200 | C119: ES | D119: 460.6 | E119: 28 | F119: 444.15 | G119: 351.03 | H119: 27
A120: B0B2F48ZMP | B120: P102GEL100 | C120: IT | D120: 451.55 | E120: 12 | F120: 412.05 | G120: 329.12 | H120: 11 | I120: 2
A121: B0050IHH4E | B121: 40.979 | C121: ES | D121: 444.71 | E121: 34 | F121: 444.71 | G121: 339.02 | H121: 34 | I121: 2
A122: B092QXCQ8K | B122: P205DIF001 | C122: FR | D122: 438.44 | E122: 32 | F122: 479.27 | G122: 343.79 | H122: 35 | I122: 2
A123: B09HMK8JDN | B123: P203TER001 | C123: ES | D123: 437.95 | E123: 5 | F123: 437.95 | G123: 365.75 | H123: 5 | I123: 1
A124: B073B67PLQ | B124: 90.884 | C124: ES | D124: 437.22 | E124: 7 | F124: 437.22 | G124: 472.5 | H124: 7 | I124: 1
A125: B097YTGFH7 | B125: P102ROB200 | C125: IT | D125: 433.99 | E125: 7 | F125: 433.99 | G125: 406 | H125: 7 | I125: 1
A126: B08C7YJB5N | B126: P201UTP001 | C126: IT | D126: 432.96 | E126: 33 | F126: 407.04 | G126: 145.5 | H126: 32
A127: B07V131F5W | B127: 40.490 | C127: DE | D127: 431.8 | E127: 20 | F127: 431.8 | G127: 361.21 | H127: 20 | I127: 1
A128: B08GY7286R | B128: P203TFO001 | C128: FR | D128: 429.83 | E128: 30 | F128: 443.8 | G128: 306.9 | H128: 31 | I128: 9
A129: B0050IHH4E | B129: 40.979 | C129: FR | D129: 429.59 | E129: 29 | F129: 542.57 | G129: 327.08 | H129: 36 | I129: 3
A130: B085R2GCKX | B130: 40.332 | C130: DE | D130: 418 | E130: 25 | F130: 351.12 | G130: 236.25 | H130: 21 | I130: 3
A131: B09B47S644 | B131: P101CUD501 | C131: DE | D131: 416.22 | E131: 13 | F131: 399.68 | G131: 271.7 | H131: 13 | I131: 4
A132: B091LRR67V | B132: P101FRI050 | C132: IT | D132: 415.55 | E132: 7 | F132: 415.55 | G132: 399.79 | H132: 7 | I132: 4
A133: B08FMLPKY9 | B133: P201UTP004 | C133: DE | D133: 413.53 | E133: 24 | F133: 413.53 | G133: 319.05 | H133: 24 | I133: 2
A134: B09LHXJXQL | B134: P102SBA007 | C134: FR | D134: 413.04 | E134: 18 | F134: 413.04 | G134: 253.08 | H134: 18 | I134: 1
A135: B0BJ2TBPJW | B135: C206UTI004 | C135: ES | D135: 405.65 | E135: 85 | F135: 387.35 | G135: 164 | H135: 82
A136: B08LZN1PWY | B136: P101TEM001 | C136: ES | D136: 404.39 | E136: 7 | F136: 462.16 | G136: 388.96 | H136: 8
A137: B088XJQ37J | B137: C301ABE001 | C137: IT | D137: 402.93 | E137: 33 | F137: 402.93 | G137: 214.35 | H137: 33 | I137: 3
A138: B0CHF7YW6B | B138: P203PAN010 | C138: DE | D138: 387.1 | E138: 14 | F138: 359.45 | G138: 240.5 | H138: 13 | I138: 2
A139: B0BD4VX5JB | B139: P203PAN002 | C139: IT | D139: 380.8 | E139: 4 | F139: 490.05 | G139: 280.55 | H139: 5
A140: B097YTGFH7 | B140: P102ROB200 | C140: DE | D140: 376.32 | E140: 9 | F140: 376.32 | G140: 522 | H140: 9 | I140: 2
A141: B07P7GGGQM | B141: BP.961 | C141: FR | D141: 374.22 | E141: 9 | F141: 374.22 | G141: 324 | H141: 9 | I141: 1
A142: B085JHTR6Q | B142: BP.790 | C142: FR | D142: 373.8 | E142: 15 | F142: 373.8 | G142: 268.95 | H142: 15
...

Sheet seller_03_2024
A1: amazon-order-id | B1: merchant-order-id | C1: purchase-date | D1: last-updated-date | E1: order-status | F1: fulfillment-channel | G1: sales-channel | H1: order-channel | I1: url | J1: ship-service-level | K1: product-name | L1: sku | M1: asin | N1: item-status | O1: quantity | P1: currency | Q1: item-price | R1: item-tax | S1: shipping-price | T1: shipping-tax | U1: gift-wrap-price | V1: gift-wrap-tax | W1: item-promotion-discount | X1: ship-promotion-discount | Y1: ship-city | Z1: ship-state | AA1: ship-postal-code | AB1: ship-country | AC1: promotion-ids | AD1: buyer-company-name | AE1: buyer-cst-number | AF1: buyer-vat-number | AG1: buyer-tax-registration-id | AH1: buyer-tax-registration-country | AI1: buyer-tax-registration-type
A2: 171-1499659-3176339 | B2: 171-1499659-3176339 | C2: 2024-03-31T20:39:14+00:00 | D2: 2024-03-31T20:40:22+00:00 | E2: Pending | F2: Amazon | G2: Amazon.fr | J2: Standard | K2: BEPER 40.405 Seche Cheveux de Voyage Pliable - Mini Seche Cheveux Silencieux, 2 Températures et 2 Vitesses | L2: 40.405_FBA | M2: B07N4C3H3V | N2: Unshipped | O2: 1 | P2: EUR | Q2: 19.9 | Y2: Courchevel | AA2: 73120 | AB2: FR
A3: 171-2567557-4574741 | B3: 171-2567557-4574741 | C3: 2024-03-31T18:05:43+00:00 | D3: 2024-04-03T01:23:10+00:00 | E3: Shipped | F3: Amazon | G3: Amazon.fr | J3: Standard | K3: Beper - Cuiseur à Vapeur Multicombustion de 5L, Économiseur d'Espace, Minuterie de 60 minutes, Cuisson à la Vapeur Saine, Puissance 400-500W - Arge | L3: BC.261_FBA | M3: B08485QRVZ | N3: Shipped | O3: 1 | P3: EUR | Q3: 39.9 | R3: 6.65 | Y3: Rouen | AA3: 76100 | AB3: FR | AC3: Free Shipping 2017/10/17 17-17-37-677
A4: 403-1418796-1133936 | B4: 403-1418796-1133936 | C4: 2024-03-31T17:41:39+00:00 | D4: 2024-04-03T11:19:38+00:00 | E4: Shipped | F4: Amazon | G4: Amazon.fr | J4: Standard | K4: Beper - Machine à Pop-Corn, Pop-Corn en 3 Minutes, Sans Matières Grasses, Circulation d'Air Chaud, Puissance 1200W - Rouge [Classe d'efficacité én | L4: 90.590Y_FBA | M4: B01KMJ9OXW | N4: Shipped | O4: 1 | P4: EUR | Q4: 44.9 | R4: 7.48 | Y4: St Maur Des Fosses | AA4: 94100 | AB4: FR | AC4: Free Shipping 2017/10/17 17-17-37-677
A5: 408-9283493-4561146 | B5: 408-9283493-4561146 | C5: 2024-03-31T16:12:40+00:00 | D5: 2024-04-02T08:32:56+00:00 | E5: Shipped | F5: Amazon | G5: Amazon.fr | J5: Standard | K5: Beper - Machine à Pop-Corn, Pop-Corn en 3 Minutes, Sans Matières Grasses, Circulation d'Air Chaud, Puissance 1200W - Rouge [Classe d'efficacité én | L5: 90.590Y_FBA | M5: B01KMJ9OXW | N5: Shipped | O5: 1 | P5: EUR | Q5: 44.9 | R5: 7.48 | Y5: Leaz | AA5: 1200 | AB5: FR | AC5: Free Shipping 2017/10/17 17-17-37-677
A6: 408-8270481-5314704 | B6: 408-8270481-5314704 | C6: 2024-03-31T16:11:15+00:00 | D6: 2024-04-03T06:49:33+00:00 | E6: Shipped | F6: Amazon | G6: Amazon.fr | J6: Standard | K6: Beper - Mixeur électrique pour milkshakes, frappés, milkshakes et cocktails, 2 vitesses, bol en aluminium 0,5 l, 100 W,Rouge | L6: BP.690_FBA | M6: B07TQVD94L | N6: Shipped | O6: 1 | P6: EUR | Q6: 50.31 | R6: 8.73 | S6: 2.47 | X6: 2.47 | Y6: Charleroi | Z6: Hainaut | AA6: 6061 | AB6: BE | AC6: Free Shipping 2017/10/17 17-17-37-677
A7: 405-0123604-5319535 | B7: 405-0123604-5319535 | C7: 2024-03-31T16:08:17+00:00 | D7: 2024-04-03T01:19:42+00:00 | E7: Shipped | F7: Amazon | G7: Amazon.fr | J7: Standard | K7: BEPER BT.710Y Crêpière électrique avec poignée, 800 W, plaque en aluminium avec revêtement antiadhésif, rouge | L7: BT.710Y_FBA | M7: B07NQ2VYGD | N7: Shipped | O7: 1 | P7: EUR | Q7: 39.9 | R7: 6.65 | S7: 1.66 | X7: 1.66 | Y7: Tournefeuille | AA7: 31170 | AB7: FR | AC7: Free Shipping 2017/10/17 17-17-37-677
A8: 171-2425871-7294725 | B8: 171-2425871-7294725 | C8: 2024-03-31T15:32:09+00:00 | D8: 2024-04-02T08:21:18+00:00 | E8: Shipped | F8: Amazon | G8: Amazon.fr | J8: Expedited | K8: Beper - Machine à Pop-Corn, Pop-Corn en 3 Minutes, Sans Matières Grasses, Circulation d'Air Chaud, Puissance 1200W - Rouge [Classe d'efficacité én | L8: 90.590Y_FBA | M8: B01KMJ9OXW | N8: Shipped | O8: 1 | P8: EUR | Q8: 44.9 | R8: 7.48 | Y8: Paris | AA8: 75017 | AB8: FR
A9: 408-1342122-3264351 | B9: 408-1342122-3264351 | C9: 2024-03-31T14:30:58+00:00 | D9: 2024-04-02T21:44:00+00:00 | E9: Shipped | F9: Amazon | G9: Amazon.fr | J9: Standard | K9: BEPER BT.710Y Crêpière électrique avec poignée, 800 W, plaque en aluminium avec revêtement antiadhésif, rouge | L9: BT.710Y_FBA | M9: B07NQ2VYGD | N9: Shipped | O9: 1 | P9: EUR | Q9: 39.9 | R9: 6.65 | Y9: Menthon-Saint-Bernard | AA9: 74290 | AB9: FR | AC9: Free Shipping 2017/10/17 17-17-37-677
A10: 402-0602668-1374723 | B10: 402-0602668-1374723 | C10: 2024-03-31T10:15:14+00:00 | D10: 2024-04-02T03:09:01+00:00 | E10: Shipped | F10: Amazon | G10: Amazon.fr | J10: Standard | K10: Beper - Masseur Anti-Cellulite pour Femme 4 en 1, Massage Infrarouge, Triple Action Circulaire, Tonifiant et Raffermissant, Puissance Réglable, Syst | L10: 40.500_FBA | M10: B0757TJRR9 | N10: Shipped | O10: 1 | P10: EUR | Q10: 44.9 | R10: 7.48 | Y10: Lagny sur marne | AA10: 77400 | AB10: FR | AC10: Free Shipping 2017/10/17 17-17-37-677
A11: 405-1320381-2982755 | B11: 405-1320381-2982755 | C11: 2024-03-31T01:30:27+00:00 | D11: 2024-04-03T01:21:31+00:00 | E11: Shipped | F11: Amazon | G11: Amazon.fr | J11: Standard | K11: BEPER 40.405 Seche Cheveux de Voyage Pliable - Mini Seche Cheveux Silencieux, 2 Températures et 2 Vitesses | L11: 40.405_FBA | M11: B07N4C3H3V | N11: Shipped | O11: 1 | P11: EUR | Q11: 19.9 | R11: 3.32 | S11: 3.99 | T11: 0.67 | Y11: CLICHY | AA11: 92110 | AB11: FR
A12: 402-4932270-9549137 | B12: 402-4932270-9549137 | C12: 2024-03-30T16:03:08+00:00 | D12: 2024-04-01T14:51:17+00:00 | E12: Shipped | F12: Amazon | G12: Amazon.fr | J12: Standard | K12: Beper - Machine à Pop-Corn, Pop-Corn en 3 Minutes, Sans Matières Grasses, Circulation d'Air Chaud, Puissance 1200W - Rouge [Classe d'efficacité én | L12: 90.590Y_FBA | M12: B01KMJ9OXW | N12: Shipped | O12: 1 | P12: EUR | Q12: 44.9 | R12: 7.48 | Y12: Lyon | AA12: 69004 | AB12: FR | AC12: Free Shipping 2017/10/17 17-17-37-677
A13: 404-3244453-6181163 | B13: 404-3244453-6181163 | C13: 2024-03-30T14:51:27+00:00 | D13: 2024-04-01T15:06:43+00:00 | E13: Shipped | F13: Amazon | G13: Amazon.fr | J13: Expedited | K13: BEPER BT.710Y Crêpière électrique avec poignée, 800 W, plaque en aluminium avec revêtement antiadhésif, rouge | L13: BT.710Y_FBA | M13: B07NQ2VYGD | N13: Shipped | O13: 1 | P13: EUR | Q13: 39.9 | R13: 6.65 | Y13: St Simeon De Bressieux | AA13: 38870 | AB13: FR
A14: 404-3364024-5653124 | B14: 404-3364024-5653124 | C14: 2024-03-29T18:41:04+00:00 | D14: 2024-04-02T03:08:43+00:00 | E14: Shipped | F14: Amazon | G14: Amazon.fr | J14: Standard | K14: Beper - Masseur Anti-Cellulite pour Femme 4 en 1, Massage Infrarouge, Triple Action Circulaire, Tonifiant et Raffermissant, Puissance Réglable, Syst | L14: 40.500_FBA | M14: B0757TJRR9 | N14: Shipped | O14: 1 | P14: EUR | Q14: 44.9 | R14: 7.48 | Y14: St Sebastien De Morsent | AA14: 27180 | AB14: FR | AC14: Free Shipping 2017/10/17 17-17-37-677
A15: 407-4288541-7357165 | B15: 407-4288541-7357165 | C15: 2024-03-29T17:44:52+00:00 | D15: 2024-04-02T01:26:35+00:00 | E15: Shipped | F15: Amazon | G15: Amazon.fr | J15: Standard | K15: BEPER 40.405 Seche Cheveux de Voyage Pliable - Mini Seche Cheveux Silencieux, 2 Températures et 2 Vitesses | L15: 40.405_FBA | M15: B07N4C3H3V | N15: Shipped | O15: 1 | P15: EUR | Q15: 19.9 | R15: 3.32 | Y15: St Jean De Vedas | AA15: 34430 | AB15: FR
A16: 404-3316547-5440357 | B16: 404-3316547-5440357 | C16: 2024-03-29T16:09:40+00:00 | D16: 2024-04-02T06:19:12+00:00 | E16: Shipped | F16: Amazon | G16: Amazon.fr | J16: Standard | K16: Beper - Mixeur électrique pour milkshakes, frappés, milkshakes et cocktails, 2 vitesses, bol en aluminium 0,5 l, 100 W,Rouge | L16: BP.690_FBA | M16: B07TQVD94L | N16: Shipped | O16: 1 | P16: EUR | Q16: 49.9 | R16: 8.32 | Y16: bram | AA16: 11150 | AB16: FR | AC16: Free Shipping 2017/10/17 17-17-37-677
A17: 403-1219089-2709129 | B17: 403-1219089-2709129 | C17: 2024-03-29T15:10:55+00:00 | D17: 2024-04-01T23:28:53+00:00 | E17: Shipped | F17: Amazon | G17: Amazon.fr | J17: Standard | K17: BEPER BT.710Y Crêpière électrique avec poignée, 800 W, plaque en aluminium avec revêtement antiadhésif, rouge | L17: BT.710Y_FBA | M17: B07NQ2VYGD | N17: Shipped | O17: 1 | P17: EUR | Q17: 39.9 | R17: 6.65 | Y17: manduel | AA17: 30129 | AB17: FR | AC17: Free Shipping 2017/10/17 17-17-37-677
A18: 408-0336320-0378768 | B18: 408-0336320-0378768 | C18: 2024-03-29T11:39:03+00:00 | D18: 2024-04-02T07:58:22+00:00 | E18: Shipped | F18: Amazon | G18: Amazon.fr | J18: Standard | K18: BEPER BT.710Y Crêpière électrique avec poignée, 800 W, plaque en aluminium avec revêtement antiadhésif, rouge | L18: BT.710Y_FBA | M18: B07NQ2VYGD | N18: Shipped | O18: 1 | P18: EUR | Q18: 39.9 | R18: 6.65 | S18: 1.67 | X18: 1.67 | Y18: Toulouse | AA18: 31300 | AB18: FR | AC18: Free Shipping 2017/10/17 17-17-37-677
A19: 404-8488041-3782750 | B19: 404-8488041-3782750 | C19: 2024-03-29T10:53:18+00:00 | D19: 2024-04-01T23:35:49+00:00 | E19: Shipped | F19: Amazon | G19: Amazon.fr | J19: Expedited | K19: BEPER BT.710Y Crêpière électrique avec poignée, 800 W, plaque en aluminium avec revêtement antiadhésif, rouge | L19: BT.710Y_FBA | M19: B07NQ2VYGD | N19: Shipped | O19: 1 | P19: EUR | Q19: 39.9 | R19: 6.65 | Y19: Chéry-lès-Pouilly les Pouilly | AA19: 2000 | AB19: FR
A20: 404-0715395-8282712 | B20: 404-0715395-8282712 | C20: 2024-03-29T09:13:00+00:00 | D20: 2024-04-01T23:28:54+00:00 | E20: Shipped | F20: Amazon | G20: Amazon.fr | J20: Expedited | K20: BEPER BT.710Y Crêpière électrique avec poignée, 800 W, plaque en aluminium avec revêtement antiadhésif, rouge | L20: BT.710Y_FBA | M20: B07NQ2VYGD | N20: Shipped | O20: 1 | P20: EUR | Q20: 39.9 | R20: 6.65 | Y20: Charly sur Marne | AA20: 2310 | AB20: FR
A21: 171-9233986-7715553 | B21: 171-9233986-7715553 | C21: 2024-03-28T20:47:58+00:00 | D21: 2024-04-02T03:09:10+00:00 | E21: Shipped | F21: Amazon | G21: Amazon.fr | J21: Expedited | K21: BEPER 50.245 Rasoir Anti Lames en Acier-Appareil pour Enlever Les Bouloches, USB Inclus, Blanc/Octane | L21: 50.245_FBA | M21: B07ZJQTGG8 | N21: Shipped | O21: 1 | P21: EUR | Q21: 19.9 | R21: 3.32 | Y21: BETHUNE | AA21: 62400 | AB21: FR
A22: 404-3211334-1069112 | B22: 404-3211334-1069112 | C22: 2024-03-28T19:08:48+00:00 | D22: 2024-03-30T02:37:00+00:00 | E22: Shipped | F22: Amazon | G22: Amazon.fr | J22: Expedited | K22: BEPER 50.700 Nettoyeur Vapeur pour Sol, Canapé, Tapis - Nettoyant Vapeur, 135° max, câble de 3 Mètres, 350 ml | L22: 50.700_FBA | M22: B01MTSEGF9 | N22: Shipped | O22: 1 | P22: EUR | Q22: 49.9 | R22: 8.32 | Y22: Foussemagne | AA22: 90150 | AB22: FR
A23: 406-4192736-4919565 | B23: 406-4192736-4919565 | C23: 2024-03-28T16:53:31+00:00 | D23: 2024-03-30T09:28:29+00:00 | E23: Shipped | F23: Amazon | G23: Amazon.fr | J23: Expedited | K23: Beper - Machine à Pop-Corn, Pop-Corn en 3 Minutes, Sans Matières Grasses, Circulation d'Air Chaud, Puissance 1200W - Rouge [Classe d'efficacité én | L23: 90.590Y_FBA | M23: B01KMJ9OXW | N23: Shipped | O23: 1 | P23: EUR | Q23: 44.9 | R23: 7.48 | Y23: Ascarat | AA23: 64220 | AB23: FR
A24: 405-1278468-6947524 | B24: 405-1278468-6947524 | C24: 2024-03-28T11:22:00+00:00 | D24: 2024-03-29T02:22:17+00:00 | E24: Shipped | F24: Amazon | G24: Amazon.fr | J24: Standard | K24: Beper - Vert & Blanc Sauna Facial et Aromathérapie 2 Puissances, Traitements Curatifs et Relaxants, Hydratation et Nettoyage du Visage, Réservoir d' | L24: 40.967N_FBA | M24: B00FAJUDU8 | N24: Shipped | O24: 1 | P24: EUR | Q24: 39.9 | R24: 6.65 | Y24: levallois perret | Z24: - | AA24: 92300 | AB24: FR | AC24: Free Shipping 2017/10/17 17-17-37-677
A25: 408-0927499-4843517 | B25: 408-0927499-4843517 | C25: 2024-03-28T10:22:50+00:00 | D25: 2024-03-29T08:09:44+00:00 | E25: Shipped | F25: Amazon | G25: Amazon.fr | J25: Standard | K25: BEPER BT.710Y Crêpière électrique avec poignée, 800 W, plaque en aluminium avec revêtement antiadhésif, rouge | L25: BT.710Y_FBA | M25: B07NQ2VYGD | N25: Shipped | O25: 1 | P25: EUR | Q25: 39.9 | R25: 6.65 | S25: 3.32 | X25: 3.32 | Y25: CHATEAURENARD | AA25: 13160 | AB25: FR | AC25: Free Shipping 2017/10/17 17-17-37-677
A26: 407-6962157-5158757 | B26: 407-6962157-5158757 | C26: 2024-03-28T06:24:40+00:00 | D26: 2024-03-29T04:23:06+00:00 | E26: Shipped | F26: Amazon | G26: Amazon.fr | J26: Standard | K26: BEPER 50.700 Nettoyeur Vapeur pour Sol, Canapé, Tapis - Nettoyant Vapeur, 135° max, câble de 3 Mètres, 350 ml | L26: 50.700_FBA | M26: B01MTSEGF9 | N26: Shipped | O26: 1 | P26: EUR | Q26: 49.9 | R26: 8.32 | S26: 1.66 | X26: 1.66 | Y26: mennecy | AA26: 91540 | AB26: FR | AC26: Free Shipping 2017/10/17 17-17-37-677
A27: 406-1497766-6778713 | B27: 406-1497766-6778713 | C27: 2024-03-27T22:16:10+00:00 | D27: 2024-03-29T04:18:14+00:00 | E27: Shipped | F27: Amazon | G27: Amazon.fr | J27: Standard | K27: BEPER BT.710Y Crêpière électrique avec poignée, 800 W, plaque en aluminium avec revêtement antiadhésif, rouge | L27: BT.710Y_FBA | M27: B07NQ2VYGD | N27: Shipped | O27: 1 | P27: EUR | Q27: 39.9 | R27: 6.65 | Y27: Nantua | AA27: 1130 | AB27: FR | AC27: Free Shipping 2017/10/17 17-17-37-677
A28: 403-5486831-6296317 | B28: 403-5486831-6296317 | C28: 2024-03-27T22:02:19+00:00 | D28: 2024-03-28T08:30:11+00:00 | E28: Shipped | F28: Amazon | G28: Amazon.fr | J28: Standard | K28: BEPER BT.710Y Crêpière électrique avec poignée, 800 W, plaque en aluminium avec revêtement antiadhésif, rouge | L28: BT.710Y_FBA | M28: B07NQ2VYGD | N28: Shipped | O28: 1 | P28: EUR | Q28: 39.9 | R28: 6.65 | S28: 3.32 | X28: 3.32 | Y28: arcueil | AA28: 94110 | AB28: FR | AC28: Free Shipping 2017/10/17 17-17-37-677
A29: 404-6830767-6475558 | B29: 404-6830767-6475558 | C29: 2024-03-27T18:43:43+00:00 | D29: 2024-03-27T22:17:45+00:00 | E29: Shipped | F29: Amazon | G29: Amazon.fr | J29: Expedited | K29: BEPER BT.710Y Crêpière électrique avec poignée, 800 W, plaque en aluminium avec revêtement antiadhésif, rouge | L29: BT.710Y_FBA | M29: B07NQ2VYGD | N29: Shipped | O29: 1 | P29: EUR | Q29: 39.9 | R29: 6.65 | Y29: MONTFERMEIL | AA29: 93370 | AB29: FR
A30: 406-8224646-9309144 | B30: 406-8224646-9309144 | C30: 2024-03-27T18:16:20+00:00 | D30: 2024-03-28T20:47:28+00:00 | E30: Shipped | F30: Amazon | G30: Amazon.fr | J30: Standard | K30: BEPER BT.710Y Crêpière électrique avec poignée, 800 W, plaque en aluminium avec revêtement antiadhésif, rouge | L30: BT.710Y_FBA | M30: B07NQ2VYGD | N30: Shipped | O30: 1 | P30: EUR | Q30: 39.9 | R30: 6.65 | S30: 1.67 | X30: 1.67 | Y30: Targon | AA30: 33760 | AB30: FR | AC30: Free Shipping 2017/10/17 17-17-37-677
A31: 171-3157907-9078734 | B31: 171-3157907-9078734 | C31: 2024-03-27T17:14:22+00:00 | D31: 2024-03-27T22:17:43+00:00 | E31: Shipped | F31: Amazon | G31: Amazon.fr | J31: Expedited | K31: BEPER BT.710Y Crêpière électrique avec poignée, 800 W, plaque en aluminium avec revêtement antiadhésif, rouge | L31: BT.710Y_FBA | M31: B07NQ2VYGD | N31: Shipped | O31: 1 | P31: EUR | Q31: 40.23 | R31: 6.98 | Y31: SPY | AA31: 5190 | AB31: BE
A32: 407-1996005-2568315 | B32: 407-1996005-2568315 | C32: 2024-03-27T15:07:23+00:00 | D32: 2024-03-28T03:16:00+00:00 | E32: Shipped | F32: Amazon | G32: Amazon.fr | J32: Standard | K32: BEPER BT.710Y Crêpière électrique avec poignée, 800 W, plaque en aluminium avec revêtement antiadhésif, rouge | L32: BT.710Y_FBA | M32: B07NQ2VYGD | N32: Shipped | O32: 1 | P32: EUR | Q32: 39.9 | R32: 6.65 | Y32: Courcelles les gisors | AA32: 60240 | AB32: FR | AC32: Free Shipping 2017/10/17 17-17-37-677
A33: 404-6224560-0753166 | B33: 404-6224560-0753166 | C33: 2024-03-27T12:59:29+00:00 | D33: 2024-03-28T08:31:04+00:00 | E33: Shipped | F33: Amazon | G33: Amazon.fr | J33: Expedited | K33: BEPER BT.710Y Crêpière électrique avec poignée, 800 W, plaque en aluminium avec revêtement antiadhésif, rouge | L33: BT.710Y_FBA | M33: B07NQ2VYGD | N33: Shipped | O33: 1 | P33: EUR | Q33: 39.9 | R33: 6.65 | Y33: Vedene | AA33: 84270 | AB33: FR
A34: 407-9265003-1683523 | B34: 407-9265003-1683523 | C34: 2024-03-27T12:13:01+00:00 | D34: 2024-03-28T12:05:44+00:00 | E34: Shipped | F34: Amazon | G34: Amazon.fr | J34: Expedited | K34: BEPER BT.710Y Crêpière électrique avec poignée, 800 W, plaque en aluminium avec revêtement antiadhésif, rouge | L34: BT.710Y_FBA | M34: B07NQ2VYGD | N34: Shipped | O34: 1 | P34: EUR | Q34: 39.9 | R34: 6.65 | Y34: CORMEILLES EN PARISIS | AA34: 95240 | AB34: FR
A35: 406-1709875-6245107 | B35: 406-1709875-6245107 | C35: 2024-03-26T16:32:50+00:00 | D35: 2024-03-26T23:02:53+00:00 | E35: Shipped | F35: Amazon | G35: Amazon.fr | J35: Standard | K35: BEPER BT.710Y Crêpière électrique avec poignée, 800 W, plaque en aluminium avec revêtement antiadhésif, rouge | L35: BT.710Y_FBA | M35: B07NQ2VYGD | N35: Shipped | O35: 1 | P35: EUR | Q35: 39.9 | R35: 6.65 | Y35: chemellier | AA35: 49320 | AB35: FR | AC35: Free Shipping 2017/10/17 17-17-37-677
A36: 408-3656938-1596349 | B36: 408-3656938-1596349 | C36: 2024-03-26T15:00:02+00:00 | D36: 2024-03-27T12:57:44+00:00 | E36: Shipped | F36: Amazon | G36: Amazon.fr | J36: Standard | K36: BEPER BT.710Y Crêpière électrique avec poignée, 800 W, plaque en aluminium avec revêtement antiadhésif, rouge | L36: BT.710Y_FBA | M36: B07NQ2VYGD | N36: Shipped | O36: 1 | P36: EUR | Q36: 39.9 | R36: 6.65 | S36: 3.32 | X36: 3.32 | Y36: Mandelieu La Napoule | AA36: 6210 | AB36: FR | AC36: Free Shipping 2017/10/17 17-17-37-677
A37: 406-7145952-7366756 | B37: 406-7145952-7366756 | C37: 2024-03-26T09:29:05+00:00 | D37: 2024-03-27T01:32:07+00:00 | E37: Shipped | F37: Amazon | G37: Amazon.fr | J37: Expedited | K37: BEPER BT.710Y Crêpière électrique avec poignée, 800 W, plaque en aluminium avec revêtement antiadhésif, rouge | L37: BT.710Y_FBA | M37: B07NQ2VYGD | N37: Shipped | O37: 1 | P37: EUR | Q37: 39.9 | R37: 6.65 | Y37: LESQUIN | AA37: 59810 | AB37: FR
A38: 403-4175617-0969134 | B38: 403-4175617-0969134 | C38: 2024-03-26T08:09:10+00:00 | D38: 2024-03-26T18:05:25+00:00 | E38: Shipped | F38: Amazon | G38: Amazon.fr | J38: Expedited | K38: BEPER 40.405 Seche Cheveux de Voyage Pliable - Mini Seche Cheveux Silencieux, 2 Températures et 2 Vitesses | L38: 40.405_FBA | M38: B07N4C3H3V | N38: Shipped | O38: 1 | P38: EUR | Q38: 19.9 | R38: 3.32 | Y38: Le Bourget Du Lac | AA38: 73370 | AB38: FR
A39: 406-7370648-0125100 | B39: 406-7370648-0125100 | C39: 2024-03-25T20:48:51+00:00 | D39: 2024-03-26T20:58:16+00:00 | E39: Shipped | F39: Amazon | G39: Amazon.fr | J39: Standard | K39: BEPER BT.602H Gaufrier 700W Cable poignée Thermo-Isolante, Rouge/Blanc | L39: BT.602H_FBA | M39: B076DCKSTJ | N39: Shipped | O39: 1 | P39: EUR | Q39: 35.19 | R39: 6.11 | Y39: Frameries | AA39: 7080 | AB39: BE | AC39: Free Shipping 2017/10/17 17-17-37-677
A40: 406-7370648-0125100 | B40: 406-7370648-0125100 | C40: 2024-03-25T20:48:51+00:00 | D40: 2024-03-26T20:58:16+00:00 | E40: Shipped | F40: Amazon | G40: Amazon.fr | J40: Standard | K40: BEPER BT.710Y Crêpière électrique avec poignée, 800 W, plaque en aluminium avec revêtement antiadhésif, rouge | L40: BT.710Y_FBA | M40: B07NQ2VYGD | N40: Shipped | O40: 1 | P40: EUR | Q40: 40.23 | R40: 6.98 | Y40: Frameries | AA40: 7080 | AB40: BE | AC40: Free Shipping 2017/10/17 17-17-37-677
A41: 403-5505788-0599541 | B41: 403-5505788-0599541 | C41: 2024-03-25T16:17:29+00:00 | D41: 2024-03-26T07:44:08+00:00 | E41: Shipped | F41: Amazon | G41: Amazon.fr | J41: Standard | K41: BEPER BT.710Y Crêpière électrique avec poignée, 800 W, plaque en aluminium avec revêtement antiadhésif, rouge | L41: BT.710Y_FBA | M41: B07NQ2VYGD | N41: Shipped | O41: 1 | P41: EUR | Q41: 39.9 | R41: 6.65 | S41: 3.32 | X41: 3.32 | Y41: laméac | AA41: 65140 | AB41: FR | AC41: Free Shipping 2017/10/17 17-17-37-677
A42: 402-9711004-1873159 | B42: 402-9711004-1873159 | C42: 2024-03-25T15:04:24+00:00 | D42: 2024-03-26T20:36:46+00:00 | E42: Shipped | F42: Amazon | G42: Amazon.fr | J42: Expedited | K42: Beper - Mixeur électrique pour milkshakes, frappés, milkshakes et cocktails, 2 vitesses, bol en aluminium 0,5 l, 100 W,Rouge | L42: BP.690_FBA | M42: B07TQVD94L | N42: Shipped | O42: 1 | P42: EUR | Q42: 49.9 | R42: 8.32 | Y42: NICE | AA42: 6000 | AB42: FR
A43: 171-5793775-2558758 | B43: 171-5793775-2558758 | C43: 2024-03-25T12:10:59+00:00 | D43: 2024-03-25T22:45:00+00:00 | E43: Shipped | F43: Amazon | G43: Amazon.fr | J43: Expedited | K43: BEPER BT.710Y Crêpière électrique avec poignée, 800 W, plaque en aluminium avec revêtement antiadhésif, rouge | L43: BT.710Y_FBA | M43: B07NQ2VYGD | N43: Shipped | O43: 1 | P43: EUR | Q43: 39.9 | R43: 6.65 | Y43: Ghyvelde | AA43: 59254 | AB43: FR
A44: 408-9212011-5857146 | B44: 408-9212011-5857146 | C44: 2024-03-25T11:24:42+00:00 | D44: 2024-03-26T04:02:14+00:00 | E44: Shipped | F44: Amazon | G44: Amazon.fr | J44: Expedited | K44: Beper - Machine à Pop-Corn, Pop-Corn en 3 Minutes, Sans Matières Grasses, Circulation d'Air Chaud, Puissance 1200W - Rouge [Classe d'efficacité én | L44: 90.590Y_FBA | M44: B01KMJ9OXW | N44: Shipped | O44: 1 | P44: EUR | Q44: 44.9 | R44: 7.48 | Y44: Venerque | AA44: 31810 | AB44: FR
A45: 403-0780668-9880336 | B45: 403-0780668-9880336 | C45: 2024-03-25T11:15:14+00:00 | D45: 2024-03-25T22:45:00+00:00 | E45: Shipped | F45: Amazon | G45: Amazon.fr | J45: Expedited | K45: BEPER BT.710Y Crêpière électrique avec poignée, 800 W, plaque en aluminium avec revêtement antiadhésif, rouge | L45: BT.710Y_FBA | M45: B07NQ2VYGD | N45: Shipped | O45: 1 | P45: EUR | Q45: 39.9 | R45: 6.65 | Y45: omissy | AA45: 2100 | AB45: FR
A46: 408-0426700-8790764 | B46: 408-0426700-8790764 | C46: 2024-03-25T07:25:14+00:00 | D46: 2024-03-25T07:28:18+00:00 | E46: Cancelled | F46: Amazon | G46: Amazon.fr | J46: Expedited | K46: Beper - Cuiseur à Vapeur Multicombustion de 5L, Économiseur d'Espace, Minuterie de 60 minutes, Cuisson à la Vapeur Saine, Puissance 400-500W - Arge | L46: BC.261_FBA | M46: B08485QRVZ | N46: Cancelled | O46: 0 | Y46: Paris | AA46: 75015 | AB46: FR
A47: 404-1635455-1089105 | B47: 404-1635455-1089105 | C47: 2024-03-24T23:57:53+00:00 | D47: 2024-03-25T02:27:57+00:00 | E47: Shipped | F47: Amazon | G47: Amazon.fr | J47: Expedited | K47: Beper - Vert & Blanc Sauna Facial et Aromathérapie 2 Puissances, Traitements Curatifs et Relaxants, Hydratation et Nettoyage du Visage, Réservoir d' | L47: 40.967N_FBA | M47: B00FAJUDU8 | N47: Shipped | O47: 1 | P47: EUR | Q47: 39.9 | R47: 6.65 | Y47: Beaucouzé | AA47: 49070 | AB47: FR
A48: 407-6229520-8448367 | B48: 407-6229520-8448367 | C48: 2024-03-24T22:21:37+00:00 | D48: 2024-03-25T03:41:33+00:00 | E48: Shipped | F48: Amazon | G48: Amazon.fr | J48: Standard | K48: BEPER BT.710Y Crêpière électrique avec poignée, 800 W, plaque en aluminium avec revêtement antiadhésif, rouge | L48: BT.710Y_FBA | M48: B07NQ2VYGD | N48: Shipped | O48: 1 | P48: EUR | Q48: 39.9 | R48: 6.65 | Y48: Argenteuil | AA48: 95100 | AB48: FR | AC48: Free Shipping 2017/10/17 17-17-37-677
A49: 403-7511760-2675505 | B49: 403-7511760-2675505 | C49: 2024-03-24T18:52:39+00:00 | D49: 2024-03-25T03:41:33+00:00 | E49: Shipped | F49: Amazon | G49: Amazon.fr | J49: Standard | K49: BEPER BT.710Y Crêpière électrique avec poignée, 800 W, plaque en aluminium avec revêtement antiadhésif, rouge | L49: BT.710Y_FBA | M49: B07NQ2VYGD | N49: Shipped | O49: 1 | P49: EUR | Q49: 39.9 | R49: 6.65 | Y49: St Denis | AA49: 93200 | AB49: FR | AC49: Free Shipping 2017/10/17 17-17-37-677
A50: 403-5829718-8935503 | B50: 403-5829718-8935503 | C50: 2024-03-24T18:47:31+00:00 | D50: 2024-03-25T15:20:17+00:00 | E50: Shipped | F50: Amazon | G50: Amazon.fr | J50: Expedited | K50: Beper - Machine à Pop-Corn, Pop-Corn en 3 Minutes, Sans Matières Grasses, Circulation d'Air Chaud, Puissance 1200W - Rouge [Classe d'efficacité én | L50: 90.590Y_FBA | M50: B01KMJ9OXW | N50: Shipped | O50: 1 | P50: EUR | Q50: 44.9 | R50: 7.48 | Y50: Quincey | AA50: 70000 | AB50: FR
A51: 404-8592418-3150745 | B51: 404-8592418-3150745 | C51: 2024-03-24T18:20:30+00:00 | D51: 2024-03-25T11:10:05+00:00 | E51: Shipped | F51: Amazon | G51: Amazon.fr | J51: Standard | K51: Beper - Mixeur électrique pour milkshakes, frappés, milkshakes et cocktails, 2 vitesses, bol en aluminium 0,5 l, 100 W,Rouge | L51: BP.690_FBA | M51: B07TQVD94L | N51: Shipped | O51: 1 | P51: EUR | Q51: 41.58 | S51: 5.99 | X51: 5.99 | Y51: Clervaux | AA51: 9710 | AB51: LU | AC51: Free Shipping 2017/10/17 17-17-37-677 | AG51: LU32780619 | AH51: LU | AI51: VAT
A52: 408-3214326-3489902 | B52: 408-3214326-3489902 | C52: 2024-03-24T14:52:25+00:00 | D52: 2024-03-25T03:43:39+00:00 | E52: Shipped | F52: Amazon | G52: Amazon.fr | J52: Expedited | K52: BEPER BT.710Y Crêpière électrique avec poignée, 800 W, plaque en aluminium avec revêtement antiadhésif, rouge | L52: BT.710Y_FBA | M52: B07NQ2VYGD | N52: Shipped | O52: 1 | P52: EUR | Q52: 39.9 | R52: 6.65 | Y52: manduel | AA52: 30129 | AB52: FR
A53: 171-1495574-3482714 | B53: 171-1495574-3482714 | C53: 2024-03-24T00:21:32+00:00 | D53: 2024-03-25T10:12:34+00:00 | E53: Shipped | F53: Amazon | G53: Amazon.fr | J53: Standard | K53: Beper - Machine à Pop-Corn, Pop-Corn en 3 Minutes, Sans Matières Grasses, Circulation d'Air Chaud, Puissance 1200W - Rouge [Classe d'efficacité én | L53: 90.590Y_FBA | M53: B01KMJ9OXW | N53: Shipped | O53: 1 | P53: EUR | Q53: 44.9 | R53: 7.48 | S53: 0.83 | X53: 0.83 | Y53: Villespy | AA53: 11170 | AB53: FR | AC53: Free Shipping 2017/10/17 17-17-37-677
A54: 171-9509096-1587514 | B54: 171-9509096-1587514 | C54: 2024-03-24T00:13:24+00:00 | D54: 2024-03-24T00:15:25+00:00 | E54: Cancelled | F54: Amazon | G54: Amazon.fr | J54: Standard | K54: Beper - Machine à Pop-Corn, Pop-Corn en 3 Minutes, Sans Matières Grasses, Circulation d'Air Chaud, Puissance 1200W - Rouge [Classe d'efficacité én | L54: 90.590Y_FBA | M54: B01KMJ9OXW | N54: Cancelled | O54: 0 | Y54: LE PRE ST GERVAIS | AA54: 93310 | AB54: FR
A55: 407-0734580-5760325 | B55: 407-0734580-5760325 | C55: 2024-03-23T19:44:52+00:00 | D55: 2024-03-24T09:11:56+00:00 | E55: Shipped | F55: Amazon | G55: Amazon.fr | J55: Expedited | K55: Beper - Masseur Anti-Cellulite pour Femme 4 en 1, Massage Infrarouge, Triple Action Circulaire, Tonifiant et Raffermissant, Puissance Réglable, Syst | L55: 40.500_FBA | M55: B0757TJRR9 | N55: Shipped | O55: 1 | P55: EUR | Q55: 44.9 | R55: 7.48 | Y55: Pau | AA55: 64000 | AB55: FR
A56: 402-6646232-9227546 | B56: 402-6646232-9227546 | C56: 2024-03-23T17:34:57+00:00 | D56: 2024-03-24T10:56:05+00:00 | E56: Shipped | F56: Amazon | G56: Amazon.fr | J56: Standard | K56: BEPER BT.710Y Crêpière électrique avec poignée, 800 W, plaque en aluminium avec revêtement antiadhésif, rouge | L56: BT.710Y_FBA | M56: B07NQ2VYGD | N56: Shipped | O56: 1 | P56: EUR | Q56: 39.9 | R56: 6.65 | Y56: DRAVEIL | AA56: 91210 | AB56: FR | AC56: Free Shipping 2017/10/17 17-17-37-677
A57: 404-3726915-1405946 | B57: 404-3726915-1405946 | C57: 2024-03-23T16:18:14+00:00 | D57: 2024-03-24T10:57:50+00:00 | E57: Shipped | F57: Amazon | G57: Amazon.fr | J57: Standard | K57: BEPER BT.710Y Crêpière électrique avec poignée, 800 W, plaque en aluminium avec revêtement antiadhésif, rouge | L57: BT.710Y_FBA | M57: B07NQ2VYGD | N57: Shipped | O57: 1 | P57: EUR | Q57: 39.9 | R57: 6.65 | Y57: Saint-Mitre-les-Remparts | AA57: 13920 | AB57: FR | AC57: Free Shipping 2017/10/17 17-17-37-677
A58: 403-9595080-0140361 | B58: 403-9595080-0140361 | C58: 2024-03-23T15:14:08+00:00 | D58: 2024-03-25T20:48:44+00:00 | E58: Shipped | F58: Amazon | G58: Amazon.fr | J58: Standard | K58: BEPER BT.710Y Crêpière électrique avec poignée, 800 W, plaque en aluminium avec revêtement antiadhésif, rouge | L58: BT.710Y_FBA | M58: B07NQ2VYGD | N58: Shipped | O58: 1 | P58: EUR | Q58: 39.9 | R58: 6.65 | S58: 1.11 | X58: 1.11 | Y58: Roanne | AA58: 42300 | AB58: FR | AC58: Free Shipping 2017/10/17 17-17-37-677
A59: 404-9447429-8413148 | B59: 404-9447429-8413148 | C59: 2024-03-23T10:43:19+00:00 | D59: 2024-03-24T11:02:37+00:00 | E59: Shipped | F59: Amazon | G59: Amazon.fr | J59: Standard | K59: Beper BF.640 - Four ventilé multifonction 12L Anneau de rallonge pour capacité totale 18L Minuterie 60 minutes Température réglable jusqu'à 250° | L59: BF.640_FBA | M59: B07YBN2FS3 | N59: Shipped | O59: 1 | P59: EUR | Q59: 99 | R59: 16.5 | Y59: paris | AA59: 75015 | AB59: FR | AC59: Free Shipping 2017/10/17 17-17-37-677
A60: 404-6269106-4795525 | B60: 404-6269106-4795525 | C60: 2024-03-23T10:34:07+00:00 | D60: 2024-03-23T10:36:21+00:00 | E60: Cancelled | F60: Amazon | G60: Amazon.fr | J60: Standard | K60: Beper BF.640 - Four ventilé multifonction 12L Anneau de rallonge pour capacité totale 18L Minuterie 60 minutes Température réglable jusqu'à 250° | L60: BF.640_FBA | M60: B07YBN2FS3 | N60: Cancelled | O60: 0 | Y60: paris | AA60: 75015 | AB60: FR
A61: 403-4123408-4516316 | B61: 403-4123408-4516316 | C61: 2024-03-22T17:54:12+00:00 | D61: 2024-03-23T00:23:11+00:00 | E61: Shipped | F61: Amazon | G61: Amazon.fr | J61: Expedited | K61: Beper - Masseur Anti-Cellulite pour Femme 4 en 1, Massage Infrarouge, Triple Action Circulaire, Tonifiant et Raffermissant, Puissance Réglable, Syst | L61: 40.500_FBA | M61: B0757TJRR9 | N61: Shipped | O61: 1 | P61: EUR | Q61: 44.9 | R61: 7.48 | Y61: hennebont | AA61: 56700 | AB61: FR
A62: 405-4367237-2000326 | B62: 405-4367237-2000326 | C62: 2024-03-22T16:42:47+00:00 | D62: 2024-03-24T10:56:08+00:00 | E62: Shipped | F62: Amazon | G62: Amazon.fr | J62: Expedited | K62: BEPER BT.710Y Crêpière électrique avec poignée, 800 W, plaque en aluminium avec revêtement antiadhésif, rouge | L62: BT.710Y_FBA | M62: B07NQ2VYGD | N62: Shipped | O62: 1 | P62: EUR | Q62: 39.9 | R62: 6.65 | Y62: Peyriac minervois | AA62: 11160 | AB62: FR
A63: 171-3537748-7962751 | B63: 171-3537748-7962751 | C63: 2024-03-22T16:33:46+00:00 | D63: 2024-03-23T02:34:45+00:00 | E63: Shipped | F63: Amazon | G63: Amazon.fr | J63: Standard | K63: Beper - Machine à Pop-Corn, Pop-Corn en 3 Minutes, Sans Matières Grasses, Circulation d'Air Chaud, Puissance 1200W - Rouge [Classe d'efficacité én | L63: 90.590Y_FBA | M63: B01KMJ9OXW | N63: Shipped | O63: 1 | P63: EUR | Q63: 44.9 | R63: 7.48 | S63: 3.32 | X63: 3.32 | Y63: Loireauxence | Z63: La Rouxiere | AA63: 44370 | AB63: FR | AC63: Free Shipping 2017/10/17 17-17-37-677
A64: 405-5025630-5177944 | B64: 405-5025630-5177944 | C64: 2024-03-22T14:59:33+00:00 | D64: 2024-03-23T17:31:32+00:00 | E64: Shipped | F64: Amazon | G64: Amazon.fr | J64: Standard | K64: BEPER P101TEM001 Chauffe-buffet, Acier inoxydable, 4 plateaux amovibles, Thermostat de température, Voyant de fonctionnement, Idéal pour les buffets | L64: P101TEM001_FBA | M64: B08LZN1PWY | N64: Shipped | O64: 1 | P64: EUR | Q64: 109 | R64: 18.17 | S64: 3.32 | X64: 3.32 | Y64: Paris | AA64: 75016 | AB64: FR | AC64: Free Shipping 2017/10/17 17-17-37-677
A65: 404-6601937-2957124 | B65: 404-6601937-2957124 | C65: 2024-03-22T11:21:59+00:00 | D65: 2024-03-22T15:24:37+00:00 | E65: Shipped | F65: Amazon | G65: Amazon.fr | J65: Standard | K65: Beper BF.640 - Four ventilé multifonction 12L Anneau de rallonge pour capacité totale 18L Minuterie 60 minutes Température réglable jusqu'à 250° | L65: BF.640_FBA | M65: B07YBN2FS3 | N65: Shipped | O65: 1 | P65: EUR | Q65: 99 | R65: 16.5 | Y65: USTARITZ | AA65: 64480 | AB65: FR | AC65: Free Shipping 2017/10/17 17-17-37-677
A66: 171-9336719-8145119 | B66: 171-9336719-8145119 | C66: 2024-03-21T17:20:43+00:00 | D66: 2024-03-24T10:56:08+00:00 | E66: Shipped | F66: Amazon | G66: Amazon.fr | J66: Expedited | K66: BEPER BT.710Y Crêpière électrique avec poignée, 800 W, plaque en aluminium avec revêtement antiadhésif, rouge | L66: BT.710Y_FBA | M66: B07NQ2VYGD | N66: Shipped | O66: 1 | P66: EUR | Q66: 39.9 | R66: 6.65 | Y66: Mantes la ville | AA66: 78711 | AB66: FR
A67: 171-0112216-7192374 | B67: 171-0112216-7192374 | C67: 2024-03-20T13:01:07+00:00 | D67: 2024-03-21T02:24:12+00:00 | E67: Shipped | F67: Amazon | G67: Amazon.fr | J67: Expedited | K67: Beper - Masseur Anti-Cellulite pour Femme 4 en 1, Massage Infrarouge, Triple Action Circulaire, Tonifiant et Raffermissant, Puissance Réglable, Syst | L67: 40.500_FBA | M67: B0757TJRR9 | N67: Shipped | O67: 1 | P67: EUR | Q67: 44.9 | R67: 7.48 | Y67: Aix En Provence | AA67: 13100 | AB67: FR
A68: 403-0868667-4395558 | B68: 403-0868667-4395558 | C68: 2024-03-19T22:29:03+00:00 | D68: 2024-03-20T17:09:51+00:00 | E68: Shipped | F68: Amazon | G68: Amazon.fr | J68: Standard | K68: Beper - Machine à Pop-Corn, Pop-Corn en 3 Minutes, Sans Matières Grasses, Circulation d'Air Chaud, Puissance 1200W - Rouge [Classe d'efficacité én | L68: 90.590Y_FBA | M68: B01KMJ9OXW | N68: Shipped | O68: 1 | P68: EUR | Q68: 44.9 | R68: 7.48 | Y68: ETAMPES SUR MARNE | AA68: 2400 | AB68: FR | AC68: Free Shipping 2017/10/17 17-17-37-677
A69: 403-7778484-6581965 | B69: 403-7778484-6581965 | C69: 2024-03-19T20:36:32+00:00 | D69: 2024-03-20T23:50:55+00:00 | E69: Shipped | F69: Amazon | G69: Amazon.fr | J69: Standard | K69: BEPER 90.882 Four Electrique Résistance au Quartz, Noir, 1050 W | L69: 90.882_FBA | M69: B06Y195DJN | N69: Shipped | O69: 1 | P69: EUR | Q69: 59.9 | R69: 9.98 | S69: 3.32 | X69: 3.32 | Y69: Bougival | AA69: 78380 | AB69: FR | AC69: Free Shipping 2017/10/17 17-17-37-677
A70: 408-3059182-2487547 | B70: 408-3059182-2487547 | C70: 2024-03-19T13:53:50+00:00 | D70: 2024-03-20T04:30:16+00:00 | E70: Shipped | F70: Amazon | G70: Amazon.fr | J70: Expedited | K70: Beper - Vert & Blanc Sauna Facial et Aromathérapie 2 Puissances, Traitements Curatifs et Relaxants, Hydratation et Nettoyage du Visage, Réservoir d' | L70: 40.967N_FBA | M70: B00FAJUDU8 | N70: Shipped | O70: 1 | P70: EUR | Q70: 39.9 | R70: 6.65 | Y70: Cabourg | AA70: 14390 | AB70: FR
A71: 403-9202772-7703559 | B71: 403-9202772-7703559 | C71: 2024-03-18T21:26:43+00:00 | D71: 2024-03-19T15:17:19+00:00 | E71: Shipped | F71: Amazon | G71: Amazon.fr | J71: Expedited | K71: BEPER 40.405 Seche Cheveux de Voyage Pliable - Mini Seche Cheveux Silencieux, 2 Températures et 2 Vitesses | L71: 40.405_FBA | M71: B07N4C3H3V | N71: Shipped | O71: 1 | P71: EUR | Q71: 19.9 | R71: 3.32 | Y71: CAVAILLON | AA71: 84300 | AB71: FR
A72: 408-2373316-6461127 | B72: 408-2373316-6461127 | C72: 2024-03-18T20:11:49+00:00 | D72: 2024-03-19T02:18:18+00:00 | E72: Shipped | F72: Amazon | G72: Amazon.fr | J72: Standard | K72: Beper - Vert & Blanc Sauna Facial et Aromathérapie 2 Puissances, Traitements Curatifs et Relaxants, Hydratation et Nettoyage du Visage, Réservoir d' | L72: 40.967N_FBA | M72: B00FAJUDU8 | N72: Shipped | O72: 1 | P72: EUR | Q72: 39.9 | R72: 6.65 | S72: 3.32 | X72: 3.32 | Y72: Pulnoy | AA72: 54425 | AB72: FR | AC72: Free Shipping 2017/10/17 17-17-37-677
A73: 406-3669486-9835513 | B73: 406-3669486-9835513 | C73: 2024-03-18T14:02:11+00:00 | D73: 2024-03-19T02:17:25+00:00 | E73: Shipped | F73: Amazon | G73: Amazon.fr | J73: Standard | K73: BEPER 50.245 Rasoir Anti Lames en Acier-Appareil pour Enlever Les Bouloches, USB Inclus, Blanc/Octane | L73: 50.245_FBA | M73: B07ZJQTGG8 | N73: Shipped | O73: 1 | P73: EUR | Q73: 19.9 | R73: 3.32 | Y73: LUISANT | AA73: 28600 | AB73: FR
A74: 408-8350316-2230758 | B74: 408-8350316-2230758 | C74: 2024-03-18T13:49:24+00:00 | D74: 2024-03-18T21:25:47+00:00 | E74: Shipped | F74: Amazon | G74: Amazon.fr | J74: Standard | K74: BEPER 50.700 Nettoyeur Vapeur pour Sol, Canapé, Tapis - Nettoyant Vapeur, 135° max, câble de 3 Mètres, 350 ml | L74: 50.700_FBA | M74: B01MTSEGF9 | N74: Shipped | O74: 1 | P74: EUR | Q74: 49.9 | R74: 8.32 | S74: 3.32 | X74: 3.32 | Y74: Marseille | AA74: 13010 | AB74: FR | AC74: Free Shipping 2017/10/17 17-17-37-677
A75: 405-2453029-0609164 | B75: 405-2453029-0609164 | C75: 2024-03-18T05:08:18+00:00 | D75: 2024-03-19T04:19:14+00:00 | E75: Shipped | F75: Amazon | G75: Amazon.fr | J75: Expedited | K75: BEPER 50.245 Rasoir Anti Lames en Acier-Appareil pour Enlever Les Bouloches, USB Inclus, Blanc/Octane | L75: 50.245_FBA | M75: B07ZJQTGG8 | N75: Shipped | O75: 1 | P75: EUR | Q75: 19.9 | R75: 3.32 | Y75: Villepinte | AA75: 93420 | AB75: FR
A76: 405-9567390-7810752 | B76: 405-9567390-7810752 | C76: 2024-03-18T01:50:14+00:00 | D76: 2024-03-18T07:27:03+00:00 | E76: Shipped | F76: Amazon | G76: Amazon.fr | J76: Expedited | K76: BEPER 50.700 Nettoyeur Vapeur pour Sol, Canapé, Tapis - Nettoyant Vapeur, 135° max, câble de 3 Mètres, 350 ml | L76: 50.700_FBA | M76: B01MTSEGF9 | N76: Shipped | O76: 1 | P76: EUR | Q76: 49.9 | R76: 8.32 | Y76: Versailles | Z76: IDF | AA76: 78000 | AB76: FR
A77: 406-0946844-9877938 | B77: 406-0946844-9877938 | C77: 2024-03-17T19:10:08+00:00 | D77: 2024-03-18T01:24:04+00:00 | E77: Shipped | F77: Amazon | G77: Amazon.fr | J77: Expedited | K77: Beper - Machine à Pop-Corn, Pop-Corn en 3 Minutes, Sans Matières Grasses, Circulation d'Air Chaud, Puissance 1200W - Rouge [Classe d'efficacité én | L77: 90.590Y_FBA | M77: B01KMJ9OXW | N77: Shipped | O77: 1 | P77: EUR | Q77: 44.9 | R77: 7.48 | Y77: paris | AA77: 75016 | AB77: FR
A78: 404-9232184-6405162 | B78: 404-9232184-6405162 | C78: 2024-03-17T18:07:55+00:00 | D78: 2024-03-19T19:30:36+00:00 | E78: Shipped | F78: Amazon | G78: Amazon.fr | J78: Expedited | K78: Beper - Machine à Pop-Corn, Pop-Corn en 3 Minutes, Sans Matières Grasses, Circulation d'Air Chaud, Puissance 1200W - Rouge [Classe d'efficacité én | L78: 90.590Y_FBA | M78: B01KMJ9OXW | N78: Shipped | O78: 1 | P78: EUR | Q78: 44.9 | R78: 7.48 | Y78: LA TALAUDIERE | AA78: 42350 | AB78: FR
A79: 171-9056524-1535516 | B79: 171-9056524-1535516 | C79: 2024-03-17T15:35:10+00:00 | D79: 2024-03-19T12:10:04+00:00 | E79: Shipped | F79: Amazon | G79: Amazon.fr | J79: Standard | K79: Beper - Machine à Pop-Corn, Pop-Corn en 3 Minutes, Sans Matières Grasses, Circulation d'Air Chaud, Puissance 1200W - Rouge [Classe d'efficacité én | L79: 90.590Y_FBA | M79: B01KMJ9OXW | N79: Shipped | O79: 1 | P79: EUR | Q79: 44.9 | R79: 7.48 | S79: 3.32 | X79: 3.32 | Y79: Blanquefort | AA79: 33290 | AB79: FR | AC79: Free Shipping 2017/10/17 17-17-37-677
A80: 403-0971744-1756330 | B80: 403-0971744-1756330 | C80: 2024-03-17T12:42:40+00:00 | D80: 2024-03-18T04:03:08+00:00 | E80: Shipped | F80: Amazon | G80: Amazon.fr | J80: Expedited | K80: Beper - Mixeur électrique pour milkshakes, frappés, milkshakes et cocktails, 2 vitesses, bol en aluminium 0,5 l, 100 W,Rouge | L80: BP.690_FBA | M80: B07TQVD94L | N80: Shipped | O80: 1 | P80: EUR | Q80: 49.9 | R80: 8.32 | Y80: torcy | AA80: 77200 | AB80: FR
A81: 404-6106288-8033939 | B81: 404-6106288-8033939 | C81: 2024-03-16T23:38:24+00:00 | D81: 2024-03-19T05:06:33+00:00 | E81: Shipped | F81: Amazon | G81: Amazon.fr | J81: Standard | K81: BEPER 50.245 Rasoir Anti Lames en Acier-Appareil pour Enlever Les Bouloches, USB Inclus, Blanc/Octane | L81: 50.245_FBA | M81: B07ZJQTGG8 | N81: Shipped | O81: 1 | P81: EUR | Q81: 19.9 | R81: 3.32 | S81: 3.99 | T81: 0.67 | Y81: Mougins | AA81: 6250 | AB81: FR
A82: 403-7805482-5428330 | B82: 403-7805482-5428330 | C82: 2024-03-16T17:10:09+00:00 | D82: 2024-03-18T02:24:52+00:00 | E82: Shipped | F82: Amazon | G82: Amazon.fr | J82: Expedited | K82: Beper - Vert & Blanc Sauna Facial et Aromathérapie 2 Puissances, Traitements Curatifs et Relaxants, Hydratation et Nettoyage du Visage, Réservoir d' | L82: 40.967N_FBA | M82: B00FAJUDU8 | N82: Shipped | O82: 1 | P82: EUR | Q82: 39.9 | R82: 6.65 | Y82: Mornac sur Seudre | AA82: 17113 | AB82: FR
A83: 406-9778121-1283516 | B83: 406-9778121-1283516 | C83: 2024-03-16T13:37:59+00:00 | D83: 2024-03-18T02:31:11+00:00 | E83: Shipped | F83: Amazon | G83: Amazon.fr | J83: Standard | K83: BEPER 50.700 Nettoyeur Vapeur pour Sol, Canapé, Tapis - Nettoyant Vapeur, 135° max, câble de 3 Mètres, 350 ml | L83: 50.700_FBA | M83: B01MTSEGF9 | N83: Shipped | O83: 1 | P83: EUR | Q83: 40.9 | S83: 3.99 | X83: 3.99 | Y83: Brest | AA83: 29200 | AB83: FR | AC83: Free Shipping 2017/10/17 17-17-37-677 | AG83: FR68529492399 | AH83: FR | AI83: VAT
A84: 407-8174714-2593963 | B84: 407-8174714-2593963 | C84: 2024-03-16T12:08:51+00:00 | D84: 2024-03-18T00:51:55+00:00 | E84: Shipped | F84: Amazon | G84: Amazon.fr | J84: Standard | K84: BEPER Rapeuse Fromage Legumes BP.400 électrique, 3 cônes en Acier interchangeables, Coupe Julienne, tranches et râpe, allié, Argenté et Noir | L84: BP.400_FBA | M84: B0823CVGHX | N84: Shipped | O84: 1 | P84: EUR | Q84: 64.9 | R84: 10.82 | S84: 0.83 | X84: 0.83 | Y84: VALENTON | AA84: 94460 | AB84: FR | AC84: Free Shipping 2017/10/17 17-17-37-677
A85: 405-4791520-3940348 | B85: 405-4791520-3940348 | C85: 2024-03-16T11:53:24+00:00 | D85: 2024-03-17T04:01:49+00:00 | E85: Shipped | F85: Amazon | G85: Amazon.fr | J85: Expedited | K85: BEPER 50.700 Nettoyeur Vapeur pour Sol, Canapé, Tapis - Nettoyant Vapeur, 135° max, câble de 3 Mètres, 350 ml | L85: 50.700_FBA | M85: B01MTSEGF9 | N85: Shipped | O85: 1 | P85: EUR | Q85: 49.9 | R85: 8.32 | Y85: Villabé | AA85: 91100 | AB85: FR
A86: 408-5201461-4321921 | B86: 408-5201461-4321921 | C86: 2024-03-15T10:47:18+00:00 | D86: 2024-03-16T21:19:00+00:00 | E86: Shipped | F86: Amazon | G86: Amazon.fr | J86: Standard | K86: Beper - Mixeur électrique pour milkshakes, frappés, milkshakes et cocktails, 2 vitesses, bol en aluminium 0,5 l, 100 W,Rouge | L86: BP.690_FBA | M86: B07TQVD94L | N86: Shipped | O86: 1 | P86: EUR | Q86: 49.9 | R86: 8.32 | S86: 3.32 | X86: 3.32 | Y86: Village Neuf | AA86: 68128 | AB86: FR | AC86: Free Shipping 2017/10/17 17-17-37-677
A87: 402-2118252-1083521 | B87: 402-2118252-1083521 | C87: 2024-03-15T09:27:08+00:00 | D87: 2024-03-16T00:35:00+00:00 | E87: Shipped | F87: Amazon | G87: Amazon.fr | J87: Standard | K87: BEPER Rapeuse Fromage Legumes BP.400 électrique, 3 cônes en Acier interchangeables, Coupe Julienne, tranches et râpe, allié, Argenté et Noir | L87: BP.400_FBA | M87: B0823CVGHX | N87: Shipped | O87: 1 | P87: EUR | Q87: 64.9 | R87: 10.82 | S87: 3.32 | X87: 3.32 | Y87: WATTIGNIES | AA87: 59139 | AB87: FR | AC87: Free Shipping 2017/10/17 17-17-37-677
A88: 408-2073695-7877129 | B88: 408-2073695-7877129 | C88: 2024-03-14T13:28:35+00:00 | D88: 2024-03-15T02:25:30+00:00 | E88: Shipped | F88: Amazon | G88: Amazon.fr | J88: Expedited | K88: BEPER 40.405 Seche Cheveux de Voyage Pliable - Mini Seche Cheveux Silencieux, 2 Températures et 2 Vitesses | L88: 40.405_FBA | M88: B07N4C3H3V | N88: Shipped | O88: 1 | P88: EUR | Q88: 19.9 | R88: 3.32 | Y88: Pont Saint Esprit | AA88: 30130 | AB88: FR
A89: 402-4954299-8316364 | B89: 402-4954299-8316364 | C89: 2024-03-14T12:36:55+00:00 | D89: 2024-03-15T00:20:16+00:00 | E89: Shipped | F89: Amazon | G89: Amazon.fr | J89: Expedited | K89: BEPER Rapeuse Fromage Legumes BP.400 électrique, 3 cônes en Acier interchangeables, Coupe Julienne, tranches et râpe, allié, Argenté et Noir | L89: BP.400_FBA | M89: B0823CVGHX | N89: Shipped | O89: 1 | P89: EUR | Q89: 64.9 | R89: 10.82 | Y89: LE SOLER | AA89: 66270 | AB89: FR
A90: 405-8677983-9537933 | B90: 405-8677983-9537933 | C90: 2024-03-14T12:13:19+00:00 | D90: 2024-03-14T21:28:36+00:00 | E90: Shipped | F90: Amazon | G90: Amazon.fr | J90: Standard | K90: BEPER 50.700 Nettoyeur Vapeur pour Sol, Canapé, Tapis - Nettoyant Vapeur, 135° max, câble de 3 Mètres, 350 ml | L90: 50.700_FBA | M90: B01MTSEGF9 | N90: Shipped | O90: 1 | P90: EUR | Q90: 49.9 | R90: 8.32 | Y90: AUXERRE | AA90: 89000 | AB90: FR | AC90: Free Shipping 2017/10/17 17-17-37-677
A91: 171-7988832-8844357 | B91: 171-7988832-8844357 | C91: 2024-03-14T10:59:27+00:00 | D91: 2024-03-15T12:37:11+00:00 | E91: Shipped | F91: Amazon | G91: Amazon.fr | J91: Standard | K91: Beper BF.640 - Four ventilé multifonction 12L Anneau de rallonge pour capacité totale 18L Minuterie 60 minutes Température réglable jusqu'à 250° | L91: BF.640_FBA | M91: B07YBN2FS3 | N91: Shipped | O91: 1 | P91: EUR | Q91: 99 | R91: 17.18 | Y91: Bruxelles | Z91: Belgique | AA91: 1150 | AB91: BE | AC91: Free Shipping 2017/10/17 17-17-37-677
A92: 408-9144924-9569920 | B92: 408-9144924-9569920 | C92: 2024-03-13T23:38:56+00:00 | D92: 2024-03-14T11:38:23+00:00 | E92: Shipped | F92: Amazon | G92: Amazon.fr | J92: Expedited | K92: BEPER BT.710Y Crêpière électrique avec poignée, 800 W, plaque en aluminium avec revêtement antiadhésif, rouge | L92: BT.710Y_FBA | M92: B07NQ2VYGD | N92: Shipped | O92: 1 | P92: EUR | Q92: 39.9 | R92: 6.65 | Y92: Limoges | Z92: - | AA92: 87100 | AB92: FR
A93: 402-8537597-5509163 | B93: 402-8537597-5509163 | C93: 2024-03-13T19:34:20+00:00 | D93: 2024-03-15T17:06:39+00:00 | E93: Shipped | F93: Amazon | G93: Amazon.fr | J93: Standard | K93: BEPER 50.700 Nettoyeur Vapeur pour Sol, Canapé, Tapis - Nettoyant Vapeur, 135° max, câble de 3 Mètres, 350 ml | L93: 50.700_FBA | M93: B01MTSEGF9 | N93: Shipped | O93: 1 | P93: EUR | Q93: 49.9 | R93: 8.32 | S93: 1.11 | X93: 1.11 | Y93: Veigy Foncenex | AA93: 74140 | AB93: FR | AC93: Free Shipping 2017/10/17 17-17-37-677
A94: 406-4949423-6818700 | B94: 406-4949423-6818700 | C94: 2024-03-13T10:32:43+00:00 | D94: 2024-03-14T08:06:37+00:00 | E94: Shipped | F94: Amazon | G94: Amazon.fr | J94: Expedited | K94: BEPER 90.882 Four Electrique Résistance au Quartz, Noir, 1050 W | L94: 90.882_FBA | M94: B06Y195DJN | N94: Shipped | O94: 1 | P94: EUR | Q94: 59.9 | R94: 9.98 | Y94: AGON COUTAINVILLE | AA94: 50230 | AB94: FR
A95: 402-0041534-4018716 | B95: 402-0041534-4018716 | C95: 2024-03-13T07:36:53+00:00 | D95: 2024-03-14T04:02:42+00:00 | E95: Shipped | F95: Amazon | G95: Amazon.fr | J95: Expedited | K95: BEPER Distributeur automatique de couvre-chaussures, ABS, blanc, taille unique | L95: C206UTI001_FBA | M95: B08JM7SZ36 | N95: Shipped | O95: 1 | P95: EUR | Q95: 49.9 | R95: 8.32 | Y95: St Martin Du Tertre | AA95: 95270 | AB95: FR
A96: 403-3623660-0290700 | B96: 403-3623660-0290700 | C96: 2024-03-12T19:22:20+00:00 | D96: 2024-03-13T04:39:30+00:00 | E96: Shipped | F96: Amazon | G96: Amazon.fr | J96: Standard | K96: BEPER Distributeur automatique de couvre-chaussures, ABS, blanc, taille unique | L96: C206UTI001_FBA | M96: B08JM7SZ36 | N96: Shipped | O96: 1 | P96: EUR | Q96: 49.9 | R96: 8.32 | S96: 1.67 | X96: 1.67 | Y96: poissy | AA96: 78300 | AB96: FR | AC96: Free Shipping 2017/10/17 17-17-37-677
A97: 403-2109157-8602746 | B97: 403-2109157-8602746 | C97: 2024-03-12T18:10:06+00:00 | D97: 2024-03-13T02:22:41+00:00 | E97: Shipped | F97: Amazon | G97: Amazon.fr | J97: Standard | K97: Beper - Mixeur électrique pour milkshakes, frappés, milkshakes et cocktails, 2 vitesses, bol en aluminium 0,5 l, 100 W,Rouge | L97: BP.690_FBA | M97: B07TQVD94L | N97: Shipped | O97: 1 | P97: EUR | Q97: 49.9 | R97: 8.32 | S97: 3.32 | X97: 3.32 | Y97: Marseille | AA97: 13007 | AB97: FR | AC97: Free Shipping 2017/10/17 17-17-37-677
A98: 406-3317849-5792301 | B98: 406-3317849-5792301 | C98: 2024-03-12T16:50:51+00:00 | D98: 2024-03-13T17:19:07+00:00 | E98: Shipped | F98: Amazon | G98: Amazon.fr | J98: Expedited | K98: BEPER BT.710Y Crêpière électrique avec poignée, 800 W, plaque en aluminium avec revêtement antiadhésif, rouge | L98: BT.710Y_FBA | M98: B07NQ2VYGD | N98: Shipped | O98: 1 | P98: EUR | Q98: 39.9 | R98: 6.65 | Y98: Eloise | AA98: 1200 | AB98: FR
A99: 404-1439171-4431537 | B99: 404-1439171-4431537 | C99: 2024-03-12T14:30:10+00:00 | D99: 2024-03-13T02:24:08+00:00 | E99: Shipped | F99: Amazon | G99: Amazon.fr | J99: Expedited | K99: Beper - Mixeur électrique pour milkshakes, frappés, milkshakes et cocktails, 2 vitesses, bol en aluminium 0,5 l, 100 W,Rouge | L99: BP.690_FBA | M99: B07TQVD94L | N99: Shipped | O99: 1 | P99: EUR | Q99: 49.9 | R99: 8.32 | Y99: Nice | AA99: 6000 | AB99: FR
A100: 406-1016757-7891530 | B100: 406-1016757-7891530 | C100: 2024-03-12T13:46:11+00:00 | D100: 2024-03-13T02:22:47+00:00 | E100: Shipped | F100: Amazon | G100: Amazon.fr | J100: Standard | K100: Beper - Mixeur électrique pour milkshakes, frappés, milkshakes et cocktails, 2 vitesses, bol en aluminium 0,5 l, 100 W,Rouge | L100: BP.690_FBA | M100: B07TQVD94L | N100: Shipped | O100: 1 | P100: EUR | Q100: 49.9 | R100: 8.32 | S100: 3.32 | X100: 3.32 | Y100: Surgeres | AA100: 17700 | AB100: FR | AC100: Free Shipping 2017/10/17 17-17-37-677
...

Sheet v_03_23
A1: Codice marketplace | B1: (Tutto) | F1: Codice marketplace | G1: IT
A3: ASIN | B3: Numero del modello | C3: Somma di Unità ordinate | D3: Somma di Ricavi ordini | F3: ASIN | G3: Numero del modello | H3: Somma di Unità ordinate | I3: Somma di Ricavi ordini
A4: B0050IHH4E | B4: 40.979 | C4: 287 | D4: 3732.24 | F4: B0050IHH4E | G4: 40.979 | H4: 294 | I4: 3824.22
A5: B009O92WU4 | B5: 40.999 | C5: 4 | D5: 33.15 | F5: B00CMAD2FG | G5: HK-NV009W | H5: 1 | I5: 20.41
A6: B00C5CCJP0 | B6: 40.993 | C6: 1 | D6: 10.64 | F6: B00EYDRS1I | G6: 90.349 | H6: 48 | I6: 319.65
A7: B00CMAD2FG | B7: HK-NV009W | C7: 2 | D7: 33.58 | F7: B00FAJUDU8 | G7: 40.967N | H7: 74 | I7: 1574.07
A8: B00EYDRS1I | B8: 90.349 | C8: 107 | D8: 604.37 | F8: B00FFBFVG2 | G8: 40.100 | H8: 5 | I8: 42.39
A9: B00FAJUDU8 | B9: 40.967N | C9: 218 | D9: 4814.19 | F9: B00J7MNQFS | G9: 40.994 | H9: 6 | I9: 112.46
A10: B00FFBED98 | B10: 40.11 | C10: 1 | D10: 27.17 | F10: B00L5GPWFG | G10: 40.120 | H10: 4 | I10: 95.58
A11: B00FFBFVG2 | B11: 40.100 | C11: 5 | D11: 42.39 | F11: B00L5H5KUW | G11: 40.121 | H11: -3 | I11: -48.93
A12: B00J7MNQFS | B12: 40.994 | C12: 6 | D12: 112.46 | F12: B00NSNZSLM | G12: 90.602 | H12: 494 | I12: 10082.54
A13: B00L5GPWFG | B13: 40.120 | C13: 4 | D13: 95.58 | F13: B00OKE4RTM | G13: 90.386 | H13: 6 | I13: 294.6
A14: B00L5H5KUW | B14: 40.121 | C14: 58 | D14: 1197.15 | F14: B00OLZPU5K | G14: 40.947 | H14: 1 | I14: 10.57
A15: B00NSNZSLM | B15: 90.602 | C15: 503 | D15: 10307.45 | F15: B00YCPX8R6 | G15: 40.969 | H15: 34 | I15: 192.44
... A213: B091LRR67V | B213: P101FRI050 | C213: 97 | D213: 6336.99 | F213: B0BTHSH5MK | G213: C103ACC001 | H213: 36 | I213: 304.26
A214: B091VSY78C | B214: P303BIP050 | C214: 5 | D214: 81.83 | F214: Totale complessivo | H214: 21937 | I214: 332933.01
A215: B09251R9RJ | B215: P304CAP001 | C215: 11 | D215: 180.66
A216: B0929CVW7Q | B216: P206ZAN110 | C216: 1 | D216: 12.42
A217: B092DN1NCS | B217: P206VEN440 | C217: 3 | D217: 24.75
A218: B092J2RHL8 | B218: P206ZAN200 | C218: 50 | D218: 369.54
A219: B092JNYG6Z | B219: P204CAL201 | C219: 1 | D219: 8.11
A220: B092QXCQ8K | B220: P205DIF001 | C220: 77 | D220: 1157.01
A221: B09495C38F | B221: P204FER002 | C221: 576 | D221: 9142.88
A222: B0953R2W31 | B222: P102ACP001 | C222: 111 | D222: 1351.69
A223: B0957PWXL8 | B223: P102ACP010 | C223: 3 | D223: 74.55
A224: B095PQJGKX | B224: C107UTT002 | C224: 3345 | D224: 27470.2
A225: B095WCSSLC | B225: C301ABE101 | C225: 59 | D225: 411.57
A226: B095X9KDJR | B226: P101BOL100 | C226: 886 | D226: 11893.82
... A288: B0BTHSH5MK | B288: C103ACC001 | C288: 38 | D288: 323.26
A289: Totale complessivo | C289: 41452 | D289: 637551.46

Sheet v_03_24
A1: Codice marketplace | B1: (Tutto) | F1: Codice marketplace | G1: IT
A3: ASIN | B3: Numero del modello | C3: Somma di Unità ordinate | D3: Somma di Ricavi ordini | F3: ASIN | G3: Numero del modello | H3: Somma di Unità ordinate | I3: Somma di Ricavi ordini
A4: B0050IHH4E | B4: 40.979 | C4: 1183 | D4: 16822.21 | F4: B0050IHH4E | G4: 40.979 | H4: 486 | I4: 6983.03
A5: B009O92WU4 | B5: 40.999 | C5: 1 | D5: 5.03 | F5: B00BH202XK | G5: 40.808A | H5: 6 | I5: 83.1
A6: B00BH202XK | B6: 40.808A | C6: 10 | D6: 127.35 | F6: B00EYDRS1I | G6: 90.349 | H6: 36 | I6: 211.74
A7: B00CMAD2FG | B7: HK-NV009W | C7: 1 | D7: 15.18 | F7: B00FFBFVG2 | G7: 40.100 | H7: 0 | I7: 0
A8: B00EYDRS1I | B8: 90.349 | C8: 48 | D8: 271.81 | F8: B00L5GPWFG | G8: 40.120 | H8: 6 | I8: 147.9
A9: B00FFBFVG2 | B9: 40.100 | C9: 0 | D9: 0 | F9: B00L5H5KUW | G9: 40.121 | H9: 275 | I9: 5023.29
A10: B00FMZ2VW8 | B10: HK-HQ601C PINK | C10: 0 | D10: 0 | F10: B00NSNZSLM | G10: 90.602 | H10: 1 | I10: 20.41
A11: B00L5GPWFG | B11: 40.120 | C11: 6 | D11: 147.9 | F11: B00OKE4RTM | G11: 90.386 | H11: 2 | I11: 98.08
A12: B00L5H5KUW | B12: 40.121 | C12: 275 | D12: 5023.29 | F12: B00YH3FRV8 | G12: 40.998 | H12: 1 | I12: 7.43
A13: B00NSNZSLM | B13: 90.602 | C13: 1 | D13: 20.41 | F13: B011LFM60E | G13: 40.948T | H13: 2 | I13: 12.96
A14: B00OKE4RTM | B14: 90.386 | C14: 2 | D14: 98.08 | F14: B011LFVLW8 | G14: 90.620 | H14: 19 | I14: 686.19
A15: B00YH3FRV8 | B15: 40.998 | C15: 1 | D15: 7.43 | F15: B017IUJA50 | G15: 90.920G | H15: 15 | I15: 209.45
... A201: B097785V2V | B201: P202VAL110 | C201: 1 | D201: 5.42 | F201: B0CXJCJF5B | G201: P101PIA003 | H201: 8 | I201: 117.36
A202: B0978ZKW4S | B202: P205DIF100 | C202: 35 | D202: 428.14 | F202: Totale complessivo | H202: 6632 | I202: 104761.64
A203: B097F45J2B | B203: P102FRU500 | C203: 2 | D203: 65.4
A204: B097HRQNRG | B204: P101FRI100 | C204: 5 | D204: 150.29
A205: B097YTGFH7 | B205: P102ROB200 | C205: 22 | D205: 1103.13
A206: B098F33WBD | B206: RCO4091819 | C206: 21 | D206: 2.93
A207: B098QM485T | B207: P101CUD050 | C207: 5 | D207: 208.96
A208: B09968BKDS | B208: P102FRU003 | C208: 243 | D208: 3443.57
A209: B09B15P5H1 | B209: P102FRU200 | C209: 6 | D209: 91.74
A210: B09B2NT2SV | B210: P102FRU150 | C210: 9 | D210: 194.04
A211: B09B47S644 | B211: P101CUD501 | C211: 79 | D211: 2302.19
A212: B09BBFTDLJ | B212: P101TOS501 | C212: 1 | D212: 61.57
A213: B09BD8BG34 | B213: P301PIS001 | C213: 188 | D213: 2349.32
A214: B09BG1GGSM | B214: P204FER003 | C214: 0 | D214: 0
... A284: B0CXJCJF5B | B284: P101PIA003 | C284: 13 | D284: 191.49
A285: (vuoto) | B285: (vuoto)
A286: Totale complessivo | C286: 13774 | D286: 219396.13

Sheet s_03_24
E1: sales-channel | F1: Amazon.it
A2: sales-channel | B2: (Tutto) | J2: (Tutto)
E3: Etichette di riga | F3: Somma di quantity | G3: Somma di item-price
A4: asin | B4: sku | C4: Somma di quantity | D4: Somma di item-price | E4: B00FAJUDU8 | F4: 72 | G4: 2152.8 | J4: sku | K4: Somma di quantity | L4: Somma di item-price
A5: B00FAJUDU8 | B5: 40.967N | C5: 3 | D5: 89.7 | E5: B00NSNZSLM | F5: 49 | G5: 1612.1
B6: 40.967N_FBA | C6: 86 | D6: 2741.4 | E6: B017IUJA50 | F6: 137 | G6: 2722.71 | J6: 40.967N_FBA | K6: 86 | L6: 2741.4
A7: B00NSNZSLM | B7: BT.603Y | C7: 2 | D7: 65.8 | E7: B01CNX6Z78 | F7: 3 | G7: 104.7
B8: BT.603Y_FBA | C8: 47 | D8: 1546.3 | E8: B01CNX704K | F8: 1 | G8: 46.9 | J8: BT.603Y_FBA | K8: 47 | L8: 1546.3
A9: B017IUJA50 | B9: 90.920G | C9: 14 | D9: 278.6 | E9: B01I497WWM | F9: 531 | G9: 10557.34
B10: 90.920G_FBA | C10: 123 | D10: 2444.11 | E10: B01KMJ9OXW | F10: 139 | G10: 4844.53 | J10: 90.920G_FBA | K10: 123 | L10: 2444.11
A11: B01CNX6Z78 | B11: 90820 | C11: 3 | D11: 104.7 | E11: B01MTSEGF9 | F11: 19 | G11: 853.1
A12: B01CNX704K | B12: 90825 | C12: 1 | D12: 46.9 | E12: B06Y17FS6D | F12: 1 | G12: 39.9
A13: B01I497WWM | B13: 90.920R | C13: 2 | D13: 39.8 | E13: B06Y195DJN | F13: 16 | G13: 798.4
B14: 90.920R_FBA | C14: 526 | D14: 10463.81 | E14: B06Y1997YH | F14: 2 | G14: 159.8 | J14: 90.920R_FBA | K14: 526 | L14: 10463.81
B15: amzn.gr.90.920R-a2o_Ri7zcG6-mSjMeKSVj-LN | C15: 3 | D15: 53.73 | E15: B0757TJRR9 | F15: 497 | G15: 16362.46
A16: B01KMJ9OXW | B16: 90.590Y | C16: 2 | D16: 69.8 | E16: B076D74TC7 | F16: 6 | G16: 232.2
B17: 90.590Y_FBA | C17: 164 | D17: 5897.23 | E17: B076DCKSTJ | F17: 106 | G17: 2713.4 | J17: 90.590Y_FBA | K17: 164 | L17: 5897.23
A18: B01MTSEGF9 | B18: 50.700_FBA | C18: 31 | D18: 1442.9 | E18: B076Q7BR6F | F18: 22 | G18: 1040.8 | J18: 50.700_FBA | K18: 31 | L18: 1442.9
A19: B06Y17FS6D | B19: 90550 | C19: 1 | D19: 39.9 | E19: B07BB2DQ4V | F19: 1 | G19: 39.9
A20: B06Y195DJN | B20: 90882 | C20: 2 | D20: 99.8 | E20: B07BHCZR84 | F20: 1 | G20: 19.9
B21: 90.882_FBA | C21: 16 | D21: 818.4 | E21: B07HM7P6MP | F21: 2 | G21: 59.8 | J21: 90.882_FBA | K21: 16 | L21: 818.4
A22: B06Y1997YH | B22: 90883 | C22: 2 | D22: 159.8 | E22: B07N4C3H3V | F22: 244 | G22: 3635.6
A23: B0757TJRR9 | B23: 40500 | C23: 64 | D23: 2132.57 | E23: B07NQ2VYGD | F23: 499 | G23: 14519.28
B24: 40.500_FBA | C24: 446 | D24: 14829.54 | E24: B07NQC6S9V | F24: 12 | G24: 506.7 | J24: 40.500_FBA | K24: 446 | L24: 14829.54
B25: amzn.gr.40.500-78_VnB2lvTKD2lNtmILtG6-VG | C25: 1 | D25: 28.95 | E25: B07P7GGGQM | F25: 16 | G25: 958.4
A26: B076D74TC7 | B26: BT.700Y_FBA | C26: 6 | D26: 232.2 | E26: B07TQVD94L | F26: 16 | G26: 602.4 | J26: BT.700Y_FBA | K26: 6 | L26: 232.2
A27: B076DCKSTJ | B27: BT.602H | C27: 9 | D27: 242.1 | E27: B07V131F5W | F27: 167 | G27: 4754.3
B28: BT.602H_FBA | C28: 98 | D28: 2506.49 | E28: B07W7S9KYM | F28: 1 | G28: 59.9 | J28: BT.602H_FBA | K28: 98 | L28: 2506.49
A29: B076Q7BR6F | B29: BC.041N | C29: 3 | D29: 149.7 | E29: B07YBN2FS3 | F29: 24 | G29: 1908.01
B30: BC.041N_FBA | C30: 20 | D30: 946 | E30: B07ZJQTGG8 | F30: 155 | G30: 2309.5 | J30: BC.041N_FBA | K30: 20 | L30: 946
A31: B07BB2DQ4V | B31: BT.150Y_FBA | C31: 1 | D31: 39.9 | E31: B0823CVGHX | F31: 60 | G31: 4194 | J31: BT.150Y_FBA | K31: 1 | L31: 39.9
A32: B07BHCZR84 | B32: BA.200Y | C32: 1 | D32: 19.9 | E32: B08485QRVZ | F32: 70 | G32: 2082.22
A33: B07HM7P6MP | B33: RI.080 | C33: 2 | D33: 59.8 | E33: B085R2GCKX | F33: 4 | G33: 91.6
A34: B07N4C3H3V | B34: 40.405_FBA | C34: 253 | D34: 3814.7 | E34: B08FDYW72J | F34: 2 | G34: 69.8 | J34: 40.405_FBA | K34: 253 | L34: 3814.7
A35: B07NQ2VYGD | B35: amzn.gr.BT.710Y_FBA-210-4xyKJjiMm2Til-AC | C35: 1 | D35: 27.93 | E35: B08GS7XW73 | F35: 27 | G35: 556.35 | J35: amzn.gr.BT.710Y_FBA-210-4xyKJjiMm2Til-AC | K35: 1 | L35: 27.93
B36: amzn.gr.BT.710Y-4MyGoFppOTLJERCkjI-cP-LN | C36: 1 | D36: 22.41 | E36: B08GY7286R | F36: 9 | G36: 197.1
B37: amzn.gr.BT.710Y-m_rMJX0XWOKRxfp7Jvoem-VG | C37: 1 | D37: 26.31 | E37: B08JM7SZ36 | F37: 86 | G37: 3431.4
B38: BT.710Y | C38: 71 | D38: 2147.41 | E38: B08JYDDFZ2 | F38: 158 | G38: 2588.2
B39: BT.710Y_FBA | C39: 487 | D39: 14757.71 | E39: B08KSBDTQD | F39: 15 | G39: 598.5 | J39: BT.710Y_FBA | K39: 487 | L39: 14757.71
A40: B07NQC6S9V | B40: BT.651Y_FBA | C40: 12 | D40: 506.7 | E40: B08LZN1PWY | F40: 19 | G40: 1430.1 | J40: BT.651Y_FBA | K40: 12 | L40: 506.7
A41: B07P7GGGQM | B41: BP.961 | C41: 4 | D41: 239.6 | E41: B096MX229M | F41: 6 | G41: 91.4
B42: BP.961_FBA | C42: 12 | D42: 718.8 | E42: B097HRQNRG | F42: 5 | G42: 189.5 | J42: BP.961_FBA | K42: 12 | L42: 718.8
A43: B07TQVD94L | B43: BP.690_FBA | C43: 26 | D43: 1093.49 | E43: B09ZBHJ91Q | F43: 4 | G43: 99.6 | J43: BP.690_FBA | K43: 26 | L43: 1093.49
A44: B07V131F5W | B44: 40490 | C44: 63 | D44: 1883.7 | E44: B0B39H1Z8J | F44: 7 | G44: 76.3
B45: 40.490_FBA | C45: 104 | D45: 2870.6 | E45: B0B6JPXDN6 | F45: 2 | G45: 44.8 | J45: 40.490_FBA | K45: 104 | L45: 2870.6
A46: B07W7S9KYM | B46: BB.200 | C46: 1 | D46: 59.9 | E46: B0B8DLSNJF | F46: 8 | G46: 199.2
A47: B07YBN2FS3 | B47: amzn.gr.BF.640-b-EtmBvvyeusk71BpvqKf3-VG | C47: 1 | D47: 70.31 | E47: B0CLVR5JN6 | F47: 5 | G47: 124.5
B48: BF.640 | C48: 6 | D48: 479.4 | E48: B0CLVS3FH6 | F48: 56 | G48: 1063.58
B49: BF.640_FBA | C49: 21 | D49: 1754.3 | E49: B0CLY2CF4T | F49: 107 | G49: 2664.3 | J49: BF.640_FBA | K49: 21 | L49: 1754.3
A50: B07ZJQTGG8 | B50: 50245 | C50: 0 | E50: Totale complessivo | F50: 3389 | G50: 93407.28
B51: 50.245_FBA | C51: 163 | D51: 2468.7 | J51: 50.245_FBA | K51: 163 | L51: 2468.7
A52: B0823CVGHX | B52: BP.400 | C52: 3 | D52: 209.7
B53: BP.400_FBA | C53: 66 | D53: 4568.4 | J53: BP.400_FBA | K53: 66 | L53: 4568.4
A54: B08485QRVZ | B54: BC.261 | C54: 4 | D54: 119.6
B55: BC.261_FBA | C55: 69 | D55: 2082.32 | J55: BC.261_FBA | K55: 69 | L55: 2082.32
A56: B085R2GCKX | B56: 40332 | C56: 4 | D56: 91.6
A57: B08FDYW72J | B57: P101CUD100 | C57: 2 | D57: 69.8
A58: B08GS7XW73 | B58: P204FER250 | C58: 3 | D58: 102.75
B59: P204FER250_FBA | C59: 24 | D59: 453.6 | J59: P204FER250_FBA | K59: 24 | L59: 453.6
A60: B08GY7286R | B60: P203TFO001 | C60: 9 | D60: 197.1
A61: B08JM7SZ36 | B61: C206UTI001 | C61: 13 | D61: 518.7
B62: C206UTI001_FBA | C62: 83 | D62: 3375.7 | J62: C206UTI001_FBA | K62: 83 | L62: 3375.7
A63: B08JYDDFZ2 | B63: C206UTI002 | C63: 41 | D63: 610.9
B64: C206UTI002_FBA | C64: 121 | D64: 2049.72 | J64: C206UTI002_FBA | K64: 121 | L64: 2049.72
A65: B08KSBDTQD | B65: P102ROB001 | C65: 2 | D65: 79.8
B66: P102ROB001_FBA | C66: 14 | D66: 568.6 | J66: P102ROB001_FBA | K66: 14 | L66: 568.6
A67: B08LZN1PWY | B67: P101TEM001 | C67: 5 | D67: 399.5
B68: P101TEM001_FBA | C68: 15 | D68: 1139.6 | J68: P101TEM001_FBA | K68: 15 | L68: 1139.6
A69: B096MX229M | B69: P102ROB050 | C69: 4 | D69: 59.6
B70: P102ROB050 _FBA | C70: 2 | D70: 31.8 | J70: P102ROB050 _FBA | K70: 2 | L70: 31.8
A71: B097HRQNRG | B71: P101FRI100 | C71: 5 | D71: 189.5
A72: B09ZBHJ91Q | B72: P201UTP100 | C72: 4 | D72: 99.6
A73: B0B39H1Z8J | B73: C106CAS001 | C73: 7 | D73: 76.3
A74: B0B6JPXDN6 | B74: P201UTP200 | C74: 1 | D74: 24.9
B75: P201UTP200_FBA | C75: 1 | D75: 19.9 | J75: P201UTP200_FBA | K75: 1 | L75: 19.9
A76: B0B8DLSNJF | B76: P302VIS050 | C76: 8 | D76: 199.2
A77: B0CLVR5JN6 | B77: P201UTP112 | C77: 5 | D77: 124.5
A78: B0CLVS3FH6 | B78: P201UTP111 | C78: 2 | D78: 49.8
B79: P201UTP111 _FBA | C79: 54 | D79: 1013.78 | J79: P201UTP111 _FBA | K79: 54 | L79: 1013.78
A80: B0CLY2CF4T | B80: P201UTP113 | C80: 10 | D80: 249
B81: P201UTP113 _FBA | C81: 97 | D81: 2415.3 | J81: P201UTP113 _FBA | K81: 97 | L81: 2415.3
A82: Totale complessivo | C82: 3584 | D82: 101722.37

Sheet pivot
A3: ASIN | B3: SKU | C3: Somma di Ordini Vendor 24 | D3: Somma di Valori ordini Vendor 24 | E3: Somma di Ordini Seller | F3: Somma di Valori ordini Seller | G3: Somma di Ordini Complessivi | H3: Somma di Valori ordini Complessivi | I3: Somma di Ordini Vendor 23 | J3: Somma di Valori ordini Vendor 23
A4: B0050IHH4E | B4: 40.979 | C4: 1183 | D4: 16822.21 | E4: 0 | F4: 0 | G4: 1183 | H4: 16822.21 | I4: 287 | J4: 3732.24
A5: B009O92WU4 | B5: 40.999 | C5: 1 | D5: 5.03 | E5: 0 | F5: 0 | G5: 1 | H5: 5.03 | I5: 4 | J5: 33.15
A6: B00BH202XK | B6: 40.808A | C6: 10 | D6: 127.35 | E6: 0 | F6: 0 | G6: 10 | H6: 127.35 | I6: 0 | J6: 0
A7: B00CMAD2FG | B7: HK-NV009W | C7: 1 | D7: 15.18 | E7: 0 | F7: 0 | G7: 1 | H7: 15.18 | I7: 2 | J7: 33.58
A8: B00FFBFVG2 | B8: 40.100 | C8: 0 | D8: 0 | E8: 0 | F8: 0 | G8: 0 | H8: 0 | I8: 5 | J8: 42.39
A9: B00L5GPWFG | B9: 40.120 | C9: 6 | D9: 147.9 | E9: 0 | F9: 0 | G9: 6 | H9: 147.9 | I9: 4 | J9: 95.58
A10: B00L5H5KUW | B10: 40.121 | C10: 275 | D10: 5023.29 | E10: 0 | F10: 0 | G10: 275 | H10: 5023.29 | I10: 58 | J10: 1197.15
A11: B00NSNZSLM | B11: 90.602 | C11: 1 | D11: 20.41 | E11: 49 | F11: 1612.1 | G11: 50 | H11: 1632.51 | I11: 503 | J11: 10307.45
A12: B00YH3FRV8 | B12: 40.998 | C12: 1 | D12: 7.43 | E12: 0 | F12: 0 | G12: 1 | H12: 7.43 | I12: 0 | J12: 0
A13: B011LFM60E | B13: 40.948T | C13: 2 | D13: 12.96 | E13: 0 | F13: 0 | G13: 2 | H13: 12.96 | I13: 2 | J13: 7.53
A14: B011LFVLW8 | B14: 90.620 | C14: 19 | D14: 686.19 | E14: 0 | F14: 0 | G14: 19 | H14: 686.19 | I14: 16 | J14: 590.39
A15: B017IUJA50 | B15: 90.920G | C15: 15 | D15: 209.45 | E15: 137 | F15: 2722.71 | G15: 152 | H15: 2932.16 | I15: 448 | J15: 6892.94
... A284: B076DD35DZ | B284: BC.002 | C284: 3 | D284: 130.44 | E284: 0 | F284: 0 | G284: 3 | H284: 130.44 | I284: 3 | J284: 130.54
A285: Totale complessivo | C285: 13773 | D285: 219317.97 | E285: 3399 | F285: 94996.87 | G285: 17172 | H285: 314314.84 | I285: 40784 | J285: 625743.48

Sheet IT
A1: ASIN | B1: SKU | C1: Ordini Vendor 24 | D1: Valori ordini Vendor 24 | E1: Ordini Seller | F1: Valori ordini Seller | G1: % seller / totale | H1: Ordini Complessivi | I1: Valori ordini Complessivi | J1: Ordini Vendor 23 | K1: Valori ordini Vendor 23 | L1: Differenza Ordini | M1: Differenza Valore | N1: Differenza Valore %
A2: B0050IHH4E | B2: 40.979 | C2: =VLOOKUP(A2,v_03_24!F:I,3,FALSE) -> 486 | D2: =VLOOKUP(A2,v_03_24!F:I,4,FALSE) -> 6983.03 | E2: 0 | F2: 0 | G2: =F2/I2 -> 0 | H2: =C2+E2 -> 486 | I2: =D2+F2 -> 6983.03 | J2: =VLOOKUP(A2,v_03_23!F:I,3,FALSE) -> 294 | K2: =VLOOKUP(A2,v_03_23!F:I,4,FALSE) -> 3824.22 | L2: =H2-J2 -> 192 | M2: =I2-K2 -> 3158.81 | N2: =M2/K2 -> 0.82600112
A3: B009O92WU4 | B3: 40.999 | C3: 0 | D3: 0 | E3: 0 | F3: 0 | H3: =C3+E3 -> 0 | I3: =D3+F3 -> 0 | J3: 0 | K3: 0 | L3: =H3-J3 -> 0 | M3: =I3-K3 -> 0
A4: B00BH202XK | B4: 40.808A | C4: =VLOOKUP(A4,v_03_24!F:I,3,FALSE) -> 6 | D4: =VLOOKUP(A4,v_03_24!F:I,4,FALSE) -> 83.1 | E4: 0 | F4: 0 | G4: =F4/I4 -> 0 | H4: =C4+E4 -> 6 | I4: =D4+F4 -> 83.1 | J4: 0 | K4: 0 | L4: =H4-J4 -> 6 | M4: =I4-K4 -> 83.1
A5: B00CMAD2FG | B5: HK-NV009W | C5: 0 | D5: 0 | E5: 0 | F5: 0 | H5: =C5+E5 -> 0 | I5: =D5+F5 -> 0 | J5: =VLOOKUP(A5,v_03_23!F:I,3,FALSE) -> 1 | K5: =VLOOKUP(A5,v_03_23!F:I,4,FALSE) -> 20.41 | L5: =H5-J5 -> -1 | M5: =I5-K5 -> -20.41 | N5: =M5/K5 -> -1
A6: B00FFBFVG2 | B6: 40.100 | C6: =VLOOKUP(A6,v_03_24!F:I,3,FALSE) -> 0 | D6: =VLOOKUP(A6,v_03_24!F:I,4,FALSE) -> 0 | E6: 0 | F6: 0 | H6: =C6+E6 -> 0 | I6: =D6+F6 -> 0 | J6: =VLOOKUP(A6,v_03_23!F:I,3,FALSE) -> 5 | K6: =VLOOKUP(A6,v_03_23!F:I,4,FALSE) -> 42.39 | L6: =H6-J6 -> -5 | M6: =I6-K6 -> -42.39 | N6: =M6/K6 -> -1
A7: B00L5GPWFG | B7: 40.120 | C7: =VLOOKUP(A7,v_03_24!F:I,3,FALSE) -> 6 | D7: =VLOOKUP(A7,v_03_24!F:I,4,FALSE) -> 147.9 | E7: 0 | F7: 0 | G7: =F7/I7 -> 0 | H7: =C7+E7 -> 6 | I7: =D7+F7 -> 147.9 | J7: =VLOOKUP(A7,v_03_23!F:I,3,FALSE) -> 4 | K7: =VLOOKUP(A7,v_03_23!F:I,4,FALSE) -> 95.58 | L7: =H7-J7 -> 2 | M7: =I7-K7 -> 52.32 | N7: =M7/K7 -> 0.54739485
A8: B00L5H5KUW | B8: 40.121 | C8: =VLOOKUP(A8,v_03_24!F:I,3,FALSE) -> 275 | D8: =VLOOKUP(A8,v_03_24!F:I,4,FALSE) -> 5023.29 | E8: 0 | F8: 0 | G8: =F8/I8 -> 0 | H8: =C8+E8 -> 275 | I8: =D8+F8 -> 5023.29 | J8: =VLOOKUP(A8,v_03_23!F:I,3,FALSE) -> -3 | K8: =VLOOKUP(A8,v_03_23!F:I,4,FALSE) -> -48.93 | L8: =H8-J8 -> 278 | M8: =I8-K8 -> 5072.22 | N8: =M8/K8 -> -103.66278
A9: B00NSNZSLM | B9: 90.602 | C9: =VLOOKUP(A9,v_03_24!F:I,3,FALSE) -> 1 | D9: =VLOOKUP(A9,v_03_24!F:I,4,FALSE) -> 20.41 | E9: =VLOOKUP(A9,s_03_24!E:G,2,FALSE) -> 49 | F9: =VLOOKUP(A9,s_03_24!E:G,3,FALSE) -> 1612.1 | G9: =F9/I9 -> 0.98749778 | H9: =C9+E9 -> 50 | I9: =D9+F9 -> 1632.51 | J9: =VLOOKUP(A9,v_03_23!F:I,3,FALSE) -> 494 | K9: =VLOOKUP(A9,v_03_23!F:I,4,FALSE) -> 10082.54 | L9: =H9-J9 -> -444 | M9: =I9-K9 -> -8450.03 | N9: =M9/K9 -> -0.83808544
A10: B00YH3FRV8 | B10: 40.998 | C10: =VLOOKUP(A10,v_03_24!F:I,3,FALSE) -> 1 | D10: =VLOOKUP(A10,v_03_24!F:I,4,FALSE) -> 7.43 | E10: 0 | F10: 0 | G10: =F10/I10 -> 0 | H10: =C10+E10 -> 1 | I10: =D10+F10 -> 7.43 | J10: 0 | K10: 0 | L10: =H10-J10 -> 1 | M10: =I10-K10 -> 7.43
A11: B011LFM60E | B11: 40.948T | C11: =VLOOKUP(A11,v_03_24!F:I,3,FALSE) -> 2 | D11: =VLOOKUP(A11,v_03_24!F:I,4,FALSE) -> 12.96 | E11: 0 | F11: 0 | G11: =F11/I11 -> 0 | H11: =C11+E11 -> 2 | I11: =D11+F11 -> 12.96 | J11: =VLOOKUP(A11,v_03_23!F:I,3,FALSE) -> 1 | K11: =VLOOKUP(A11,v_03_23!F:I,4,FALSE) -> 3.9 | L11: =H11-J11 -> 1 | M11: =I11-K11 -> 9.06 | N11: =M11/K11 -> 2.3230769
A12: B011LFVLW8 | B12: 90.620 | C12: =VLOOKUP(A12,v_03_24!F:I,3,FALSE) -> 19 | D12: =VLOOKUP(A12,v_03_24!F:I,4,FALSE) -> 686.19 | E12: 0 | F12: 0 | G12: =F12/I12 -> 0 | H12: =C12+E12 -> 19 | I12: =D12+F12 -> 686.19 | J12: =VLOOKUP(A12,v_03_23!F:I,3,FALSE) -> 16 | K12: =VLOOKUP(A12,v_03_23!F:I,4,FALSE) -> 590.39 | L12: =H12-J12 -> 3 | M12: =I12-K12 -> 95.8 | N12: =M12/K12 -> 0.16226562
A13: B017IUJA50 | B13: 90.920G | C13: =VLOOKUP(A13,v_03_24!F:I,3,FALSE) -> 15 | D13: =VLOOKUP(A13,v_03_24!F:I,4,FALSE) -> 209.45 | E13: =VLOOKUP(A13,s_03_24!E:G,2,FALSE) -> 137 | F13: =VLOOKUP(A13,s_03_24!E:G,3,FALSE) -> 2722.71 | G13: =F13/I13 -> 0.92856802 | H13: =C13+E13 -> 152 | I13: =D13+F13 -> 2932.16 | J13: =VLOOKUP(A13,v_03_23!F:I,3,FALSE) -> 329 | K13: =VLOOKUP(A13,v_03_23!F:I,4,FALSE) -> 5312.75 | L13: =H13-J13 -> -177 | M13: =I13-K13 -> -2380.59 | N13: =M13/K13 -> -0.44808997
A14: B01CHW1L88 | B14: PE.001 | C14: =VLOOKUP(A14,v_03_24!F:I,3,FALSE) -> 1 | D14: =VLOOKUP(A14,v_03_24!F:I,4,FALSE) -> 15.05 | E14: 0 | F14: 0 | G14: =F14/I14 -> 0 | H14: =C14+E14 -> 1 | I14: =D14+F14 -> 15.05 | J14: 0 | K14: 0 | L14: =H14-J14 -> 1 | M14: =I14-K14 -> 15.05
A15: B01CNX6UIM | B15: PE.300 | C15: =VLOOKUP(A15,v_03_24!F:I,3,FALSE) -> 0 | D15: =VLOOKUP(A15,v_03_24!F:I,4,FALSE) -> 0 | E15: 0 | F15: 0 | H15: =C15+E15 -> 0 | I15: =D15+F15 -> 0 | J15: 0 | K15: 0 | L15: =H15-J15 -> 0 | M15: =I15-K15 -> 0
A16: B01CNX704K | B16: 90.825 | C16: 0 | D16: 0 | E16: =VLOOKUP(A16,s_03_24!E:G,2,FALSE) -> 1 | F16: =VLOOKUP(A16,s_03_24!E:G,3,FALSE) -> 46.9 | G16: =F16/I16 -> 1 | H16: =C16+E16 -> 1 | I16: =D16+F16 -> 46.9 | J16: 0 | K16: 0 | L16: =H16-J16 -> 1 | M16: =I16-K16 -> 46.9
A17: B01CNX71NA | B17: 90.871 | C17: =VLOOKUP(A17,v_03_24!F:I,3,FALSE) -> 1 | D17: =VLOOKUP(A17,v_03_24!F:I,4,FALSE) -> 86.86 | E17: 0 | F17: 0 | G17: =F17/I17 -> 0 | H17: =C17+E17 -> 1 | I17: =D17+F17 -> 86.86 | J17: =VLOOKUP(A17,v_03_23!F:I,3,FALSE) -> 11 | K17: =VLOOKUP(A17,v_03_23!F:I,4,FALSE) -> 903.8 | L17: =H17-J17 -> -10 | M17: =I17-K17 -> -816.94 | N17: =M17/K17 -> -0.90389467
A18: B01I497WWM | B18: 90.920R | C18: =VLOOKUP(A18,v_03_24!F:I,3,FALSE) -> 14 | D18: =VLOOKUP(A18,v_03_24!F:I,4,FALSE) -> 260.2 | E18: =VLOOKUP(A18,s_03_24!E:G,2,FALSE) -> 531 | F18: =VLOOKUP(A18,s_03_24!E:G,3,FALSE) -> 10557.34 | G18: =F18/I18 -> 0.97594647 | H18: =C18+E18 -> 545 | I18: =D18+F18 -> 10817.54 | J18: =VLOOKUP(A18,v_03_23!F:I,3,FALSE) -> 1296 | K18: =VLOOKUP(A18,v_03_23!F:I,4,FALSE) -> 18280.61 | L18: =H18-J18 -> -751 | M18: =I18-K18 -> -7463.07 | N18: =M18/K18 -> -0.4082506
A19: B01II7S968 | B19: MD.217 | C19: 0 | D19: 0 | E19: 0 | F19: 0 | H19: =C19+E19 -> 0 | I19: =D19+F19 -> 0 | J19: 0 | K19: 0 | L19: =H19-J19 -> 0 | M19: =I19-K19 -> 0
A20: B01KMJ9OXW | B20: 90.590Y | C20: =VLOOKUP(A20,v_03_24!F:I,3,FALSE) -> 1 | D20: =VLOOKUP(A20,v_03_24!F:I,4,FALSE) -> 35.32 | E20: =VLOOKUP(A20,s_03_24!E:G,2,FALSE) -> 139 | F20: =VLOOKUP(A20,s_03_24!E:G,3,FALSE) -> 4844.53 | G20: =F20/I20 -> 0.99276207 | H20: =C20+E20 -> 140 | I20: =D20+F20 -> 4879.85 | J20: =VLOOKUP(A20,v_03_23!F:I,3,FALSE) -> 244 | K20: =VLOOKUP(A20,v_03_23!F:I,4,FALSE) -> 7663.28 | L20: =H20-J20 -> -104 | M20: =I20-K20 -> -2783.43 | N20: =M20/K20 -> -0.36321653
A21: B06WGS8ZVG | B21: 90.131 | C21: =VLOOKUP(A21,v_03_24!F:I,3,FALSE) -> 2 | D21: =VLOOKUP(A21,v_03_24!F:I,4,FALSE) -> 27.28 | E21: 0 | F21: 0 | G21: =F21/I21 -> 0 | H21: =C21+E21 -> 2 | I21: =D21+F21 -> 27.28 | J21: =VLOOKUP(A21,v_03_23!F:I,3,FALSE) -> 9 | K21: =VLOOKUP(A21,v_03_23!F:I,4,FALSE) -> 105.59 | L21: =H21-J21 -> -7 | M21: =I21-K21 -> -78.31 | N21: =M21/K21 -> -0.7416422
A22: B06XPK3BTC | B22: 40.450GO | C22: =VLOOKUP(A22,v_03_24!F:I,3,FALSE) -> 2 | D22: =VLOOKUP(A22,v_03_24!F:I,4,FALSE) -> 31.65 | E22: 0 | F22: 0 | G22: =F22/I22 -> 0 | H22: =C22+E22 -> 2 | I22: =D22+F22 -> 31.65 | J22: =VLOOKUP(A22,v_03_23!F:I,3,FALSE) -> 6 | K22: =VLOOKUP(A22,v_03_23!F:I,4,FALSE) -> 90.34 | L22: =H22-J22 -> -4 | M22: =I22-K22 -> -58.69 | N22: =M22/K22 -> -0.64965685
A23: B06XYMCV3W | B23: 90.485H | C23: =VLOOKUP(A23,v_03_24!F:I,3,FALSE) -> 0 | D23: =VLOOKUP(A23,v_03_24!F:I,4,FALSE) -> 0 | E23: 0 | F23: 0 | H23: =C23+E23 -> 0 | I23: =D23+F23 -> 0 | J23: 0 | K23: 0 | L23: =H23-J23 -> 0 | M23: =I23-K23 -> 0
A24: B06Y17FS6D | B24: 90.550 | C24: =VLOOKUP(A24,v_03_24!F:I,3,FALSE) -> 49 | D24: =VLOOKUP(A24,v_03_24!F:I,4,FALSE) -> 1395.95 | E24: =VLOOKUP(A24,s_03_24!E:G,2,FALSE) -> 1 | F24: =VLOOKUP(A24,s_03_24!E:G,3,FALSE) -> 39.9 | G24: =F24/I24 -> 0.027788418 | H24: =C24+E24 -> 50 | I24: =D24+F24 -> 1435.85 | J24: =VLOOKUP(A24,v_03_23!F:I,3,FALSE) -> 29 | K24: =VLOOKUP(A24,v_03_23!F:I,4,FALSE) -> 710.79 | L24: =H24-J24 -> 21 | M24: =I24-K24 -> 725.06 | N24: =M24/K24 -> 1.0200763
A25: B06Y195DJN | B25: 90.882 | C25: 0 | D25: 0 | E25: =VLOOKUP(A25,s_03_24!E:G,2,FALSE) -> 16 | F25: =VLOOKUP(A25,s_03_24!E:G,3,FALSE) -> 798.4 | G25: =F25/I25 -> 1 | H25: =C25+E25 -> 16 | I25: =D25+F25 -> 798.4 | J25: 0 | K25: 0 | L25: =H25-J25 -> 16 | M25: =I25-K25 -> 798.4
A26: B073B67PLQ | B26: 90.884 | C26: =VLOOKUP(A26,v_03_24!F:I,3,FALSE) -> 14 | D26: =VLOOKUP(A26,v_03_24!F:I,4,FALSE) -> 1136.27 | E26: 0 | F26: 0 | G26: =F26/I26 -> 0 | H26: =C26+E26 -> 14 | I26: =D26+F26 -> 1136.27 | J26: =VLOOKUP(A26,v_03_23!F:I,3,FALSE) -> 68 | K26: =VLOOKUP(A26,v_03_23!F:I,4,FALSE) -> 5010.92 | L26: =H26-J26 -> -54 | M26: =I26-K26 -> -3874.65 | N26: =M26/K26 -> -0.77324124
A27: B075K5C2QG | B27: RI.201 | C27: =VLOOKUP(A27,v_03_24!F:I,3,FALSE) -> 2 | D27: =VLOOKUP(A27,v_03_24!F:I,4,FALSE) -> 40.82 | E27: 0 | F27: 0 | G27: =F27/I27 -> 0 | H27: =C27+E27 -> 2 | I27: =D27+F27 -> 40.82 | J27: =VLOOKUP(A27,v_03_23!F:I,3,FALSE) -> -2 | K27: =VLOOKUP(A27,v_03_23!F:I,4,FALSE) -> -33.5 | L27: =H27-J27 -> 4 | M27: =I27-K27 -> 74.32 | N27: =M27/K27 -> -2.2185075
A28: B075RF5S3N | B28: BC.160A | C28: =VLOOKUP(A28,v_03_24!F:I,3,FALSE) -> 5 | D28: =VLOOKUP(A28,v_03_24!F:I,4,FALSE) -> 129.21 | E28: 0 | F28: 0 | G28: =F28/I28 -> 0 | H28: =C28+E28 -> 5 | I28: =D28+F28 -> 129.21 | J28: =VLOOKUP(A28,v_03_23!F:I,3,FALSE) -> 17 | K28: =VLOOKUP(A28,v_03_23!F:I,4,FALSE) -> 351.12 | L28: =H28-J28 -> -12 | M28: =I28-K28 -> -221.91 | N28: =M28/K28 -> -0.63200615
A29: B075RF8FM9 | B29: BC.160G | C29: =VLOOKUP(A29,v_03_24!F:I,3,FALSE) -> 0 | D29: =VLOOKUP(A29,v_03_24!F:I,4,FALSE) -> 0 | E29: 0 | F29: 0 | H29: =C29+E29 -> 0 | I29: =D29+F29 -> 0 | J29: =VLOOKUP(A29,v_03_23!F:I,3,FALSE) -> 0 | K29: =VLOOKUP(A29,v_03_23!F:I,4,FALSE) -> 0 | L29: =H29-J29 -> 0 | M29: =I29-K29 -> 0
A30: B075XR3T8V | B30: BT.600Y | C30: 0 | D30: 0 | E30: 0 | F30: 0 | H30: =C30+E30 -> 0 | I30: =D30+F30 -> 0 | J30: 0 | K30: 0 | L30: =H30-J30 -> 0 | M30: =I30-K30 -> 0
A31: B076D74TC7 | B31: BT.700Y | C31: 0 | D31: 0 | E31: =VLOOKUP(A31,s_03_24!E:G,2,FALSE) -> 6 | F31: =VLOOKUP(A31,s_03_24!E:G,3,FALSE) -> 232.2 | G31: =F31/I31 -> 1 | H31: =C31+E31 -> 6 | I31: =D31+F31 -> 232.2 | J31: 0 | K31: 0 | L31: =H31-J31 -> 6 | M31: =I31-K31 -> 232.2
A32: B076DC4VWG | B32: 40.501 | C32: =VLOOKUP(A32,v_03_24!F:I,3,FALSE) -> 0 | D32: =VLOOKUP(A32,v_03_24!F:I,4,FALSE) -> 0 | E32: 0 | F32: 0 | H32: =C32+E32 -> 0 | I32: =D32+F32 -> 0 | J32: =VLOOKUP(A32,v_03_23!F:I,3,FALSE) -> 3 | K32: =VLOOKUP(A32,v_03_23!F:I,4,FALSE) -> 62.68 | L32: =H32-J32 -> -3 | M32: =I32-K32 -> -62.68 | N32: =M32/K32 -> -1
A33: B076DCL19C | B33: BP.720 | C33: =VLOOKUP(A33,v_03_24!F:I,3,FALSE) -> 17 | D33: =VLOOKUP(A33,v_03_24!F:I,4,FALSE) -> 814.3 | E33: 0 | F33: 0 | G33: =F33/I33 -> 0 | H33: =C33+E33 -> 17 | I33: =D33+F33 -> 814.3 | J33: =VLOOKUP(A33,v_03_23!F:I,3,FALSE) -> 24 | K33: =VLOOKUP(A33,v_03_23!F:I,4,FALSE) -> 1436.05 | L33: =H33-J33 -> -7 | M33: =I33-K33 -> -621.75 | N33: =M33/K33 -> -0.43295846
A34: B076DCX3JH | B34: BB.103 | C34: 0 | D34: 0 | E34: 0 | F34: 0 | H34: =C34+E34 -> 0 | I34: =D34+F34 -> 0 | J34: 0 | K34: 0 | L34: =H34-J34 -> 0 | M34: =I34-K34 -> 0
A35: B076QCMZX1 | B35: 40.821 | C35: =VLOOKUP(A35,v_03_24!F:I,3,FALSE) -> 162 | D35: =VLOOKUP(A35,v_03_24!F:I,4,FALSE) -> 1977.32 | E35: 0 | F35: 0 | G35: =F35/I35 -> 0 | H35: =C35+E35 -> 162 | I35: =D35+F35 -> 1977.32 | J35: =VLOOKUP(A35,v_03_23!F:I,3,FALSE) -> 97 | K35: =VLOOKUP(A35,v_03_23!F:I,4,FALSE) -> 866.21 | L35: =H35-J35 -> 65 | M35: =I35-K35 -> 1111.11 | N35: =M35/K35 -> 1.2827259
A36: B076QFRRZ5 | B36: 40.931 | C36: =VLOOKUP(A36,v_03_24!F:I,3,FALSE) -> 40 | D36: =VLOOKUP(A36,v_03_24!F:I,4,FALSE) -> 573.31 | E36: 0 | F36: 0 | G36: =F36/I36 -> 0 | H36: =C36+E36 -> 40 | I36: =D36+F36 -> 573.31 | J36: =VLOOKUP(A36,v_03_23!F:I,3,FALSE) -> 178 | K36: =VLOOKUP(A36,v_03_23!F:I,4,FALSE) -> 2411.94 | L36: =H36-J36 -> -138 | M36: =I36-K36 -> -1838.63 | N36: =M36/K36 -> -0.76230337
A37: B079SB5VJZ | B37: 50451 | C37: =VLOOKUP(A37,v_03_24!F:I,3,FALSE) -> 2 | D37: =VLOOKUP(A37,v_03_24!F:I,4,FALSE) -> 91.63 | E37: 0 | F37: 0 | G37: =F37/I37 -> 0 | H37: =C37+E37 -> 2 | I37: =D37+F37 -> 91.63 | J37: =VLOOKUP(A37,v_03_23!F:I,3,FALSE) -> 265 | K37: =VLOOKUP(A37,v_03_23!F:I,4,FALSE) -> 8761.44 | L37: =H37-J37 -> -263 | M37: =I37-K37 -> -8669.81 | N37: =M37/K37 -> -0.98954167
A38: B07B9CBD91 | B38: VE.550 | C38: 0 | D38: 0 | E38: 0 | F38: 0 | H38: =C38+E38 -> 0 | I38: =D38+F38 -> 0 | J38: 0 | K38: 0 | L38: =H38-J38 -> 0 | M38: =I38-K38 -> 0
A39: B07B9CPH62 | B39: BG.200Y | C39: =VLOOKUP(A39,v_03_24!F:I,3,FALSE) -> 6 | D39: =VLOOKUP(A39,v_03_24!F:I,4,FALSE) -> 294.6 | E39: 0 | F39: 0 | G39: =F39/I39 -> 0 | H39: =C39+E39 -> 6 | I39: =D39+F39 -> 294.6 | J39: =VLOOKUP(A39,v_03_23!F:I,3,FALSE) -> 32 | K39: =VLOOKUP(A39,v_03_23!F:I,4,FALSE) -> 1571.2 | L39: =H39-J39 -> -26 | M39: =I39-K39 -> -1276.6 | N39: =M39/K39 -> -0.8125
A40: B07BHCZR84 | B40: BA.200Y | C40: =VLOOKUP(A40,v_03_24!F:I,3,FALSE) -> 22 | D40: =VLOOKUP(A40,v_03_24!F:I,4,FALSE) -> 266.22 | E40: =VLOOKUP(A40,s_03_24!E:G,2,FALSE) -> 1 | F40: =VLOOKUP(A40,s_03_24!E:G,3,FALSE) -> 19.9 | G40: =F40/I40 -> 0.069551237 | H40: =C40+E40 -> 23 | I40: =D40+F40 -> 286.12 | J40: =VLOOKUP(A40,v_03_23!F:I,3,FALSE) -> 36 | K40: =VLOOKUP(A40,v_03_23!F:I,4,FALSE) -> 385.44 | L40: =H40-J40 -> -13 | M40: =I40-K40 -> -99.32 | N40: =M40/K40 -> -0.25767954
A41: B07BHTW4WV | B41: VE.210 | C41: 0 | D41: 0 | E41: 0 | F41: 0 | H41: =C41+E41 -> 0 | I41: =D41+F41 -> 0 | J41: 0 | K41: 0 | L41: =H41-J41 -> 0 | M41: =I41-K41 -> 0
A42: B07CZ4WMB8 | B42: 40.330 | C42: 0 | D42: 0 | E42: 0 | F42: 0 | H42: =C42+E42 -> 0 | I42: =D42+F42 -> 0 | J42: 0 | K42: 0 | L42: =H42-J42 -> 0 | M42: =I42-K42 -> 0
A43: B07F187NFQ | B43: 50.900 | C43: =VLOOKUP(A43,v_03_24!F:I,3,FALSE) -> 1 | D43: =VLOOKUP(A43,v_03_24!F:I,4,FALSE) -> 3.77 | E43: 0 | F43: 0 | G43: =F43/I43 -> 0 | H43: =C43+E43 -> 1 | I43: =D43+F43 -> 3.77 | J43: =VLOOKUP(A43,v_03_23!F:I,3,FALSE) -> 1 | K43: =VLOOKUP(A43,v_03_23!F:I,4,FALSE) -> 4.3 | L43: =H43-J43 -> 0 | M43: =I43-K43 -> -0.53 | N43: =M43/K43 -> -0.12325581
A44: B07FN14FSN | B44: 50.160 | C44: 0 | D44: 0 | E44: 0 | F44: 0 | H44: =C44+E44 -> 0 | I44: =D44+F44 -> 0 | J44: 0 | K44: 0 | L44: =H44-J44 -> 0 | M44: =I44-K44 -> 0
A45: B07HFPYL56 | B45: BC.353 | C45: 0 | D45: 0 | E45: 0 | F45: 0 | H45: =C45+E45 -> 0 | I45: =D45+F45 -> 0 | J45: 0 | K45: 0 | L45: =H45-J45 -> 0 | M45: =I45-K45 -> 0
A46: B07HFQH172 | B46: BC.250 | C46: 0 | D46: 0 | E46: 0 | F46: 0 | H46: =C46+E46 -> 0 | I46: =D46+F46 -> 0 | J46: 0 | K46: 0 | L46: =H46-J46 -> 0 | M46: =I46-K46 -> 0
A47: B07HHDSJHM | B47: BI.504 | C47: 0 | D47: 0 | E47: 0 | F47: 0 | H47: =C47+E47 -> 0 | I47: =D47+F47 -> 0 | J47: =VLOOKUP(A47,v_03_23!F:I,3,FALSE) -> 19 | K47: =VLOOKUP(A47,v_03_23!F:I,4,FALSE) -> 104.26 | L47: =H47-J47 -> -19 | M47: =I47-K47 -> -104.26 | N47: =M47/K47 -> -1
A48: B07HM7P6MP | B48: RI.080 | C48: =VLOOKUP(A48,v_03_24!F:I,3,FALSE) -> 10 | D48: =VLOOKUP(A48,v_03_24!F:I,4,FALSE) -> 253.92 | E48: =VLOOKUP(A48,s_03_24!E:G,2,FALSE) -> 2 | F48: =VLOOKUP(A48,s_03_24!E:G,3,FALSE) -> 59.8 | G48: =F48/I48 -> 0.19061584 | H48: =C48+E48 -> 12 | I48: =D48+F48 -> 313.72 | J48: =VLOOKUP(A48,v_03_23!F:I,3,FALSE) -> 112 | K48: =VLOOKUP(A48,v_03_23!F:I,4,FALSE) -> 2439.18 | L48: =H48-J48 -> -100 | M48: =I48-K48 -> -2125.46 | N48: =M48/K48 -> -0.87138301
A49: B07MC8ZVRM | B49: 40.452 | C49: 0 | D49: 0 | E49: 0 | F49: 0 | H49: =C49+E49 -> 0 | I49: =D49+F49 -> 0 | J49: 0 | K49: 0 | L49: =H49-J49 -> 0 | M49: =I49-K49 -> 0
A50: B07NNZSW1W | B50: BT.110 | C50: =VLOOKUP(A50,v_03_24!F:I,3,FALSE) -> 1 | D50: =VLOOKUP(A50,v_03_24!F:I,4,FALSE) -> 19.72 | E50: 0 | F50: 0 | G50: =F50/I50 -> 0 | H50: =C50+E50 -> 1 | I50: =D50+F50 -> 19.72 | J50: 0 | K50: 0 | L50: =H50-J50 -> 1 | M50: =I50-K50 -> 19.72
A51: B07NP6YY5W | B51: BP.200 | C51: 0 | D51: 0 | E51: 0 | F51: 0 | H51: =C51+E51 -> 0 | I51: =D51+F51 -> 0 | J51: 0 | K51: 0 | L51: =H51-J51 -> 0 | M51: =I51-K51 -> 0
A52: B07NQ1T7YK | B52: BP.101H | C52: =VLOOKUP(A52,v_03_24!F:I,3,FALSE) -> 13 | D52: =VLOOKUP(A52,v_03_24!F:I,4,FALSE) -> 182.92 | E52: 0 | F52: 0 | G52: =F52/I52 -> 0 | H52: =C52+E52 -> 13 | I52: =D52+F52 -> 182.92 | J52: =VLOOKUP(A52,v_03_23!F:I,3,FALSE) -> 208 | K52: =VLOOKUP(A52,v_03_23!F:I,4,FALSE) -> 2539.68 | L52: =H52-J52 -> -195 | M52: =I52-K52 -> -2356.76 | N52: =M52/K52 -> -0.92797518
A53: B07P7L18T9 | B53: 40.102 | C53: =VLOOKUP(A53,v_03_24!F:I,3,FALSE) -> 1 | D53: =VLOOKUP(A53,v_03_24!F:I,4,FALSE) -> 13.81 | E53: 0 | F53: 0 | G53: =F53/I53 -> 0 | H53: =C53+E53 -> 1 | I53: =D53+F53 -> 13.81 | J53: =VLOOKUP(A53,v_03_23!F:I,3,FALSE) -> 1 | K53: =VLOOKUP(A53,v_03_23!F:I,4,FALSE) -> 15.85 | L53: =H53-J53 -> 0 | M53: =I53-K53 -> -2.04 | N53: =M53/K53 -> -0.12870662
A54: B07PCQJ1P8 | B54: BT.410 | C54: 0 | D54: 0 | E54: 0 | F54: 0 | H54: =C54+E54 -> 0 | I54: =D54+F54 -> 0 | J54: 0 | K54: 0 | L54: =H54-J54 -> 0 | M54: =I54-K54 -> 0
A55: B07PTQPT16 | B55: BF.570 | C55: 0 | D55: 0 | E55: 0 | F55: 0 | H55: =C55+E55 -> 0 | I55: =D55+F55 -> 0 | J55: 0 | K55: 0 | L55: =H55-J55 -> 0 | M55: =I55-K55 -> 0
A56: B07QX1RJRH | B56: 40.742 | C56: =VLOOKUP(A56,v_03_24!F:I,3,FALSE) -> 2 | D56: =VLOOKUP(A56,v_03_24!F:I,4,FALSE) -> 48.17 | E56: 0 | F56: 0 | G56: =F56/I56 -> 0 | H56: =C56+E56 -> 2 | I56: =D56+F56 -> 48.17 | J56: =VLOOKUP(A56,v_03_23!F:I,3,FALSE) -> 3 | K56: =VLOOKUP(A56,v_03_23!F:I,4,FALSE) -> 52.38 | L56: =H56-J56 -> -1 | M56: =I56-K56 -> -4.21 | N56: =M56/K56 -> -0.080374189
A57: B07QZ89PLH | B57: 40.403 | C57: 0 | D57: 0 | E57: 0 | F57: 0 | H57: =C57+E57 -> 0 | I57: =D57+F57 -> 0 | J57: 0 | K57: 0 | L57: =H57-J57 -> 0 | M57: =I57-K57 -> 0
A58: B07TQVD94L | B58: BP.690 | C58: =VLOOKUP(A58,v_03_24!F:I,3,FALSE) -> 6 | D58: =VLOOKUP(A58,v_03_24!F:I,4,FALSE) -> 147.06 | E58: =VLOOKUP(A58,s_03_24!E:G,2,FALSE) -> 16 | F58: =VLOOKUP(A58,s_03_24!E:G,3,FALSE) -> 602.4 | G58: =F58/I58 -> 0.80377872 | H58: =C58+E58 -> 22 | I58: =D58+F58 -> 749.46 | J58: =VLOOKUP(A58,v_03_23!F:I,3,FALSE) -> 90 | K58: =VLOOKUP(A58,v_03_23!F:I,4,FALSE) -> 2205.9 | L58: =H58-J58 -> -68 | M58: =I58-K58 -> -1456.44 | N58: =M58/K58 -> -0.66024752
A59: B07TSNB5WG | B59: BP.102 | C59: =VLOOKUP(A59,v_03_24!F:I,3,FALSE) -> 0 | D59: =VLOOKUP(A59,v_03_24!F:I,4,FALSE) -> 0 | E59: 0 | F59: 0 | H59: =C59+E59 -> 0 | I59: =D59+F59 -> 0 | J59: =VLOOKUP(A59,v_03_23!F:I,3,FALSE) -> 608 | K59: =VLOOKUP(A59,v_03_23!F:I,4,FALSE) -> 7423.68 | L59: =H59-J59 -> -608 | M59: =I59-K59 -> -7423.68 | N59: =M59/K59 -> -1
A60: B07V131F5W | B60: 40.490 | C60: =VLOOKUP(A60,v_03_24!F:I,3,FALSE) -> 105 | D60: =VLOOKUP(A60,v_03_24!F:I,4,FALSE) -> 2591.61 | E60: =VLOOKUP(A60,s_03_24!E:G,2,FALSE) -> 167 | F60: =VLOOKUP(A60,s_03_24!E:G,3,FALSE) -> 4754.3 | G60: =F60/I60 -> 0.64720368 | H60: =C60+E60 -> 272 | I60: =D60+F60 -> 7345.91 | J60: =VLOOKUP(A60,v_03_23!F:I,3,FALSE) -> 292 | K60: =VLOOKUP(A60,v_03_23!F:I,4,FALSE) -> 6779.04 | L60: =H60-J60 -> -20 | M60: =I60-K60 -> 566.87 | N60: =M60/K60 -> 0.083620985
A61: B07XVWXVK1 | B61: RI.503 | C61: 0 | D61: 0 | E61: 0 | F61: 0 | H61: =C61+E61 -> 0 | I61: =D61+F61 -> 0 | J61: 0 | K61: 0 | L61: =H61-J61 -> 0 | M61: =I61-K61 -> 0
A62: B07YBFRMM7 | B62: BB.210 | C62: 0 | D62: 0 | E62: 0 | F62: 0 | H62: =C62+E62 -> 0 | I62: =D62+F62 -> 0 | J62: 0 | K62: 0 | L62: =H62-J62 -> 0 | M62: =I62-K62 -> 0
A63: B07YBNB2QY | B63: 50161 | C63: 0 | D63: 0 | E63: 0 | F63: 0 | H63: =C63+E63 -> 0 | I63: =D63+F63 -> 0 | J63: 0 | K63: 0 | L63: =H63-J63 -> 0 | M63: =I63-K63 -> 0
A64: B07YBNPZPJ | B64: BP.552 | C64: =VLOOKUP(A64,v_03_24!F:I,3,FALSE) -> 3 | D64: =VLOOKUP(A64,v_03_24!F:I,4,FALSE) -> 92.19 | E64: 0 | F64: 0 | G64: =F64/I64 -> 0 | H64: =C64+E64 -> 3 | I64: =D64+F64 -> 92.19 | J64: =VLOOKUP(A64,v_03_23!F:I,3,FALSE) -> 43 | K64: =VLOOKUP(A64,v_03_23!F:I,4,FALSE) -> 961.97 | L64: =H64-J64 -> -40 | M64: =I64-K64 -> -869.78 | N64: =M64/K64 -> -0.90416541
A65: B07ZJMFB3R | B65: BC.510 | C65: =VLOOKUP(A65,v_03_24!F:I,3,FALSE) -> 12 | D65: =VLOOKUP(A65,v_03_24!F:I,4,FALSE) -> 709.12 | E65: 0 | F65: 0 | G65: =F65/I65 -> 0 | H65: =C65+E65 -> 12 | I65: =D65+F65 -> 709.12 | J65: =VLOOKUP(A65,v_03_23!F:I,3,FALSE) -> 30 | K65: =VLOOKUP(A65,v_03_23!F:I,4,FALSE) -> 1694.4 | L65: =H65-J65 -> -18 | M65: =I65-K65 -> -985.28 | N65: =M65/K65 -> -0.58149197
A66: B07ZJQTGG8 | B66: 50.245 | C66: =VLOOKUP(A66,v_03_24!F:I,3,FALSE) -> 107 | D66: =VLOOKUP(A66,v_03_24!F:I,4,FALSE) -> 1345.75 | E66: =VLOOKUP(A66,s_03_24!E:G,2,FALSE) -> 155 | F66: =VLOOKUP(A66,s_03_24!E:G,3,FALSE) -> 2309.5 | G66: =F66/I66 -> 0.63183093 | H66: =C66+E66 -> 262 | I66: =D66+F66 -> 3655.25 | J66: =VLOOKUP(A66,v_03_23!F:I,3,FALSE) -> 1851 | K66: =VLOOKUP(A66,v_03_23!F:I,4,FALSE) -> 22600.71 | L66: =H66-J66 -> -1589 | M66: =I66-K66 -> -18945.46 | N66: =M66/K66 -> -0.83826836
A67: B0823CVGHX | B67: BP.400 | C67: 0 | D67: 0 | E67: =VLOOKUP(A67,s_03_24!E:G,2,FALSE) -> 60 | F67: =VLOOKUP(A67,s_03_24!E:G,3,FALSE) -> 4194 | G67: =F67/I67 -> 1 | H67: =C67+E67 -> 60 | I67: =D67+F67 -> 4194 | J67: 0 | K67: 0 | L67: =H67-J67 -> 60 | M67: =I67-K67 -> 4194
A68: B08485QRVZ | B68: BC.261 | C68: =VLOOKUP(A68,v_03_24!F:I,3,FALSE) -> 1 | D68: =VLOOKUP(A68,v_03_24!F:I,4,FALSE) -> 24.88 | E68: =VLOOKUP(A68,s_03_24!E:G,2,FALSE) -> 70 | F68: =VLOOKUP(A68,s_03_24!E:G,3,FALSE) -> 2082.22 | G68: =F68/I68 -> 0.9881923 | H68: =C68+E68 -> 71 | I68: =D68+F68 -> 2107.1 | J68: =VLOOKUP(A68,v_03_23!F:I,3,FALSE) -> 435 | K68: =VLOOKUP(A68,v_03_23!F:I,4,FALSE) -> 8878.35 | L68: =H68-J68 -> -364 | M68: =I68-K68 -> -6771.25 | N68: =M68/K68 -> -0.76266987
A69: B084C3JTC2 | B69: 40.406 | C69: =VLOOKUP(A69,v_03_24!F:I,3,FALSE) -> 28 | D69: =VLOOKUP(A69,v_03_24!F:I,4,FALSE) -> 676.38 | E69: 0 | F69: 0 | G69: =F69/I69 -> 0 | H69: =C69+E69 -> 28 | I69: =D69+F69 -> 676.38 | J69: =VLOOKUP(A69,v_03_23!F:I,3,FALSE) -> 112 | K69: =VLOOKUP(A69,v_03_23!F:I,4,FALSE) -> 2745.12 | L69: =H69-J69 -> -84 | M69: =I69-K69 -> -2068.74 | N69: =M69/K69 -> -0.7536064
A70: B084PN7WPZ | B70: XUADA001 | C70: =VLOOKUP(A70,v_03_24!F:I,3,FALSE) -> 5 | D70: =VLOOKUP(A70,v_03_24!F:I,4,FALSE) -> 24.55 | E70: 0 | F70: 0 | G70: =F70/I70 -> 0 | H70: =C70+E70 -> 5 | I70: =D70+F70 -> 24.55 | J70: =VLOOKUP(A70,v_03_23!F:I,3,FALSE) -> 2 | K70: =VLOOKUP(A70,v_03_23!F:I,4,FALSE) -> 13.18 | L70: =H70-J70 -> 3 | M70: =I70-K70 -> 11.37 | N70: =M70/K70 -> 0.86267071
A71: B084TG23R3 | B71: C102BOT001 | C71: =VLOOKUP(A71,v_03_24!F:I,3,FALSE) -> 1 | D71: =VLOOKUP(A71,v_03_24!F:I,4,FALSE) -> 7.62 | E71: 0 | F71: 0 | G71: =F71/I71 -> 0 | H71: =C71+E71 -> 1 | I71: =D71+F71 -> 7.62 | J71: =VLOOKUP(A71,v_03_23!F:I,3,FALSE) -> 75 | K71: =VLOOKUP(A71,v_03_23!F:I,4,FALSE) -> 547.5 | L71: =H71-J71 -> -74 | M71: =I71-K71 -> -539.88 | N71: =M71/K71 -> -0.98608219
A72: B084TGLFLM | B72: C102BOT002 | C72: =VLOOKUP(A72,v_03_24!F:I,3,FALSE) -> 29 | D72: =VLOOKUP(A72,v_03_24!F:I,4,FALSE) -> 189.95 | E72: 0 | F72: 0 | G72: =F72/I72 -> 0 | H72: =C72+E72 -> 29 | I72: =D72+F72 -> 189.95 | J72: =VLOOKUP(A72,v_03_23!F:I,3,FALSE) -> 195 | K72: =VLOOKUP(A72,v_03_23!F:I,4,FALSE) -> 783.9 | L72: =H72-J72 -> -166 | M72: =I72-K72 -> -593.95 | N72: =M72/K72 -> -0.75768593
A73: B084TGLSDV | B73: C102BOT004 | C73: =VLOOKUP(A73,v_03_24!F:I,3,FALSE) -> 57 | D73: =VLOOKUP(A73,v_03_24!F:I,4,FALSE) -> 357.47 | E73: 0 | F73: 0 | G73: =F73/I73 -> 0 | H73: =C73+E73 -> 57 | I73: =D73+F73 -> 357.47 | J73: =VLOOKUP(A73,v_03_23!F:I,3,FALSE) -> 87 | K73: =VLOOKUP(A73,v_03_23!F:I,4,FALSE) -> 425.18 | L73: =H73-J73 -> -30 | M73: =I73-K73 -> -67.71 | N73: =M73/K73 -> -0.1592502
A74: B085JHSWJW | B74: RCOBP630 | C74: =VLOOKUP(A74,v_03_24!F:I,3,FALSE) -> 1 | D74: =VLOOKUP(A74,v_03_24!F:I,4,FALSE) -> 5.98 | E74: 0 | F74: 0 | G74: =F74/I74 -> 0 | H74: =C74+E74 -> 1 | I74: =D74+F74 -> 5.98 | J74: =VLOOKUP(A74,v_03_23!F:I,3,FALSE) -> 1 | K74: =VLOOKUP(A74,v_03_23!F:I,4,FALSE) -> 8.11 | L74: =H74-J74 -> 0 | M74: =I74-K74 -> -2.13 | N74: =M74/K74 -> -0.26263872
A75: B085JHZT67 | B75: P206VEN420 | C75: =VLOOKUP(A75,v_03_24!F:I,3,FALSE) -> 5 | D75: =VLOOKUP(A75,v_03_24!F:I,4,FALSE) -> 81.55 | E75: 0 | F75: 0 | G75: =F75/I75 -> 0 | H75: =C75+E75 -> 5 | I75: =D75+F75 -> 81.55 | J75: 0 | K75: 0 | L75: =H75-J75 -> 5 | M75: =I75-K75 -> 81.55
A76: B085JJ747G | B76: P206VEN260 | C76: 0 | D76: 0 | E76: 0 | F76: 0 | H76: =C76+E76 -> 0 | I76: =D76+F76 -> 0 | J76: 0 | K76: 0 | L76: =H76-J76 -> 0 | M76: =I76-K76 -> 0
A77: B085JJ81R7 | B77: RCO9003028 | C77: =VLOOKUP(A77,v_03_24!F:I,3,FALSE) -> 43 | D77: =VLOOKUP(A77,v_03_24!F:I,4,FALSE) -> 278.64 | E77: 0 | F77: 0 | G77: =F77/I77 -> 0 | H77: =C77+E77 -> 43 | I77: =D77+F77 -> 278.64 | J77: =VLOOKUP(A77,v_03_23!F:I,3,FALSE) -> 99 | K77: =VLOOKUP(A77,v_03_23!F:I,4,FALSE) -> 641.49 | L77: =H77-J77 -> -56 | M77: =I77-K77 -> -362.85 | N77: =M77/K77 -> -0.56563625
A78: B085JJ8RC6 | B78: BB.050 | C78: =VLOOKUP(A78,v_03_24!F:I,3,FALSE) -> 16 | D78: =VLOOKUP(A78,v_03_24!F:I,4,FALSE) -> 206.03 | E78: 0 | F78: 0 | G78: =F78/I78 -> 0 | H78: =C78+E78 -> 16 | I78: =D78+F78 -> 206.03 | J78: =VLOOKUP(A78,v_03_23!F:I,3,FALSE) -> 668 | K78: =VLOOKUP(A78,v_03_23!F:I,4,FALSE) -> 8150.61 | L78: =H78-J78 -> -652 | M78: =I78-K78 -> -7944.58 | N78: =M78/K78 -> -0.97472214
A79: B085JJ9J4N | B79: P206RAF200 | C79: =VLOOKUP(A79,v_03_24!F:I,3,FALSE) -> 10 | D79: =VLOOKUP(A79,v_03_24!F:I,4,FALSE) -> 204.1 | E79: 0 | F79: 0 | G79: =F79/I79 -> 0 | H79: =C79+E79 -> 10 | I79: =D79+F79 -> 204.1 | J79: 0 | K79: 0 | L79: =H79-J79 -> 10 | M79: =I79-K79 -> 204.1
A80: B085JJFLGY | B80: RCO9003022 | C80: =VLOOKUP(A80,v_03_24!F:I,3,FALSE) -> 54 | D80: =VLOOKUP(A80,v_03_24!F:I,4,FALSE) -> 261.66 | E80: 0 | F80: 0 | G80: =F80/I80 -> 0 | H80: =C80+E80 -> 54 | I80: =D80+F80 -> 261.66 | J80: =VLOOKUP(A80,v_03_23!F:I,3,FALSE) -> 148 | K80: =VLOOKUP(A80,v_03_23!F:I,4,FALSE) -> 717.97 | L80: =H80-J80 -> -94 | M80: =I80-K80 -> -456.31 | N80: =M80/K80 -> -0.6355558
A81: B085JJMBM7 | B81: P206VEN400 | C81: =VLOOKUP(A81,v_03_24!F:I,3,FALSE) -> 2 | D81: =VLOOKUP(A81,v_03_24!F:I,4,FALSE) -> 28.91 | E81: 0 | F81: 0 | G81: =F81/I81 -> 0 | H81: =C81+E81 -> 2 | I81: =D81+F81 -> 28.91 | J81: =VLOOKUP(A81,v_03_23!F:I,3,FALSE) -> 15 | K81: =VLOOKUP(A81,v_03_23!F:I,4,FALSE) -> 121.65 | L81: =H81-J81 -> -13 | M81: =I81-K81 -> -92.74 | N81: =M81/K81 -> -0.76235101
A82: B085R2GCKX | B82: 40.332 | C82: =VLOOKUP(A82,v_03_24!F:I,3,FALSE) -> 43 | D82: =VLOOKUP(A82,v_03_24!F:I,4,FALSE) -> 712.92 | E82: =VLOOKUP(A82,s_03_24!E:G,2,FALSE) -> 4 | F82: =VLOOKUP(A82,s_03_24!E:G,3,FALSE) -> 91.6 | G82: =F82/I82 -> 0.11385671 | H82: =C82+E82 -> 47 | I82: =D82+F82 -> 804.52 | J82: =VLOOKUP(A82,v_03_23!F:I,3,FALSE) -> 261 | K82: =VLOOKUP(A82,v_03_23!F:I,4,FALSE) -> 3828.87 | L82: =H82-J82 -> -214 | M82: =I82-K82 -> -3024.35 | N82: =M82/K82 -> -0.78988057
A83: B085R2NT18 | B83: 3BEPI001 | C83: 0 | D83: 0 | E83: 0 | F83: 0 | H83: =C83+E83 -> 0 | I83: =D83+F83 -> 0 | J83: 0 | K83: 0 | L83: =H83-J83 -> 0 | M83: =I83-K83 -> 0
A84: B088PL1CY6 | B84: P206VEN100 | C84: 0 | D84: 0 | E84: 0 | F84: 0 | H84: =C84+E84 -> 0 | I84: =D84+F84 -> 0 | J84: 0 | K84: 0 | L84: =H84-J84 -> 0 | M84: =I84-K84 -> 0
A85: B088V4DR59 | B85: P206ZAN040 | C85: =VLOOKUP(A85,v_03_24!F:I,3,FALSE) -> 12 | D85: =VLOOKUP(A85,v_03_24!F:I,4,FALSE) -> 631.3 | E85: 0 | F85: 0 | G85: =F85/I85 -> 0 | H85: =C85+E85 -> 12 | I85: =D85+F85 -> 631.3 | J85: =VLOOKUP(A85,v_03_23!F:I,3,FALSE) -> 1 | K85: =VLOOKUP(A85,v_03_23!F:I,4,FALSE) -> 51.7 | L85: =H85-J85 -> 11 | M85: =I85-K85 -> 579.6 | N85: =M85/K85 -> 11.210832
A86: B088V7DR7L | B86: P206VEN130 | C86: 0 | D86: 0 | E86: 0 | F86: 0 | H86: =C86+E86 -> 0 | I86: =D86+F86 -> 0 | J86: 0 | K86: 0 | L86: =H86-J86 -> 0 | M86: =I86-K86 -> 0
A87: B088XJQ37J | B87: C301ABE001 | C87: =VLOOKUP(A87,v_03_24!F:I,3,FALSE) -> 33 | D87: =VLOOKUP(A87,v_03_24!F:I,4,FALSE) -> 402.93 | E87: 0 | F87: 0 | G87: =F87/I87 -> 0 | H87: =C87+E87 -> 33 | I87: =D87+F87 -> 402.93 | J87: =VLOOKUP(A87,v_03_23!F:I,3,FALSE) -> 303 | K87: =VLOOKUP(A87,v_03_23!F:I,4,FALSE) -> 3202.71 | L87: =H87-J87 -> -270 | M87: =I87-K87 -> -2799.78 | N87: =M87/K87 -> -0.87419092
A88: B089BGZSNM | B88: P101CUD001 | C88: 0 | D88: 0 | E88: 0 | F88: 0 | H88: =C88+E88 -> 0 | I88: =D88+F88 -> 0 | J88: 0 | K88: 0 | L88: =H88-J88 -> 0 | M88: =I88-K88 -> 0
A89: B08B66J4C3 | B89: P101PIA001 | C89: =VLOOKUP(A89,v_03_24!F:I,3,FALSE) -> 0 | D89: =VLOOKUP(A89,v_03_24!F:I,4,FALSE) -> 0 | E89: 0 | F89: 0 | H89: =C89+E89 -> 0 | I89: =D89+F89 -> 0 | J89: =VLOOKUP(A89,v_03_23!F:I,3,FALSE) -> 545 | K89: =VLOOKUP(A89,v_03_23!F:I,4,FALSE) -> 6738.53 | L89: =H89-J89 -> -545 | M89: =I89-K89 -> -6738.53 | N89: =M89/K89 -> -1
A90: B08B8M2B7B | B90: P102EST001 | C90: =VLOOKUP(A90,v_03_24!F:I,3,FALSE) -> 8 | D90: =VLOOKUP(A90,v_03_24!F:I,4,FALSE) -> 261.6 | E90: 0 | F90: 0 | G90: =F90/I90 -> 0 | H90: =C90+E90 -> 8 | I90: =D90+F90 -> 261.6 | J90: =VLOOKUP(A90,v_03_23!F:I,3,FALSE) -> 7 | K90: =VLOOKUP(A90,v_03_23!F:I,4,FALSE) -> 211.75 | L90: =H90-J90 -> 1 | M90: =I90-K90 -> 49.85 | N90: =M90/K90 -> 0.23541913
A91: B08C7YJB5N | B91: P201UTP001 | C91: =VLOOKUP(A91,v_03_24!F:I,3,FALSE) -> 33 | D91: =VLOOKUP(A91,v_03_24!F:I,4,FALSE) -> 432.96 | E91: 0 | F91: 0 | G91: =F91/I91 -> 0 | H91: =C91+E91 -> 33 | I91: =D91+F91 -> 432.96 | J91: =VLOOKUP(A91,v_03_23!F:I,3,FALSE) -> 128 | K91: =VLOOKUP(A91,v_03_23!F:I,4,FALSE) -> 1143.04 | L91: =H91-J91 -> -95 | M91: =I91-K91 -> -710.08 | N91: =M91/K91 -> -0.6212206
A92: B08DHZDXVV | B92: P102SBA100 | C92: =VLOOKUP(A92,v_03_24!F:I,3,FALSE) -> 4 | D92: =VLOOKUP(A92,v_03_24!F:I,4,FALSE) -> 88.2 | E92: 0 | F92: 0 | G92: =F92/I92 -> 0 | H92: =C92+E92 -> 4 | I92: =D92+F92 -> 88.2 | J92: =VLOOKUP(A92,v_03_23!F:I,3,FALSE) -> 16 | K92: =VLOOKUP(A92,v_03_23!F:I,4,FALSE) -> 288.51 | L92: =H92-J92 -> -12 | M92: =I92-K92 -> -200.31 | N92: =M92/K92 -> -0.69429136
A93: B08DJ3K9J8 | B93: p102rob100 | C93: =VLOOKUP(A93,v_03_24!F:I,3,FALSE) -> 1 | D93: =VLOOKUP(A93,v_03_24!F:I,4,FALSE) -> 9.75 | E93: 0 | F93: 0 | G93: =F93/I93 -> 0 | H93: =C93+E93 -> 1 | I93: =D93+F93 -> 9.75 | J93: =VLOOKUP(A93,v_03_23!F:I,3,FALSE) -> 1 | K93: =VLOOKUP(A93,v_03_23!F:I,4,FALSE) -> 12.21 | L93: =H93-J93 -> 0 | M93: =I93-K93 -> -2.46 | N93: =M93/K93 -> -0.2014742
A94: B08DL66NZ9 | B94: P301ASC001 | C94: 0 | D94: 0 | E94: 0 | F94: 0 | H94: =C94+E94 -> 0 | I94: =D94+F94 -> 0 | J94: 0 | K94: 0 | L94: =H94-J94 -> 0 | M94: =I94-K94 -> 0
A95: B08F5GYFKS | B95: P102FRU001 | C95: 0 | D95: 0 | E95: 0 | F95: 0 | H95: =C95+E95 -> 0 | I95: =D95+F95 -> 0 | J95: =VLOOKUP(A95,v_03_23!F:I,3,FALSE) -> 1 | K95: =VLOOKUP(A95,v_03_23!F:I,4,FALSE) -> 12.21 | L95: =H95-J95 -> -1 | M95: =I95-K95 -> -12.21 | N95: =M95/K95 -> -1
A96: B08FDP7T13 | B96: P101FOR001 | C96: 0 | D96: 0 | E96: 0 | F96: 0 | H96: =C96+E96 -> 0 | I96: =D96+F96 -> 0 | J96: 0 | K96: 0 | L96: =H96-J96 -> 0 | M96: =I96-K96 -> 0
A97: B08FDYW72J | B97: P101CUD100 | C97: =VLOOKUP(A97,v_03_24!F:I,3,FALSE) -> 6 | D97: =VLOOKUP(A97,v_03_24!F:I,4,FALSE) -> 147.06 | E97: =VLOOKUP(A97,s_03_24!E:G,2,FALSE) -> 2 | F97: =VLOOKUP(A97,s_03_24!E:G,3,FALSE) -> 69.8 | G97: =F97/I97 -> 0.32186664 | H97: =C97+E97 -> 8 | I97: =D97+F97 -> 216.86 | J97: =VLOOKUP(A97,v_03_23!F:I,3,FALSE) -> 13 | K97: =VLOOKUP(A97,v_03_23!F:I,4,FALSE) -> 318.63 | L97: =H97-J97 -> -5 | M97: =I97-K97 -> -101.77 | N97: =M97/K97 -> -0.31939868
A98: B08FF245TD | B98: P101CUD500 | C98: =VLOOKUP(A98,v_03_24!F:I,3,FALSE) -> 2 | D98: =VLOOKUP(A98,v_03_24!F:I,4,FALSE) -> 54.55 | E98: 0 | F98: 0 | G98: =F98/I98 -> 0 | H98: =C98+E98 -> 2 | I98: =D98+F98 -> 54.55 | J98: =VLOOKUP(A98,v_03_23!F:I,3,FALSE) -> 7 | K98: =VLOOKUP(A98,v_03_23!F:I,4,FALSE) -> 177.75 | L98: =H98-J98 -> -5 | M98: =I98-K98 -> -123.2 | N98: =M98/K98 -> -0.6931083
A99: B08FJGGZ1D | B99: 70.405 | C99: 0 | D99: 0 | E99: 0 | F99: 0 | H99: =C99+E99 -> 0 | I99: =D99+F99 -> 0 | J99: =VLOOKUP(A99,v_03_23!F:I,3,FALSE) -> 4 | K99: =VLOOKUP(A99,v_03_23!F:I,4,FALSE) -> 64.1 | L99: =H99-J99 -> -4 | M99: =I99-K99 -> -64.1 | N99: =M99/K99 -> -1
A100: B08FMLPKY9 | B100: P201UTP004 | C100: =VLOOKUP(A100,v_03_24!F:I,3,FALSE) -> 9 | D100: =VLOOKUP(A100,v_03_24!F:I,4,FALSE) -> 182.97 | E100: 0 | F100: 0 | G100: =F100/I100 -> 0 | H100: =C100+E100 -> 9 | I100: =D100+F100 -> 182.97 | J100: =VLOOKUP(A100,v_03_23!F:I,3,FALSE) -> 88 | K100: =VLOOKUP(A100,v_03_23!F:I,4,FALSE) -> 1595.46 | L100: =H100-J100 -> -79 | M100: =I100-K100 -> -1412.49 | N100: =M100/K100 -> -0.88531834
...

Sheet Complessivo
A1: ASIN | B1: SKU | C1: Ordini Vendor 24 | D1: Valori ordini Vendor 24 | E1: Ordini Seller | F1: Valori ordini Seller | G1: % seller / totale | H1: Ordini Complessivi | I1: Valori ordini Complessivi | J1: Ordini Vendor 23 | K1: Valori ordini Vendor 23 | L1: Differenza Ordini | M1: Differenza Valore | N1: Differenza Valore %
A2: B0050IHH4E | B2: 40.979 | C2: =VLOOKUP(A2,v_03_24!A:D,3,FALSE) -> 1183 | D2: =VLOOKUP(A2,v_03_24!A:D,4,FALSE) -> 16822.21 | E2: 0 | F2: 0 | G2: =F2/I2 -> 0 | H2: =C2+E2 -> 1183 | I2: =D2+F2 -> 16822.21 | J2: =VLOOKUP(A2,v_03_23!A:D,3,FALSE) -> 287 | K2: =VLOOKUP(A2,v_03_23!A:D,4,FALSE) -> 3732.24 | L2: =H2-J2 -> 896 | M2: =I2-K2 -> 13089.97 | N2: =M2/K2 -> 3.5072691
A3: B009O92WU4 | B3: 40.999 | C3: =VLOOKUP(A3,v_03_24!A:D,3,FALSE) -> 1 | D3: =VLOOKUP(A3,v_03_24!A:D,4,FALSE) -> 5.03 | E3: 0 | F3: 0 | G3: =F3/I3 -> 0 | H3: =C3+E3 -> 1 | I3: =D3+F3 -> 5.03 | J3: =VLOOKUP(A3,v_03_23!A:D,3,FALSE) -> 4 | K3: =VLOOKUP(A3,v_03_23!A:D,4,FALSE) -> 33.15 | L3: =H3-J3 -> -3 | M3: =I3-K3 -> -28.12 | N3: =M3/K3 -> -0.84826546
A4: B00BH202XK | B4: 40.808A | C4: =VLOOKUP(A4,v_03_24!A:D,3,FALSE) -> 10 | D4: =VLOOKUP(A4,v_03_24!A:D,4,FALSE) -> 127.35 | E4: 0 | F4: 0 | G4: =F4/I4 -> 0 | H4: =C4+E4 -> 10 | I4: =D4+F4 -> 127.35 | J4: 0 | K4: 0 | L4: =H4-J4 -> 10 | M4: =I4-K4 -> 127.35
A5: B00CMAD2FG | B5: HK-NV009W | C5: =VLOOKUP(A5,v_03_24!A:D,3,FALSE) -> 1 | D5: =VLOOKUP(A5,v_03_24!A:D,4,FALSE) -> 15.18 | E5: 0 | F5: 0 | G5: =F5/I5 -> 0 | H5: =C5+E5 -> 1 | I5: =D5+F5 -> 15.18 | J5: =VLOOKUP(A5,v_03_23!A:D,3,FALSE) -> 2 | K5: =VLOOKUP(A5,v_03_23!A:D,4,FALSE) -> 33.58 | L5: =H5-J5 -> -1 | M5: =I5-K5 -> -18.4 | N5: =M5/K5 -> -0.54794521
A6: B00FFBFVG2 | B6: 40.100 | C6: =VLOOKUP(A6,v_03_24!A:D,3,FALSE) -> 0 | D6: =VLOOKUP(A6,v_03_24!A:D,4,FALSE) -> 0 | E6: 0 | F6: 0 | H6: =C6+E6 -> 0 | I6: =D6+F6 -> 0 | J6: =VLOOKUP(A6,v_03_23!A:D,3,FALSE) -> 5 | K6: =VLOOKUP(A6,v_03_23!A:D,4,FALSE) -> 42.39 | L6: =H6-J6 -> -5 | M6: =I6-K6 -> -42.39 | N6: =M6/K6 -> -1
A7: B00L5GPWFG | B7: 40.120 | C7: =VLOOKUP(A7,v_03_24!A:D,3,FALSE) -> 6 | D7: =VLOOKUP(A7,v_03_24!A:D,4,FALSE) -> 147.9 | E7: 0 | F7: 0 | G7: =F7/I7 -> 0 | H7: =C7+E7 -> 6 | I7: =D7+F7 -> 147.9 | J7: =VLOOKUP(A7,v_03_23!A:D,3,FALSE) -> 4 | K7: =VLOOKUP(A7,v_03_23!A:D,4,FALSE) -> 95.58 | L7: =H7-J7 -> 2 | M7: =I7-K7 -> 52.32 | N7: =M7/K7 -> 0.54739485
A8: B00L5H5KUW | B8: 40.121 | C8: =VLOOKUP(A8,v_03_24!A:D,3,FALSE) -> 275 | D8: =VLOOKUP(A8,v_03_24!A:D,4,FALSE) -> 5023.29 | E8: 0 | F8: 0 | G8: =F8/I8 -> 0 | H8: =C8+E8 -> 275 | I8: =D8+F8 -> 5023.29 | J8: =VLOOKUP(A8,v_03_23!A:D,3,FALSE) -> 58 | K8: =VLOOKUP(A8,v_03_23!A:D,4,FALSE) -> 1197.15 | L8: =H8-J8 -> 217 | M8: =I8-K8 -> 3826.14 | N8: =M8/K8 -> 3.1960406
A9: B00NSNZSLM | B9: 90.602 | C9: =VLOOKUP(A9,v_03_24!A:D,3,FALSE) -> 1 | D9: =VLOOKUP(A9,v_03_24!A:D,4,FALSE) -> 20.41 | E9: =VLOOKUP(A9,s_03_24!A:C,2,FALSE) -> BT.603Y | F9: =VLOOKUP(A9,s_03_24!A:C,3,FALSE) -> 2 | G9: =F9/I9 -> 0.089245872 | H9: =C9+E9 -> #VALUE! | I9: =D9+F9 -> 22.41 | J9: =VLOOKUP(A9,v_03_23!A:D,3,FALSE) -> 503 | K9: =VLOOKUP(A9,v_03_23!A:D,4,FALSE) -> 10307.45 | L9: =H9-J9 -> #VALUE! | M9: =I9-K9 -> -10285.04 | N9: =M9/K9 -> -0.99782584
A10: B00YH3FRV8 | B10: 40.998 | C10: =VLOOKUP(A10,v_03_24!A:D,3,FALSE) -> 1 | D10: =VLOOKUP(A10,v_03_24!A:D,4,FALSE) -> 7.43 | E10: 0 | F10: 0 | G10: =F10/I10 -> 0 | H10: =C10+E10 -> 1 | I10: =D10+F10 -> 7.43 | J10: 0 | K10: 0 | L10: =H10-J10 -> 1 | M10: =I10-K10 -> 7.43
A11: B011LFM60E | B11: 40.948T | C11: =VLOOKUP(A11,v_03_24!A:D,3,FALSE) -> 2 | D11: =VLOOKUP(A11,v_03_24!A:D,4,FALSE) -> 12.96 | E11: 0 | F11: 0 | G11: =F11/I11 -> 0 | H11: =C11+E11 -> 2 | I11: =D11+F11 -> 12.96 | J11: =VLOOKUP(A11,v_03_23!A:D,3,FALSE) -> 2 | K11: =VLOOKUP(A11,v_03_23!A:D,4,FALSE) -> 7.53 | L11: =H11-J11 -> 0 | M11: =I11-K11 -> 5.43 | N11: =M11/K11 -> 0.72111554
A12: B011LFVLW8 | B12: 90.620 | C12: =VLOOKUP(A12,v_03_24!A:D,3,FALSE) -> 19 | D12: =VLOOKUP(A12,v_03_24!A:D,4,FALSE) -> 686.19 | E12: 0 | F12: 0 | G12: =F12/I12 -> 0 | H12: =C12+E12 -> 19 | I12: =D12+F12 -> 686.19 | J12: =VLOOKUP(A12,v_03_23!A:D,3,FALSE) -> 16 | K12: =VLOOKUP(A12,v_03_23!A:D,4,FALSE) -> 590.39 | L12: =H12-J12 -> 3 | M12: =I12-K12 -> 95.8 | N12: =M12/K12 -> 0.16226562
A13: B017IUJA50 | B13: 90.920G | C13: =VLOOKUP(A13,v_03_24!A:D,3,FALSE) -> 15 | D13: =VLOOKUP(A13,v_03_24!A:D,4,FALSE) -> 209.45 | E13: =VLOOKUP(A13,s_03_24!A:C,2,FALSE) -> 90.920G | F13: =VLOOKUP(A13,s_03_24!A:C,3,FALSE) -> 14 | G13: =F13/I13 -> 0.062653838 | H13: =C13+E13 -> #VALUE! | I13: =D13+F13 -> 223.45 | J13: =VLOOKUP(A13,v_03_23!A:D,3,FALSE) -> 448 | K13: =VLOOKUP(A13,v_03_23!A:D,4,FALSE) -> 6892.94 | L13: =H13-J13 -> #VALUE! | M13: =I13-K13 -> -6669.49 | N13: =M13/K13 -> -0.96758277
A14: B01CHW1L88 | B14: PE.001 | C14: =VLOOKUP(A14,v_03_24!A:D,3,FALSE) -> 1 | D14: =VLOOKUP(A14,v_03_24!A:D,4,FALSE) -> 15.05 | E14: 0 | F14: 0 | G14: =F14/I14 -> 0 | H14: =C14+E14 -> 1 | I14: =D14+F14 -> 15.05 | J14: 0 | K14: 0 | L14: =H14-J14 -> 1 | M14: =I14-K14 -> 15.05
A15: B01CNX6UIM | B15: PE.300 | C15: =VLOOKUP(A15,v_03_24!A:D,3,FALSE) -> 3 | D15: =VLOOKUP(A15,v_03_24!A:D,4,FALSE) -> 17.19 | E15: 0 | F15: 0 | G15: =F15/I15 -> 0 | H15: =C15+E15 -> 3 | I15: =D15+F15 -> 17.19 | J15: 0 | K15: 0 | L15: =H15-J15 -> 3 | M15: =I15-K15 -> 17.19
A16: B01CNX704K | B16: 90.825 | C16: =VLOOKUP(A16,v_03_24!A:D,3,FALSE) -> 1 | D16: =VLOOKUP(A16,v_03_24!A:D,4,FALSE) -> 22.97 | E16: =VLOOKUP(A16,s_03_24!A:C,2,FALSE) -> 90825 | F16: =VLOOKUP(A16,s_03_24!A:C,3,FALSE) -> 1 | G16: =F16/I16 -> 0.041718815 | H16: =C16+E16 -> 90826 | I16: =D16+F16 -> 23.97 | J16: =VLOOKUP(A16,v_03_23!A:D,3,FALSE) -> 8 | K16: =VLOOKUP(A16,v_03_23!A:D,4,FALSE) -> 317.23 | L16: =H16-J16 -> 90818 | M16: =I16-K16 -> -293.26 | N16: =M16/K16 -> -0.92443968
A17: B01CNX71NA | B17: 90.871 | C17: =VLOOKUP(A17,v_03_24!A:D,3,FALSE) -> 12 | D17: =VLOOKUP(A17,v_03_24!A:D,4,FALSE) -> 1075.69 | E17: 0 | F17: 0 | G17: =F17/I17 -> 0 | H17: =C17+E17 -> 12 | I17: =D17+F17 -> 1075.69 | J17: =VLOOKUP(A17,v_03_23!A:D,3,FALSE) -> 15 | K17: =VLOOKUP(A17,v_03_23!A:D,4,FALSE) -> 1218.42 | L17: =H17-J17 -> -3 | M17: =I17-K17 -> -142.73 | N17: =M17/K17 -> -0.11714351
A18: B01I497WWM | B18: 90.920R | C18: =VLOOKUP(A18,v_03_24!A:D,3,FALSE) -> 23 | D18: =VLOOKUP(A18,v_03_24!A:D,4,FALSE) -> 410.8 | E18: =VLOOKUP(A18,s_03_24!A:C,2,FALSE) -> 90.920R | F18: =VLOOKUP(A18,s_03_24!A:C,3,FALSE) -> 2 | G18: =F18/I18 -> 0.0048449612 | H18: =C18+E18 -> #VALUE! | I18: =D18+F18 -> 412.8 | J18: =VLOOKUP(A18,v_03_23!A:D,3,FALSE) -> 1369 | K18: =VLOOKUP(A18,v_03_23!A:D,4,FALSE) -> 19434.44 | L18: =H18-J18 -> #VALUE! | M18: =I18-K18 -> -19021.64 | N18: =M18/K18 -> -0.97875936
A19: B01II7S968 | B19: MD.217 | C19: =VLOOKUP(A19,v_03_24!A:D,3,FALSE) -> 6 | D19: =VLOOKUP(A19,v_03_24!A:D,4,FALSE) -> 36.93 | E19: 0 | F19: 0 | G19: =F19/I19 -> 0 | H19: =C19+E19 -> 6 | I19: =D19+F19 -> 36.93 | J19: =VLOOKUP(A19,v_03_23!A:D,3,FALSE) -> 5 | K19: =VLOOKUP(A19,v_03_23!A:D,4,FALSE) -> 28.78 | L19: =H19-J19 -> 1 | M19: =I19-K19 -> 8.15 | N19: =M19/K19 -> 0.28318277
A20: B01KMJ9OXW | B20: 90.590Y | C20: =VLOOKUP(A20,v_03_24!A:D,3,FALSE) -> 9 | D20: =VLOOKUP(A20,v_03_24!A:D,4,FALSE) -> 267.96 | E20: =VLOOKUP(A20,s_03_24!A:C,2,FALSE) -> 90.590Y | F20: =VLOOKUP(A20,s_03_24!A:C,3,FALSE) -> 2 | G20: =F20/I20 -> 0.007408505 | H20: =C20+E20 -> #VALUE! | I20: =D20+F20 -> 269.96 | J20: =VLOOKUP(A20,v_03_23!A:D,3,FALSE) -> 649 | K20: =VLOOKUP(A20,v_03_23!A:D,4,FALSE) -> 20773.87 | L20: =H20-J20 -> #VALUE! | M20: =I20-K20 -> -20503.91 | N20: =M20/K20 -> -0.98700483
A21: B06WGS8ZVG | B21: 90.131 | C21: =VLOOKUP(A21,v_03_24!A:D,3,FALSE) -> 2 | D21: =VLOOKUP(A21,v_03_24!A:D,4,FALSE) -> 27.28 | E21: 0 | F21: 0 | G21: =F21/I21 -> 0 | H21: =C21+E21 -> 2 | I21: =D21+F21 -> 27.28 | J21: =VLOOKUP(A21,v_03_23!A:D,3,FALSE) -> 11 | K21: =VLOOKUP(A21,v_03_23!A:D,4,FALSE) -> 126.91 | L21: =H21-J21 -> -9 | M21: =I21-K21 -> -99.63 | N21: =M21/K21 -> -0.78504452
A22: B06XPK3BTC | B22: 40.450GO | C22: =VLOOKUP(A22,v_03_24!A:D,3,FALSE) -> 4 | D22: =VLOOKUP(A22,v_03_24!A:D,4,FALSE) -> 51.29 | E22: 0 | F22: 0 | G22: =F22/I22 -> 0 | H22: =C22+E22 -> 4 | I22: =D22+F22 -> 51.29 | J22: =VLOOKUP(A22,v_03_23!A:D,3,FALSE) -> 7 | K22: =VLOOKUP(A22,v_03_23!A:D,4,FALSE) -> 105 | L22: =H22-J22 -> -3 | M22: =I22-K22 -> -53.71 | N22: =M22/K22 -> -0.51152381
A23: B06XYMCV3W | B23: 90.485H | C23: =VLOOKUP(A23,v_03_24!A:D,3,FALSE) -> 0 | D23: =VLOOKUP(A23,v_03_24!A:D,4,FALSE) -> 0 | E23: 0 | F23: 0 | H23: =C23+E23 -> 0 | I23: =D23+F23 -> 0 | J23: 0 | K23: 0 | L23: =H23-J23 -> 0 | M23: =I23-K23 -> 0
A24: B06Y17FS6D | B24: 90.550 | C24: =VLOOKUP(A24,v_03_24!A:D,3,FALSE) -> 49 | D24: =VLOOKUP(A24,v_03_24!A:D,4,FALSE) -> 1395.95 | E24: =VLOOKUP(A24,s_03_24!A:C,2,FALSE) -> 90550 | F24: =VLOOKUP(A24,s_03_24!A:C,3,FALSE) -> 1 | G24: =F24/I24 -> 0.00071584523 | H24: =C24+E24 -> 90599 | I24: =D24+F24 -> 1396.95 | J24: =VLOOKUP(A24,v_03_23!A:D,3,FALSE) -> 83 | K24: =VLOOKUP(A24,v_03_23!A:D,4,FALSE) -> 2525.98 | L24: =H24-J24 -> 90516 | M24: =I24-K24 -> -1129.03 | N24: =M24/K24 -> -0.44696712
A25: B06Y195DJN | B25: 90.882 | C25: =VLOOKUP(A25,v_03_24!A:D,3,FALSE) -> 1 | D25: =VLOOKUP(A25,v_03_24!A:D,4,FALSE) -> 31.06 | E25: =VLOOKUP(A25,s_03_24!A:C,2,FALSE) -> 90882 | F25: =VLOOKUP(A25,s_03_24!A:C,3,FALSE) -> 2 | G25: =F25/I25 -> 0.060496068 | H25: =C25+E25 -> 90883 | I25: =D25+F25 -> 33.06 | J25: =VLOOKUP(A25,v_03_23!A:D,3,FALSE) -> 87 | K25: =VLOOKUP(A25,v_03_23!A:D,4,FALSE) -> 3702.45 | L25: =H25-J25 -> 90796 | M25: =I25-K25 -> -3669.39 | N25: =M25/K25 -> -0.99107078
A26: B073B67PLQ | B26: 90.884 | C26: =VLOOKUP(A26,v_03_24!A:D,3,FALSE) -> 25 | D26: =VLOOKUP(A26,v_03_24!A:D,4,FALSE) -> 1858.24 | E26: 0 | F26: 0 | G26: =F26/I26 -> 0 | H26: =C26+E26 -> 25 | I26: =D26+F26 -> 1858.24 | J26: =VLOOKUP(A26,v_03_23!A:D,3,FALSE) -> 171 | K26: =VLOOKUP(A26,v_03_23!A:D,4,FALSE) -> 11876.9 | L26: =H26-J26 -> -146 | M26: =I26-K26 -> -10018.66 | N26: =M26/K26 -> -0.84354166
A27: B075K5C2QG | B27: RI.201 | C27: =VLOOKUP(A27,v_03_24!A:D,3,FALSE) -> 2 | D27: =VLOOKUP(A27,v_03_24!A:D,4,FALSE) -> 40.82 | E27: 0 | F27: 0 | G27: =F27/I27 -> 0 | H27: =C27+E27 -> 2 | I27: =D27+F27 -> 40.82 | J27: =VLOOKUP(A27,v_03_23!A:D,3,FALSE) -> -2 | K27: =VLOOKUP(A27,v_03_23!A:D,4,FALSE) -> -33.5 | L27: =H27-J27 -> 4 | M27: =I27-K27 -> 74.32 | N27: =M27/K27 -> -2.2185075
A28: B075RF5S3N | B28: BC.160A | C28: =VLOOKUP(A28,v_03_24!A:D,3,FALSE) -> 5 | D28: =VLOOKUP(A28,v_03_24!A:D,4,FALSE) -> 129.21 | E28: 0 | F28: 0 | G28: =F28/I28 -> 0 | H28: =C28+E28 -> 5 | I28: =D28+F28 -> 129.21 | J28: =VLOOKUP(A28,v_03_23!A:D,3,FALSE) -> 20 | K28: =VLOOKUP(A28,v_03_23!A:D,4,FALSE) -> 410.88 | L28: =H28-J28 -> -15 | M28: =I28-K28 -> -281.67 | N28: =M28/K28 -> -0.68552862
A29: B075RF8FM9 | B29: BC.160G | C29: =VLOOKUP(A29,v_03_24!A:D,3,FALSE) -> 0 | D29: =VLOOKUP(A29,v_03_24!A:D,4,FALSE) -> 0 | E29: 0 | F29: 0 | H29: =C29+E29 -> 0 | I29: =D29+F29 -> 0 | J29: =VLOOKUP(A29,v_03_23!A:D,3,FALSE) -> 0 | K29: =VLOOKUP(A29,v_03_23!A:D,4,FALSE) -> 0 | L29: =H29-J29 -> 0 | M29: =I29-K29 -> 0
A30: B075XR3T8V | B30: BT.600Y | C30: =VLOOKUP(A30,v_03_24!A:D,3,FALSE) -> 7 | D30: =VLOOKUP(A30,v_03_24!A:D,4,FALSE) -> 257.01 | E30: 0 | F30: 0 | G30: =F30/I30 -> 0 | H30: =C30+E30 -> 7 | I30: =D30+F30 -> 257.01 | J30: =VLOOKUP(A30,v_03_23!A:D,3,FALSE) -> 10 | K30: =VLOOKUP(A30,v_03_23!A:D,4,FALSE) -> 298.17 | L30: =H30-J30 -> -3 | M30: =I30-K30 -> -41.16 | N30: =M30/K30 -> -0.13804206
A31: B076D74TC7 | B31: BT.700Y | C31: =VLOOKUP(A31,v_03_24!A:D,3,FALSE) -> 4 | D31: =VLOOKUP(A31,v_03_24!A:D,4,FALSE) -> 156.28 | E31: =VLOOKUP(A31,s_03_24!A:C,2,FALSE) -> BT.700Y_FBA | F31: =VLOOKUP(A31,s_03_24!A:C,3,FALSE) -> 6 | G31: =F31/I31 -> 0.036973133 | H31: =C31+E31 -> #VALUE! | I31: =D31+F31 -> 162.28 | J31: =VLOOKUP(A31,v_03_23!A:D,3,FALSE) -> 3 | K31: =VLOOKUP(A31,v_03_23!A:D,4,FALSE) -> 91.12 | L31: =H31-J31 -> #VALUE! | M31: =I31-K31 -> 71.16 | N31: =M31/K31 -> 0.7809482
A32: B076DC4VWG | B32: 40.501 | C32: =VLOOKUP(A32,v_03_24!A:D,3,FALSE) -> 6 | D32: =VLOOKUP(A32,v_03_24!A:D,4,FALSE) -> 150.78 | E32: 0 | F32: 0 | G32: =F32/I32 -> 0 | H32: =C32+E32 -> 6 | I32: =D32+F32 -> 150.78 | J32: =VLOOKUP(A32,v_03_23!A:D,3,FALSE) -> 8 | K32: =VLOOKUP(A32,v_03_23!A:D,4,FALSE) -> 170.93 | L32: =H32-J32 -> -2 | M32: =I32-K32 -> -20.15 | N32: =M32/K32 -> -0.11788451
A33: B076DCL19C | B33: BP.720 | C33: =VLOOKUP(A33,v_03_24!A:D,3,FALSE) -> 19 | D33: =VLOOKUP(A33,v_03_24!A:D,4,FALSE) -> 922.48 | E33: 0 | F33: 0 | G33: =F33/I33 -> 0 | H33: =C33+E33 -> 19 | I33: =D33+F33 -> 922.48 | J33: =VLOOKUP(A33,v_03_23!A:D,3,FALSE) -> 30 | K33: =VLOOKUP(A33,v_03_23!A:D,4,FALSE) -> 1776.28 | L33: =H33-J33 -> -11 | M33: =I33-K33 -> -853.8 | N33: =M33/K33 -> -0.48066746
A34: B076DCX3JH | B34: BB.103 | C34: =VLOOKUP(A34,v_03_24!A:D,3,FALSE) -> 1 | D34: =VLOOKUP(A34,v_03_24!A:D,4,FALSE) -> 19.59 | E34: 0 | F34: 0 | G34: =F34/I34 -> 0 | H34: =C34+E34 -> 1 | I34: =D34+F34 -> 19.59 | J34: =VLOOKUP(A34,v_03_23!A:D,3,FALSE) -> 0 | K34: =VLOOKUP(A34,v_03_23!A:D,4,FALSE) -> 0 | L34: =H34-J34 -> 1 | M34: =I34-K34 -> 19.59
A35: B076QCMZX1 | B35: 40.821 | C35: =VLOOKUP(A35,v_03_24!A:D,3,FALSE) -> 170 | D35: =VLOOKUP(A35,v_03_24!A:D,4,FALSE) -> 2082.7 | E35: 0 | F35: 0 | G35: =F35/I35 -> 0 | H35: =C35+E35 -> 170 | I35: =D35+F35 -> 2082.7 | J35: =VLOOKUP(A35,v_03_23!A:D,3,FALSE) -> 107 | K35: =VLOOKUP(A35,v_03_23!A:D,4,FALSE) -> 956.31 | L35: =H35-J35 -> 63 | M35: =I35-K35 -> 1126.39 | N35: =M35/K35 -> 1.1778503
A36: B076QFRRZ5 | B36: 40.931 | C36: =VLOOKUP(A36,v_03_24!A:D,3,FALSE) -> 52 | D36: =VLOOKUP(A36,v_03_24!A:D,4,FALSE) -> 763.71 | E36: 0 | F36: 0 | G36: =F36/I36 -> 0 | H36: =C36+E36 -> 52 | I36: =D36+F36 -> 763.71 | J36: =VLOOKUP(A36,v_03_23!A:D,3,FALSE) -> 198 | K36: =VLOOKUP(A36,v_03_23!A:D,4,FALSE) -> 2743.69 | L36: =H36-J36 -> -146 | M36: =I36-K36 -> -1979.98 | N36: =M36/K36 -> -0.72164858
A37: B079SB5VJZ | B37: 50451 | C37: =VLOOKUP(A37,v_03_24!A:D,3,FALSE) -> 7 | D37: =VLOOKUP(A37,v_03_24!A:D,4,FALSE) -> 325.84 | E37: 0 | F37: 0 | G37: =F37/I37 -> 0 | H37: =C37+E37 -> 7 | I37: =D37+F37 -> 325.84 | J37: =VLOOKUP(A37,v_03_23!A:D,3,FALSE) -> 268 | K37: =VLOOKUP(A37,v_03_23!A:D,4,FALSE) -> 8898.39 | L37: =H37-J37 -> -261 | M37: =I37-K37 -> -8572.55 | N37: =M37/K37 -> -0.96338214
A38: B07B9CBD91 | B38: VE.550 | C38: =VLOOKUP(A38,v_03_24!A:D,3,FALSE) -> 1 | D38: =VLOOKUP(A38,v_03_24!A:D,4,FALSE) -> 117.41 | E38: 0 | F38: 0 | G38: =F38/I38 -> 0 | H38: =C38+E38 -> 1 | I38: =D38+F38 -> 117.41 | J38: 0 | K38: 0 | L38: =H38-J38 -> 1 | M38: =I38-K38 -> 117.41
A39: B07B9CPH62 | B39: BG.200Y | C39: =VLOOKUP(A39,v_03_24!A:D,3,FALSE) -> 46 | D39: =VLOOKUP(A39,v_03_24!A:D,4,FALSE) -> 2537.23 | E39: 0 | F39: 0 | G39: =F39/I39 -> 0 | H39: =C39+E39 -> 46 | I39: =D39+F39 -> 2537.23 | J39: =VLOOKUP(A39,v_03_23!A:D,3,FALSE) -> 36 | K39: =VLOOKUP(A39,v_03_23!A:D,4,FALSE) -> 1791.27 | L39: =H39-J39 -> 10 | M39: =I39-K39 -> 745.96 | N39: =M39/K39 -> 0.41644197
A40: B07BHCZR84 | B40: BA.200Y | C40: =VLOOKUP(A40,v_03_24!A:D,3,FALSE) -> 32 | D40: =VLOOKUP(A40,v_03_24!A:D,4,FALSE) -> 372.1 | E40: =VLOOKUP(A40,s_03_24!A:C,2,FALSE) -> BA.200Y | F40: =VLOOKUP(A40,s_03_24!A:C,3,FALSE) -> 1 | G40: =F40/I40 -> 0.0026802466 | H40: =C40+E40 -> #VALUE! | I40: =D40+F40 -> 373.1 | J40: =VLOOKUP(A40,v_03_23!A:D,3,FALSE) -> 56 | K40: =VLOOKUP(A40,v_03_23!A:D,4,FALSE) -> 569.06 | L40: =H40-J40 -> #VALUE! | M40: =I40-K40 -> -195.96 | N40: =M40/K40 -> -0.34435736
A41: B07BHTW4WV | B41: VE.210 | C41: =VLOOKUP(A41,v_03_24!A:D,3,FALSE) -> 0 | D41: =VLOOKUP(A41,v_03_24!A:D,4,FALSE) -> 0 | E41: 0 | F41: 0 | H41: =C41+E41 -> 0 | I41: =D41+F41 -> 0 | J41: 0 | K41: 0 | L41: =H41-J41 -> 0 | M41: =I41-K41 -> 0
A42: B07CZ4WMB8 | B42: 40.330 | C42: =VLOOKUP(A42,v_03_24!A:D,3,FALSE) -> 9 | D42: =VLOOKUP(A42,v_03_24!A:D,4,FALSE) -> 206.62 | E42: 0 | F42: 0 | G42: =F42/I42 -> 0 | H42: =C42+E42 -> 9 | I42: =D42+F42 -> 206.62 | J42: =VLOOKUP(A42,v_03_23!A:D,3,FALSE) -> 1 | K42: =VLOOKUP(A42,v_03_23!A:D,4,FALSE) -> 20.75 | L42: =H42-J42 -> 8 | M42: =I42-K42 -> 185.87 | N42: =M42/K42 -> 8.9575904
A43: B07F187NFQ | B43: 50.900 | C43: =VLOOKUP(A43,v_03_24!A:D,3,FALSE) -> 3 | D43: =VLOOKUP(A43,v_03_24!A:D,4,FALSE) -> 14.35 | E43: 0 | F43: 0 | G43: =F43/I43 -> 0 | H43: =C43+E43 -> 3 | I43: =D43+F43 -> 14.35 | J43: =VLOOKUP(A43,v_03_23!A:D,3,FALSE) -> 3 | K43: =VLOOKUP(A43,v_03_23!A:D,4,FALSE) -> 13.57 | L43: =H43-J43 -> 0 | M43: =I43-K43 -> 0.78 | N43: =M43/K43 -> 0.057479735
A44: B07FN14FSN | B44: 50.160 | C44: =VLOOKUP(A44,v_03_24!A:D,3,FALSE) -> 1 | D44: =VLOOKUP(A44,v_03_24!A:D,4,FALSE) -> 29.03 | E44: 0 | F44: 0 | G44: =F44/I44 -> 0 | H44: =C44+E44 -> 1 | I44: =D44+F44 -> 29.03 | J44: =VLOOKUP(A44,v_03_23!A:D,3,FALSE) -> 1 | K44: =VLOOKUP(A44,v_03_23!A:D,4,FALSE) -> 33.5 | L44: =H44-J44 -> 0 | M44: =I44-K44 -> -4.47 | N44: =M44/K44 -> -0.13343284
A45: B07HFPYL56 | B45: BC.353 | C45: =VLOOKUP(A45,v_03_24!A:D,3,FALSE) -> 1 | D45: =VLOOKUP(A45,v_03_24!A:D,4,FALSE) -> 55.62 | E45: 0 | F45: 0 | G45: =F45/I45 -> 0 | H45: =C45+E45 -> 1 | I45: =D45+F45 -> 55.62 | J45: 0 | K45: 0 | L45: =H45-J45 -> 1 | M45: =I45-K45 -> 55.62
A46: B07HFQH172 | B46: BC.250 | C46: =VLOOKUP(A46,v_03_24!A:D,3,FALSE) -> 1 | D46: =VLOOKUP(A46,v_03_24!A:D,4,FALSE) -> 41.58 | E46: 0 | F46: 0 | G46: =F46/I46 -> 0 | H46: =C46+E46 -> 1 | I46: =D46+F46 -> 41.58 | J46: =VLOOKUP(A46,v_03_23!A:D,3,FALSE) -> 5 | K46: =VLOOKUP(A46,v_03_23!A:D,4,FALSE) -> 187.72 | L46: =H46-J46 -> -4 | M46: =I46-K46 -> -146.14 | N46: =M46/K46 -> -0.77849989
A47: B07HHDSJHM | B47: BI.504 | C47: =VLOOKUP(A47,v_03_24!A:D,3,FALSE) -> 0 | D47: =VLOOKUP(A47,v_03_24!A:D,4,FALSE) -> 0 | E47: 0 | F47: 0 | H47: =C47+E47 -> 0 | I47: =D47+F47 -> 0 | J47: =VLOOKUP(A47,v_03_23!A:D,3,FALSE) -> 23 | K47: =VLOOKUP(A47,v_03_23!A:D,4,FALSE) -> 137.26 | L47: =H47-J47 -> -23 | M47: =I47-K47 -> -137.26 | N47: =M47/K47 -> -1
A48: B07HM7P6MP | B48: RI.080 | C48: =VLOOKUP(A48,v_03_24!A:D,3,FALSE) -> 10 | D48: =VLOOKUP(A48,v_03_24!A:D,4,FALSE) -> 253.92 | E48: =VLOOKUP(A48,s_03_24!A:C,2,FALSE) -> RI.080 | F48: =VLOOKUP(A48,s_03_24!A:C,3,FALSE) -> 2 | G48: =F48/I48 -> 0.0078149422 | H48: =C48+E48 -> #VALUE! | I48: =D48+F48 -> 255.92 | J48: =VLOOKUP(A48,v_03_23!A:D,3,FALSE) -> 114 | K48: =VLOOKUP(A48,v_03_23!A:D,4,FALSE) -> 2484.12 | L48: =H48-J48 -> #VALUE! | M48: =I48-K48 -> -2228.2 | N48: =M48/K48 -> -0.8969776
A49: B07MC8ZVRM | B49: 40.452 | C49: =VLOOKUP(A49,v_03_24!A:D,3,FALSE) -> 8 | D49: =VLOOKUP(A49,v_03_24!A:D,4,FALSE) -> 196.7 | E49: 0 | F49: 0 | G49: =F49/I49 -> 0 | H49: =C49+E49 -> 8 | I49: =D49+F49 -> 196.7 | J49: 0 | K49: 0 | L49: =H49-J49 -> 8 | M49: =I49-K49 -> 196.7
A50: B07NNZSW1W | B50: BT.110 | C50: =VLOOKUP(A50,v_03_24!A:D,3,FALSE) -> 4 | D50: =VLOOKUP(A50,v_03_24!A:D,4,FALSE) -> 64.51 | E50: 0 | F50: 0 | G50: =F50/I50 -> 0 | H50: =C50+E50 -> 4 | I50: =D50+F50 -> 64.51 | J50: =VLOOKUP(A50,v_03_23!A:D,3,FALSE) -> 1 | K50: =VLOOKUP(A50,v_03_23!A:D,4,FALSE) -> 23.02 | L50: =H50-J50 -> 3 | M50: =I50-K50 -> 41.49 | N50: =M50/K50 -> 1.8023458
A51: B07NP6YY5W | B51: BP.200 | C51: =VLOOKUP(A51,v_03_24!A:D,3,FALSE) -> 1 | D51: =VLOOKUP(A51,v_03_24!A:D,4,FALSE) -> 91.6 | E51: 0 | F51: 0 | G51: =F51/I51 -> 0 | H51: =C51+E51 -> 1 | I51: =D51+F51 -> 91.6 | J51: =VLOOKUP(A51,v_03_23!A:D,3,FALSE) -> 1 | K51: =VLOOKUP(A51,v_03_23!A:D,4,FALSE) -> 74.92 | L51: =H51-J51 -> 0 | M51: =I51-K51 -> 16.68 | N51: =M51/K51 -> 0.22263748
A52: B07NQ1T7YK | B52: BP.101H | C52: =VLOOKUP(A52,v_03_24!A:D,3,FALSE) -> 203 | D52: =VLOOKUP(A52,v_03_24!A:D,4,FALSE) -> 2645.87 | E52: 0 | F52: 0 | G52: =F52/I52 -> 0 | H52: =C52+E52 -> 203 | I52: =D52+F52 -> 2645.87 | J52: =VLOOKUP(A52,v_03_23!A:D,3,FALSE) -> 234 | K52: =VLOOKUP(A52,v_03_23!A:D,4,FALSE) -> 2906.02 | L52: =H52-J52 -> -31 | M52: =I52-K52 -> -260.15 | N52: =M52/K52 -> -0.089521063
A53: B07P7L18T9 | B53: 40.102 | C53: =VLOOKUP(A53,v_03_24!A:D,3,FALSE) -> 1 | D53: =VLOOKUP(A53,v_03_24!A:D,4,FALSE) -> 13.81 | E53: 0 | F53: 0 | G53: =F53/I53 -> 0 | H53: =C53+E53 -> 1 | I53: =D53+F53 -> 13.81 | J53: =VLOOKUP(A53,v_03_23!A:D,3,FALSE) -> 1 | K53: =VLOOKUP(A53,v_03_23!A:D,4,FALSE) -> 15.85 | L53: =H53-J53 -> 0 | M53: =I53-K53 -> -2.04 | N53: =M53/K53 -> -0.12870662
A54: B07PCQJ1P8 | B54: BT.410 | C54: =VLOOKUP(A54,v_03_24!A:D,3,FALSE) -> 1 | D54: =VLOOKUP(A54,v_03_24!A:D,4,FALSE) -> 33.25 | E54: 0 | F54: 0 | G54: =F54/I54 -> 0 | H54: =C54+E54 -> 1 | I54: =D54+F54 -> 33.25 | J54: 0 | K54: 0 | L54: =H54-J54 -> 1 | M54: =I54-K54 -> 33.25
A55: B07PTQPT16 | B55: BF.570 | C55: =VLOOKUP(A55,v_03_24!A:D,3,FALSE) -> 1 | D55: =VLOOKUP(A55,v_03_24!A:D,4,FALSE) -> 54.9 | E55: 0 | F55: 0 | G55: =F55/I55 -> 0 | H55: =C55+E55 -> 1 | I55: =D55+F55 -> 54.9 | J55: =VLOOKUP(A55,v_03_23!A:D,3,FALSE) -> 2 | K55: =VLOOKUP(A55,v_03_23!A:D,4,FALSE) -> 115.25 | L55: =H55-J55 -> -1 | M55: =I55-K55 -> -60.35 | N55: =M55/K55 -> -0.52364425
A56: B07QX1RJRH | B56: 40.742 | C56: =VLOOKUP(A56,v_03_24!A:D,3,FALSE) -> 3 | D56: =VLOOKUP(A56,v_03_24!A:D,4,FALSE) -> 72.88 | E56: 0 | F56: 0 | G56: =F56/I56 -> 0 | H56: =C56+E56 -> 3 | I56: =D56+F56 -> 72.88 | J56: =VLOOKUP(A56,v_03_23!A:D,3,FALSE) -> 4 | K56: =VLOOKUP(A56,v_03_23!A:D,4,FALSE) -> 71.6 | L56: =H56-J56 -> -1 | M56: =I56-K56 -> 1.28 | N56: =M56/K56 -> 0.017877095
A57: B07QZ89PLH | B57: 40.403 | C57: =VLOOKUP(A57,v_03_24!A:D,3,FALSE) -> 1 | D57: =VLOOKUP(A57,v_03_24!A:D,4,FALSE) -> 17.07 | E57: 0 | F57: 0 | G57: =F57/I57 -> 0 | H57: =C57+E57 -> 1 | I57: =D57+F57 -> 17.07 | J57: 0 | K57: 0 | L57: =H57-J57 -> 1 | M57: =I57-K57 -> 17.07
A58: B07TQVD94L | B58: BP.690 | C58: =VLOOKUP(A58,v_03_24!A:D,3,FALSE) -> 8 | D58: =VLOOKUP(A58,v_03_24!A:D,4,FALSE) -> 198.65 | E58: =VLOOKUP(A58,s_03_24!A:C,2,FALSE) -> BP.690_FBA | F58: =VLOOKUP(A58,s_03_24!A:C,3,FALSE) -> 26 | G58: =F58/I58 -> 0.11573559 | H58: =C58+E58 -> #VALUE! | I58: =D58+F58 -> 224.65 | J58: =VLOOKUP(A58,v_03_23!A:D,3,FALSE) -> 113 | K58: =VLOOKUP(A58,v_03_23!A:D,4,FALSE) -> 2781.97 | L58: =H58-J58 -> #VALUE! | M58: =I58-K58 -> -2557.32 | N58: =M58/K58 -> -0.91924787
A59: B07TSNB5WG | B59: BP.102 | C59: =VLOOKUP(A59,v_03_24!A:D,3,FALSE) -> 0 | D59: =VLOOKUP(A59,v_03_24!A:D,4,FALSE) -> 0 | E59: 0 | F59: 0 | H59: =C59+E59 -> 0 | I59: =D59+F59 -> 0 | J59: =VLOOKUP(A59,v_03_23!A:D,3,FALSE) -> 672 | K59: =VLOOKUP(A59,v_03_23!A:D,4,FALSE) -> 8325.42 | L59: =H59-J59 -> -672 | M59: =I59-K59 -> -8325.42 | N59: =M59/K59 -> -1
A60: B07V131F5W | B60: 40.490 | C60: =VLOOKUP(A60,v_03_24!A:D,3,FALSE) -> 172 | D60: =VLOOKUP(A60,v_03_24!A:D,4,FALSE) -> 4167.01 | E60: =VLOOKUP(A60,s_03_24!A:C,2,FALSE) -> 40490 | F60: =VLOOKUP(A60,s_03_24!A:C,3,FALSE) -> 63 | G60: =F60/I60 -> 0.014893582 | H60: =C60+E60 -> 40662 | I60: =D60+F60 -> 4230.01 | J60: =VLOOKUP(A60,v_03_23!A:D,3,FALSE) -> 449 | K60: =VLOOKUP(A60,v_03_23!A:D,4,FALSE) -> 10497.8 | L60: =H60-J60 -> 40213 | M60: =I60-K60 -> -6267.79 | N60: =M60/K60 -> -0.59705748
A61: B07XVWXVK1 | B61: RI.503 | C61: =VLOOKUP(A61,v_03_24!A:D,3,FALSE) -> 1 | D61: =VLOOKUP(A61,v_03_24!A:D,4,FALSE) -> 157.5 | E61: 0 | F61: 0 | G61: =F61/I61 -> 0 | H61: =C61+E61 -> 1 | I61: =D61+F61 -> 157.5 | J61: =VLOOKUP(A61,v_03_23!A:D,3,FALSE) -> 0 | K61: =VLOOKUP(A61,v_03_23!A:D,4,FALSE) -> 0 | L61: =H61-J61 -> 1 | M61: =I61-K61 -> 157.5
A62: B07YBFRMM7 | B62: BB.210 | C62: =VLOOKUP(A62,v_03_24!A:D,3,FALSE) -> 0 | D62: =VLOOKUP(A62,v_03_24!A:D,4,FALSE) -> 0 | E62: 0 | F62: 0 | H62: =C62+E62 -> 0 | I62: =D62+F62 -> 0 | J62: 0 | K62: 0 | L62: =H62-J62 -> 0 | M62: =I62-K62 -> 0
A63: B07YBNB2QY | B63: 50161 | C63: =VLOOKUP(A63,v_03_24!A:D,3,FALSE) -> 9 | D63: =VLOOKUP(A63,v_03_24!A:D,4,FALSE) -> 384.04 | E63: 0 | F63: 0 | G63: =F63/I63 -> 0 | H63: =C63+E63 -> 9 | I63: =D63+F63 -> 384.04 | J63: =VLOOKUP(A63,v_03_23!A:D,3,FALSE) -> 58 | K63: =VLOOKUP(A63,v_03_23!A:D,4,FALSE) -> 2421.78 | L63: =H63-J63 -> -49 | M63: =I63-K63 -> -2037.74 | N63: =M63/K63 -> -0.84142242
A64: B07YBNPZPJ | B64: BP.552 | C64: =VLOOKUP(A64,v_03_24!A:D,3,FALSE) -> 6 | D64: =VLOOKUP(A64,v_03_24!A:D,4,FALSE) -> 165.58 | E64: 0 | F64: 0 | G64: =F64/I64 -> 0 | H64: =C64+E64 -> 6 | I64: =D64+F64 -> 165.58 | J64: =VLOOKUP(A64,v_03_23!A:D,3,FALSE) -> 46 | K64: =VLOOKUP(A64,v_03_23!A:D,4,FALSE) -> 1036.73 | L64: =H64-J64 -> -40 | M64: =I64-K64 -> -871.15 | N64: =M64/K64 -> -0.84028628
A65: B07ZJMFB3R | B65: BC.510 | C65: =VLOOKUP(A65,v_03_24!A:D,3,FALSE) -> 41 | D65: =VLOOKUP(A65,v_03_24!A:D,4,FALSE) -> 2246.32 | E65: 0 | F65: 0 | G65: =F65/I65 -> 0 | H65: =C65+E65 -> 41 | I65: =D65+F65 -> 2246.32 | J65: =VLOOKUP(A65,v_03_23!A:D,3,FALSE) -> 36 | K65: =VLOOKUP(A65,v_03_23!A:D,4,FALSE) -> 2029.2 | L65: =H65-J65 -> 5 | M65: =I65-K65 -> 217.12 | N65: =M65/K65 -> 0.10699783
A66: B07ZJQTGG8 | B66: 50.245 | C66: =VLOOKUP(A66,v_03_24!A:D,3,FALSE) -> 120 | D66: =VLOOKUP(A66,v_03_24!A:D,4,FALSE) -> 1506.88 | E66: =VLOOKUP(A66,s_03_24!A:C,2,FALSE) -> 50245 | F66: =VLOOKUP(A66,s_03_24!A:C,3,FALSE) -> 0 | G66: =F66/I66 -> 0 | H66: =C66+E66 -> 50365 | I66: =D66+F66 -> 1506.88 | J66: =VLOOKUP(A66,v_03_23!A:D,3,FALSE) -> 2597 | K66: =VLOOKUP(A66,v_03_23!A:D,4,FALSE) -> 31902.6 | L66: =H66-J66 -> 47768 | M66: =I66-K66 -> -30395.72 | N66: =M66/K66 -> -0.95276623
A67: B0823CVGHX | B67: BP.400 | C67: =VLOOKUP(A67,v_03_24!A:D,3,FALSE) -> 0 | D67: =VLOOKUP(A67,v_03_24!A:D,4,FALSE) -> 0 | E67: =VLOOKUP(A67,s_03_24!A:C,2,FALSE) -> BP.400 | F67: =VLOOKUP(A67,s_03_24!A:C,3,FALSE) -> 3 | G67: =F67/I67 -> 1 | H67: =C67+E67 -> #VALUE! | I67: =D67+F67 -> 3 | J67: =VLOOKUP(A67,v_03_23!A:D,3,FALSE) -> 76 | K67: =VLOOKUP(A67,v_03_23!A:D,4,FALSE) -> 4126.62 | L67: =H67-J67 -> #VALUE! | M67: =I67-K67 -> -4123.62 | N67: =M67/K67 -> -0.99927301
A68: B08485QRVZ | B68: BC.261 | C68: =VLOOKUP(A68,v_03_24!A:D,3,FALSE) -> 1 | D68: =VLOOKUP(A68,v_03_24!A:D,4,FALSE) -> 24.88 | E68: =VLOOKUP(A68,s_03_24!A:C,2,FALSE) -> BC.261 | F68: =VLOOKUP(A68,s_03_24!A:C,3,FALSE) -> 4 | G68: =F68/I68 -> 0.13850416 | H68: =C68+E68 -> #VALUE! | I68: =D68+F68 -> 28.88 | J68: =VLOOKUP(A68,v_03_23!A:D,3,FALSE) -> 477 | K68: =VLOOKUP(A68,v_03_23!A:D,4,FALSE) -> 10184.49 | L68: =H68-J68 -> #VALUE! | M68: =I68-K68 -> -10155.61 | N68: =M68/K68 -> -0.99716432
A69: B084C3JTC2 | B69: 40.406 | C69: =VLOOKUP(A69,v_03_24!A:D,3,FALSE) -> 30 | D69: =VLOOKUP(A69,v_03_24!A:D,4,FALSE) -> 726.79 | E69: 0 | F69: 0 | G69: =F69/I69 -> 0 | H69: =C69+E69 -> 30 | I69: =D69+F69 -> 726.79 | J69: =VLOOKUP(A69,v_03_23!A:D,3,FALSE) -> 126 | K69: =VLOOKUP(A69,v_03_23!A:D,4,FALSE) -> 3095.05 | L69: =H69-J69 -> -96 | M69: =I69-K69 -> -2368.26 | N69: =M69/K69 -> -0.76517665
A70: B084PN7WPZ | B70: XUADA001 | C70: =VLOOKUP(A70,v_03_24!A:D,3,FALSE) -> 6 | D70: =VLOOKUP(A70,v_03_24!A:D,4,FALSE) -> 31 | E70: 0 | F70: 0 | G70: =F70/I70 -> 0 | H70: =C70+E70 -> 6 | I70: =D70+F70 -> 31 | J70: =VLOOKUP(A70,v_03_23!A:D,3,FALSE) -> 2 | K70: =VLOOKUP(A70,v_03_23!A:D,4,FALSE) -> 13.18 | L70: =H70-J70 -> 4 | M70: =I70-K70 -> 17.82 | N70: =M70/K70 -> 1.3520486
A71: B084TG23R3 | B71: C102BOT001 | C71: =VLOOKUP(A71,v_03_24!A:D,3,FALSE) -> 1 | D71: =VLOOKUP(A71,v_03_24!A:D,4,FALSE) -> 7.62 | E71: 0 | F71: 0 | G71: =F71/I71 -> 0 | H71: =C71+E71 -> 1 | I71: =D71+F71 -> 7.62 | J71: =VLOOKUP(A71,v_03_23!A:D,3,FALSE) -> 153 | K71: =VLOOKUP(A71,v_03_23!A:D,4,FALSE) -> 956.68 | L71: =H71-J71 -> -152 | M71: =I71-K71 -> -949.06 | N71: =M71/K71 -> -0.99203495
A72: B084TGLFLM | B72: C102BOT002 | C72: =VLOOKUP(A72,v_03_24!A:D,3,FALSE) -> 82 | D72: =VLOOKUP(A72,v_03_24!A:D,4,FALSE) -> 542.86 | E72: 0 | F72: 0 | G72: =F72/I72 -> 0 | H72: =C72+E72 -> 82 | I72: =D72+F72 -> 542.86 | J72: =VLOOKUP(A72,v_03_23!A:D,3,FALSE) -> 384 | K72: =VLOOKUP(A72,v_03_23!A:D,4,FALSE) -> 1553.73 | L72: =H72-J72 -> -302 | M72: =I72-K72 -> -1010.87 | N72: =M72/K72 -> -0.65060854
A73: B084TGLSDV | B73: C102BOT004 | C73: =VLOOKUP(A73,v_03_24!A:D,3,FALSE) -> 110 | D73: =VLOOKUP(A73,v_03_24!A:D,4,FALSE) -> 709.19 | E73: 0 | F73: 0 | G73: =F73/I73 -> 0 | H73: =C73+E73 -> 110 | I73: =D73+F73 -> 709.19 | J73: =VLOOKUP(A73,v_03_23!A:D,3,FALSE) -> 337 | K73: =VLOOKUP(A73,v_03_23!A:D,4,FALSE) -> 1442.57 | L73: =H73-J73 -> -227 | M73: =I73-K73 -> -733.38 | N73: =M73/K73 -> -0.50838434
A74: B085JHSWJW | B74: RCOBP630 | C74: =VLOOKUP(A74,v_03_24!A:D,3,FALSE) -> 1 | D74: =VLOOKUP(A74,v_03_24!A:D,4,FALSE) -> 5.98 | E74: 0 | F74: 0 | G74: =F74/I74 -> 0 | H74: =C74+E74 -> 1 | I74: =D74+F74 -> 5.98 | J74: =VLOOKUP(A74,v_03_23!A:D,3,FALSE) -> 1 | K74: =VLOOKUP(A74,v_03_23!A:D,4,FALSE) -> 8.11 | L74: =H74-J74 -> 0 | M74: =I74-K74 -> -2.13 | N74: =M74/K74 -> -0.26263872
A75: B085JHZT67 | B75: P206VEN420 | C75: =VLOOKUP(A75,v_03_24!A:D,3,FALSE) -> 8 | D75: =VLOOKUP(A75,v_03_24!A:D,4,FALSE) -> 131.03 | E75: 0 | F75: 0 | G75: =F75/I75 -> 0 | H75: =C75+E75 -> 8 | I75: =D75+F75 -> 131.03 | J75: 0 | K75: 0 | L75: =H75-J75 -> 8 | M75: =I75-K75 -> 131.03
A76: B085JJ747G | B76: P206VEN260 | C76: =VLOOKUP(A76,v_03_24!A:D,3,FALSE) -> 0 | D76: =VLOOKUP(A76,v_03_24!A:D,4,FALSE) -> 0 | E76: 0 | F76: 0 | H76: =C76+E76 -> 0 | I76: =D76+F76 -> 0 | J76: 0 | K76: 0 | L76: =H76-J76 -> 0 | M76: =I76-K76 -> 0
A77: B085JJ81R7 | B77: RCO9003028 | C77: =VLOOKUP(A77,v_03_24!A:D,3,FALSE) -> 65 | D77: =VLOOKUP(A77,v_03_24!A:D,4,FALSE) -> 429.36 | E77: 0 | F77: 0 | G77: =F77/I77 -> 0 | H77: =C77+E77 -> 65 | I77: =D77+F77 -> 429.36 | J77: =VLOOKUP(A77,v_03_23!A:D,3,FALSE) -> 106 | K77: =VLOOKUP(A77,v_03_23!A:D,4,FALSE) -> 693.19 | L77: =H77-J77 -> -41 | M77: =I77-K77 -> -263.83 | N77: =M77/K77 -> -0.38060272
A78: B085JJ8RC6 | B78: BB.050 | C78: =VLOOKUP(A78,v_03_24!A:D,3,FALSE) -> 99 | D78: =VLOOKUP(A78,v_03_24!A:D,4,FALSE) -> 1328.46 | E78: 0 | F78: 0 | G78: =F78/I78 -> 0 | H78: =C78+E78 -> 99 | I78: =D78+F78 -> 1328.46 | J78: =VLOOKUP(A78,v_03_23!A:D,3,FALSE) -> 983 | K78: =VLOOKUP(A78,v_03_23!A:D,4,FALSE) -> 12470.11 | L78: =H78-J78 -> -884 | M78: =I78-K78 -> -11141.65 | N78: =M78/K78 -> -0.89346846
A79: B085JJ9J4N | B79: P206RAF200 | C79: =VLOOKUP(A79,v_03_24!A:D,3,FALSE) -> 18 | D79: =VLOOKUP(A79,v_03_24!A:D,4,FALSE) -> 414.31 | E79: 0 | F79: 0 | G79: =F79/I79 -> 0 | H79: =C79+E79 -> 18 | I79: =D79+F79 -> 414.31 | J79: 0 | K79: 0 | L79: =H79-J79 -> 18 | M79: =I79-K79 -> 414.31
A80: B085JJFLGY | B80: RCO9003022 | C80: =VLOOKUP(A80,v_03_24!A:D,3,FALSE) -> 55 | D80: =VLOOKUP(A80,v_03_24!A:D,4,FALSE) -> 269.98 | E80: 0 | F80: 0 | G80: =F80/I80 -> 0 | H80: =C80+E80 -> 55 | I80: =D80+F80 -> 269.98 | J80: =VLOOKUP(A80,v_03_23!A:D,3,FALSE) -> 151 | K80: =VLOOKUP(A80,v_03_23!A:D,4,FALSE) -> 737.45 | L80: =H80-J80 -> -96 | M80: =I80-K80 -> -467.47 | N80: =M80/K80 -> -0.6339006
A81: B085JJMBM7 | B81: P206VEN400 | C81: =VLOOKUP(A81,v_03_24!A:D,3,FALSE) -> 4 | D81: =VLOOKUP(A81,v_03_24!A:D,4,FALSE) -> 42.46 | E81: 0 | F81: 0 | G81: =F81/I81 -> 0 | H81: =C81+E81 -> 4 | I81: =D81+F81 -> 42.46 | J81: =VLOOKUP(A81,v_03_23!A:D,3,FALSE) -> 19 | K81: =VLOOKUP(A81,v_03_23!A:D,4,FALSE) -> 154.82 | L81: =H81-J81 -> -15 | M81: =I81-K81 -> -112.36 | N81: =M81/K81 -> -0.72574603
A82: B085R2GCKX | B82: 40.332 | C82: =VLOOKUP(A82,v_03_24!A:D,3,FALSE) -> 83 | D82: =VLOOKUP(A82,v_03_24!A:D,4,FALSE) -> 1386.3 | E82: =VLOOKUP(A82,s_03_24!A:C,2,FALSE) -> 40332 | F82: =VLOOKUP(A82,s_03_24!A:C,3,FALSE) -> 4 | G82: =F82/I82 -> 0.0028770769 | H82: =C82+E82 -> 40415 | I82: =D82+F82 -> 1390.3 | J82: =VLOOKUP(A82,v_03_23!A:D,3,FALSE) -> 514 | K82: =VLOOKUP(A82,v_03_23!A:D,4,FALSE) -> 7846.58 | L82: =H82-J82 -> 39901 | M82: =I82-K82 -> -6456.28 | N82: =M82/K82 -> -0.82281453
A83: B085R2NT18 | B83: 3BEPI001 | C83: =VLOOKUP(A83,v_03_24!A:D,3,FALSE) -> 17 | D83: =VLOOKUP(A83,v_03_24!A:D,4,FALSE) -> 336.87 | E83: 0 | F83: 0 | G83: =F83/I83 -> 0 | H83: =C83+E83 -> 17 | I83: =D83+F83 -> 336.87 | J83: =VLOOKUP(A83,v_03_23!A:D,3,FALSE) -> 1 | K83: =VLOOKUP(A83,v_03_23!A:D,4,FALSE) -> 25.69 | L83: =H83-J83 -> 16 | M83: =I83-K83 -> 311.18 | N83: =M83/K83 -> 12.112884
A84: B088PL1CY6 | B84: P206VEN100 | C84: =VLOOKUP(A84,v_03_24!A:D,3,FALSE) -> 4 | D84: =VLOOKUP(A84,v_03_24!A:D,4,FALSE) -> 103.27 | E84: 0 | F84: 0 | G84: =F84/I84 -> 0 | H84: =C84+E84 -> 4 | I84: =D84+F84 -> 103.27 | J84: =VLOOKUP(A84,v_03_23!A:D,3,FALSE) -> 0 | K84: =VLOOKUP(A84,v_03_23!A:D,4,FALSE) -> 0 | L84: =H84-J84 -> 4 | M84: =I84-K84 -> 103.27
A85: B088V4DR59 | B85: P206ZAN040 | C85: =VLOOKUP(A85,v_03_24!A:D,3,FALSE) -> 13 | D85: =VLOOKUP(A85,v_03_24!A:D,4,FALSE) -> 685.83 | E85: 0 | F85: 0 | G85: =F85/I85 -> 0 | H85: =C85+E85 -> 13 | I85: =D85+F85 -> 685.83 | J85: =VLOOKUP(A85,v_03_23!A:D,3,FALSE) -> 1 | K85: =VLOOKUP(A85,v_03_23!A:D,4,FALSE) -> 51.7 | L85: =H85-J85 -> 12 | M85: =I85-K85 -> 634.13 | N85: =M85/K85 -> 12.265571
A86: B088V7DR7L | B86: P206VEN130 | C86: =VLOOKUP(A86,v_03_24!A:D,3,FALSE) -> 5 | D86: =VLOOKUP(A86,v_03_24!A:D,4,FALSE) -> 165.45 | E86: 0 | F86: 0 | G86: =F86/I86 -> 0 | H86: =C86+E86 -> 5 | I86: =D86+F86 -> 165.45 | J86: =VLOOKUP(A86,v_03_23!A:D,3,FALSE) -> 1 | K86: =VLOOKUP(A86,v_03_23!A:D,4,FALSE) -> 37.03 | L86: =H86-J86 -> 4 | M86: =I86-K86 -> 128.42 | N86: =M86/K86 -> 3.4679989
A87: B088XJQ37J | B87: C301ABE001 | C87: =VLOOKUP(A87,v_03_24!A:D,3,FALSE) -> 37 | D87: =VLOOKUP(A87,v_03_24!A:D,4,FALSE) -> 452.17 | E87: 0 | F87: 0 | G87: =F87/I87 -> 0 | H87: =C87+E87 -> 37 | I87: =D87+F87 -> 452.17 | J87: =VLOOKUP(A87,v_03_23!A:D,3,FALSE) -> 336 | K87: =VLOOKUP(A87,v_03_23!A:D,4,FALSE) -> 3555.66 | L87: =H87-J87 -> -299 | M87: =I87-K87 -> -3103.49 | N87: =M87/K87 -> -0.87283092
A88: B089BGZSNM | B88: P101CUD001 | C88: =VLOOKUP(A88,v_03_24!A:D,3,FALSE) -> 0 | D88: =VLOOKUP(A88,v_03_24!A:D,4,FALSE) -> 0 | E88: 0 | F88: 0 | H88: =C88+E88 -> 0 | I88: =D88+F88 -> 0 | J88: =VLOOKUP(A88,v_03_23!A:D,3,FALSE) -> 28 | K88: =VLOOKUP(A88,v_03_23!A:D,4,FALSE) -> 736.86 | L88: =H88-J88 -> -28 | M88: =I88-K88 -> -736.86 | N88: =M88/K88 -> -1
A89: B08B66J4C3 | B89: P101PIA001 | C89: =VLOOKUP(A89,v_03_24!A:D,3,FALSE) -> 0 | D89: =VLOOKUP(A89,v_03_24!A:D,4,FALSE) -> 0 | E89: 0 | F89: 0 | H89: =C89+E89 -> 0 | I89: =D89+F89 -> 0 | J89: =VLOOKUP(A89,v_03_23!A:D,3,FALSE) -> 931 | K89: =VLOOKUP(A89,v_03_23!A:D,4,FALSE) -> 11587.15 | L89: =H89-J89 -> -931 | M89: =I89-K89 -> -11587.15 | N89: =M89/K89 -> -1
A90: B08B8M2B7B | B90: P102EST001 | C90: =VLOOKUP(A90,v_03_24!A:D,3,FALSE) -> 10 | D90: =VLOOKUP(A90,v_03_24!A:D,4,FALSE) -> 327.83 | E90: 0 | F90: 0 | G90: =F90/I90 -> 0 | H90: =C90+E90 -> 10 | I90: =D90+F90 -> 327.83 | J90: =VLOOKUP(A90,v_03_23!A:D,3,FALSE) -> 17 | K90: =VLOOKUP(A90,v_03_23!A:D,4,FALSE) -> 541.82 | L90: =H90-J90 -> -7 | M90: =I90-K90 -> -213.99 | N90: =M90/K90 -> -0.39494666
A91: B08C7YJB5N | B91: P201UTP001 | C91: =VLOOKUP(A91,v_03_24!A:D,3,FALSE) -> 35 | D91: =VLOOKUP(A91,v_03_24!A:D,4,FALSE) -> 465.99 | E91: 0 | F91: 0 | G91: =F91/I91 -> 0 | H91: =C91+E91 -> 35 | I91: =D91+F91 -> 465.99 | J91: =VLOOKUP(A91,v_03_23!A:D,3,FALSE) -> 132 | K91: =VLOOKUP(A91,v_03_23!A:D,4,FALSE) -> 1192.15 | L91: =H91-J91 -> -97 | M91: =I91-K91 -> -726.16 | N91: =M91/K91 -> -0.60911798
A92: B08DHZDXVV | B92: P102SBA100 | C92: =VLOOKUP(A92,v_03_24!A:D,3,FALSE) -> 6 | D92: =VLOOKUP(A92,v_03_24!A:D,4,FALSE) -> 133.04 | E92: 0 | F92: 0 | G92: =F92/I92 -> 0 | H92: =C92+E92 -> 6 | I92: =D92+F92 -> 133.04 | J92: =VLOOKUP(A92,v_03_23!A:D,3,FALSE) -> 20 | K92: =VLOOKUP(A92,v_03_23!A:D,4,FALSE) -> 352.08 | L92: =H92-J92 -> -14 | M92: =I92-K92 -> -219.04 | N92: =M92/K92 -> -0.62213133
A93: B08DJ3K9J8 | B93: p102rob100 | C93: =VLOOKUP(A93,v_03_24!A:D,3,FALSE) -> 2 | D93: =VLOOKUP(A93,v_03_24!A:D,4,FALSE) -> 19.58 | E93: 0 | F93: 0 | G93: =F93/I93 -> 0 | H93: =C93+E93 -> 2 | I93: =D93+F93 -> 19.58 | J93: =VLOOKUP(A93,v_03_23!A:D,3,FALSE) -> 1 | K93: =VLOOKUP(A93,v_03_23!A:D,4,FALSE) -> 12.21 | L93: =H93-J93 -> 1 | M93: =I93-K93 -> 7.37 | N93: =M93/K93 -> 0.6036036
A94: B08DL66NZ9 | B94: P301ASC001 | C94: =VLOOKUP(A94,v_03_24!A:D,3,FALSE) -> 11 | D94: =VLOOKUP(A94,v_03_24!A:D,4,FALSE) -> 229.16 | E94: 0 | F94: 0 | G94: =F94/I94 -> 0 | H94: =C94+E94 -> 11 | I94: =D94+F94 -> 229.16 | J94: =VLOOKUP(A94,v_03_23!A:D,3,FALSE) -> 7 | K94: =VLOOKUP(A94,v_03_23!A:D,4,FALSE) -> 159.74 | L94: =H94-J94 -> 4 | M94: =I94-K94 -> 69.42 | N94: =M94/K94 -> 0.43458119
A95: B08F5GYFKS | B95: P102FRU001 | C95: =VLOOKUP(A95,v_03_24!A:D,3,FALSE) -> 1 | D95: =VLOOKUP(A95,v_03_24!A:D,4,FALSE) -> 10.45 | E95: 0 | F95: 0 | G95: =F95/I95 -> 0 | H95: =C95+E95 -> 1 | I95: =D95+F95 -> 10.45 | J95: =VLOOKUP(A95,v_03_23!A:D,3,FALSE) -> 12 | K95: =VLOOKUP(A95,v_03_23!A:D,4,FALSE) -> 134.85 | L95: =H95-J95 -> -11 | M95: =I95-K95 -> -124.4 | N95: =M95/K95 -> -0.92250649
A96: B08FDP7T13 | B96: P101FOR001 | C96: =VLOOKUP(A96,v_03_24!A:D,3,FALSE) -> 1 | D96: =VLOOKUP(A96,v_03_24!A:D,4,FALSE) -> 74.43 | E96: 0 | F96: 0 | G96: =F96/I96 -> 0 | H96: =C96+E96 -> 1 | I96: =D96+F96 -> 74.43 | J96: 0 | K96: 0 | L96: =H96-J96 -> 1 | M96: =I96-K96 -> 74.43
A97: B08FDYW72J | B97: P101CUD100 | C97: =VLOOKUP(A97,v_03_24!A:D,3,FALSE) -> 65 | D97: =VLOOKUP(A97,v_03_24!A:D,4,FALSE) -> 1892.39 | E97: =VLOOKUP(A97,s_03_24!A:C,2,FALSE) -> P101CUD100 | F97: =VLOOKUP(A97,s_03_24!A:C,3,FALSE) -> 2 | G97: =F97/I97 -> 0.0010557488 | H97: =C97+E97 -> #VALUE! | I97: =D97+F97 -> 1894.39 | J97: =VLOOKUP(A97,v_03_23!A:D,3,FALSE) -> 107 | K97: =VLOOKUP(A97,v_03_23!A:D,4,FALSE) -> 3117.19 | L97: =H97-J97 -> #VALUE! | M97: =I97-K97 -> -1222.8 | N97: =M97/K97 -> -0.39227638
A98: B08FF245TD | B98: P101CUD500 | C98: =VLOOKUP(A98,v_03_24!A:D,3,FALSE) -> 2 | D98: =VLOOKUP(A98,v_03_24!A:D,4,FALSE) -> 54.55 | E98: 0 | F98: 0 | G98: =F98/I98 -> 0 | H98: =C98+E98 -> 2 | I98: =D98+F98 -> 54.55 | J98: =VLOOKUP(A98,v_03_23!A:D,3,FALSE) -> 11 | K98: =VLOOKUP(A98,v_03_23!A:D,4,FALSE) -> 305.15 | L98: =H98-J98 -> -9 | M98: =I98-K98 -> -250.6 | N98: =M98/K98 -> -0.82123546
A99: B08FJGGZ1D | B99: 70.405 | C99: =VLOOKUP(A99,v_03_24!A:D,3,FALSE) -> 19 | D99: =VLOOKUP(A99,v_03_24!A:D,4,FALSE) -> 152.1 | E99: 0 | F99: 0 | G99: =F99/I99 -> 0 | H99: =C99+E99 -> 19 | I99: =D99+F99 -> 152.1 | J99: =VLOOKUP(A99,v_03_23!A:D,3,FALSE) -> 4 | K99: =VLOOKUP(A99,v_03_23!A:D,4,FALSE) -> 64.1 | L99: =H99-J99 -> 15 | M99: =I99-K99 -> 88 | N99: =M99/K99 -> 1.3728549
A100: B08FMLPKY9 | B100: P201UTP004 | C100: =VLOOKUP(A100,v_03_24!A:D,3,FALSE) -> 80 | D100: =VLOOKUP(A100,v_03_24!A:D,4,FALSE) -> 1377.67 | E100: 0 | F100: 0 | G100: =F100/I100 -> 0 | H100: =C100+E100 -> 80 | I100: =D100+F100 -> 1377.67 | J100: =VLOOKUP(A100,v_03_23!A:D,3,FALSE) -> 168 | K100: =VLOOKUP(A100,v_03_23!A:D,4,FALSE) -> 2981.78 | L100: =H100-J100 -> -88 | M100: =I100-K100 -> -1604.11 | N100: =M100/K100 -> -0.53797061
...
