Workbook

Sheet vendor_02_2023
A1: Programma=[Retail] | B1: Visualizza per=[ASIN] | C1: Paesi=[IT;ES;DE;FR;UK;NL;SE] | D1: Aziende=[Beper s.r.l.;Beper s.r.l.;Beper s.r.l. - DE Account;Beper s.r.l. - FR Account;Beper s.r.l. - GB Account;Beper s.r.l. - NL Account;Beper s.r.l. - SE Account] | E1: Lingua=[it_IT] | F1: Valuta=[EUR] | G1: Intervallo report=[Mese] | H1: Intervallo di visualizzazione=[01/02/23 - 28/02/23] | I1: Report aggiornato=[01/04/24]
A2: ASIN | B2: Numero del modello | C2: Codice marketplace | D2: Ricavi ordini | E2: Unità ordinate | F2: Ricavi spedizioni | G2: COGS spedizioni | H2: Unità spedite | I2: Resi cliente
A3: B01I497WWM | B3: 90.920R | C3: IT | D3: 30066.66 | E3: 2222 | F3: 30676.77 | G3: 19018.52 | H3: 2275 | I3: 198
A4: B07ZJQTGG8 | B4: 50.245 | C4: IT | D4: 25188.39 | E4: 2063 | F4: 25322.7 | G4: 16406.9 | H4: 2074 | I4: 71
A5: B096MX229M | B5: P102ROB050 | C5: DE | D5: 17654.29 | E5: 1419 | F5: 17469.22 | G5: 10791.6 | H5: 1405 | I5: 125
A6: B095PQJGKX | B6: C107UTT002 | C6: ES | D6: 15786.08 | E6: 1930 | F6: 15794.26 | G6: 9173.44 | H6: 1931 | I6: 56
A7: B08GY7286R | B7: P203TFO001 | C7: IT | D7: 14353 | E7: 748 | F7: 14939.17 | G7: 7779.98 | H7: 780 | I7: 62
A8: B08485QRVZ | B8: BC.261 | C8: IT | D8: 13551.02 | E8: 664 | F8: 13755.12 | G8: 11654.4 | H8: 674 | I8: 35
A9: B096MX229M | B9: P102ROB050 | C9: FR | D9: 12664.05 | E9: 1133 | F9: 12592.35 | G9: 8600.4 | H9: 1124 | I9: 44
A10: B01KMJ9OXW | B10: 90.590Y | C10: FR | D10: 11559.69 | E10: 349 | F10: 11593.14 | G10: 6915 | H10: 350 | I10: 31
A11: B079SB5VJZ | B11: 50451 | C11: IT | D11: 11019.9 | E11: 337 | F11: 10333.2 | G11: 10599.59 | H11: 316 | I11: 15
A12: B00NSNZSLM | B12: 90.602 | C12: IT | D12: 10511.15 | E12: 515 | F12: 10347.87 | G12: 8617.51 | H12: 507 | I12: 29
A13: B085JJ8RC6 | B13: BB.050 | C13: IT | D13: 10327.56 | E13: 846 | F13: 10061.04 | G13: 8343.53 | H13: 824 | I13: 105
A14: B0757TJRR9 | B14: 40.500 | C14: IT | D14: 10284.5 | E14: 382 | F14: 10343.36 | G14: 7114.91 | H14: 384 | I14: 30
... A67: B08GY7286R | B67: P203TFO001 | C67: DE | D67: 2244.48 | E67: 168 | F67: 2191.04 | G67: 1727.82 | H67: 164 | I67: 14
A68: B00L5H5KUW | B68: 40.121 | C68: ES | D68: 2229.19 | E68: 122 | F68: 2346.22 | G68: 1641.17 | H68: 130
A69: B0B39H1Z8J | B69: C106CAS001 | C69: FR | D69: 2227.5 | E69: 270 | F69: 2227.5 | G69: 1657.8 | H69: 270 | I69: 2
A70: B085JJJR91 | B70: BC.210 | C70: FR | D70: 2151.92 | E70: 74 | F70: 2268.24 | G70: 2250.48 | H70: 78 | I70: 4
A71: B07KYWNC7Z | B71: 40.405 | C71: IT | D71: 2118.97 | E71: 108 | F71: 2022.94 | G71: 1587.62 | H71: 103 | I71: 5
A72: B08GS7XW73 | B72: P204FER250 | C72: IT | D72: 2111.81 | E72: 131 | F72: 1927.84 | G72: 1516.72 | H72: 119 | I72: 8
A73: B076QFRRZ5 | B73: 40.931 | C73: IT | D73: 2062.9 | E73: 149 | F73: 2063.44 | G73: 1003.06 | H73: 149 | I73: 24
A74: B08GY7286R | B74: P203TFO001 | C74: FR | D74: 2061.71 | E74: 114 | F74: 2130.38 | G74: 1230.15 | H74: 118 | I74: 12
A75: B017IUJA50 | B75: 90.920G | C75: FR | D75: 1921.25 | E75: 145 | F75: 1828.5 | G75: 1175.9 | H75: 138 | I75: 12
A76: B09BD8BG34 | B76: P301PIS001 | C76: IT | D76: 1913.17 | E76: 181 | F76: 1860.32 | G76: 1489.62 | H76: 176 | I76: 6
A77: B07YZZZVXP | B77: MD.404 | C77: DE | D77: 1897.28 | E77: 30 | F77: 1961.2 | G77: 1449.08 | H77: 31 | I77: 14
A78: B08485QRVZ | B78: BC.261 | C78: FR | D78: 1895.99 | E78: 60 | F78: 1988.83 | G78: 1083 | H78: 63 | I78: 1
A79: B00FAJUDU8 | B79: 40.967N | C79: IT | D79: 1877.72 | E79: 92 | F79: 1857.31 | G79: 1378.4 | H79: 91 | I79: 8
A80: B0BD83RNDG | B80: C106CAS002 | C80: IT | D80: 1839.18 | E80: 174 | F80: 1849.75 | G80: 1524.04 | H80: 175 | I80: 4
... A82: B07N4C3H3V | B82: 40.405 | C82: DE | D82: 1768.29 | E82: 177 | F82: 1728.29 | G82: 1067.4 | H82: 173 | I82: 3
A83: B085JJJR91 | B83: BC.210 | C83: DE | D83: 1743.56 | E83: 52 | F83: 1710.03 | G83: 1463.1 | H83: 51
A84: B08FDYW72J | B84: P101CUD100 | C84: DE | D84: 1657.83 | E84: 47 | F84: 1650.19 | G84: 835.8 | H84: 47 | I84: 12
A85: B00FAJUDU8 | B85: 40.967N | C85: FR | D85: 1618.5 | E85: 78 | F85: 1597.75 | G85: 1017.46 | H85: 77 | I85: 6
A86: B0BJ2TBPJW | B86: C206UTI004 | C86: IT | D86: 1615.55 | E86: 395 | F86: 1627.82 | G86: 1128.54 | H86: 398 | I86: 1
A87: B09KYD9JGY | B87: P301PIS100 | C87: IT | D87: 1591.98 | E87: 78 | F87: 1530.75 | G87: 1151.39 | H87: 75 | I87: 19
A88: B09KYD9JGY | B88: P301PIS100 | C88: FR | D88: 1556.25 | E88: 75 | F88: 1535.5 | G88: 1134.69 | H88: 74 | I88: 9
A89: B08FMLPKY9 | B89: P201UTP004 | C89: IT | D89: 1552.45 | E89: 83 | F89: 1613.82 | G89: 812.11 | H89: 86 | I89: 3
A90: B09KYD9JGY | B90: P301PIS100 | C90: ES | D90: 1510.96 | E90: 76 | F90: 1533.2 | G90: 1191.42 | H90: 77 | I90: 15
A91: B07TQVD94L | B91: BP.690 | C91: IT | D91: 1470.6 | E91: 60 | F91: 1544.13 | G91: 1709.1 | H91: 63 | I91: 1
A92: B08LZN1PWY | B92: P101TEM001 | C92: ES | D92: 1444.25 | E92: 25 | F92: 1444.25 | G92: 939.85 | H92: 25
A93: B07BB2DQ4V | B93: BT.150Y | C93: DE | D93: 1412.76 | E93: 47 | F93: 1387.05 | G93: 884.71 | H93: 46 | I93: 3
A94: B08MX1SQKC | B94: P302VIS001 | C94: IT | D94: 1404.15 | E94: 115 | F94: 1379.73 | G94: 896 | H94: 113 | I94: 6
A95: B0B6JPXDN6 | B95: P201UTP200 | C95: DE | D95: 1387.76 | E95: 83 | F95: 1404.48 | G95: 1121.41 | H95: 84 | I95: 9
A96: B01M4O6145 | B96: 90.071 | C96: IT | D96: 1379.23 | E96: 65 | F96: 1336.77 | G96: 917.03 | H96: 63 | I96: 12
A97: B09146GTKW | B97: P302VIS002 | C97: FR | D97: 1361.25 | E97: 165 | F97: 1344.75 | G97: 939 | H97: 163 | I97: 5
A98: B08JYWF3PK | B98: C102COC101 | C98: FR | D98: 1353 | E98: 164 | F98: 1344.75 | G98: 901.95 | H98: 163 | I98: 1
A99: B07NQC6S9V | B99: BT.651Y | C99: IT | D99: 1331.46 | E99: 28 | F99: 1441.86 | G99: 1024.5 | H99: 31 | I99: 14
A100: B09D8G2H7Q | B100: P102SBA500 | C100: IT | D100: 1322.86 | E100: 15 | F100: 1315.68 | G100: 1073.29 | H100: 15 | I100: 3
A101: B088XJQ37J | B101: C301ABE001 | C101: IT | D101: 1321.25 | E101: 125 | F101: 1215.55 | G101: 699.07 | H101: 115 | I101: 1
A102: B07P7GGGQM | B102: BP.961 | C102: DE | D102: 1309.88 | E102: 26 | F102: 1232.43 | G102: 720.5 | H102: 25 | I102: 10
A103: B0BD83RNDG | B103: C106CAS002 | C103: ES | D103: 1289.86 | E103: 121 | F103: 1257.88 | G103: 1027.28 | H103: 118 | I103: 4
A104: B076Q7BR6F | B104: BC.041N | C104: FR | D104: 1288.98 | E104: 31 | F104: 1247.4 | G104: 932.4 | H104: 30 | I104: 3
A105: B084TGLFLM | B105: C102BOT002 | C105: IT | D105: 1277.2 | E105: 347 | F105: 1161.44 | G105: 1058.46 | H105: 318
A106: B01I497WWM | B106: 90.920R | C106: ES | D106: 1266.12 | E106: 78 | F106: 1249.6 | G106: 645.73 | H106: 77 | I106: 12
A107: B07V131F5W | B107: 40.490 | C107: ES | D107: 1199.12 | E107: 52 | F107: 1129.94 | G107: 732.01 | H107: 49
A108: B07YBNB2QY | B108: 50161 | C108: DE | D108: 1190.09 | E108: 29 | F108: 1190.71 | G108: 884.34 | H108: 29 | I108: 12
A109: B09495C38F | B109: P204FER002 | C109: DE | D109: 1184.58 | E109: 71 | F109: 1201.3 | G109: 888.03 | H109: 72 | I109: 1
A110: B07B9CPH62 | B110: BG.200Y | C110: IT | D110: 1178.4 | E110: 24 | F110: 1227.5 | G110: 948.46 | H110: 25 | I110: 1
A111: B09L4SLDSZ | B111: P203TFO100 | C111: IT | D111: 1176.48 | E111: 48 | F111: 1200.99 | G111: 827.2 | H111: 49 | I111: 5
A112: B08FMLPKY9 | B112: P201UTP004 | C112: FR | D112: 1167.14 | E112: 67 | F112: 1097.46 | G112: 733.16 | H112: 63 | I112: 5
A113: B09B47S644 | B113: P101CUD501 | C113: DE | D113: 1143.07 | E113: 41 | F113: 1064.59 | G113: 732.88 | H113: 38 | I113: 5
A114: B08B66J4C3 | B114: P101PIA001 | C114: FR | D114: 1130.22 | E114: 91 | F114: 1068.12 | G114: 594.31 | H114: 86 | I114: 6
A115: B085JHTR6Q | B115: BP.790 | C115: IT | D115: 1127.46 | E115: 46 | F115: 1078.44 | G115: 607.67 | H115: 44 | I115: 3
A116: B0B5XB4X2T | B116: P102ACP100 | C116: IT | D116: 1125.39 | E116: 69 | F116: 1125.39 | G116: 1177.32 | H116: 69
A117: B08GS7XW73 | B117: P204FER250 | C117: FR | D117: 1114.88 | E117: 64 | F117: 1149.72 | G117: 854.34 | H117: 66 | I117: 2
A118: B0BD83RNDG | B118: C106CAS002 | C118: DE | D118: 1094.84 | E118: 101 | F118: 1149.04 | G118: 930.32 | H118: 106 | I118: 6
A119: B095X9KDJR | B119: P101BOL100 | C119: IT | D119: 1092.77 | E119: 67 | F119: 1060.15 | G119: 854.7 | H119: 65 | I119: 2
A120: B07Q38Z7CK | B120: BC.060 | C120: FR | D120: 1061.82 | E120: 51 | F120: 1065.92 | G120: 865.81 | H120: 51 | I120: 2
A121: B0823CVGHX | B121: BP.400 | C121: DE | D121: 1059.57 | E121: 19 | F121: 1002.44 | G121: 757.45 | H121: 18 | I121: 6
A122: B06Y17FS6D | B122: 90.550 | C122: FR | D122: 1056.38 | E122: 31 | F122: 1056.38 | G122: 853.69 | H122: 31 | I122: 6
A123: B07SSLRCT6 | B123: BP.304 | C123: FR | D123: 1054.87 | E123: 67 | F123: 1038.92 | G123: 580.74 | H123: 66 | I123: 3
A124: B085R2GCKX | B124: 40.332 | C124: ES | D124: 1036.35 | E124: 63 | F124: 987 | G124: 489.28 | H124: 60 | I124: 5
A125: B0B39H1Z8J | B125: C106CAS001 | C125: ES | D125: 1030.68 | E125: 126 | F125: 1022.5 | G125: 729.68 | H125: 125 | I125: 5
A126: B08JM7SZ36 | B126: C206UTI001 | C126: DE | D126: 1016.32 | E126: 35 | F126: 843.82 | G126: 595 | H126: 29 | I126: 13
A127: B085R2GCKX | B127: 40.332 | C127: FR | D127: 1011.38 | E127: 61 | F127: 978.22 | G127: 630.77 | H127: 59
A128: B08B66J4C3 | B128: P101PIA001 | C128: DE | D128: 976.56 | E128: 78 | F128: 951.52 | G128: 552.15 | H128: 76
A129: B097HRQNRG | B129: P101FRI100 | C129: IT | D129: 972.74 | E129: 34 | F129: 1029.96 | G129: 599.8 | H129: 36 | I129: 8
A130: B085JJ81R7 | B130: RCO9003028 | C130: IT | D130: 967.96 | E130: 139 | F130: 1004.46 | G130: 532.8 | H130: 144 | I130: 2
A131: B097HRQNRG | B131: P101FRI100 | C131: FR | D131: 966.68 | E131: 24 | F131: 966.68 | G131: 494.16 | H131: 24 | I131: 13
A132: B09D8G2H7Q | B132: P102SBA500 | C132: FR | D132: 956.04 | E132: 10 | F132: 956.04 | G132: 701.3 | H132: 10 | I132: 1
A133: B084TGLSDV | B133: C102BOT004 | C133: IT | D133: 952.03 | E133: 259 | F133: 959.33 | G133: 704.55 | H133: 260 | I133: 4
A134: B09ZBHJ91Q | B134: P201UTP100 | C134: IT | D134: 944.27 | E134: 77 | F134: 626.81 | G134: 551.45 | H134: 51 | I134: 7
A135: B07TSNB5WG | B135: BP.102 | C135: FR | D135: 943.36 | E135: 67 | F135: 915.2 | G135: 703.78 | H135: 65 | I135: 3
A136: B0B2F48ZMP | B136: P102GEL100 | C136: FR | D136: 898.84 | E136: 23 | F136: 859.76 | G136: 685.72 | H136: 22 | I136: 4
A137: B07YBN2FS3 | B137: BF.640 | C137: FR | D137: 893.05 | E137: 14 | F137: 893.05 | G137: 515.06 | H137: 14 | I137: 1
A138: B0B6JPXDN6 | B138: P201UTP200 | C138: IT | D138: 880.74 | E138: 54 | F138: 945.98 | G138: 769.08 | H138: 58 | I138: 6
A139: B00EYDRS1I | B139: 90.349 | C139: IT | D139: 878.28 | E139: 159 | F139: 868.6 | G139: 518.57 | H139: 157 | I139: 7
A140: B0953R2W31 | B140: P102ACP001 | C140: IT | D140: 878.14 | E140: 72 | F140: 914.77 | G140: 433.07 | H140: 75 | I140: 7
... A144: B0BBH12BYN | B144: P101COS001 | C144: IT | D144: 810.72 | E144: 9 | F144: 810.72 | G144: 654.03 | H144: 9 | I144: 2
A145: B073B57HQH | B145: 90.886 | C145: IT | D145: 809.04 | E145: 8 | F145: 809.04 | G145: 733.6 | H145: 8
A146: B08C7YJB5N | B146: P201UTP001 | C146: IT | D146: 801.33 | E146: 89 | F146: 811.17 | G146: 650.55 | H146: 89 | I146: 6
A147: B073B67PLQ | B147: 90.884 | C147: FR | D147: 799.92 | E147: 12 | F147: 799.92 | G147: 810 | H147: 12
A148: B09BD8BG34 | B148: P301PIS001 | C148: ES | D148: 779.83 | E148: 73 | F148: 706.86 | G148: 578.6 | H148: 66 | I148: 2
A149: B00L5H5KUW | B149: 40.121 | C149: FR | D149: 779.26 | E149: 47 | F149: 862.16 | G149: 804.44 | H149: 52
A150: B0B8DLSNJF | B150: P302VIS050 | C150: IT | D150: 766.57 | E150: 47 | F150: 815.5 | G150: 704.42 | H150: 50 | I150: 16
A151: B08HCT78N3 | B151: P202ASP400 | C151: IT | D151: 766.57 | E151: 47 | F151: 750.26 | G151: 297.99 | H151: 46 | I151: 48
A152: B085R2GCKX | B152: 40.332 | C152: DE | D152: 752.4 | E152: 45 | F152: 769.12 | G152: 451.5 | H152: 46 | I152: 5
A153: B076DCL19C | B153: BP.720 | C153: IT | D153: 744.9 | E153: 13 | F153: 744.9 | G153: 528.77 | H153: 13 | I153: 9
A154: B07NQ2VYGD | B154: BT.710Y | C154: GB | D154: 735.84 | E154: 29 | F154: 811.84 | G154: 664.21 | H154: 32 | I154: 1
A155: B0BD83RNDG | B155: C106CAS002 | C155: FR | D155: 731 | E155: 68 | F155: 720.25 | G155: 586.71 | H155: 67 | I155: 2
A156: B09HMK8JDN | B156: P203TER001 | C156: IT | D156: 729.5 | E156: 10 | F156: 729.5 | G156: 754.6 | H156: 10 | I156: 3
...

Sheet vendor_02_2024
A1: ASIN | B1: Numero del modello | C1: Codice marketplace | D1: Ricavi ordini | E1: Unità ordinate | F1: Ricavi spedizioni | G1: COGS spedizioni | H1: Unità spedite | I1: Resi cliente
A2: B0CPFRMPTM | B2: P101CAF001 | C2: IT | D2: 9465.85 | E2: 382 | F2: 9375.1 | G2: 10043.5 | H2: 379 | I2: 3
A3: B0050IHH4E | B3: 40.979 | C3: DE | D3: 9135.52 | E3: 646 | F3: 8823.12 | G3: 5691.84 | H3: 624 | I3: 16
A4: B0CC5QZ9CJ | B4: C206UTI006 | C4: FR | D4: 8784.54 | E4: 1319 | F4: 8897.76 | G4: 5409.39 | H4: 1336 | I4: 8
A5: B07ZJQTGG8 | B5: 50.245 | C5: IT | D5: 8094.4 | E5: 638 | F5: 8192.08 | G5: 5445.78 | H5: 646 | I5: 20
A6: B00L5H5KUW | B6: 40.121 | C6: IT | D6: 7577.95 | E6: 424 | F6: 7019.45 | G6: 4695.43 | H6: 392 | I6: 2
A7: B0BBH12BYN | B7: P101COS001 | C7: IT | D7: 7189.97 | E7: 83 | F7: 6924.69 | G7: 4687.06 | H7: 80 | I7: 14
A8: B0CHF7YW6B | B8: P203PAN010 | C8: IT | D8: 6394.47 | E8: 253 | F8: 6364.71 | G8: 4680.5 | H8: 253 | I8: 55
A9: B06Y17FS6D | B9: 90.550 | C9: IT | D9: 5475.75 | E9: 197 | F9: 5406.6 | G9: 4508 | H9: 196 | I9: 7
A10: B0CHFQXMZX | B10: P203PAN001 | C10: IT | D10: 4902.9 | E10: 354 | F10: 4930.6 | G10: 3382 | H10: 356 | I10: 7
A11: B0050IHH4E | B11: 40.979 | C11: IT | D11: 4876.26 | E11: 311 | F11: 4736.87 | G11: 3022.06 | H11: 302 | I11: 18
A12: B09146GTKW | B12: P302VIS002 | C12: IT | D12: 4828.53 | E12: 421 | F12: 4862.97 | G12: 2544 | H12: 424 | I12: 33
A13: B017IUJA50 | B13: 90.920G | C13: IT | D13: 4464.61 | E13: 274 | F13: 4549.25 | G13: 2329.65 | H13: 279 | I13: 11
... A28: B0BNNH9RZQ | B28: P302VIS060 | C28: IT | D28: 1835.74 | E28: 165 | F28: 1824.24 | G28: 1190.76 | H28: 164 | I28: 19
A29: B07JGVMFY1 | B29: BP.581 | C29: FR | D29: 1820.24 | E29: 122 | F29: 1760.56 | G29: 1188.26 | H29: 118
A30: B06Y1997YH | B30: 90.883 | C30: IT | D30: 1743.72 | E30: 30 | F30: 1571.82 | G30: 1130.94 | H30: 27 | I30: 2
A31: B0BTHSH5MK | B31: C103ACC001 | C31: IT | D31: 1742.62 | E31: 188 | F31: 1807.11 | G31: 1085.4 | H31: 197 | I31: 1
A32: B073B67PLQ | B32: 90.884 | C32: IT | D32: 1715.37 | E32: 21 | F32: 1716.83 | G32: 1385.5 | H32: 21 | I32: 2
A33: B0BVZG7FPY | B33: P206VEN600 | C33: IT | D33: 1665.99 | E33: 41 | F33: 990.13 | G33: 649.95 | H33: 25 | I33: 1
A34: B0BNNH9RZQ | B34: P302VIS060 | C34: DE | D34: 1661.52 | E34: 132 | F34: 1749.16 | G34: 1054.99 | H34: 139 | I34: 26
A35: B08L9D9KR9 | B35: P202VAL001 | C35: IT | D35: 1604.4 | E35: 28 | F35: 1489.8 | G35: 1170 | H35: 26 | I35: 2
A36: B0CFB71DMN | B36: C203PUL004 | C36: IT | D36: 1566.85 | E36: 277 | F36: 1426.09 | G36: 718.8 | H36: 251 | I36: 2
A37: B07ZJMFB3R | B37: BC.510 | C37: IT | D37: 1547.1 | E37: 27 | F37: 1547.1 | G37: 1252.8 | H37: 27
A38: B0BD83RNDG | B38: C106CAS002 | C38: FR | D38: 1429.75 | E38: 133 | F38: 1408.25 | G38: 988.43 | H38: 131 | I38: 2
A39: B0BNNH9RZQ | B39: P302VIS060 | C39: ES | D39: 1424.94 | E39: 114 | F39: 1476.96 | G39: 824.42 | H39: 118 | I39: 32
A40: B0B8DLSNJF | B40: P302VIS050 | C40: IT | D40: 1419.28 | E40: 88 | F40: 1052.15 | G40: 913.9 | H40: 65
A41: B08FDYW72J | B41: P101CUD100 | C41: DE | D41: 1414.8 | E41: 45 | F41: 1420.75 | G41: 911.25 | H41: 45 | I41: 4
A42: B0CHF7YW6B | B42: P203PAN010 | C42: FR | D42: 1343.58 | E42: 49 | F42: 1316.16 | G42: 888 | H42: 48 | I42: 17
A43: B07SSLRCT6 | B43: BP.304 | C43: IT | D43: 1343.45 | E43: 97 | F43: 1371.15 | G43: 939.25 | H43: 99 | I43: 3
A44: B0050IHH4E | B44: 40.979 | C44: FR | D44: 1311.73 | E44: 80 | F44: 1298.23 | G44: 732.37 | H44: 79 | I44: 1
A45: B08L9D9KR9 | B45: P202VAL001 | C45: DE | D45: 1292.31 | E45: 20 | F45: 1634.77 | G45: 1125 | H45: 25
A46: B09B47S644 | B46: P101CUD501 | C46: FR | D46: 1279.52 | E46: 44 | F46: 1279.52 | G46: 908.6 | H46: 44 | I46: 3
A47: B0BNNH9RZQ | B47: P302VIS060 | C47: FR | D47: 1266.84 | E47: 102 | F47: 1254.42 | G47: 767.33 | H47: 101 | I47: 4
A48: B09B47S644 | B48: P101CUD501 | C48: DE | D48: 1264.5 | E48: 42 | F48: 1266.54 | G48: 877.8 | H48: 42 | I48: 5
A49: B076QCMZX1 | B49: 40.821 | C49: IT | D49: 1257.63 | E49: 103 | F49: 1221 | G49: 849.15 | H49: 100 | I49: 7
A50: B07Q38Z7CK | B50: BC.060 | C50: IT | D50: 1245.32 | E50: 59 | F50: 1224.91 | G50: 870 | H50: 58
A51: B0B2F48ZMP | B51: P102GEL100 | C51: FR | D51: 1159.67 | E51: 30 | F51: 1121.84 | G51: 867.68 | H51: 29 | I51: 2
A52: B09NBXYF5J | B52: P101TOS002 | C52: FR | D52: 1124.64 | E52: 50 | F52: 562.32 | G52: 320.75 | H52: 25
A53: B0050IHH4E | B53: 40.979 | C53: ES | D53: 1087.35 | E53: 80 | F53: 901.68 | G53: 652.98 | H53: 66 | I53: 4
A54: B0CHWMFNNT | B54: P202ASP250 | C54: FR | D54: 1081.08 | E54: 26 | F54: 1164.24 | G54: 840 | H54: 28
A55: B07W7S9KYM | B55: BB.200 | C55: IT | D55: 1070.5 | E55: 27 | F55: 1193.19 | G55: 1181.1 | H55: 30 | I55: 20
A56: B095PQJGKX | B56: C107UTT002 | C56: IT | D56: 1060.56 | E56: 95 | F56: 1021.27 | G56: 486.68 | H56: 92 | I56: 1
A57: B07TQVD94L | B57: BP.690 | C57: IT | D57: 1029.42 | E57: 42 | F57: 1029.42 | G57: 1134 | H57: 42 | I57: 1
A58: B0BD83RNDG | B58: C106CAS002 | C58: IT | D58: 981.68 | E58: 89 | F58: 981.68 | G58: 635.2 | H58: 89 | I58: 1
A59: B09D8G2H7Q | B59: P102SBA500 | C59: FR | D59: 964.47 | E59: 9 | F59: 858.1 | G59: 646.4 | H59: 8 | I59: 4
A60: B095PQJGKX | B60: C107UTT002 | C60: ES | D60: 930.52 | E60: 77 | F60: 955.14 | G60: 422.14 | H60: 79 | I60: 4
A61: B076DCL19C | B61: BP.720 | C61: IT | D61: 910.1 | E61: 19 | F61: 958 | G61: 788.85 | H61: 20
A62: B097HRQNRG | B62: P101FRI100 | C62: DE | D62: 909.23 | E62: 31 | F62: 1026.55 | G62: 787.5 | H62: 35 | I62: 2
A63: B0CHFQXMZX | B63: P203PAN001 | C63: FR | D63: 897.75 | E63: 57 | F63: 913.5 | G63: 551 | H63: 58 | I63: 4
A64: B07B9CPH62 | B64: BG.200Y | C64: FR | D64: 891.94 | E64: 12 | F64: 891.94 | G64: 486 | H64: 12
A65: B0BD4VX5JB | B65: P203PAN002 | C65: IT | D65: 889.57 | E65: 9 | F65: 975.4 | G65: 579.8 | H65: 10 | I65: 13
A66: B0B39H1Z8J | B66: C106CAS001 | C66: IT | D66: 882.01 | E66: 80 | F66: 819.73 | G66: 405.5 | H66: 74 | I66: 3
A67: B073B67PLQ | B67: 90.884 | C67: FR | D67: 878.9 | E67: 11 | F67: 878.9 | G67: 742.5 | H67: 11 | I67: 2
A68: B01M4O6145 | B68: 90.071 | C68: IT | D68: 877.63 | E68: 43 | F68: 918.45 | G68: 838.45 | H68: 45 | I68: 2
A69: B09495C38F | B69: P204FER002 | C69: IT | D69: 864.43 | E69: 53 | F69: 799.19 | G69: 581.63 | H69: 49 | I69: 3
A70: B08FMLPKY9 | B70: P201UTP004 | C70: FR | D70: 845.58 | E70: 51 | F70: 878.74 | G70: 715.5 | H70: 53 | I70: 1
A71: B0BTHSH5MK | B71: C103ACC001 | C71: FR | D71: 841.5 | E71: 102 | F71: 849.75 | G71: 607.55 | H71: 103
A72: B085R2GCKX | B72: 40.332 | C72: DE | D72: 840.52 | E72: 50 | F72: 823.8 | G72: 551.25 | H72: 49 | I72: 6
A73: B076QFRRZ5 | B73: 40.931 | C73: IT | D73: 818.58 | E73: 57 | F73: 742.35 | G73: 328.94 | H73: 51 | I73: 9
A74: B0CLVS3FH6 | B74: P201UTP111 | C74: IT | D74: 815.5 | E74: 50 | F74: 603.47 | G74: 518 | H74: 37 | I74: 31
A75: B0CPFRMPTM | B75: P101CAF001 | C75: ES | D75: 815.43 | E75: 33 | F75: 766.01 | G75: 821.5 | H75: 31
A76: B011LFVLW8 | B76: 90.620 | C76: IT | D76: 784.8 | E76: 24 | F76: 719.4 | G76: 594 | H76: 22 | I76: 2
A77: B08FDYW72J | B77: P101CUD100 | C77: FR | D77: 772.52 | E77: 31 | F77: 797.44 | G77: 648 | H77: 32 | I77: 1
A78: B08JYWF3PK | B78: C102COC101 | C78: IT | D78: 765.85 | E78: 85 | F78: 783.87 | G78: 522 | H78: 87
A79: B0CFB71DMN | B79: C203PUL004 | C79: FR | D79: 752.58 | E79: 113 | F79: 752.58 | G79: 328.65 | H79: 113
A80: B0B39H1Z8J | B80: C106CAS001 | C80: ES | D80: 735.54 | E80: 69 | F80: 692.9 | G80: 372.45 | H80: 65 | I80: 1
A81: B09KYD9JGY | B81: P301PIS100 | C81: IT | D81: 734.95 | E81: 31 | F81: 681.35 | G81: 433.84 | H81: 29 | I81: 3
A82: B09146GTKW | B82: P302VIS002 | C82: FR | D82: 726 | E82: 88 | F82: 734.25 | G82: 534 | H82: 89 | I82: 1
A83: B0CHFQXMZX | B83: P203PAN001 | C83: ES | D83: 718.52 | E83: 46 | F83: 796.62 | G83: 484.5 | H83: 51 | I83: 24
A84: B0CLVS3FH6 | B84: P201UTP111 | C84: DE | D84: 716.28 | E84: 38 | F84: 716.28 | G84: 532 | H84: 38 | I84: 2
A85: B084TGLSDV | B85: C102BOT004 | C85: IT | D85: 694.56 | E85: 118 | F85: 475.28 | G85: 242.27 | H85: 80 | I85: 1
A86: B097HRQNRG | B86: P101FRI100 | C86: FR | D86: 673.08 | E86: 21 | F86: 817.58 | G86: 585 | H86: 26 | I86: 1
A87: B07MC8ZVRM | B87: 40.452 | C87: FR | D87: 672.84 | E87: 27 | F87: 598.08 | G87: 432.81 | H87: 24
A88: B0BVBY1RWS | B88: P206VEN550 | C88: DE | D88: 670.88 | E88: 16 | F88: 670.88 | G88: 560 | H88: 16 | I88: 7
A89: B08JYWF3PK | B89: C102COC101 | C89: FR | D89: 660 | E89: 80 | F89: 635.25 | G89: 462 | H89: 77 | I89: 1
A90: B09ZBHJ91Q | B90: P201UTP100 | C90: IT | D90: 637.1 | E90: 46 | F90: 581.7 | G90: 441 | H90: 42
A91: B07B9CPH62 | B91: BG.200Y | C91: DE | D91: 620.5 | E91: 12 | F91: 621.85 | G91: 486 | H91: 12
A92: B097HRQNRG | B92: P101FRI100 | C92: IT | D92: 600.81 | E92: 21 | F92: 726.98 | G92: 585 | H92: 26 | I92: 1
A93: B076Q7BR6F | B93: BC.041N | C93: IT | D93: 584.31 | E93: 14 | F93: 584.31 | G93: 504 | H93: 14 | I93: 2
A94: B09BD8BG34 | B94: P301PIS001 | C94: ES | D94: 578.57 | E94: 47 | F94: 578.57 | G94: 413.6 | H94: 47 | I94: 10
A95: B07BHCZR84 | B95: BA.200Y | C95: IT | D95: 573.23 | E95: 47 | F95: 548.81 | G95: 378.51 | H95: 45 | I95: 1
A96: B079SB5VJZ | B96: 50451 | C96: IT | D96: 572.62 | E96: 13 | F96: 572.62 | G96: 438.75 | H96: 13 | I96: 3
A97: B01CNX71NA | B97: 90.871 | C97: IT | D97: 572.22 | E97: 5 | F97: 572.22 | G97: 332.5 | H97: 5
A98: B07ZJQTGG8 | B98: 50.245 | C98: FR | D98: 571.32 | E98: 46 | F98: 583.74 | G98: 396.21 | H98: 47
A99: B09968BKDS | B99: P102FRU003 | C99: IT | D99: 560.5 | E99: 40 | F99: 546 | G99: 370.03 | H99: 39
A100: B0BHHV552D | B100: P203TER201 | C100: FR | D100: 553.42 | E100: 31 | F100: 536.84 | G100: 295.75 | H100: 30 | I100: 20
A101: B0BBH12BYN | B101: P101COS001 | C101: DE | D101: 549.6 | E101: 6 | F101: 641.2 | G101: 446.92 | H101: 7 | I101: 1
A102: B0B8JVTQYQ | B102: P101CUD200 | C102: ES | D102: 544.44 | E102: 12 | F102: 499.07 | G102: 378 | H102: 11
A103: B0BBH12BYN | B103: P101COS001 | C103: ES | D103: 540.48 | E103: 6 | F103: 540.48 | G103: 345.17 | H103: 6
A104: B096MX229M | B104: P102ROB050 | C104: IT | D104: 540.46 | E104: 44 | F104: 540.46 | G104: 334.4 | H104: 44 | I104: 2
A105: B08GS7XW73 | B105: P204FER250 | C105: IT | D105: 521.92 | E105: 32 | F105: 489.3 | G105: 391.5 | H105: 30 | I105: 1
A106: B07NQ2VYGD | B106: BT.710Y | C106: ES | D106: 516.93 | E106: 21 | F106: 294.54 | G106: 174 | H106: 12
A107: B085JHSWJH | B107: BP.802 | C107: FR | D107: 516.75 | E107: 39 | F107: 516.75 | G107: 331.1 | H107: 39
A108: B08B8M2B7B | B108: P102EST001 | C108: IT | D108: 490.5 | E108: 15 | F108: 490.5 | G108: 315.67 | H108: 15
A109: B0B39H1Z8J | B109: C106CAS001 | C109: FR | D109: 483.75 | E109: 45 | F109: 430 | G109: 222 | H109: 40
A110: B0B3N9ZNT2 | B110: P101CUD051 | C110: IT | D110: 480.69 | E110: 15 | F110: 480.69 | G110: 349.86 | H110: 15 | I110: 2
A111: B09BD8BG34 | B111: P301PIS001 | C111: FR | D111: 471.96 | E111: 38 | F111: 409.86 | G111: 290.4 | H111: 33 | I111: 1
A112: B08HCT78N3 | B112: P202ASP400 | C112: IT | D112: 465.08 | E112: 44 | F112: 475.65 | G112: 297 | H112: 45 | I112: 2
A113: B07KYWNC7Z | B113: 40.405 | C113: IT | D113: 464.25 | E113: 21 | F113: 443.84 | G113: 333 | H113: 20 | I113: 2
A114: B07P7GGGQM | B114: BP.961 | C114: DE | D114: 461.23 | E114: 11 | F114: 587.02 | G114: 504 | H114: 14 | I114: 1
...

Sheet seller_02_2024
A1: amazon-order-id | B1: merchant-order-id | C1: purchase-date | D1: last-updated-date | E1: order-status | F1: fulfillment-channel | G1: sales-channel | H1: order-channel | I1: url | J1: ship-service-level | K1: product-name | L1: sku | M1: asin | N1: item-status | O1: quantity | P1: currency | Q1: item-price | R1: item-tax | S1: shipping-price | T1: shipping-tax | U1: gift-wrap-price | V1: gift-wrap-tax | W1: item-promotion-discount | X1: ship-promotion-discount | Y1: ship-city | Z1: ship-state | AA1: ship-postal-code | AB1: ship-country | AC1: promotion-ids | AD1: buyer-company-name | AE1: buyer-cst-number | AF1: buyer-vat-number | AG1: buyer-tax-registration-id | AH1: buyer-tax-registration-country | AI1: buyer-tax-registration-type
A2: 405-5748540-3173901 | B2: 405-5748540-3173901 | C2: 2024-02-29T20:28:36+00:00 | D2: 2024-03-04T01:15:21+00:00 | E2: Shipped | F2: Amazon | G2: Amazon.fr | J2: Standard | K2: BEPER BT.710Y Crêpière électrique avec poignée, 800 W, plaque en aluminium avec revêtement antiadhésif, rouge | L2: BT.710Y_FBA | M2: B07NQ2VYGD | N2: Shipped | O2: 1 | P2: EUR | Q2: 39.9 | R2: 6.65 | S2: 0.83 | X2: 0.83 | Y2: Bagneux | AA2: 92220 | AB2: FR | AC2: Free Shipping 2017/10/17 17-17-37-677
A3: 171-3315909-6981140 | B3: 171-3315909-6981140 | C3: 2024-02-29T20:20:43+00:00 | D3: 2024-03-01T16:30:40+00:00 | E3: Shipped | F3: Amazon | G3: Amazon.fr | J3: Standard | K3: BEPER BT.710Y Crêpière électrique avec poignée, 800 W, plaque en aluminium avec revêtement antiadhésif, rouge | L3: BT.710Y_FBA | M3: B07NQ2VYGD | N3: Shipped | O3: 1 | P3: EUR | Q3: 39.9 | R3: 6.65 | S3: 1.67 | X3: 1.67 | Y3: Vaux le pénil | AA3: 77000 | AB3: FR | AC3: Free Shipping 2017/10/17 17-17-37-677
A4: 404-7228953-0182728 | B4: 404-7228953-0182728 | C4: 2024-02-29T19:06:50+00:00 | D4: 2024-03-01T10:56:11+00:00 | E4: Shipped | F4: Amazon | G4: Amazon.fr | J4: Standard | K4: BEPER BT.710Y Crêpière électrique avec poignée, 800 W, plaque en aluminium avec revêtement antiadhésif, rouge | L4: BT.710Y_FBA | M4: B07NQ2VYGD | N4: Shipped | O4: 1 | P4: EUR | Q4: 39.9 | R4: 6.65 | Y4: LE MANS | AA4: 72100 | AB4: FR | AC4: Free Shipping 2017/10/17 17-17-37-677
A5: 404-5208901-0567553 | B5: 404-5208901-0567553 | C5: 2024-02-29T16:51:11+00:00 | D5: 2024-03-01T10:32:06+00:00 | E5: Shipped | F5: Amazon | G5: Amazon.fr | J5: Expedited | K5: BEPER 50.700 Nettoyeur Vapeur pour Sol, Canapé, Tapis - Nettoyant Vapeur, 135° max, câble de 3 Mètres, 350 ml | L5: 50.700_FBA | M5: B01MTSEGF9 | N5: Shipped | O5: 1 | P5: EUR | Q5: 49.9 | R5: 8.32 | Y5: Roissy-en-France | Z5: IDF | AA5: 95700 | AB5: FR
A6: 403-1479699-4346739 | B6: 403-1479699-4346739 | C6: 2024-02-29T16:04:25+00:00 | D6: 2024-02-29T16:20:22+00:00 | E6: Cancelled | F6: Amazon | G6: Amazon.fr | J6: Expedited | K6: Beper - Machine à Pop-Corn, Pop-Corn en 3 Minutes, Sans Matières Grasses, Circulation d'Air Chaud, Puissance 1200W - Rouge [Classe d'efficacité én | L6: 90.590Y_FBA | M6: B01KMJ9OXW | N6: Cancelled | O6: 0 | Y6: St Aunes | AA6: 34130 | AB6: FR
A7: 403-4262482-2499565 | B7: 403-4262482-2499565 | C7: 2024-02-29T14:19:31+00:00 | D7: 2024-02-29T23:45:05+00:00 | E7: Shipped | F7: Amazon | G7: Amazon.fr | J7: Standard | K7: Beper - Machine à Pop-Corn, Pop-Corn en 3 Minutes, Sans Matières Grasses, Circulation d'Air Chaud, Puissance 1200W - Rouge [Classe d'efficacité én | L7: 90.590Y_FBA | M7: B01KMJ9OXW | N7: Shipped | O7: 1 | P7: EUR | Q7: 44.9 | R7: 7.79 | S7: 2.47 | X7: 2.47 | Y7: Strepy-bracquegnies | AA7: 7110 | AB7: BE | AC7: Free Shipping 2017/10/17 17-17-37-677
A8: 404-7699547-2737150 | B8: 404-7699547-2737150 | C8: 2024-02-29T13:44:12+00:00 | D8: 2024-02-29T21:31:36+00:00 | E8: Shipped | F8: Amazon | G8: Amazon.fr | J8: Expedited | K8: BEPER BT.710Y Crêpière électrique avec poignée, 800 W, plaque en aluminium avec revêtement antiadhésif, rouge | L8: BT.710Y_FBA | M8: B07NQ2VYGD | N8: Shipped | O8: 2 | P8: EUR | Q8: 79.8 | R8: 13.3 | Y8: NICE | Z8: - | AA8: 6000 | AB8: FR
A9: 407-2306782-6777128 | B9: 407-2306782-6777128 | C9: 2024-02-29T13:26:54+00:00 | D9: 2024-03-01T03:26:36+00:00 | E9: Shipped | F9: Amazon | G9: Amazon.fr | J9: Expedited | K9: Beper - Vert & Blanc Sauna Facial et Aromathérapie 2 Puissances, Traitements Curatifs et Relaxants, Hydratation et Nettoyage du Visage, Réservoir d' | L9: 40.967N_FBA | M9: B00FAJUDU8 | N9: Shipped | O9: 1 | P9: EUR | Q9: 39.9 | R9: 6.65 | Y9: Paris | AA9: 75017 | AB9: FR
A10: 404-9509364-4987529 | B10: 404-9509364-4987529 | C10: 2024-02-28T19:06:05+00:00 | D10: 2024-02-29T07:52:17+00:00 | E10: Shipped | F10: Amazon | G10: Amazon.fr | J10: Expedited | K10: Beper - Machine à Pop-Corn, Pop-Corn en 3 Minutes, Sans Matières Grasses, Circulation d'Air Chaud, Puissance 1200W - Rouge [Classe d'efficacité én | L10: 90.590Y_FBA | M10: B01KMJ9OXW | N10: Shipped | O10: 1 | P10: EUR | Q10: 44.9 | R10: 7.48 | Y10: Merignac | AA10: 33700 | AB10: FR
A11: 406-4079321-5371530 | B11: 406-4079321-5371530 | C11: 2024-02-28T13:42:28+00:00 | D11: 2024-03-07T02:27:35+00:00 | E11: Shipped | F11: Amazon | G11: Amazon.fr | J11: Expedited | K11: BEPER Distributeur automatique de couvre-chaussures, ABS, blanc, taille unique | L11: C206UTI001_FBA | M11: B08JM7SZ36 | N11: Shipped | O11: 2 | P11: EUR | Q11: 99.8 | R11: 16.64 | Y11: ST TROPEZ | AA11: 83990 | AB11: FR
A12: 171-0524532-6619517 | B12: 171-0524532-6619517 | C12: 2024-02-28T12:13:56+00:00 | D12: 2024-02-29T01:30:46+00:00 | E12: Shipped | F12: Amazon | G12: Amazon.fr | J12: Expedited | K12: BEPER BT.602H Gaufrier 700W Cable poignée Thermo-Isolante, Rouge/Blanc | L12: BT.602H_FBA | M12: B076DCKSTJ | N12: Shipped | O12: 1 | P12: EUR | Q12: 34.9 | R12: 5.82 | Y12: Fouras | AA12: 17450 | AB12: FR
A13: 171-6271965-1018725 | B13: 171-6271965-1018725 | C13: 2024-02-28T10:39:57+00:00 | D13: 2024-02-29T01:32:32+00:00 | E13: Shipped | F13: Amazon | G13: Amazon.fr | J13: Expedited | K13: BEPER 50.700 Nettoyeur Vapeur pour Sol, Canapé, Tapis - Nettoyant Vapeur, 135° max, câble de 3 Mètres, 350 ml | L13: 50.700_FBA | M13: B01MTSEGF9 | N13: Shipped | O13: 1 | P13: EUR | Q13: 49.9 | R13: 8.32 | Y13: Toulouse | AA13: 31100 | AB13: FR
A14: 406-2825047-4865914 | B14: 406-2825047-4865914 | C14: 2024-02-28T08:21:01+00:00 | D14: 2024-02-28T12:30:39+00:00 | E14: Shipped | F14: Amazon | G14: Amazon.fr | J14: Expedited | K14: BEPER BT.710Y Crêpière électrique avec poignée, 800 W, plaque en aluminium avec revêtement antiadhésif, rouge | L14: BT.710Y_FBA | M14: B07NQ2VYGD | N14: Shipped | O14: 1 | P14: EUR | Q14: 39.9 | R14: 6.65 | Y14: Oloron sainte marie | AA14: 64400 | AB14: FR
A15: 407-3195543-2260353 | B15: 407-3195543-2260353 | C15: 2024-02-27T21:03:55+00:00 | D15: 2024-03-02T00:02:05+00:00 | E15: Shipped | F15: Amazon | G15: Amazon.fr | J15: Standard | K15: BEPER BT.710Y Crêpière électrique avec poignée, 800 W, plaque en aluminium avec revêtement antiadhésif, rouge | L15: BT.710Y_FBA | M15: B07NQ2VYGD | N15: Shipped | O15: 1 | P15: EUR | Q15: 39.9 | R15: 6.65 | S15: 0.27 | X15: 0.27 | Y15: Bordeaux | AA15: 33000 | AB15: FR | AC15: Free Shipping 2017/10/17 17-17-37-677
A16: 405-4938954-9370745 | B16: 405-4938954-9370745 | C16: 2024-02-27T19:36:32+00:00 | D16: 2024-02-28T15:21:21+00:00 | E16: Shipped | F16: Amazon | G16: Amazon.fr | J16: Expedited | K16: Beper - Machine à Pop-Corn, Pop-Corn en 3 Minutes, Sans Matières Grasses, Circulation d'Air Chaud, Puissance 1200W - Rouge [Classe d'efficacité én | L16: 90.590Y_FBA | M16: B01KMJ9OXW | N16: Shipped | O16: 1 | P16: EUR | Q16: 44.9 | R16: 7.48 | Y16: Bonneville Avit Fumadieres | AA16: 24230 | AB16: FR
A17: 403-4114106-8420368 | B17: 403-4114106-8420368 | C17: 2024-02-27T18:42:11+00:00 | D17: 2024-02-28T02:27:34+00:00 | E17: Shipped | F17: Amazon | G17: Amazon.fr | J17: Expedited | K17: BEPER BT.710Y Crêpière électrique avec poignée, 800 W, plaque en aluminium avec revêtement antiadhésif, rouge | L17: BT.710Y_FBA | M17: B07NQ2VYGD | N17: Shipped | O17: 1 | P17: EUR | Q17: 39.9 | R17: 6.65 | Y17: bazancourt | AA17: 51110 | AB17: FR
A18: 403-3306891-3853917 | B18: 403-3306891-3853917 | C18: 2024-02-27T17:18:33+00:00 | D18: 2024-02-29T03:52:29+00:00 | E18: Shipped | F18: Amazon | G18: Amazon.fr | J18: Standard | K18: BEPER BT.710Y Crêpière électrique avec poignée, 800 W, plaque en aluminium avec revêtement antiadhésif, rouge | L18: BT.710Y_FBA | M18: B07NQ2VYGD | N18: Shipped | O18: 1 | P18: EUR | Q18: 39.9 | R18: 6.65 | S18: 3.32 | X18: 3.32 | Y18: Orange | Z18: Vaucluse | AA18: 84100 | AB18: FR | AC18: Free Shipping 2017/10/17 17-17-37-677
A19: 404-1236735-1081902 | B19: 404-1236735-1081902 | C19: 2024-02-27T16:15:10+00:00 | D19: 2024-02-28T12:20:09+00:00 | E19: Shipped | F19: Amazon | G19: Amazon.fr | J19: Standard | K19: Beper - Cuiseur à Vapeur Multicombustion de 5L, Économiseur d'Espace, Minuterie de 60 minutes, Cuisson à la Vapeur Saine, Puissance 400-500W - Arge | L19: BC.261_FBA | M19: B08485QRVZ | N19: Shipped | O19: 1 | P19: EUR | Q19: 39.9 | R19: 6.65 | S19: 3.32 | X19: 3.32 | Y19: Saint-Amand-Montrond | AA19: 18200 | AB19: FR | AC19: Free Shipping 2017/10/17 17-17-37-677
A20: 171-9512897-1425940 | B20: 171-9512897-1425940 | C20: 2024-02-27T14:22:29+00:00 | D20: 2024-02-28T11:08:14+00:00 | E20: Shipped | F20: Amazon | G20: Amazon.fr | J20: Standard | K20: Beper BF.640 - Four ventilé multifonction 12L Anneau de rallonge pour capacité totale 18L Minuterie 60 minutes Température réglable jusqu'à 250° | L20: BF.640_FBA | M20: B07YBN2FS3 | N20: Shipped | O20: 1 | P20: EUR | Q20: 99 | R20: 16.5 | Y20: LABASTIDE ST PIERRE | AA20: 82370 | AB20: FR | AC20: Free Shipping 2017/10/17 17-17-37-677
A21: 403-4162250-7026753 | B21: 403-4162250-7026753 | C21: 2024-02-27T09:08:12+00:00 | D21: 2024-02-27T09:25:03+00:00 | E21: Cancelled | F21: Amazon | G21: Amazon.fr | J21: Standard | K21: BEPER BT.710Y Crêpière électrique avec poignée, 800 W, plaque en aluminium avec revêtement antiadhésif, rouge | L21: BT.710Y_FBA | M21: B07NQ2VYGD | N21: Cancelled | O21: 0 | Y21: LAMORLAYE | AA21: 60260 | AB21: FR | AC21: Free Shipping 2017/10/17 17-17-37-677
A22: 405-2195406-4629145 | B22: 405-2195406-4629145 | C22: 2024-02-27T07:48:46+00:00 | D22: 2024-02-27T20:26:41+00:00 | E22: Shipped | F22: Amazon | G22: Amazon.fr | J22: Expedited | K22: BEPER 50.700 Nettoyeur Vapeur pour Sol, Canapé, Tapis - Nettoyant Vapeur, 135° max, câble de 3 Mètres, 350 ml | L22: 50.700_FBA | M22: B01MTSEGF9 | N22: Shipped | O22: 1 | P22: EUR | Q22: 49.9 | R22: 8.32 | Y22: Montpellier | AA22: 34000 | AB22: FR
A23: 402-6733882-9715545 | B23: 402-6733882-9715545 | C23: 2024-02-27T02:16:39+00:00 | D23: 2024-02-27T02:31:50+00:00 | E23: Cancelled | F23: Amazon | G23: Amazon.fr | J23: Standard | K23: BEPER BT.710Y Crêpière électrique avec poignée, 800 W, plaque en aluminium avec revêtement antiadhésif, rouge | L23: BT.710Y_FBA | M23: B07NQ2VYGD | N23: Cancelled | O23: 0 | Y23: LE BLANC MESNIL | AA23: 93150 | AB23: FR
A24: 404-3961814-0651540 | B24: 404-3961814-0651540 | C24: 2024-02-27T00:54:11+00:00 | D24: 2024-02-28T03:49:46+00:00 | E24: Shipped | F24: Amazon | G24: Amazon.fr | J24: Standard | K24: BEPER BT.710Y Crêpière électrique avec poignée, 800 W, plaque en aluminium avec revêtement antiadhésif, rouge | L24: BT.710Y_FBA | M24: B07NQ2VYGD | N24: Shipped | O24: 1 | P24: EUR | Q24: 39.9 | R24: 6.65 | S24: 3.32 | X24: 3.32 | Y24: Marseille | AA24: 13006 | AB24: FR | AC24: Free Shipping 2017/10/17 17-17-37-677
A25: 407-6426127-6527546 | B25: 407-6426127-6527546 | C25: 2024-02-26T22:30:28+00:00 | D25: 2024-02-28T12:21:08+00:00 | E25: Shipped | F25: Amazon | G25: Amazon.fr | J25: Standard | K25: Beper - Machine à Pop-Corn, Pop-Corn en 3 Minutes, Sans Matières Grasses, Circulation d'Air Chaud, Puissance 1200W - Rouge [Classe d'efficacité én | L25: 90.590Y_FBA | M25: B01KMJ9OXW | N25: Shipped | O25: 1 | P25: EUR | Q25: 44.9 | R25: 7.48 | S25: 0.83 | X25: 0.83 | Y25: Croix | AA25: 59170 | AB25: FR | AC25: Free Shipping 2017/10/17 17-17-37-677
A26: 407-8680279-9617150 | B26: 407-8680279-9617150 | C26: 2024-02-26T22:25:07+00:00 | D26: 2024-02-28T22:12:39+00:00 | E26: Shipped | F26: Amazon | G26: Amazon.fr | J26: Standard | K26: Beper - Machine à Pop-Corn, Pop-Corn en 3 Minutes, Sans Matières Grasses, Circulation d'Air Chaud, Puissance 1200W - Rouge [Classe d'efficacité én | L26: 90.590Y_FBA | M26: B01KMJ9OXW | N26: Shipped | O26: 1 | P26: EUR | Q26: 44.9 | R26: 7.48 | S26: 0.83 | X26: 0.83 | Y26: Arcueil | AA26: 94110 | AB26: FR | AC26: Free Shipping 2017/10/17 17-17-37-677
A27: 403-6501864-4350727 | B27: 403-6501864-4350727 | C27: 2024-02-26T21:19:43+00:00 | D27: 2024-02-27T04:56:50+00:00 | E27: Shipped | F27: Amazon | G27: Amazon.fr | J27: Standard | K27: BEPER BT.710Y Crêpière électrique avec poignée, 800 W, plaque en aluminium avec revêtement antiadhésif, rouge | L27: BT.710Y_FBA | M27: B07NQ2VYGD | N27: Shipped | O27: 1 | P27: EUR | Q27: 39.9 | R27: 6.65 | S27: 3.32 | X27: 3.32 | Y27: L'Isle-sur-la-Sorgue | AA27: 84800 | AB27: FR | AC27: Free Shipping 2017/10/17 17-17-37-677
A28: 405-9914630-9017966 | B28: 405-9914630-9017966 | C28: 2024-02-26T19:29:42+00:00 | D28: 2024-02-27T07:52:25+00:00 | E28: Shipped | F28: Amazon | G28: Amazon.fr | J28: Standard | K28: BEPER BT.710Y Crêpière électrique avec poignée, 800 W, plaque en aluminium avec revêtement antiadhésif, rouge | L28: BT.710Y_FBA | M28: B07NQ2VYGD | N28: Shipped | O28: 1 | P28: EUR | Q28: 39.9 | R28: 6.65 | Y28: St Herblain | AA28: 44800 | AB28: FR | AC28: Free Shipping 2017/10/17 17-17-37-677
A29: 404-7268355-1429934 | B29: 404-7268355-1429934 | C29: 2024-02-26T17:42:54+00:00 | D29: 2024-02-27T00:28:52+00:00 | E29: Shipped | F29: Amazon | G29: Amazon.fr | J29: Expedited | K29: BEPER BT.710Y Crêpière électrique avec poignée, 800 W, plaque en aluminium avec revêtement antiadhésif, rouge | L29: BT.710Y_FBA | M29: B07NQ2VYGD | N29: Shipped | O29: 1 | P29: EUR | Q29: 39.9 | R29: 6.65 | Y29: algolsheim | AA29: 68600 | AB29: FR
A30: 405-2022639-4876344 | B30: 405-2022639-4876344 | C30: 2024-02-26T15:37:10+00:00 | D30: 2024-02-27T04:33:48+00:00 | E30: Shipped | F30: Amazon | G30: Amazon.fr | J30: Standard | K30: BEPER BT.710Y Crêpière électrique avec poignée, 800 W, plaque en aluminium avec revêtement antiadhésif, rouge | L30: BT.710Y_FBA | M30: B07NQ2VYGD | N30: Shipped | O30: 1 | P30: EUR | Q30: 39.9 | R30: 6.65 | S30: 3.32 | X30: 3.32 | Y30: Pierrefitte Sur Seine | AA30: 93380 | AB30: FR | AC30: Free Shipping 2017/10/17 17-17-37-677
A31: 405-0037849-7716361 | B31: 405-0037849-7716361 | C31: 2024-02-26T13:15:37+00:00 | D31: 2024-02-27T04:56:24+00:00 | E31: Shipped | F31: Amazon | G31: Amazon.fr | J31: Expedited | K31: BEPER BT.710Y Crêpière électrique avec poignée, 800 W, plaque en aluminium avec revêtement antiadhésif, rouge | L31: BT.710Y_FBA | M31: B07NQ2VYGD | N31: Shipped | O31: 1 | P31: EUR | Q31: 39.9 | R31: 6.65 | Y31: matemale | AA31: 66210 | AB31: FR
A32: 403-4571122-8710729 | B32: 403-4571122-8710729 | C32: 2024-02-26T12:46:40+00:00 | D32: 2024-02-26T19:24:30+00:00 | E32: Shipped | F32: Amazon | G32: Amazon.fr | J32: Expedited | K32: Beper BF.640 - Four ventilé multifonction 12L Anneau de rallonge pour capacité totale 18L Minuterie 60 minutes Température réglable jusqu'à 250° | L32: BF.640_FBA | M32: B07YBN2FS3 | N32: Shipped | O32: 1 | P32: EUR | Q32: 99 | R32: 16.5 | Y32: VITRY SUR SEINE | AA32: 94400 | AB32: FR
A33: 171-3587644-2609900 | B33: 171-3587644-2609900 | C33: 2024-02-26T12:23:35+00:00 | D33: 2024-02-27T02:30:25+00:00 | E33: Shipped | F33: Amazon | G33: Amazon.fr | J33: Expedited | K33: BEPER BT.710Y Crêpière électrique avec poignée, 800 W, plaque en aluminium avec revêtement antiadhésif, rouge | L33: BT.710Y_FBA | M33: B07NQ2VYGD | N33: Shipped | O33: 2 | P33: EUR | Q33: 79.8 | R33: 13.84 | Y33: Anderlecht | AA33: 1070 | AB33: BE
A34: 404-7410750-3447546 | B34: 404-7410750-3447546 | C34: 2024-02-26T08:32:20+00:00 | D34: 2024-02-27T09:15:51+00:00 | E34: Shipped | F34: Amazon | G34: Amazon.fr | J34: Expedited | K34: Beper - Machine à Pop-Corn, Pop-Corn en 3 Minutes, Sans Matières Grasses, Circulation d'Air Chaud, Puissance 1200W - Rouge [Classe d'efficacité én | L34: 90.590Y_FBA | M34: B01KMJ9OXW | N34: Shipped | O34: 1 | P34: EUR | Q34: 44.9 | R34: 7.48 | Y34: La Penne | AA34: 6260 | AB34: FR
A35: 407-8147695-4288363 | B35: 407-8147695-4288363 | C35: 2024-02-25T22:12:57+00:00 | D35: 2024-02-26T02:21:03+00:00 | E35: Shipped | F35: Amazon | G35: Amazon.fr | J35: Expedited | K35: BEPER BT.710Y Crêpière électrique avec poignée, 800 W, plaque en aluminium avec revêtement antiadhésif, rouge | L35: BT.710Y_FBA | M35: B07NQ2VYGD | N35: Shipped | O35: 1 | P35: EUR | Q35: 39.9 | R35: 6.65 | Y35: Ivry Sur Seine | AA35: 94200 | AB35: FR
A36: 407-5366691-0114743 | B36: 407-5366691-0114743 | C36: 2024-02-25T21:56:39+00:00 | D36: 2024-02-26T12:20:11+00:00 | E36: Shipped | F36: Amazon | G36: Amazon.fr | J36: Expedited | K36: Beper - Machine à Pop-Corn, Pop-Corn en 3 Minutes, Sans Matières Grasses, Circulation d'Air Chaud, Puissance 1200W - Rouge [Classe d'efficacité én | L36: 90.590Y_FBA | M36: B01KMJ9OXW | N36: Shipped | O36: 1 | P36: EUR | Q36: 44.9 | R36: 7.48 | Y36: Lyon | AA36: 69004 | AB36: FR
A37: 171-8348783-6107561 | B37: 171-8348783-6107561 | C37: 2024-02-25T21:44:42+00:00 | D37: 2024-02-26T04:56:47+00:00 | E37: Shipped | F37: Amazon | G37: Amazon.fr | J37: Expedited | K37: BEPER BT.710Y Crêpière électrique avec poignée, 800 W, plaque en aluminium avec revêtement antiadhésif, rouge | L37: BT.710Y_FBA | M37: B07NQ2VYGD | N37: Shipped | O37: 1 | P37: EUR | Q37: 39.9 | R37: 6.65 | Y37: Beaumont de pertuis | AA37: 84120 | AB37: FR
A38: 408-7761563-3924340 | B38: 408-7761563-3924340 | C38: 2024-02-25T18:55:02+00:00 | D38: 2024-02-26T04:57:34+00:00 | E38: Shipped | F38: Amazon | G38: Amazon.fr | J38: Expedited | K38: BEPER BT.710Y Crêpière électrique avec poignée, 800 W, plaque en aluminium avec revêtement antiadhésif, rouge | L38: BT.710Y_FBA | M38: B07NQ2VYGD | N38: Shipped | O38: 1 | P38: EUR | Q38: 39.9 | R38: 6.65 | Y38: Marseille | AA38: 13006 | AB38: FR
A39: 171-6568599-5969115 | B39: 171-6568599-5969115 | C39: 2024-02-25T16:06:44+00:00 | D39: 2024-02-26T02:04:28+00:00 | E39: Shipped | F39: Amazon | G39: Amazon.fr | J39: Standard | K39: BEPER BT.710Y Crêpière électrique avec poignée, 800 W, plaque en aluminium avec revêtement antiadhésif, rouge | L39: BT.710Y_FBA | M39: B07NQ2VYGD | N39: Shipped | O39: 1 | P39: EUR | Q39: 39.9 | R39: 6.65 | Y39: ST RAMBERT EN BUGEY | AA39: 1230 | AB39: FR | AC39: Free Shipping 2017/10/17 17-17-37-677
A40: 407-9983301-1856328 | B40: 407-9983301-1856328 | C40: 2024-02-25T14:59:44+00:00 | D40: 2024-02-27T01:40:58+00:00 | E40: Shipped | F40: Amazon | G40: Amazon.fr | J40: Standard | K40: BEPER BT.700Y Crêpière électrique avec Spatule en Bois, 1300W, Plaque antiadhésive, Rouge | L40: BT.700Y_FBA | M40: B076D74TC7 | N40: Shipped | O40: 1 | P40: EUR | Q40: 49.9 | R40: 8.32 | S40: 3.32 | X40: 3.32 | Y40: Argenteuil | AA40: 95100 | AB40: FR | AC40: Free Shipping 2017/10/17 17-17-37-677
A41: 405-2584220-5019525 | B41: 405-2584220-5019525 | C41: 2024-02-25T10:58:52+00:00 | D41: 2024-02-26T12:46:39+00:00 | E41: Shipped | F41: Amazon | G41: Amazon.fr | J41: Expedited | K41: Beper - Machine à Pop-Corn, Pop-Corn en 3 Minutes, Sans Matières Grasses, Circulation d'Air Chaud, Puissance 1200W - Rouge [Classe d'efficacité én | L41: 90.590Y_FBA | M41: B01KMJ9OXW | N41: Shipped | O41: 1 | P41: EUR | Q41: 44.9 | R41: 7.48 | Y41: Serres sur Arget | AA41: 9000 | AB41: FR
A42: 407-7665869-5357945 | B42: 407-7665869-5357945 | C42: 2024-02-25T09:37:33+00:00 | D42: 2024-02-26T02:19:35+00:00 | E42: Shipped | F42: Amazon | G42: Amazon.fr | J42: Expedited | K42: BEPER BT.710Y Crêpière électrique avec poignée, 800 W, plaque en aluminium avec revêtement antiadhésif, rouge | L42: BT.710Y_FBA | M42: B07NQ2VYGD | N42: Shipped | O42: 1 | P42: EUR | Q42: 39.9 | R42: 6.92 | Y42: FLEMALLE | AA42: 4400 | AB42: BE
A43: 171-9679099-7329125 | B43: 171-9679099-7329125 | C43: 2024-02-24T22:35:02+00:00 | D43: 2024-02-26T23:43:54+00:00 | E43: Shipped | F43: Amazon | G43: Amazon.fr | J43: Expedited | K43: Beper - Machine à Pop-Corn, Pop-Corn en 3 Minutes, Sans Matières Grasses, Circulation d'Air Chaud, Puissance 1200W - Rouge [Classe d'efficacité én | L43: 90.590Y_FBA | M43: B01KMJ9OXW | N43: Shipped | O43: 1 | P43: EUR | Q43: 44.9 | R43: 7.48 | Y43: La Balme De Sillingy | Z43: France | AA43: 74330 | AB43: FR
A44: 171-5020831-7177168 | B44: 171-5020831-7177168 | C44: 2024-02-24T13:12:47+00:00 | D44: 2024-02-25T02:21:33+00:00 | E44: Shipped | F44: Amazon | G44: Amazon.fr | J44: Expedited | K44: BEPER BT.710Y Crêpière électrique avec poignée, 800 W, plaque en aluminium avec revêtement antiadhésif, rouge | L44: BT.710Y_FBA | M44: B07NQ2VYGD | N44: Shipped | O44: 1 | P44: EUR | Q44: 39.9 | R44: 6.65 | Y44: Savigny sur Orge | AA44: 91600 | AB44: FR
A45: 405-9091102-4597131 | B45: 405-9091102-4597131 | C45: 2024-02-24T10:47:35+00:00 | D45: 2024-02-25T02:21:33+00:00 | E45: Shipped | F45: Amazon | G45: Amazon.fr | J45: Expedited | K45: BEPER BT.710Y Crêpière électrique avec poignée, 800 W, plaque en aluminium avec revêtement antiadhésif, rouge | L45: BT.710Y_FBA | M45: B07NQ2VYGD | N45: Shipped | O45: 1 | P45: EUR | Q45: 39.9 | R45: 6.65 | Y45: Chilly Mazarin | AA45: 91380 | AB45: FR
A46: 403-0475192-7531548 | B46: 403-0475192-7531548 | C46: 2024-02-23T20:04:23+00:00 | D46: 2024-02-24T01:49:38+00:00 | E46: Shipped | F46: Amazon | G46: Amazon.fr | J46: Expedited | K46: Beper - Machine à Pop-Corn, Pop-Corn en 3 Minutes, Sans Matières Grasses, Circulation d'Air Chaud, Puissance 1200W - Rouge [Classe d'efficacité én | L46: 90.590Y_FBA | M46: B01KMJ9OXW | N46: Shipped | O46: 1 | P46: EUR | Q46: 44.9 | R46: 7.48 | S46: 6.99 | T46: 1.17 | Y46: Argentat-sur-Dordogne | AA46: 19400 | AB46: FR
A47: 406-8567071-0012303 | B47: 406-8567071-0012303 | C47: 2024-02-23T18:08:24+00:00 | D47: 2024-02-24T03:42:31+00:00 | E47: Shipped | F47: Amazon | G47: Amazon.fr | J47: Standard | K47: BEPER BT.710Y Crêpière électrique avec poignée, 800 W, plaque en aluminium avec revêtement antiadhésif, rouge | L47: BT.710Y_FBA | M47: B07NQ2VYGD | N47: Shipped | O47: 1 | P47: EUR | Q47: 39.9 | R47: 6.65 | Y47: Roullee | AA47: 72600 | AB47: FR | AC47: Free Shipping 2017/10/17 17-17-37-677
A48: 404-3547241-3770757 | B48: 404-3547241-3770757 | C48: 2024-02-23T15:53:38+00:00 | D48: 2024-02-26T02:02:57+00:00 | E48: Shipped | F48: Amazon | G48: Amazon.fr | J48: Standard | K48: Beper - Machine à Pop-Corn, Pop-Corn en 3 Minutes, Sans Matières Grasses, Circulation d'Air Chaud, Puissance 1200W - Rouge [Classe d'efficacité én | L48: 90.590Y_FBA | M48: B01KMJ9OXW | N48: Shipped | O48: 1 | P48: EUR | Q48: 44.9 | R48: 7.48 | S48: 3.32 | X48: 3.32 | Y48: CHAMPIEN | AA48: 80700 | AB48: FR | AC48: Free Shipping 2017/10/17 17-17-37-677
A49: 405-8245476-0164307 | B49: 405-8245476-0164307 | C49: 2024-02-23T14:45:33+00:00 | D49: 2024-02-24T00:35:17+00:00 | E49: Shipped | F49: Amazon | G49: Amazon.fr | J49: Standard | K49: BEPER BT.710Y Crêpière électrique avec poignée, 800 W, plaque en aluminium avec revêtement antiadhésif, rouge | L49: BT.710Y_FBA | M49: B07NQ2VYGD | N49: Shipped | O49: 1 | P49: EUR | Q49: 39.9 | R49: 6.65 | Y49: frencq | AA49: 62630 | AB49: FR | AC49: Free Shipping 2017/10/17 17-17-37-677
A50: 403-5716635-9883563 | B50: 403-5716635-9883563 | C50: 2024-02-23T14:43:09+00:00 | D50: 2024-02-23T14:44:04+00:00 | E50: Cancelled | F50: Amazon | G50: Amazon.fr | J50: Expedited | K50: BEPER BT.710Y Crêpière électrique avec poignée, 800 W, plaque en aluminium avec revêtement antiadhésif, rouge | L50: BT.710Y_FBA | M50: B07NQ2VYGD | N50: Cancelled | O50: 0 | Y50: Montivilliers | AA50: 76290 | AB50: FR
A51: 402-4115330-2318733 | B51: 402-4115330-2318733 | C51: 2024-02-23T10:47:33+00:00 | D51: 2024-02-24T00:35:30+00:00 | E51: Shipped | F51: Amazon | G51: Amazon.fr | J51: Expedited | K51: Beper - Machine à Pop-Corn, Pop-Corn en 3 Minutes, Sans Matières Grasses, Circulation d'Air Chaud, Puissance 1200W - Rouge [Classe d'efficacité én | L51: 90.590Y_FBA | M51: B01KMJ9OXW | N51: Shipped | O51: 1 | P51: EUR | Q51: 44.9 | R51: 7.48 | Y51: GAUJAC | AA51: 30330 | AB51: FR
A52: 406-7943739-2697932 | B52: 406-7943739-2697932 | C52: 2024-02-22T20:28:58+00:00 | D52: 2024-02-23T02:18:16+00:00 | E52: Shipped | F52: Amazon | G52: Amazon.fr | J52: Expedited | K52: BEPER BT.710Y Crêpière électrique avec poignée, 800 W, plaque en aluminium avec revêtement antiadhésif, rouge | L52: BT.710Y_FBA | M52: B07NQ2VYGD | N52: Shipped | O52: 1 | P52: EUR | Q52: 39.9 | R52: 6.65 | Y52: Enghien-les-Bains | AA52: 95880 | AB52: FR
A53: 407-7001720-6749119 | B53: 407-7001720-6749119 | C53: 2024-02-22T19:46:42+00:00 | D53: 2024-02-23T04:54:05+00:00 | E53: Shipped | F53: Amazon | G53: Amazon.fr | J53: Expedited | K53: BEPER BT.710Y Crêpière électrique avec poignée, 800 W, plaque en aluminium avec revêtement antiadhésif, rouge | L53: BT.710Y_FBA | M53: B07NQ2VYGD | N53: Shipped | O53: 1 | P53: EUR | Q53: 39.9 | R53: 6.65 | Y53: Toulouse | AA53: 31300 | AB53: FR
A54: 171-7695828-9892351 | B54: 171-7695828-9892351 | C54: 2024-02-22T18:31:36+00:00 | D54: 2024-02-23T01:55:05+00:00 | E54: Shipped | F54: Amazon | G54: Amazon.fr | J54: Standard | K54: BEPER BT.710Y Crêpière électrique avec poignée, 800 W, plaque en aluminium avec revêtement antiadhésif, rouge | L54: BT.710Y_FBA | M54: B07NQ2VYGD | N54: Shipped | O54: 1 | P54: EUR | Q54: 39.9 | R54: 6.65 | S54: 3.32 | X54: 3.32 | Y54: Avallon | AA54: 89200 | AB54: FR | AC54: Free Shipping 2017/10/17 17-17-37-677
A55: 171-2096770-5502768 | B55: 171-2096770-5502768 | C55: 2024-02-22T17:16:21+00:00 | D55: 2024-02-27T18:45:22+00:00 | E55: Cancelled | F55: Amazon | G55: Amazon.fr | J55: Standard | K55: BEPER BT.710Y Crêpière électrique avec poignée, 800 W, plaque en aluminium avec revêtement antiadhésif, rouge | L55: BT.710Y_FBA | M55: B07NQ2VYGD | N55: Cancelled | O55: 0 | Y55: Vaux le pénil | AA55: 77000 | AB55: FR | AC55: Free Shipping 2017/10/17 17-17-37-677
A56: 171-7226232-3017950 | B56: 171-7226232-3017950 | C56: 2024-02-22T17:14:33+00:00 | D56: 2024-02-23T20:37:30+00:00 | E56: Cancelled | F56: Amazon | G56: Amazon.fr | J56: Standard | K56: BEPER BT.710Y Crêpière électrique avec poignée, 800 W, plaque en aluminium avec revêtement antiadhésif, rouge | L56: BT.710Y_FBA | M56: B07NQ2VYGD | N56: Cancelled | O56: 0 | Y56: Vaux le pénil | AA56: 77000 | AB56: FR | AC56: Free Shipping 2017/10/17 17-17-37-677
A57: 405-1035593-2225903 | B57: 405-1035593-2225903 | C57: 2024-02-22T15:40:50+00:00 | D57: 2024-02-27T10:42:36+00:00 | E57: Shipped | F57: Amazon | G57: Amazon.fr | J57: Standard | K57: Beper - Machine à Pop-Corn, Pop-Corn en 3 Minutes, Sans Matières Grasses, Circulation d'Air Chaud, Puissance 1200W - Rouge [Classe d'efficacité én | L57: 90.590Y_FBA | M57: B01KMJ9OXW | N57: Shipped | O57: 1 | P57: EUR | Q57: 36.8 | Y57: LYON | AA57: 69003 | AB57: FR | AG57: FR24830908794 | AH57: FR | AI57: VAT
A58: 407-3962313-3480318 | B58: 407-3962313-3480318 | C58: 2024-02-22T13:54:34+00:00 | D58: 2024-02-23T00:32:25+00:00 | E58: Shipped | F58: Amazon | G58: Amazon.fr | J58: Expedited | K58: BEPER BT.710Y Crêpière électrique avec poignée, 800 W, plaque en aluminium avec revêtement antiadhésif, rouge | L58: BT.710Y_FBA | M58: B07NQ2VYGD | N58: Shipped | O58: 1 | P58: EUR | Q58: 39.9 | R58: 6.65 | Y58: ROSNY SOUS BOIS | AA58: 93110 | AB58: FR
A59: 406-4245920-9158746 | B59: 406-4245920-9158746 | C59: 2024-02-22T12:28:53+00:00 | D59: 2024-02-22T12:52:25+00:00 | E59: Cancelled | F59: Amazon | G59: Amazon.fr | J59: Expedited | K59: BEPER BT.710Y Crêpière électrique avec poignée, 800 W, plaque en aluminium avec revêtement antiadhésif, rouge | L59: BT.710Y_FBA | M59: B07NQ2VYGD | N59: Cancelled | O59: 0 | Y59: Saran | AA59: 45770 | AB59: FR
A60: 407-2461730-8526767 | B60: 407-2461730-8526767 | C60: 2024-02-22T08:58:51+00:00 | D60: 2024-02-22T13:11:45+00:00 | E60: Shipped | F60: Amazon | G60: Amazon.fr | J60: Expedited | K60: BEPER BT.710Y Crêpière électrique avec poignée, 800 W, plaque en aluminium avec revêtement antiadhésif, rouge | L60: BT.710Y_FBA | M60: B07NQ2VYGD | N60: Shipped | O60: 1 | P60: EUR | Q60: 32.7 | Y60: Igoville | AA60: 27460 | AB60: FR | AG60: FR90515333284 | AH60: FR | AI60: VAT
A61: 402-7465435-4985161 | B61: 402-7465435-4985161 | C61: 2024-02-21T22:48:15+00:00 | D61: 2024-02-22T22:01:35+00:00 | E61: Shipped | F61: Amazon | G61: Amazon.fr | J61: Expedited | K61: BEPER Rapeuse Fromage Legumes BP.400 électrique, 3 cônes en Acier interchangeables, Coupe Julienne, tranches et râpe, allié, Argenté et Noir | L61: BP.400_FBA | M61: B0823CVGHX | N61: Shipped | O61: 1 | P61: EUR | Q61: 64.9 | R61: 10.82 | Y61: Acheres | AA61: 78260 | AB61: FR
A62: 406-0571090-8706747 | B62: 406-0571090-8706747 | C62: 2024-02-21T20:45:29+00:00 | D62: 2024-02-22T02:04:28+00:00 | E62: Shipped | F62: Amazon | G62: Amazon.fr | J62: Expedited | K62: BEPER BT.710Y Crêpière électrique avec poignée, 800 W, plaque en aluminium avec revêtement antiadhésif, rouge | L62: BT.710Y_FBA | M62: B07NQ2VYGD | N62: Shipped | O62: 1 | P62: EUR | Q62: 39.9 | R62: 6.65 | Y62: COURBEVOIE | AA62: 92400 | AB62: FR
A63: 404-4030149-6583537 | B63: 404-4030149-6583537 | C63: 2024-02-21T18:11:01+00:00 | D63: 2024-02-22T04:52:56+00:00 | E63: Shipped | F63: Amazon | G63: Amazon.fr | J63: Standard | K63: BEPER BT.710Y Crêpière électrique avec poignée, 800 W, plaque en aluminium avec revêtement antiadhésif, rouge | L63: BT.710Y_FBA | M63: B07NQ2VYGD | N63: Shipped | O63: 1 | P63: EUR | Q63: 39.9 | R63: 6.65 | S63: 3.32 | X63: 3.32 | Y63: Noves | AA63: 13550 | AB63: FR | AC63: Free Shipping 2017/10/17 17-17-37-677
A64: 408-8290667-8621121 | B64: 408-8290667-8621121 | C64: 2024-02-21T16:22:46+00:00 | D64: 2024-02-23T19:20:06+00:00 | E64: Shipped | F64: Amazon | G64: Amazon.fr | J64: Expedited | K64: Beper - Machine à Pop-Corn, Pop-Corn en 3 Minutes, Sans Matières Grasses, Circulation d'Air Chaud, Puissance 1200W - Rouge [Classe d'efficacité én | L64: 90.590Y_FBA | M64: B01KMJ9OXW | N64: Shipped | O64: 1 | P64: EUR | Q64: 44.9 | R64: 7.48 | Y64: Hennebont | AA64: 56700 | AB64: FR
A65: 403-5712125-5364334 | B65: 403-5712125-5364334 | C65: 2024-02-21T16:11:23+00:00 | D65: 2024-02-22T16:36:57+00:00 | E65: Shipped | F65: Amazon | G65: Amazon.fr | J65: Standard | K65: BEPER BT.710Y Crêpière électrique avec poignée, 800 W, plaque en aluminium avec revêtement antiadhésif, rouge | L65: BT.710Y_FBA | M65: B07NQ2VYGD | N65: Shipped | O65: 1 | P65: EUR | Q65: 39.9 | R65: 6.65 | S65: 1.67 | X65: 1.67 | Y65: Gemmelaincourt | AA65: 88170 | AB65: FR | AC65: Free Shipping 2017/10/17 17-17-37-677
A66: 407-2972967-8161966 | B66: 407-2972967-8161966 | C66: 2024-02-21T15:55:55+00:00 | D66: 2024-02-22T11:52:19+00:00 | E66: Shipped | F66: Amazon | G66: Amazon.fr | J66: Standard | K66: BEPER BT.710Y Crêpière électrique avec poignée, 800 W, plaque en aluminium avec revêtement antiadhésif, rouge | L66: BT.710Y_FBA | M66: B07NQ2VYGD | N66: Shipped | O66: 1 | P66: EUR | Q66: 39.9 | R66: 6.65 | S66: 3.32 | X66: 3.32 | Y66: Elven | AA66: 56250 | AB66: FR | AC66: Free Shipping 2017/10/17 17-17-37-677
A67: 171-7675914-9350761 | B67: 171-7675914-9350761 | C67: 2024-02-21T12:52:13+00:00 | D67: 2024-02-22T04:59:31+00:00 | E67: Shipped | F67: Amazon | G67: Amazon.fr | J67: Standard | K67: BEPER 50.700 Nettoyeur Vapeur pour Sol, Canapé, Tapis - Nettoyant Vapeur, 135° max, câble de 3 Mètres, 350 ml | L67: 50.700_FBA | M67: B01MTSEGF9 | N67: Shipped | O67: 1 | P67: EUR | Q67: 49.9 | R67: 8.32 | S67: 3.32 | X67: 3.32 | Y67: Hyeres | AA67: 83400 | AB67: FR | AC67: Free Shipping 2017/10/17 17-17-37-677
A68: 406-3560559-8967551 | B68: 406-3560559-8967551 | C68: 2024-02-21T12:31:45+00:00 | D68: 2024-02-22T11:52:16+00:00 | E68: Shipped | F68: Amazon | G68: Amazon.fr | J68: Standard | K68: Beper - Machine à Pop-Corn, Pop-Corn en 3 Minutes, Sans Matières Grasses, Circulation d'Air Chaud, Puissance 1200W - Rouge [Classe d'efficacité én | L68: 90.590Y_FBA | M68: B01KMJ9OXW | N68: Shipped | O68: 1 | P68: EUR | Q68: 44.9 | R68: 7.48 | Y68: GELLAINVILLE | AA68: 28630 | AB68: FR | AC68: Free Shipping 2017/10/17 17-17-37-677
A69: 406-5141813-3355521 | B69: 406-5141813-3355521 | C69: 2024-02-21T12:22:09+00:00 | D69: 2024-02-21T12:29:06+00:00 | E69: Cancelled | F69: Amazon | G69: Amazon.fr | J69: Standard | K69: Beper - Machine à Pop-Corn, Pop-Corn en 3 Minutes, Sans Matières Grasses, Circulation d'Air Chaud, Puissance 1200W - Rouge [Classe d'efficacité én | L69: 90.590Y_FBA | M69: B01KMJ9OXW | N69: Cancelled | O69: 0 | Y69: GELLAINVILLE | AA69: 28630 | AB69: FR | AC69: Free Shipping 2017/10/17 17-17-37-677
A70: 407-8132842-6404357 | B70: 407-8132842-6404357 | C70: 2024-02-21T10:47:54+00:00 | D70: 2024-02-22T02:30:02+00:00 | E70: Shipped | F70: Amazon | G70: Amazon.fr | J70: Expedited | K70: BEPER BT.710Y Crêpière électrique avec poignée, 800 W, plaque en aluminium avec revêtement antiadhésif, rouge | L70: BT.710Y_FBA | M70: B07NQ2VYGD | N70: Shipped | O70: 1 | P70: EUR | Q70: 39.9 | R70: 6.65 | Y70: Paris | AA70: 75116 | AB70: FR
A71: 405-6229856-1593129 | B71: 405-6229856-1593129 | C71: 2024-02-21T09:08:20+00:00 | D71: 2024-02-22T00:31:40+00:00 | E71: Shipped | F71: Amazon | G71: Amazon.fr | J71: Expedited | K71: BEPER Distributeur automatique de couvre-chaussures, ABS, blanc, taille unique | L71: C206UTI001_FBA | M71: B08JM7SZ36 | N71: Shipped | O71: 1 | P71: EUR | Q71: 49.9 | R71: 8.32 | Y71: Asnières-sur-Seine | AA71: 92600 | AB71: FR
A72: 408-4640724-9933114 | B72: 408-4640724-9933114 | C72: 2024-02-20T22:05:37+00:00 | D72: 2024-02-26T06:48:19+00:00 | E72: Cancelled | F72: Amazon | G72: Amazon.fr | J72: Standard | K72: BEPER BT.710Y Crêpière électrique avec poignée, 800 W, plaque en aluminium avec revêtement antiadhésif, rouge | L72: BT.710Y_FBA | M72: B07NQ2VYGD | N72: Cancelled | O72: 0 | Y72: Cergy | AA72: 95000 | AB72: FR | AC72: Free Shipping 2017/10/17 17-17-37-677
A73: 407-9062187-0974764 | B73: 407-9062187-0974764 | C73: 2024-02-20T21:59:01+00:00 | D73: 2024-02-22T02:05:06+00:00 | E73: Shipped | F73: Amazon | G73: Amazon.fr | J73: Standard | K73: BEPER BT.710Y Crêpière électrique avec poignée, 800 W, plaque en aluminium avec revêtement antiadhésif, rouge | L73: BT.710Y_FBA | M73: B07NQ2VYGD | N73: Shipped | O73: 1 | P73: EUR | Q73: 39.9 | R73: 6.65 | S73: 1.66 | X73: 1.66 | Y73: Boisbreteau | AA73: 16480 | AB73: FR | AC73: Free Shipping 2017/10/17 17-17-37-677
A74: 407-4970806-4523557 | B74: 407-4970806-4523557 | C74: 2024-02-20T18:26:04+00:00 | D74: 2024-02-21T11:54:10+00:00 | E74: Shipped | F74: Amazon | G74: Amazon.fr | J74: Standard | K74: Beper BF.640 - Four ventilé multifonction 12L Anneau de rallonge pour capacité totale 18L Minuterie 60 minutes Température réglable jusqu'à 250° | L74: BF.640_FBA | M74: B07YBN2FS3 | N74: Shipped | O74: 1 | P74: EUR | Q74: 99 | R74: 16.5 | S74: 3.32 | X74: 3.32 | Y74: La Ménitré | AA74: 49250 | AB74: FR | AC74: Free Shipping 2017/10/17 17-17-37-677
A75: 405-8347241-1521937 | B75: 405-8347241-1521937 | C75: 2024-02-20T07:16:20+00:00 | D75: 2024-02-20T12:07:20+00:00 | E75: Shipped | F75: Amazon | G75: Amazon.fr | J75: Expedited | K75: Beper - Machine à Pop-Corn, Pop-Corn en 3 Minutes, Sans Matières Grasses, Circulation d'Air Chaud, Puissance 1200W - Rouge [Classe d'efficacité én | L75: 90.590Y_FBA | M75: B01KMJ9OXW | N75: Shipped | O75: 1 | P75: EUR | Q75: 44.9 | R75: 7.48 | Y75: Epone | AA75: 78680 | AB75: FR
A76: 408-1830232-6163546 | B76: 408-1830232-6163546 | C76: 2024-02-19T22:21:41+00:00 | D76: 2024-02-20T18:32:06+00:00 | E76: Shipped | F76: Amazon | G76: Amazon.fr | J76: Expedited | K76: Beper - Machine à Pop-Corn, Pop-Corn en 3 Minutes, Sans Matières Grasses, Circulation d'Air Chaud, Puissance 1200W - Rouge [Classe d'efficacité én | L76: 90.590Y_FBA | M76: B01KMJ9OXW | N76: Shipped | O76: 1 | P76: EUR | Q76: 44.9 | R76: 7.48 | Y76: Malaunay | AA76: 76770 | AB76: FR
A77: 405-8945806-6984347 | B77: 405-8945806-6984347 | C77: 2024-02-19T20:32:54+00:00 | D77: 2024-02-20T12:19:59+00:00 | E77: Shipped | F77: Amazon | G77: Amazon.fr | J77: Expedited | K77: BEPER BT.710Y Crêpière électrique avec poignée, 800 W, plaque en aluminium avec revêtement antiadhésif, rouge | L77: BT.710Y_FBA | M77: B07NQ2VYGD | N77: Shipped | O77: 1 | P77: EUR | Q77: 39.9 | R77: 6.65 | Y77: Toulouse | AA77: 31300 | AB77: FR
A78: 404-7927370-2089109 | B78: 404-7927370-2089109 | C78: 2024-02-19T18:56:30+00:00 | D78: 2024-02-20T20:53:36+00:00 | E78: Shipped | F78: Amazon | G78: Amazon.fr | J78: Expedited | K78: Beper - Machine à Pop-Corn, Pop-Corn en 3 Minutes, Sans Matières Grasses, Circulation d'Air Chaud, Puissance 1200W - Rouge [Classe d'efficacité én | L78: 90.590Y_FBA | M78: B01KMJ9OXW | N78: Shipped | O78: 1 | P78: EUR | Q78: 44.9 | R78: 7.48 | Y78: Marseille | Z78: France | AA78: 13008 | AB78: FR
A79: 171-8477874-9551545 | B79: 171-8477874-9551545 | C79: 2024-02-19T17:35:43+00:00 | D79: 2024-02-20T20:04:27+00:00 | E79: Shipped | F79: Amazon | G79: Amazon.fr | J79: Expedited | K79: BEPER BT.710Y Crêpière électrique avec poignée, 800 W, plaque en aluminium avec revêtement antiadhésif, rouge | L79: BT.710Y_FBA | M79: B07NQ2VYGD | N79: Shipped | O79: 1 | P79: EUR | Q79: 39.9 | R79: 6.65 | Y79: Fontaine-la-Guyon | AA79: 28190 | AB79: FR
A80: 407-2852858-8143530 | B80: 407-2852858-8143530 | C80: 2024-02-19T16:26:02+00:00 | D80: 2024-02-20T01:57:28+00:00 | E80: Shipped | F80: Amazon | G80: Amazon.fr | J80: Standard | K80: BEPER BT.710Y Crêpière électrique avec poignée, 800 W, plaque en aluminium avec revêtement antiadhésif, rouge | L80: BT.710Y_FBA | M80: B07NQ2VYGD | N80: Shipped | O80: 1 | P80: EUR | Q80: 39.9 | R80: 6.65 | S80: 3.32 | X80: 3.32 | Y80: Vue | AA80: 44640 | AB80: FR | AC80: Free Shipping 2017/10/17 17-17-37-677
A81: 406-4562021-2987533 | B81: 406-4562021-2987533 | C81: 2024-02-19T14:22:15+00:00 | D81: 2024-02-20T01:56:39+00:00 | E81: Shipped | F81: Amazon | G81: Amazon.fr | J81: Standard | K81: BEPER BT.710Y Crêpière électrique avec poignée, 800 W, plaque en aluminium avec revêtement antiadhésif, rouge | L81: BT.710Y_FBA | M81: B07NQ2VYGD | N81: Shipped | O81: 1 | P81: EUR | Q81: 39.9 | R81: 6.65 | Y81: Chauvigny | AA81: 86300 | AB81: FR | AC81: Free Shipping 2017/10/17 17-17-37-677
A82: 403-6642022-8841959 | B82: 403-6642022-8841959 | C82: 2024-02-19T13:22:17+00:00 | D82: 2024-02-22T00:25:21+00:00 | E82: Shipped | F82: Amazon | G82: Amazon.fr | J82: Standard | K82: BEPER BT.710Y Crêpière électrique avec poignée, 800 W, plaque en aluminium avec revêtement antiadhésif, rouge | L82: BT.710Y_FBA | M82: B07NQ2VYGD | N82: Shipped | O82: 1 | P82: EUR | Q82: 39.9 | R82: 6.65 | S82: 1.11 | X82: 1.11 | Y82: Aubigny les clouzeaux | AA82: 85430 | AB82: FR | AC82: Free Shipping 2017/10/17 17-17-37-677
A83: 405-0070346-7894707 | B83: 405-0070346-7894707 | C83: 2024-02-19T10:50:59+00:00 | D83: 2024-02-21T13:25:45+00:00 | E83: Shipped | F83: Amazon | G83: Amazon.fr | J83: Standard | K83: BEPER BT.710Y Crêpière électrique avec poignée, 800 W, plaque en aluminium avec revêtement antiadhésif, rouge | L83: BT.710Y_FBA | M83: B07NQ2VYGD | N83: Shipped | O83: 1 | P83: EUR | Q83: 39.9 | S83: 0.58 | X83: 0.58 | Y83: Genève | AA83: 1217 | AB83: CH
A84: 405-9616613-6010748 | B84: 405-9616613-6010748 | C84: 2024-02-19T10:10:03+00:00 | D84: 2024-02-20T01:56:17+00:00 | E84: Shipped | F84: Amazon | G84: Amazon.fr | J84: Standard | K84: Beper - Machine à Pop-Corn, Pop-Corn en 3 Minutes, Sans Matières Grasses, Circulation d'Air Chaud, Puissance 1200W - Rouge [Classe d'efficacité én | L84: 90.590Y_FBA | M84: B01KMJ9OXW | N84: Shipped | O84: 1 | P84: EUR | Q84: 44.9 | R84: 7.48 | S84: 3.32 | X84: 3.32 | Y84: MANHEULLES | AA84: 55160 | AB84: FR | AC84: Free Shipping 2017/10/17 17-17-37-677
A85: 408-1587967-3256305 | B85: 408-1587967-3256305 | C85: 2024-02-19T09:12:35+00:00 | D85: 2024-02-19T12:34:45+00:00 | E85: Shipped | F85: Amazon | G85: Amazon.fr | J85: Expedited | K85: BEPER BT.710Y Crêpière électrique avec poignée, 800 W, plaque en aluminium avec revêtement antiadhésif, rouge | L85: BT.710Y_FBA | M85: B07NQ2VYGD | N85: Shipped | O85: 1 | P85: EUR | Q85: 39.9 | R85: 6.65 | Y85: nouzonville | AA85: 8700 | AB85: FR
A86: 171-0868333-0286704 | B86: 171-0868333-0286704 | C86: 2024-02-19T07:14:50+00:00 | D86: 2024-02-19T15:52:36+00:00 | E86: Shipped | F86: Amazon | G86: Amazon.fr | J86: Expedited | K86: Beper - Machine à Pop-Corn, Pop-Corn en 3 Minutes, Sans Matières Grasses, Circulation d'Air Chaud, Puissance 1200W - Rouge [Classe d'efficacité én | L86: 90.590Y_FBA | M86: B01KMJ9OXW | N86: Shipped | O86: 1 | P86: EUR | Q86: 44.9 | R86: 7.48 | Y86: Perpignan | AA86: 66000 | AB86: FR
A87: 403-4797871-3433938 | B87: 403-4797871-3433938 | C87: 2024-02-19T06:40:11+00:00 | D87: 2024-02-19T12:36:44+00:00 | E87: Shipped | F87: Amazon | G87: Amazon.fr | J87: Expedited | K87: BEPER BT.150Y Machine à Hot Dog, 750W, 5 levels de Cuissons, Design Vintage, Rouge | L87: BT.150Y_FBA | M87: B07BB2DQ4V | N87: Shipped | O87: 1 | P87: EUR | Q87: 49.9 | R87: 8.32 | Y87: Saint Symphorien sur Coise | AA87: 69590 | AB87: FR
A88: 405-8351529-3567520 | B88: 405-8351529-3567520 | C88: 2024-02-19T05:16:23+00:00 | D88: 2024-02-20T01:57:13+00:00 | E88: Shipped | F88: Amazon | G88: Amazon.fr | J88: Standard | K88: BEPER BT.710Y Crêpière électrique avec poignée, 800 W, plaque en aluminium avec revêtement antiadhésif, rouge | L88: BT.710Y_FBA | M88: B07NQ2VYGD | N88: Shipped | O88: 1 | P88: EUR | Q88: 39.9 | R88: 6.65 | Y88: PESSAC | AA88: 33600 | AB88: FR | AC88: Free Shipping 2017/10/17 17-17-37-677
A89: 406-2619455-7569967 | B89: 406-2619455-7569967 | C89: 2024-02-19T00:28:35+00:00 | D89: 2024-02-19T00:39:55+00:00 | E89: Cancelled | F89: Amazon | G89: Amazon.fr | J89: Expedited | K89: Beper - Machine à Pop-Corn, Pop-Corn en 3 Minutes, Sans Matières Grasses, Circulation d'Air Chaud, Puissance 1200W - Rouge [Classe d'efficacité én | L89: 90.590Y_FBA | M89: B01KMJ9OXW | N89: Cancelled | O89: 0 | Y89: GELLAINVILLE | AA89: 28630 | AB89: FR
A90: 402-4585232-2736318 | B90: 402-4585232-2736318 | C90: 2024-02-18T20:18:54+00:00 | D90: 2024-02-19T02:31:45+00:00 | E90: Shipped | F90: Amazon | G90: Amazon.fr | J90: Expedited | K90: BEPER BT.710Y Crêpière électrique avec poignée, 800 W, plaque en aluminium avec revêtement antiadhésif, rouge | L90: BT.710Y_FBA | M90: B07NQ2VYGD | N90: Shipped | O90: 1 | P90: EUR | Q90: 39.9 | R90: 6.65 | Y90: Vendhuile | Z90: France | AA90: 2420 | AB90: FR
A91: 404-8613333-5327542 | B91: 404-8613333-5327542 | C91: 2024-02-18T18:46:19+00:00 | D91: 2024-02-19T01:37:01+00:00 | E91: Shipped | F91: Amazon | G91: Amazon.fr | J91: Standard | K91: BEPER BT.710Y Crêpière électrique avec poignée, 800 W, plaque en aluminium avec revêtement antiadhésif, rouge | L91: BT.710Y_FBA | M91: B07NQ2VYGD | N91: Shipped | O91: 1 | P91: EUR | Q91: 39.9 | R91: 6.65 | Y91: PLOUGUERNEAU | AA91: 29880 | AB91: FR | AC91: Free Shipping 2017/10/17 17-17-37-677
A92: 404-7484037-1183511 | B92: 404-7484037-1183511 | C92: 2024-02-18T18:39:56+00:00 | D92: 2024-02-19T09:52:23+00:00 | E92: Shipped | F92: Amazon | G92: Amazon.fr | J92: Standard | K92: Beper BF.640 - Four ventilé multifonction 12L Anneau de rallonge pour capacité totale 18L Minuterie 60 minutes Température réglable jusqu'à 250° | L92: BF.640_FBA | M92: B07YBN2FS3 | N92: Shipped | O92: 1 | P92: EUR | Q92: 99 | R92: 16.5 | Y92: Montigny Lencoup | AA92: 77520 | AB92: FR | AC92: Free Shipping 2017/10/17 17-17-37-677
A93: 403-9168139-5429967 | B93: 403-9168139-5429967 | C93: 2024-02-18T11:54:44+00:00 | D93: 2024-02-19T21:56:45+00:00 | E93: Shipped | F93: Amazon | G93: Amazon.fr | J93: Expedited | K93: BEPER BT.710Y Crêpière électrique avec poignée, 800 W, plaque en aluminium avec revêtement antiadhésif, rouge | L93: BT.710Y_FBA | M93: B07NQ2VYGD | N93: Shipped | O93: 1 | P93: EUR | Q93: 39.9 | R93: 6.65 | Y93: Conde Sur L Escaut | Z93: Haut De France | AA93: 59163 | AB93: FR
A94: 403-9008628-5597915 | B94: 403-9008628-5597915 | C94: 2024-02-18T11:50:19+00:00 | D94: 2024-02-18T11:54:37+00:00 | E94: Cancelled | F94: Amazon | G94: Amazon.fr | J94: Expedited | K94: BEPER BT.710Y Crêpière électrique avec poignée, 800 W, plaque en aluminium avec revêtement antiadhésif, rouge | L94: BT.710Y_FBA | M94: B07NQ2VYGD | N94: Cancelled | O94: 0 | Y94: La Rue-Saint-Pierre | AA94: 60510 | AB94: FR
A95: 402-1601318-1319514 | B95: 402-1601318-1319514 | C95: 2024-02-18T08:25:01+00:00 | D95: 2024-02-19T04:09:55+00:00 | E95: Shipped | F95: Amazon | G95: Amazon.fr | J95: Expedited | K95: BEPER BT.710Y Crêpière électrique avec poignée, 800 W, plaque en aluminium avec revêtement antiadhésif, rouge | L95: BT.710Y_FBA | M95: B07NQ2VYGD | N95: Shipped | O95: 1 | P95: EUR | Q95: 39.9 | R95: 6.65 | Y95: Tarbes | AA95: 65000 | AB95: FR
A96: 404-9187640-6154727 | B96: 404-9187640-6154727 | C96: 2024-02-17T22:44:21+00:00 | D96: 2024-02-19T03:37:23+00:00 | E96: Shipped | F96: Amazon | G96: Amazon.fr | J96: Expedited | K96: BEPER BT.710Y Crêpière électrique avec poignée, 800 W, plaque en aluminium avec revêtement antiadhésif, rouge | L96: BT.710Y_FBA | M96: B07NQ2VYGD | N96: Shipped | O96: 1 | P96: EUR | Q96: 39.9 | R96: 6.65 | Y96: VAUREAL | AA96: 95490 | AB96: FR
A97: 402-1363239-2645116 | B97: 402-1363239-2645116 | C97: 2024-02-17T22:33:28+00:00 | D97: 2024-02-20T13:15:57+00:00 | E97: Shipped | F97: Amazon | G97: Amazon.fr | J97: Expedited | K97: BEPER 50.700 Nettoyeur Vapeur pour Sol, Canapé, Tapis - Nettoyant Vapeur, 135° max, câble de 3 Mètres, 350 ml | L97: 50.700_FBA | M97: B01MTSEGF9 | N97: Shipped | O97: 1 | P97: EUR | Q97: 49.9 | R97: 8.32 | Y97: Lyon | AA97: 69003 | AB97: FR
A98: 405-7736994-2812352 | B98: 405-7736994-2812352 | C98: 2024-02-17T22:04:43+00:00 | D98: 2024-02-20T09:16:13+00:00 | E98: Shipped | F98: Amazon | G98: Amazon.fr | J98: Standard | K98: Beper - Machine à Pop-Corn, Pop-Corn en 3 Minutes, Sans Matières Grasses, Circulation d'Air Chaud, Puissance 1200W - Rouge [Classe d'efficacité én | L98: 90.590Y_FBA | M98: B01KMJ9OXW | N98: Shipped | O98: 1 | P98: EUR | Q98: 44.9 | R98: 7.48 | S98: 1.67 | X98: 1.67 | Y98: Chateauneuf sur Isere | AA98: 26300 | AB98: FR | AC98: Free Shipping 2017/10/17 17-17-37-677
A99: 171-9674807-5172359 | B99: 171-9674807-5172359 | C99: 2024-02-17T21:32:00+00:00 | D99: 2024-02-19T01:37:02+00:00 | E99: Shipped | F99: Amazon | G99: Amazon.fr | J99: Standard | K99: BEPER 50.700 Nettoyeur Vapeur pour Sol, Canapé, Tapis - Nettoyant Vapeur, 135° max, câble de 3 Mètres, 350 ml | L99: 50.700_FBA | M99: B01MTSEGF9 | N99: Shipped | O99: 1 | P99: EUR | Q99: 49.9 | R99: 8.32 | S99: 3.32 | X99: 3.32 | Y99: Lucciana | AA99: 20290 | AB99: FR | AC99: Free Shipping 2017/10/17 17-17-37-677
A100: 171-7689674-2205135 | B100: 171-7689674-2205135 | C100: 2024-02-17T21:08:13+00:00 | D100: 2024-02-19T01:35:09+00:00 | E100: Shipped | F100: Amazon | G100: Amazon.fr | J100: Standard | K100: BEPER BT.710Y Crêpière électrique avec poignée, 800 W, plaque en aluminium avec revêtement antiadhésif, rouge | L100: BT.710Y_FBA | M100: B07NQ2VYGD | N100: Shipped | O100: 1 | P100: EUR | Q100: 39.9 | R100: 6.65 | Y100: NEUFCHATEL EN BRAY | AA100: 76270 | AB100: FR | AC100: Free Shipping 2017/10/17 17-17-37-677
...

Sheet v_02_2023
A1: Codice marketplace | B1: (Tutto) | F1: Codice marketplace | G1: IT
A3: ASIN | B3: Numero del modello | C3: Somma di Unità ordinate | D3: Somma di Ricavi ordini | F3: ASIN | G3: Numero del modello | H3: Somma di Unità ordinate | I3: Somma di Ricavi ordini
A4: B0050IHH4E | B4: 40.979 | C4: 31 | D4: 404.7 | F4: B0050IHH4E | G4: 40.979 | H4: 24 | I4: 312.72
A5: B00BH202XK | B5: 40.808A | C5: 2 | D5: 35.73 | F5: B00BH202XK | G5: 40.808A | H5: 2 | I5: 35.73
A6: B00C5CCJP0 | B6: 40.993 | C6: 4 | D6: 43.54 | F6: B00CMAD2FG | G6: HK-NV009W | H6: 1 | I6: 19.87
A7: B00CMAD2FG | B7: HK-NV009W | C7: 2 | D7: 32.58 | F7: B00EYDRS1I | G7: 90.349 | H7: 159 | I7: 878.28
A8: B00EYDRS1I | B8: 90.349 | C8: 198 | D8: 1106.56 | F8: B00FAJUDU8 | G8: 40.967N | H8: 92 | I8: 1877.72
A9: B00EZ4185S | B9: RI.501SL | C9: 0 | D9: 0 | F9: B00FFBFVG2 | G9: 40.100 | H9: 3 | I9: 18.99
A10: B00FAJUDU8 | B10: 40.967N | C10: 195 | D10: 4239.58 | F10: B00J7MNQFS | G10: 40.994 | H10: 3 | I10: 49.83
A11: B00FFBFVG2 | B11: 40.100 | C11: 5 | D11: 32.25 | F11: B00L5GPWFG | G11: 40.120 | H11: 2 | I11: 49.02
A12: B00J7MNQFS | B12: 40.994 | C12: 4 | D12: 69.7 | F12: B00L5H5KUW | G12: 40.121 | H12: 202 | I12: 3294.62
A13: B00L5GPWFG | B13: 40.120 | C13: 2 | D13: 49.02 | F13: B00NSNZSLM | G13: 90.602 | H13: 515 | I13: 10511.15
A14: B00L5H5KUW | B14: 40.121 | C14: 374 | D14: 6370.16 | F14: B00OKE4RTM | G14: 90.386 | H14: 1 | I14: 53.22
A15: B00NSNZSLM | B15: 90.602 | C15: 529 | D15: 10857.32 | F15: B00OLZPU5K | G15: 40.947 | H15: 3 | I15: 31.71
... A204: B08NDZKNF5 | B204: P102CON001 | C204: 19 | D204: 547.96 | F204: B0BRQB2J4B | G204: PET005 | H204: 39 | I204: 156.78
A205: B08NF8TQKT | B205: P102FRU100 | C205: 12 | D205: 266.54 | F205: Totale complessivo | H205: 21467 | I205: 329286.49
A206: B08NTD853X | B206: P102SBA006 | C206: 17 | D206: 139.9
A207: B08V4VTTQN | B207: C107UTT001 | C207: 17 | D207: 119.85
A208: B08XQT9P5C | B208: P102GEL001 | C208: 2 | D208: 83.08
A209: B08XVV3PVK | B209: P303MED001 | C209: 3 | D209: 27.27
A210: B08XWBGJHR | B210: P101PIA002 | C210: 0 | D210: 0
A211: B09146GTKW | B211: P302VIS002 | C211: 2634 | D211: 21633.79
A212: B091C5XQZN | B212: P202ASP001 | C212: 6 | D212: 236.64
A213: B091LRR67V | B213: P101FRI050 | C213: 72 | D213: 4725.07
A214: B091VSY78C | B214: P303BIP050 | C214: 1 | D214: 20.41
A215: B09251R9RJ | B215: P304CAP001 | C215: 8 | D215: 130.9
A216: B0929CVW7Q | B216: P206ZAN110 | C216: 4 | D216: 48.84
A217: B092DN1NCS | B217: P206VEN440 | C217: 2 | D217: 16.5
... A289: B0BRQB2J4B | B289: PET005 | C289: 43 | D289: 172.91
A290: Totale complessivo | C290: 39365 | D290: 612405.58

Sheet v_02_2024
A1: Codice marketplace | B1: (Tutto) | F1: Codice marketplace | G1: IT
A3: ASIN | B3: Numero del modello | C3: Somma di Unità ordinate | D3: Somma di Ricavi ordini | F3: ASIN | G3: Numero del modello | H3: Somma di Unità ordinate | I3: Somma di Ricavi ordini
A4: B0050IHH4E | B4: 40.979 | C4: 1117 | D4: 16410.86 | F4: B0050IHH4E | G4: 40.979 | H4: 311 | I4: 4876.26
A5: B00BH202XK | B5: 40.808A | C5: 2 | D5: 22.85 | F5: B00BH202XK | G5: 40.808A | H5: 1 | I5: 13.85
A6: B00EYDRS1I | B6: 90.349 | C6: 23 | D6: 131.27 | F6: B00EYDRS1I | G6: 90.349 | H6: 17 | I6: 102.19
A7: B00FAJUDU8 | B7: 40.967N | C7: 0 | D7: 0 | F7: B00FFBFVG2 | G7: 40.100 | H7: 0 | I7: 0
A8: B00FFBED98 | B8: 40.11 | C8: 1 | D8: 41.24 | F8: B00J7MNQFS | G8: 40.994 | H8: 3 | I8: 61.3
A9: B00FFBFVG2 | B9: 40.100 | C9: 0 | D9: 0 | F9: B00L5GPWFG | G9: 40.120 | H9: 3 | I9: 73.53
A10: B00FMZ2VW8 | B10: HK-HQ601C PINK | C10: 0 | D10: 0 | F10: B00L5H5KUW | G10: 40.121 | H10: 424 | I10: 7577.95
A11: B00J7MNQFS | B11: 40.994 | C11: 3 | D11: 61.3 | F11: B00NSNZSLM | G11: 90.602 | H11: 0 | I11: 0
A12: B00L5GPWFG | B12: 40.120 | C12: 3 | D12: 73.53 | F12: B00OKE4RTM | G12: 90.386 | H12: 3 | I12: 147.35
A13: B00L5H5KUW | B13: 40.121 | C13: 424 | D13: 7577.95 | F13: B00OLZPU5K | G13: 40.947 | H13: 1 | I13: 10.57
A14: B00NSNZSLM | B14: 90.602 | C14: 1 | D14: 27.03 | F14: B011LFVLW8 | G14: 90.620 | H14: 24 | I14: 784.8
A15: B00OKE4RTM | B15: 90.386 | C15: 3 | D15: 147.35 | F15: B011LH9V8M | G15: 40.958V | H15: 1 | I15: 6.73
... A198: B095X9KDJR | B198: P101BOL100 | C198: 1 | D198: 16.45 | F198: B0CPFRMPTM | G198: P101CAF001 | H198: 382 | I198: 9465.85
A199: B096KVY46G | B199: P303MED050 | C199: 5 | D199: 68.65 | F199: Totale complessivo | H199: 7751 | I199: 134126.27
A200: B096MX229M | B200: P102ROB050 | C200: 250 | D200: 3151.84
A201: B096SVXQDX | B201: P201UTP011 | C201: 2 | D201: 28.26
A202: B097785V2V | B202: P202VAL110 | C202: 14 | D202: 57.29
A203: B0978ZKW4S | B203: P205DIF100 | C203: 54 | D203: 664.1
A204: B097F45J2B | B204: P102FRU500 | C204: 3 | D204: 88.7
A205: B097HRQNRG | B205: P101FRI100 | C205: 78 | D205: 2332.18
A206: B097YTGFH7 | B206: P102ROB200 | C206: 10 | D206: 642.61
A207: B098QM485T | B207: P101CUD050 | C207: 2 | D207: 83.86
A208: B09968BKDS | B208: P102FRU003 | C208: 292 | D208: 4099.28
A209: B09B15P5H1 | B209: P102FRU200 | C209: 7 | D209: 131.05
A210: B09B2NT2SV | B210: P102FRU150 | C210: 4 | D210: 112.76
A211: B09B47S644 | B211: P101CUD501 | C211: 106 | D211: 3110.64
... A286: B0CPFRMPTM | B286: P101CAF001 | C286: 425 | D286: 10531.95
A287: Totale complessivo | C287: 15469 | D287: 257741.07

Sheet s_02_2024
A1: sales-channel | B1: (Tutto) | E1: sales-channel | F1: Amazon.it
A3: Etichette di riga | B3: Somma di quantity | C3: Somma di item-price | E3: Etichette di riga | F3: Somma di quantity | G3: Somma di item-price
A4: B0050IHH4E | B4: 1 | C4: 19.9 | E4: B0050IHH4E | F4: 1 | G4: 19.9
A5: B00FAJUDU8 | B5: 38 | C5: 1231.71 | E5: B00FAJUDU8 | F5: 36 | G5: 1151.91
A6: B00NSNZSLM | B6: 96 | C6: 2882.4 | E6: B00NSNZSLM | F6: 96 | G6: 2882.4
A7: B017IUJA50 | B7: 7 | C7: 155.61 | E7: B017IUJA50 | F7: 7 | G7: 155.61
A8: B01CNX704K | B8: 5 | C8: 234.5 | E8: B01CNX704K | F8: 5 | G8: 234.5
A9: B01I497WWM | B9: 1084 | C9: 21587.91 | E9: B01I497WWM | F9: 1084 | G9: 21587.91
A10: B01KMJ9OXW | B10: 346 | C10: 12658.72 | E10: B01KMJ9OXW | F10: 285 | G10: 9936.02
A11: B01MTSEGF9 | B11: 31 | C11: 1446.9 | E11: B01MTSEGF9 | F11: 20 | G11: 898
A12: B06Y17FS6D | B12: 3 | C12: 49.9 | E12: B06Y195DJN | F12: 31 | G12: 1546.9
A13: B06Y195DJN | B13: 32 | C13: 1606.8 | E13: B0757TJRR9 | F13: 602 | G13: 19788.01
A14: B0757TJRR9 | B14: 606 | C14: 19967.61 | E14: B075FX6RFP | F14: 25 | G14: 950.5
A15: B075FX6RFP | B15: 25 | C15: 950.5 | E15: B076D74TC7 | F15: 4 | G15: 147.96
... A50: B0CLY2CF4T | B50: 56 | C50: 1299.4 | E50: Totale complessivo | F50: 4207 | G50: 118277.01
A51: (vuoto)
A52: Totale complessivo | B52: 4616 | C52: 135835.27

Sheet pivot
A3: ASIN | B3: SKU | C3: Somma di Ordini Vendor 24 | D3: Somma di Valori ordini Vendor 24 | E3: Somma di Ordini Seller 24 | F3: Somma di Valori ordini Seller 24 | G3: Somma di Ordini Complessivi 24 | H3: Somma di Valori ordini Complessivi 24 | I3: Somma di Ordini Vendor 23 | J3: Somma di Valori ordini Vendor 23
A4: B0050IHH4E | B4: 40.979 | C4: 1117 | D4: 16410.86 | E4: 1 | F4: 19.9 | G4: 1118 | H4: 16430.76 | I4: 31 | J4: 404.7
A5: B00BH202XK | B5: 40.808A | C5: 2 | D5: 22.85 | E5: 0 | F5: 0 | G5: 2 | H5: 22.85 | I5: 2 | J5: 35.73
A6: B00C5CCJP0 | B6: 40.993 | C6: 0 | D6: 0 | E6: 0 | F6: 0 | G6: 0 | H6: 0 | I6: 4 | J6: 43.54
A7: B00CMAD2FG | B7: HK-NV009W | C7: 0 | D7: 0 | E7: 0 | F7: 0 | G7: 0 | H7: 0 | I7: 2 | J7: 32.58
A8: B00EYDRS1I | B8: 90.349 | C8: 23 | D8: 131.27 | E8: 0 | F8: 0 | G8: 23 | H8: 131.27 | I8: 198 | J8: 1106.56
A9: B00EZ4185S | B9: RI.501SL | C9: 0 | D9: 0 | E9: 0 | F9: 0 | G9: 0 | H9: 0 | I9: 0 | J9: 0
A10: B00FAJUDU8 | B10: 40.967N | C10: 0 | D10: 0 | E10: 38 | F10: 1231.71 | G10: 38 | H10: 1231.71 | I10: 195 | J10: 4239.58
A11: B00FFBED98 | B11: 40.11 | C11: 1 | D11: 41.24 | E11: 0 | F11: 0 | G11: 1 | H11: 41.24 | I11: 0 | J11: 0
A12: B00FFBFVG2 | B12: 40.100 | C12: 0 | D12: 0 | E12: 0 | F12: 0 | G12: 0 | H12: 0 | I12: 5 | J12: 32.25
A13: B00FMZ2VW8 | B13: HK-HQ601C PINK | C13: 0 | D13: 0 | E13: 0 | F13: 0 | G13: 0 | H13: 0 | I13: 0 | J13: 0
A14: B00J7MNQFS | B14: 40.994 | C14: 3 | D14: 61.3 | E14: 0 | F14: 0 | G14: 3 | H14: 61.3 | I14: 4 | J14: 69.7
A15: B00L5GPWFG | B15: 40.120 | C15: 3 | D15: 73.53 | E15: 0 | F15: 0 | G15: 3 | H15: 73.53 | I15: 2 | J15: 49.02
... A358: (vuoto) | B358: Totale complessivo | C358: 15469 | D358: 257741.07 | E358: 4616 | F358: 135835.27 | G358: 20085 | H358: 393576.34 | I358: 39365 | J358: 612405.58
A359: Totale complessivo | C359: 30938 | D359: 515482.14 | E359: 9231 | F359: 271541.54 | G359: 40169 | H359: 787023.68 | I359: 78730 | J359: 1224811.2

Sheet complessivo
A1: ASIN | B1: SKU | C1: Ordini Vendor 24 | D1: Valori ordini Vendor 24 | E1: Ordini Seller 24 | F1: Valori ordini Seller 24 | G1: % seller / totale | H1: Ordini Complessivi 24 | I1: Valori ordini Complessivi 24 | J1: Ordini Vendor 23 | K1: Valori ordini Vendor 23 | L1: Differenza Ordini | M1: Differenza Valore | N1: Differenza Valore %
A2: B0050IHH4E | B2: 40.979 | C2: 1117 | D2: 16410.86 | E2: =VLOOKUP(A2,s_02_2024!E:G,2,FALSE) -> 1 | F2: =VLOOKUP(A2,s_02_2024!E:G,3,FALSE) -> 19.9 | G2: =F2/I2 -> 0.001211143 | H2: =E2+C2 -> 1118 | I2: =F2+D2 -> 16430.76 | J2: =VLOOKUP(A2,v_02_2023!A:D,3,FALSE) -> 31 | K2: =VLOOKUP(A2,v_02_2023!A:D,4,FALSE) -> 404.7 | L2: =H2-J2 -> 1087 | M2: =I2-K2 -> 16026.06 | N2: =M2/K2 -> 39.599852
A3: B00BH202XK | B3: 40.808A | C3: 2 | D3: 22.85 | E3: 0 | F3: 0 | G3: =F3/I3 -> 0 | H3: =E3+C3 -> 2 | I3: =F3+D3 -> 22.85 | J3: =VLOOKUP(A3,v_02_2023!A:D,3,FALSE) -> 2 | K3: =VLOOKUP(A3,v_02_2023!A:D,4,FALSE) -> 35.73 | L3: =H3-J3 -> 0 | M3: =I3-K3 -> -12.88 | N3: =M3/K3 -> -0.36048139
A4: B00EYDRS1I | B4: 90.349 | C4: 23 | D4: 131.27 | E4: 0 | F4: 0 | G4: =F4/I4 -> 0 | H4: =E4+C4 -> 23 | I4: =F4+D4 -> 131.27 | J4: =VLOOKUP(A4,v_02_2023!A:D,3,FALSE) -> 198 | K4: =VLOOKUP(A4,v_02_2023!A:D,4,FALSE) -> 1106.56 | L4: =H4-J4 -> -175 | M4: =I4-K4 -> -975.29 | N4: =M4/K4 -> -0.8813711
A5: B00FAJUDU8 | B5: 40.967N | C5: 0 | D5: 0 | E5: =VLOOKUP(A5,s_02_2024!E:G,2,FALSE) -> 36 | F5: =VLOOKUP(A5,s_02_2024!E:G,3,FALSE) -> 1151.91 | G5: =F5/I5 -> 1 | H5: =E5+C5 -> 36 | I5: =F5+D5 -> 1151.91 | J5: =VLOOKUP(A5,v_02_2023!A:D,3,FALSE) -> 195 | K5: =VLOOKUP(A5,v_02_2023!A:D,4,FALSE) -> 4239.58 | L5: =H5-J5 -> -159 | M5: =I5-K5 -> -3087.67 | N5: =M5/K5 -> -0.7282962
A6: B00FFBED98 | B6: 40.11 | C6: 1 | D6: 41.24 | E6: 0 | F6: 0 | G6: =F6/I6 -> 0 | H6: =E6+C6 -> 1 | I6: =F6+D6 -> 41.24 | J6: 0 | K6: 0 | L6: =H6-J6 -> 1 | M6: =I6-K6 -> 41.24
A7: B00FFBFVG2 | B7: 40.100 | C7: 0 | D7: 0 | E7: 0 | F7: 0 | H7: =E7+C7 -> 0 | I7: =F7+D7 -> 0 | J7: =VLOOKUP(A7,v_02_2023!A:D,3,FALSE) -> 5 | K7: =VLOOKUP(A7,v_02_2023!A:D,4,FALSE) -> 32.25 | L7: =H7-J7 -> -5 | M7: =I7-K7 -> -32.25 | N7: =M7/K7 -> -1
A8: B00FMZ2VW8 | B8: HK-HQ601C PINK | C8: 0 | D8: 0 | E8: 0 | F8: 0 | H8: =E8+C8 -> 0 | I8: =F8+D8 -> 0 | J8: 0 | K8: 0 | L8: =H8-J8 -> 0 | M8: =I8-K8 -> 0
A9: B00J7MNQFS | B9: 40.994 | C9: 3 | D9: 61.3 | E9: 0 | F9: 0 | G9: =F9/I9 -> 0 | H9: =E9+C9 -> 3 | I9: =F9+D9 -> 61.3 | J9: =VLOOKUP(A9,v_02_2023!A:D,3,FALSE) -> 4 | K9: =VLOOKUP(A9,v_02_2023!A:D,4,FALSE) -> 69.7 | L9: =H9-J9 -> -1 | M9: =I9-K9 -> -8.4 | N9: =M9/K9 -> -0.1205165
A10: B00L5GPWFG | B10: 40.120 | C10: 3 | D10: 73.53 | E10: 0 | F10: 0 | G10: =F10/I10 -> 0 | H10: =E10+C10 -> 3 | I10: =F10+D10 -> 73.53 | J10: =VLOOKUP(A10,v_02_2023!A:D,3,FALSE) -> 2 | K10: =VLOOKUP(A10,v_02_2023!A:D,4,FALSE) -> 49.02 | L10: =H10-J10 -> 1 | M10: =I10-K10 -> 24.51 | N10: =M10/K10 -> 0.5
A11: B00L5H5KUW | B11: 40.121 | C11: 424 | D11: 7577.95 | E11: 0 | F11: 0 | G11: =F11/I11 -> 0 | H11: =E11+C11 -> 424 | I11: =F11+D11 -> 7577.95 | J11: =VLOOKUP(A11,v_02_2023!A:D,3,FALSE) -> 374 | K11: =VLOOKUP(A11,v_02_2023!A:D,4,FALSE) -> 6370.16 | L11: =H11-J11 -> 50 | M11: =I11-K11 -> 1207.79 | N11: =M11/K11 -> 0.1896012
A12: B00NSNZSLM | B12: 90.602 | C12: 1 | D12: 27.03 | E12: =VLOOKUP(A12,s_02_2024!E:G,2,FALSE) -> 96 | F12: =VLOOKUP(A12,s_02_2024!E:G,3,FALSE) -> 2882.4 | G12: =F12/I12 -> 0.99070952 | H12: =E12+C12 -> 97 | I12: =F12+D12 -> 2909.43 | J12: =VLOOKUP(A12,v_02_2023!A:D,3,FALSE) -> 529 | K12: =VLOOKUP(A12,v_02_2023!A:D,4,FALSE) -> 10857.32 | L12: =H12-J12 -> -432 | M12: =I12-K12 -> -7947.89 | N12: =M12/K12 -> -0.73203056
A13: B00OKE4RTM | B13: 90.386 | C13: 3 | D13: 147.35 | E13: 0 | F13: 0 | G13: =F13/I13 -> 0 | H13: =E13+C13 -> 3 | I13: =F13+D13 -> 147.35 | J13: =VLOOKUP(A13,v_02_2023!A:D,3,FALSE) -> 1 | K13: =VLOOKUP(A13,v_02_2023!A:D,4,FALSE) -> 53.22 | L13: =H13-J13 -> 2 | M13: =I13-K13 -> 94.13 | N13: =M13/K13 -> 1.768696
A14: B00OLZPU5K | B14: 40.947 | C14: 1 | D14: 10.57 | E14: 0 | F14: 0 | G14: =F14/I14 -> 0 | H14: =E14+C14 -> 1 | I14: =F14+D14 -> 10.57 | J14: =VLOOKUP(A14,v_02_2023!A:D,3,FALSE) -> 3 | K14: =VLOOKUP(A14,v_02_2023!A:D,4,FALSE) -> 31.71 | L14: =H14-J14 -> -2 | M14: =I14-K14 -> -21.14 | N14: =M14/K14 -> -0.66666667
A15: B011LFVLW8 | B15: 90.620 | C15: 24 | D15: 784.8 | E15: 0 | F15: 0 | G15: =F15/I15 -> 0 | H15: =E15+C15 -> 24 | I15: =F15+D15 -> 784.8 | J15: =VLOOKUP(A15,v_02_2023!A:D,3,FALSE) -> 103 | K15: =VLOOKUP(A15,v_02_2023!A:D,4,FALSE) -> 2946.83 | L15: =H15-J15 -> -79 | M15: =I15-K15 -> -2162.03 | N15: =M15/K15 -> -0.73367992
A16: B011LH9V8M | B16: 40.958V | C16: 1 | D16: 6.73 | E16: 0 | F16: 0 | G16: =F16/I16 -> 0 | H16: =E16+C16 -> 1 | I16: =F16+D16 -> 6.73 | J16: 0 | K16: 0 | L16: =H16-J16 -> 1 | M16: =I16-K16 -> 6.73
A17: B015T5GR0C | B17: 40.760 | C17: 1 | D17: 4.83 | E17: 0 | F17: 0 | G17: =F17/I17 -> 0 | H17: =E17+C17 -> 1 | I17: =F17+D17 -> 4.83 | J17: 0 | K17: 0 | L17: =H17-J17 -> 1 | M17: =I17-K17 -> 4.83
A18: B016MWFVIU | B18: 40.761 | C18: 1 | D18: 16.31 | E18: 0 | F18: 0 | G18: =F18/I18 -> 0 | H18: =E18+C18 -> 1 | I18: =F18+D18 -> 16.31 | J18: 0 | K18: 0 | L18: =H18-J18 -> 1 | M18: =I18-K18 -> 16.31
A19: B017IUJA50 | B19: 90.920G | C19: 293 | D19: 4779.63 | E19: =VLOOKUP(A19,s_02_2024!E:G,2,FALSE) -> 7 | F19: =VLOOKUP(A19,s_02_2024!E:G,3,FALSE) -> 155.61 | G19: =F19/I19 -> 0.031530382 | H19: =E19+C19 -> 300 | I19: =F19+D19 -> 4935.24 | J19: =VLOOKUP(A19,v_02_2023!A:D,3,FALSE) -> 468 | K19: =VLOOKUP(A19,v_02_2023!A:D,4,FALSE) -> 7132.71 | L19: =H19-J19 -> -168 | M19: =I19-K19 -> -2197.47 | N19: =M19/K19 -> -0.30808346
A20: B01CHW1L88 | B20: PE.001 | C20: 1 | D20: 9.54 | E20: 0 | F20: 0 | G20: =F20/I20 -> 0 | H20: =E20+C20 -> 1 | I20: =F20+D20 -> 9.54 | J20: 0 | K20: 0 | L20: =H20-J20 -> 1 | M20: =I20-K20 -> 9.54
A21: B01CHW1YD0 | B21: PE.140 | C21: 2 | D21: 19.03 | E21: 0 | F21: 0 | G21: =F21/I21 -> 0 | H21: =E21+C21 -> 2 | I21: =F21+D21 -> 19.03 | J21: 0 | K21: 0 | L21: =H21-J21 -> 2 | M21: =I21-K21 -> 19.03
A22: B01CHW20UQ | B22: PE.400 | C22: 1 | D22: 11.39 | E22: 0 | F22: 0 | G22: =F22/I22 -> 0 | H22: =E22+C22 -> 1 | I22: =F22+D22 -> 11.39 | J22: 0 | K22: 0 | L22: =H22-J22 -> 1 | M22: =I22-K22 -> 11.39
A23: B01CNX6UIM | B23: PE.300 | C23: 2 | D23: 10.81 | E23: 0 | F23: 0 | G23: =F23/I23 -> 0 | H23: =E23+C23 -> 2 | I23: =F23+D23 -> 10.81 | J23: 0 | K23: 0 | L23: =H23-J23 -> 2 | M23: =I23-K23 -> 10.81
A24: B01CNX6Z78 | B24: 90.820 | C24: 11 | D24: 244.89 | E24: 0 | F24: 0 | G24: =F24/I24 -> 0 | H24: =E24+C24 -> 11 | I24: =F24+D24 -> 244.89 | J24: =VLOOKUP(A24,v_02_2023!A:D,3,FALSE) -> 42 | K24: =VLOOKUP(A24,v_02_2023!A:D,4,FALSE) -> 878.33 | L24: =H24-J24 -> -31 | M24: =I24-K24 -> -633.44 | N24: =M24/K24 -> -0.7211868
A25: B01CNX704K | B25: 90.825 | C25: 1 | D25: 21.26 | E25: =VLOOKUP(A25,s_02_2024!E:G,2,FALSE) -> 5 | F25: =VLOOKUP(A25,s_02_2024!E:G,3,FALSE) -> 234.5 | G25: =F25/I25 -> 0.9168752 | H25: =E25+C25 -> 6 | I25: =F25+D25 -> 255.76 | J25: =VLOOKUP(A25,v_02_2023!A:D,3,FALSE) -> 2 | K25: =VLOOKUP(A25,v_02_2023!A:D,4,FALSE) -> 70.34 | L25: =H25-J25 -> 4 | M25: =I25-K25 -> 185.42 | N25: =M25/K25 -> 2.6360535
A26: B01CNX71NA | B26: 90.871 | C26: 9 | D26: 891.66 | E26: 0 | F26: 0 | G26: =F26/I26 -> 0 | H26: =E26+C26 -> 9 | I26: =F26+D26 -> 891.66 | J26: =VLOOKUP(A26,v_02_2023!A:D,3,FALSE) -> 7 | K26: =VLOOKUP(A26,v_02_2023!A:D,4,FALSE) -> 566.9 | L26: =H26-J26 -> 2 | M26: =I26-K26 -> 324.76 | N26: =M26/K26 -> 0.57286999
A27: B01CNXP36C | B27: 40.981N | C27: 1 | D27: 9.13 | E27: 0 | F27: 0 | G27: =F27/I27 -> 0 | H27: =E27+C27 -> 1 | I27: =F27+D27 -> 9.13 | J27: 0 | K27: 0 | L27: =H27-J27 -> 1 | M27: =I27-K27 -> 9.13
A28: B01HM47LF8 | B28: MD.004 | C28: 3 | D28: 10.22 | E28: 0 | F28: 0 | G28: =F28/I28 -> 0 | H28: =E28+C28 -> 3 | I28: =F28+D28 -> 10.22 | J28: =VLOOKUP(A28,v_02_2023!A:D,3,FALSE) -> 9 | K28: =VLOOKUP(A28,v_02_2023!A:D,4,FALSE) -> 30.95 | L28: =H28-J28 -> -6 | M28: =I28-K28 -> -20.73 | N28: =M28/K28 -> -0.66978998
A29: B01I497WWM | B29: 90.920R | C29: 4 | D29: 66.56 | E29: =VLOOKUP(A29,s_02_2024!E:G,2,FALSE) -> 1084 | F29: =VLOOKUP(A29,s_02_2024!E:G,3,FALSE) -> 21587.91 | G29: =F29/I29 -> 0.99692627 | H29: =E29+C29 -> 1088 | I29: =F29+D29 -> 21654.47 | J29: =VLOOKUP(A29,v_02_2023!A:D,3,FALSE) -> 2309 | K29: =VLOOKUP(A29,v_02_2023!A:D,4,FALSE) -> 31490.19 | L29: =H29-J29 -> -1221 | M29: =I29-K29 -> -9835.72 | N29: =M29/K29 -> -0.31234235
A30: B01IHGX2HQ | B30: MD.104 | C30: 13 | D30: 50.63 | E30: 0 | F30: 0 | G30: =F30/I30 -> 0 | H30: =E30+C30 -> 13 | I30: =F30+D30 -> 50.63 | J30: =VLOOKUP(A30,v_02_2023!A:D,3,FALSE) -> 2 | K30: =VLOOKUP(A30,v_02_2023!A:D,4,FALSE) -> 11.51 | L30: =H30-J30 -> 11 | M30: =I30-K30 -> 39.12 | N30: =M30/K30 -> 3.3987837
A31: B01II7S968 | B31: MD.217 | C31: 5 | D31: 29.95 | E31: 0 | F31: 0 | G31: =F31/I31 -> 0 | H31: =E31+C31 -> 5 | I31: =F31+D31 -> 29.95 | J31: =VLOOKUP(A31,v_02_2023!A:D,3,FALSE) -> 1 | K31: =VLOOKUP(A31,v_02_2023!A:D,4,FALSE) -> 5.46 | L31: =H31-J31 -> 4 | M31: =I31-K31 -> 24.49 | N31: =M31/K31 -> 4.485348
A32: B01K6P6NT0 | B32: 40.400 | C32: 0 | D32: 0 | E32: 0 | F32: 0 | H32: =E32+C32 -> 0 | I32: =F32+D32 -> 0 | J32: =VLOOKUP(A32,v_02_2023!A:D,3,FALSE) -> 1 | K32: =VLOOKUP(A32,v_02_2023!A:D,4,FALSE) -> 18.93 | L32: =H32-J32 -> -1 | M32: =I32-K32 -> -18.93 | N32: =M32/K32 -> -1
A33: B01KMJ9OXW | B33: 90.590Y | C33: 5 | D33: 145.4 | E33: =VLOOKUP(A33,s_02_2024!E:G,2,FALSE) -> 285 | F33: =VLOOKUP(A33,s_02_2024!E:G,3,FALSE) -> 9936.02 | G33: =F33/I33 -> 0.98557743 | H33: =E33+C33 -> 290 | I33: =F33+D33 -> 10081.42 | J33: =VLOOKUP(A33,v_02_2023!A:D,3,FALSE) -> 677 | K33: =VLOOKUP(A33,v_02_2023!A:D,4,FALSE) -> 21012.58 | L33: =H33-J33 -> -387 | M33: =I33-K33 -> -10931.16 | N33: =M33/K33 -> -0.52021979
A34: B01M4O6145 | B34: 90.071 | C34: 69 | D34: 1416.11 | E34: 0 | F34: 0 | G34: =F34/I34 -> 0 | H34: =E34+C34 -> 69 | I34: =F34+D34 -> 1416.11 | J34: =VLOOKUP(A34,v_02_2023!A:D,3,FALSE) -> 71 | K34: =VLOOKUP(A34,v_02_2023!A:D,4,FALSE) -> 1552.39 | L34: =H34-J34 -> -2 | M34: =I34-K34 -> -136.28 | N34: =M34/K34 -> -0.087787218
A35: B01MFA4H6K | B35: S304 | C35: 0 | D35: 0 | E35: 0 | F35: 0 | H35: =E35+C35 -> 0 | I35: =F35+D35 -> 0 | J35: 0 | K35: 0 | L35: =H35-J35 -> 0 | M35: =I35-K35 -> 0
A36: B01MTSEGF9 | B36: 50.700 | C36: 0 | D36: 0 | E36: =VLOOKUP(A36,s_02_2024!E:G,2,FALSE) -> 20 | F36: =VLOOKUP(A36,s_02_2024!E:G,3,FALSE) -> 898 | G36: =F36/I36 -> 1 | H36: =E36+C36 -> 20 | I36: =F36+D36 -> 898 | J36: =VLOOKUP(A36,v_02_2023!A:D,3,FALSE) -> 228 | K36: =VLOOKUP(A36,v_02_2023!A:D,4,FALSE) -> 6544.37 | L36: =H36-J36 -> -208 | M36: =I36-K36 -> -5646.37 | N36: =M36/K36 -> -0.86278282
A37: B01N12PI05 | B37: PE.301 | C37: 10 | D37: 36.22 | E37: 0 | F37: 0 | G37: =F37/I37 -> 0 | H37: =E37+C37 -> 10 | I37: =F37+D37 -> 36.22 | J37: 0 | K37: 0 | L37: =H37-J37 -> 10 | M37: =I37-K37 -> 36.22
A38: B01N4L0SUV | B38: 40.926 | C38: 1 | D38: 20.92 | E38: 0 | F38: 0 | G38: =F38/I38 -> 0 | H38: =E38+C38 -> 1 | I38: =F38+D38 -> 20.92 | J38: =VLOOKUP(A38,v_02_2023!A:D,3,FALSE) -> -1 | K38: =VLOOKUP(A38,v_02_2023!A:D,4,FALSE) -> -15.29 | L38: =H38-J38 -> 2 | M38: =I38-K38 -> 36.21 | N38: =M38/K38 -> -2.3682145
A39: B06W2JZMNV | B39: 90.200 | C39: 1 | D39: 36.58 | E39: 0 | F39: 0 | G39: =F39/I39 -> 0 | H39: =E39+C39 -> 1 | I39: =F39+D39 -> 36.58 | J39: 0 | K39: 0 | L39: =H39-J39 -> 1 | M39: =I39-K39 -> 36.58
A40: B06WGS8ZVG | B40: 90.131 | C40: 2 | D40: 25.04 | E40: 0 | F40: 0 | G40: =F40/I40 -> 0 | H40: =E40+C40 -> 2 | I40: =F40+D40 -> 25.04 | J40: =VLOOKUP(A40,v_02_2023!A:D,3,FALSE) -> 5 | K40: =VLOOKUP(A40,v_02_2023!A:D,4,FALSE) -> 56.77 | L40: =H40-J40 -> -3 | M40: =I40-K40 -> -31.73 | N40: =M40/K40 -> -0.55892197
A41: B06XPK3BTC | B41: 40.450GO | C41: 8 | D41: 105.87 | E41: 0 | F41: 0 | G41: =F41/I41 -> 0 | H41: =E41+C41 -> 8 | I41: =F41+D41 -> 105.87 | J41: =VLOOKUP(A41,v_02_2023!A:D,3,FALSE) -> 10 | K41: =VLOOKUP(A41,v_02_2023!A:D,4,FALSE) -> 153.45 | L41: =H41-J41 -> -2 | M41: =I41-K41 -> -47.58 | N41: =M41/K41 -> -0.31006843
A42: B06XPYSCGJ | B42: 40.939 | C42: 4 | D42: 15.41 | E42: 0 | F42: 0 | G42: =F42/I42 -> 0 | H42: =E42+C42 -> 4 | I42: =F42+D42 -> 15.41 | J42: =VLOOKUP(A42,v_02_2023!A:D,3,FALSE) -> 17 | K42: =VLOOKUP(A42,v_02_2023!A:D,4,FALSE) -> 64.22 | L42: =H42-J42 -> -13 | M42: =I42-K42 -> -48.81 | N42: =M42/K42 -> -0.7600436
A43: B06XQ25NLB | B43: 40.220 | C43: 0 | D43: 0 | E43: 0 | F43: 0 | H43: =E43+C43 -> 0 | I43: =F43+D43 -> 0 | J43: =VLOOKUP(A43,v_02_2023!A:D,3,FALSE) -> 0 | K43: =VLOOKUP(A43,v_02_2023!A:D,4,FALSE) -> 0 | L43: =H43-J43 -> 0 | M43: =I43-K43 -> 0
A44: B06Y17FS6D | B44: 90.550 | C44: 199 | D44: 5568.49 | E44: =VLOOKUP(A44,s_02_2024!E:G,2,FALSE) -> #N/A | F44: =VLOOKUP(A44,s_02_2024!E:G,3,FALSE) -> #N/A | G44: =F44/I44 -> #N/A | H44: =E44+C44 -> #N/A | I44: =F44+D44 -> #N/A | J44: =VLOOKUP(A44,v_02_2023!A:D,3,FALSE) -> 196 | K44: =VLOOKUP(A44,v_02_2023!A:D,4,FALSE) -> 5302.56 | L44: =H44-J44 -> #N/A | M44: =I44-K44 -> #N/A | N44: =M44/K44 -> #N/A
A45: B06Y195DJN | B45: 90.882 | C45: 4 | D45: 135.73 | E45: =VLOOKUP(A45,s_02_2024!E:G,2,FALSE) -> 31 | F45: =VLOOKUP(A45,s_02_2024!E:G,3,FALSE) -> 1546.9 | G45: =F45/I45 -> 0.91933461 | H45: =E45+C45 -> 35 | I45: =F45+D45 -> 1682.63 | J45: =VLOOKUP(A45,v_02_2023!A:D,3,FALSE) -> 60 | K45: =VLOOKUP(A45,v_02_2023!A:D,4,FALSE) -> 2486.71 | L45: =H45-J45 -> -25 | M45: =I45-K45 -> -804.08 | N45: =M45/K45 -> -0.32335093
A46: B06Y1997YH | B46: 90.883 | C46: 33 | D46: 1917.99 | E46: 0 | F46: 0 | G46: =F46/I46 -> 0 | H46: =E46+C46 -> 33 | I46: =F46+D46 -> 1917.99 | J46: =VLOOKUP(A46,v_02_2023!A:D,3,FALSE) -> 64 | K46: =VLOOKUP(A46,v_02_2023!A:D,4,FALSE) -> 3716.24 | L46: =H46-J46 -> -31 | M46: =I46-K46 -> -1798.25 | N46: =M46/K46 -> -0.48388963
A47: B06Y1P6DPZ | B47: VE.112 | C47: 2 | D47: 47.22 | E47: 0 | F47: 0 | G47: =F47/I47 -> 0 | H47: =E47+C47 -> 2 | I47: =F47+D47 -> 47.22 | J47: 0 | K47: 0 | L47: =H47-J47 -> 2 | M47: =I47-K47 -> 47.22
A48: B073B57HQH | B48: 90.886 | C48: 0 | D48: 0 | E48: 0 | F48: 0 | H48: =E48+C48 -> 0 | I48: =F48+D48 -> 0 | J48: =VLOOKUP(A48,v_02_2023!A:D,3,FALSE) -> 8 | K48: =VLOOKUP(A48,v_02_2023!A:D,4,FALSE) -> 809.04 | L48: =H48-J48 -> -8 | M48: =I48-K48 -> -809.04 | N48: =M48/K48 -> -1
A49: B073B67PLQ | B49: 90.884 | C49: 37 | D49: 2906.57 | E49: 0 | F49: 0 | G49: =F49/I49 -> 0 | H49: =E49+C49 -> 37 | I49: =F49+D49 -> 2906.57 | J49: =VLOOKUP(A49,v_02_2023!A:D,3,FALSE) -> 60 | K49: =VLOOKUP(A49,v_02_2023!A:D,4,FALSE) -> 4280.89 | L49: =H49-J49 -> -23 | M49: =I49-K49 -> -1374.32 | N49: =M49/K49 -> -0.32103605
A50: B0757TJRR9 | B50: 40.500 | C50: 1 | D50: 24.92 | E50: =VLOOKUP(A50,s_02_2024!E:G,2,FALSE) -> 602 | F50: =VLOOKUP(A50,s_02_2024!E:G,3,FALSE) -> 19788.01 | G50: =F50/I50 -> 0.99874224 | H50: =E50+C50 -> 603 | I50: =F50+D50 -> 19812.93 | J50: =VLOOKUP(A50,v_02_2023!A:D,3,FALSE) -> 872 | K50: =VLOOKUP(A50,v_02_2023!A:D,4,FALSE) -> 22779.27 | L50: =H50-J50 -> -269 | M50: =I50-K50 -> -2966.34 | N50: =M50/K50 -> -0.13022103
A51: B075FX6RFP | B51: BC.040N | C51: 8 | D51: 266 | E51: =VLOOKUP(A51,s_02_2024!E:G,2,FALSE) -> 25 | F51: =VLOOKUP(A51,s_02_2024!E:G,3,FALSE) -> 950.5 | G51: =F51/I51 -> 0.78133991 | H51: =E51+C51 -> 33 | I51: =F51+D51 -> 1216.5 | J51: =VLOOKUP(A51,v_02_2023!A:D,3,FALSE) -> 10 | K51: =VLOOKUP(A51,v_02_2023!A:D,4,FALSE) -> 349.2 | L51: =H51-J51 -> 23 | M51: =I51-K51 -> 867.3 | N51: =M51/K51 -> 2.483677
A52: B075K5C2QG | B52: RI.201 | C52: 3 | D52: 59.91 | E52: 0 | F52: 0 | G52: =F52/I52 -> 0 | H52: =E52+C52 -> 3 | I52: =F52+D52 -> 59.91 | J52: =VLOOKUP(A52,v_02_2023!A:D,3,FALSE) -> -1 | K52: =VLOOKUP(A52,v_02_2023!A:D,4,FALSE) -> -14.75 | L52: =H52-J52 -> 4 | M52: =I52-K52 -> 74.66 | N52: =M52/K52 -> -5.0616949
A53: B075RF5S3N | B53: BC.160A | C53: 8 | D53: 187.22 | E53: 0 | F53: 0 | G53: =F53/I53 -> 0 | H53: =E53+C53 -> 8 | I53: =F53+D53 -> 187.22 | J53: =VLOOKUP(A53,v_02_2023!A:D,3,FALSE) -> 20 | K53: =VLOOKUP(A53,v_02_2023!A:D,4,FALSE) -> 422.81 | L53: =H53-J53 -> -12 | M53: =I53-K53 -> -235.59 | N53: =M53/K53 -> -0.55720063
A54: B075XR3T8V | B54: BT.600Y | C54: 10 | D54: 318.14 | E54: 0 | F54: 0 | G54: =F54/I54 -> 0 | H54: =E54+C54 -> 10 | I54: =F54+D54 -> 318.14 | J54: =VLOOKUP(A54,v_02_2023!A:D,3,FALSE) -> 3 | K54: =VLOOKUP(A54,v_02_2023!A:D,4,FALSE) -> 108.39 | L54: =H54-J54 -> 7 | M54: =I54-K54 -> 209.75 | N54: =M54/K54 -> 1.9351416
A55: B076D74TC7 | B55: BT.700Y | C55: 9 | D55: 287.17 | E55: =VLOOKUP(A55,s_02_2024!E:G,2,FALSE) -> 4 | F55: =VLOOKUP(A55,s_02_2024!E:G,3,FALSE) -> 147.96 | G55: =F55/I55 -> 0.34003631 | H55: =E55+C55 -> 13 | I55: =F55+D55 -> 435.13 | J55: =VLOOKUP(A55,v_02_2023!A:D,3,FALSE) -> 24 | K55: =VLOOKUP(A55,v_02_2023!A:D,4,FALSE) -> 699.71 | L55: =H55-J55 -> -11 | M55: =I55-K55 -> -264.58 | N55: =M55/K55 -> -0.37812808
A56: B076DC4VWG | B56: 40.501 | C56: 6 | D56: 149.54 | E56: 0 | F56: 0 | G56: =F56/I56 -> 0 | H56: =E56+C56 -> 6 | I56: =F56+D56 -> 149.54 | J56: =VLOOKUP(A56,v_02_2023!A:D,3,FALSE) -> 4 | K56: =VLOOKUP(A56,v_02_2023!A:D,4,FALSE) -> 74 | L56: =H56-J56 -> 2 | M56: =I56-K56 -> 75.54 | N56: =M56/K56 -> 1.0208108
A57: B076DCF8PV | B57: BB.102 | C57: 1 | D57: 20.41 | E57: 0 | F57: 0 | G57: =F57/I57 -> 0 | H57: =E57+C57 -> 1 | I57: =F57+D57 -> 20.41 | J57: 0 | K57: 0 | L57: =H57-J57 -> 1 | M57: =I57-K57 -> 20.41
A58: B076DCKSTJ | B58: BT.602H | C58: 5 | D58: 102.22 | E58: =VLOOKUP(A58,s_02_2024!E:G,2,FALSE) -> 144 | F58: =VLOOKUP(A58,s_02_2024!E:G,3,FALSE) -> 3615.6 | G58: =F58/I58 -> 0.97250539 | H58: =E58+C58 -> 149 | I58: =F58+D58 -> 3717.82 | J58: =VLOOKUP(A58,v_02_2023!A:D,3,FALSE) -> 407 | K58: =VLOOKUP(A58,v_02_2023!A:D,4,FALSE) -> 8225.59 | L58: =H58-J58 -> -258 | M58: =I58-K58 -> -4507.77 | N58: =M58/K58 -> -0.54801783
A59: B076DCL19C | B59: BP.720 | C59: 21 | D59: 1025.54 | E59: 0 | F59: 0 | G59: =F59/I59 -> 0 | H59: =E59+C59 -> 21 | I59: =F59+D59 -> 1025.54 | J59: =VLOOKUP(A59,v_02_2023!A:D,3,FALSE) -> 14 | K59: =VLOOKUP(A59,v_02_2023!A:D,4,FALSE) -> 808.78 | L59: =H59-J59 -> 7 | M59: =I59-K59 -> 216.76 | N59: =M59/K59 -> 0.26800861
A60: B076DCX3JH | B60: BB.103 | C60: 1 | D60: 37.46 | E60: 0 | F60: 0 | G60: =F60/I60 -> 0 | H60: =E60+C60 -> 1 | I60: =F60+D60 -> 37.46 | J60: 0 | K60: 0 | L60: =H60-J60 -> 1 | M60: =I60-K60 -> 37.46
A61: B076DD35DZ | B61: BC.002 | C61: 6 | D61: 247.44 | E61: 0 | F61: 0 | G61: =F61/I61 -> 0 | H61: =E61+C61 -> 6 | I61: =F61+D61 -> 247.44 | J61: =VLOOKUP(A61,v_02_2023!A:D,3,FALSE) -> 6 | K61: =VLOOKUP(A61,v_02_2023!A:D,4,FALSE) -> 265.89 | L61: =H61-J61 -> 0 | M61: =I61-K61 -> -18.45 | N61: =M61/K61 -> -0.069389597
A62: B076Q7BR6F | B62: BC.041N | C62: 16 | D62: 667.13 | E62: =VLOOKUP(A62,s_02_2024!E:G,2,FALSE) -> 21 | F62: =VLOOKUP(A62,s_02_2024!E:G,3,FALSE) -> 1029.9 | G62: =F62/I62 -> 0.60688379 | H62: =E62+C62 -> 37 | I62: =F62+D62 -> 1697.03 | J62: =VLOOKUP(A62,v_02_2023!A:D,3,FALSE) -> 163 | K62: =VLOOKUP(A62,v_02_2023!A:D,4,FALSE) -> 6724.18 | L62: =H62-J62 -> -126 | M62: =I62-K62 -> -5027.15 | N62: =M62/K62 -> -0.74762276
A63: B076QCMZX1 | B63: 40.821 | C63: 121 | D63: 1441.72 | E63: 0 | F63: 0 | G63: =F63/I63 -> 0 | H63: =E63+C63 -> 121 | I63: =F63+D63 -> 1441.72 | J63: =VLOOKUP(A63,v_02_2023!A:D,3,FALSE) -> 8 | K63: =VLOOKUP(A63,v_02_2023!A:D,4,FALSE) -> 79.73 | L63: =H63-J63 -> 113 | M63: =I63-K63 -> 1361.99 | N63: =M63/K63 -> 17.082529
A64: B076QFRRZ5 | B64: 40.931 | C64: 85 | D64: 1190.6 | E64: 0 | F64: 0 | G64: =F64/I64 -> 0 | H64: =E64+C64 -> 85 | I64: =F64+D64 -> 1190.6 | J64: =VLOOKUP(A64,v_02_2023!A:D,3,FALSE) -> 183 | K64: =VLOOKUP(A64,v_02_2023!A:D,4,FALSE) -> 2633.03 | L64: =H64-J64 -> -98 | M64: =I64-K64 -> -1442.43 | N64: =M64/K64 -> -0.54782133
A65: B079SB5VJZ | B65: 50451 | C65: 18 | D65: 781.58 | E65: 0 | F65: 0 | G65: =F65/I65 -> 0 | H65: =E65+C65 -> 18 | I65: =F65+D65 -> 781.58 | J65: =VLOOKUP(A65,v_02_2023!A:D,3,FALSE) -> 339 | K65: =VLOOKUP(A65,v_02_2023!A:D,4,FALSE) -> 11109.66 | L65: =H65-J65 -> -321 | M65: =I65-K65 -> -10328.08 | N65: =M65/K65 -> -0.92964861
A66: B07B9CBD91 | B66: VE.550 | C66: 1 | D66: 117.41 | E66: 0 | F66: 0 | G66: =F66/I66 -> 0 | H66: =E66+C66 -> 1 | I66: =F66+D66 -> 117.41 | J66: 0 | K66: 0 | L66: =H66-J66 -> 1 | M66: =I66-K66 -> 117.41
A67: B07B9CPH62 | B67: BG.200Y | C67: 28 | D67: 1709.64 | E67: 0 | F67: 0 | G67: =F67/I67 -> 0 | H67: =E67+C67 -> 28 | I67: =F67+D67 -> 1709.64 | J67: =VLOOKUP(A67,v_02_2023!A:D,3,FALSE) -> 39 | K67: =VLOOKUP(A67,v_02_2023!A:D,4,FALSE) -> 1931.85 | L67: =H67-J67 -> -11 | M67: =I67-K67 -> -222.21 | N67: =M67/K67 -> -0.11502446
A68: B07BB2DQ4V | B68: BT.150Y | C68: 3 | D68: 93.34 | E68: =VLOOKUP(A68,s_02_2024!E:G,2,FALSE) -> 12 | F68: =VLOOKUP(A68,s_02_2024!E:G,3,FALSE) -> 478.8 | G68: =F68/I68 -> 0.83685811 | H68: =E68+C68 -> 15 | I68: =F68+D68 -> 572.14 | J68: =VLOOKUP(A68,v_02_2023!A:D,3,FALSE) -> 95 | K68: =VLOOKUP(A68,v_02_2023!A:D,4,FALSE) -> 2881.49 | L68: =H68-J68 -> -80 | M68: =I68-K68 -> -2309.35 | N68: =M68/K68 -> -0.801443
A69: B07BHCZR84 | B69: BA.200Y | C69: 47 | D69: 573.23 | E69: 0 | F69: 0 | G69: =F69/I69 -> 0 | H69: =E69+C69 -> 47 | I69: =F69+D69 -> 573.23 | J69: =VLOOKUP(A69,v_02_2023!A:D,3,FALSE) -> 17 | K69: =VLOOKUP(A69,v_02_2023!A:D,4,FALSE) -> 177.33 | L69: =H69-J69 -> 30 | M69: =I69-K69 -> 395.9 | N69: =M69/K69 -> 2.2325608
A70: B07BHTW4WV | B70: VE.210 | C70: 1 | D70: 55.84 | E70: 0 | F70: 0 | G70: =F70/I70 -> 0 | H70: =E70+C70 -> 1 | I70: =F70+D70 -> 55.84 | J70: 0 | K70: 0 | L70: =H70-J70 -> 1 | M70: =I70-K70 -> 55.84
A71: B07CZ4WMB8 | B71: 40.330 | C71: 2 | D71: 49.42 | E71: 0 | F71: 0 | G71: =F71/I71 -> 0 | H71: =E71+C71 -> 2 | I71: =F71+D71 -> 49.42 | J71: =VLOOKUP(A71,v_02_2023!A:D,3,FALSE) -> 1 | K71: =VLOOKUP(A71,v_02_2023!A:D,4,FALSE) -> 14.14 | L71: =H71-J71 -> 1 | M71: =I71-K71 -> 35.28 | N71: =M71/K71 -> 2.4950495
A72: B07F187NFQ | B72: 50.900 | C72: 10 | D72: 42.48 | E72: 0 | F72: 0 | G72: =F72/I72 -> 0 | H72: =E72+C72 -> 10 | I72: =F72+D72 -> 42.48 | J72: 0 | K72: 0 | L72: =H72-J72 -> 10 | M72: =I72-K72 -> 42.48
A73: B07FN14FSN | B73: 50.160 | C73: 1 | D73: 28.84 | E73: 0 | F73: 0 | G73: =F73/I73 -> 0 | H73: =E73+C73 -> 1 | I73: =F73+D73 -> 28.84 | J73: 0 | K73: 0 | L73: =H73-J73 -> 1 | M73: =I73-K73 -> 28.84
A74: B07HFQH172 | B74: BC.250 | C74: 1 | D74: 41.93 | E74: 0 | F74: 0 | G74: =F74/I74 -> 0 | H74: =E74+C74 -> 1 | I74: =F74+D74 -> 41.93 | J74: =VLOOKUP(A74,v_02_2023!A:D,3,FALSE) -> 18 | K74: =VLOOKUP(A74,v_02_2023!A:D,4,FALSE) -> 740.32 | L74: =H74-J74 -> -17 | M74: =I74-K74 -> -698.39 | N74: =M74/K74 -> -0.94336233
A75: B07HHDSJHM | B75: BI.504 | C75: 0 | D75: 0 | E75: 0 | F75: 0 | H75: =E75+C75 -> 0 | I75: =F75+D75 -> 0 | J75: =VLOOKUP(A75,v_02_2023!A:D,3,FALSE) -> 1 | K75: =VLOOKUP(A75,v_02_2023!A:D,4,FALSE) -> 4.02 | L75: =H75-J75 -> -1 | M75: =I75-K75 -> -4.02 | N75: =M75/K75 -> -1
A76: B07HM7P6MP | B76: RI.080 | C76: 0 | D76: 0 | E76: =VLOOKUP(A76,s_02_2024!E:G,2,FALSE) -> 21 | F76: =VLOOKUP(A76,s_02_2024!E:G,3,FALSE) -> 607.9 | G76: =F76/I76 -> 1 | H76: =E76+C76 -> 21 | I76: =F76+D76 -> 607.9 | J76: =VLOOKUP(A76,v_02_2023!A:D,3,FALSE) -> 31 | K76: =VLOOKUP(A76,v_02_2023!A:D,4,FALSE) -> 756.86 | L76: =H76-J76 -> -10 | M76: =I76-K76 -> -148.96 | N76: =M76/K76 -> -0.19681315
A77: B07JGVMFY1 | B77: BP.581 | C77: 134 | D77: 1996.13 | E77: 0 | F77: 0 | G77: =F77/I77 -> 0 | H77: =E77+C77 -> 134 | I77: =F77+D77 -> 1996.13 | J77: =VLOOKUP(A77,v_02_2023!A:D,3,FALSE) -> 20 | K77: =VLOOKUP(A77,v_02_2023!A:D,4,FALSE) -> 287 | L77: =H77-J77 -> 114 | M77: =I77-K77 -> 1709.13 | N77: =M77/K77 -> 5.9551568
A78: B07KYWNC7Z | B78: 40.405 | C78: 22 | D78: 495.66 | E78: 0 | F78: 0 | G78: =F78/I78 -> 0 | H78: =E78+C78 -> 22 | I78: =F78+D78 -> 495.66 | J78: =VLOOKUP(A78,v_02_2023!A:D,3,FALSE) -> 113 | K78: =VLOOKUP(A78,v_02_2023!A:D,4,FALSE) -> 2230.52 | L78: =H78-J78 -> -91 | M78: =I78-K78 -> -1734.86 | N78: =M78/K78 -> -0.77778276
A79: B07MC8ZVRM | B79: 40.452 | C79: 27 | D79: 672.84 | E79: 0 | F79: 0 | G79: =F79/I79 -> 0 | H79: =E79+C79 -> 27 | I79: =F79+D79 -> 672.84 | J79: 0 | K79: 0 | L79: =H79-J79 -> 27 | M79: =I79-K79 -> 672.84
A80: B07N4C3H3V | B80: 40.405 | C80: -14 | D80: -161.38 | E80: =VLOOKUP(A80,s_02_2024!E:G,2,FALSE) -> 191 | F80: =VLOOKUP(A80,s_02_2024!E:G,3,FALSE) -> 2840.52 | G80: =F80/I80 -> 1.0602357 | H80: =E80+C80 -> 177 | I80: =F80+D80 -> 2679.14 | J80: =VLOOKUP(A80,v_02_2023!A:D,3,FALSE) -> 236 | K80: =VLOOKUP(A80,v_02_2023!A:D,4,FALSE) -> 2488.22 | L80: =H80-J80 -> -59 | M80: =I80-K80 -> 190.92 | N80: =M80/K80 -> 0.07672955
A81: B07NNZSW1W | B81: BT.110 | C81: 4 | D81: 67.67 | E81: 0 | F81: 0 | G81: =F81/I81 -> 0 | H81: =E81+C81 -> 4 | I81: =F81+D81 -> 67.67 | J81: =VLOOKUP(A81,v_02_2023!A:D,3,FALSE) -> 3 | K81: =VLOOKUP(A81,v_02_2023!A:D,4,FALSE) -> 71.39 | L81: =H81-J81 -> 1 | M81: =I81-K81 -> -3.72 | N81: =M81/K81 -> -0.052108138
A82: B07NP6YY5W | B82: BP.200 | C82: 0 | D82: 0 | E82: 0 | F82: 0 | H82: =E82+C82 -> 0 | I82: =F82+D82 -> 0 | J82: =VLOOKUP(A82,v_02_2023!A:D,3,FALSE) -> 4 | K82: =VLOOKUP(A82,v_02_2023!A:D,4,FALSE) -> 232.54 | L82: =H82-J82 -> -4 | M82: =I82-K82 -> -232.54 | N82: =M82/K82 -> -1
A83: B07NQ1T7YK | B83: BP.101H | C83: 625 | D83: 7845.7 | E83: 0 | F83: 0 | G83: =F83/I83 -> 0 | H83: =E83+C83 -> 625 | I83: =F83+D83 -> 7845.7 | J83: =VLOOKUP(A83,v_02_2023!A:D,3,FALSE) -> 272 | K83: =VLOOKUP(A83,v_02_2023!A:D,4,FALSE) -> 3345.17 | L83: =H83-J83 -> 353 | M83: =I83-K83 -> 4500.53 | N83: =M83/K83 -> 1.3453816
A84: B07NQ2VYGD | B84: BT.710Y | C84: 26 | D84: 674.39 | E84: =VLOOKUP(A84,s_02_2024!E:G,2,FALSE) -> 580 | F84: =VLOOKUP(A84,s_02_2024!E:G,3,FALSE) -> 17328.23 | G84: =F84/I84 -> 0.96253934 | H84: =E84+C84 -> 606 | I84: =F84+D84 -> 18002.62 | J84: =VLOOKUP(A84,v_02_2023!A:D,3,FALSE) -> 365 | K84: =VLOOKUP(A84,v_02_2023!A:D,4,FALSE) -> 11245.48 | L84: =H84-J84 -> 241 | M84: =I84-K84 -> 6757.14 | N84: =M84/K84 -> 0.60087609
A85: B07NQC6S9V | B85: BT.651Y | C85: 10 | D85: 406.4 | E85: =VLOOKUP(A85,s_02_2024!E:G,2,FALSE) -> 9 | F85: =VLOOKUP(A85,s_02_2024!E:G,3,FALSE) -> 435.1 | G85: =F85/I85 -> 0.51705288 | H85: =E85+C85 -> 19 | I85: =F85+D85 -> 841.5 | J85: =VLOOKUP(A85,v_02_2023!A:D,3,FALSE) -> 158 | K85: =VLOOKUP(A85,v_02_2023!A:D,4,FALSE) -> 6173.9 | L85: =H85-J85 -> -139 | M85: =I85-K85 -> -5332.4 | N85: =M85/K85 -> -0.86370042
A86: B07P7GGGQM | B86: BP.961 | C86: 32 | D86: 1367.57 | E86: =VLOOKUP(A86,s_02_2024!E:G,2,FALSE) -> 10 | F86: =VLOOKUP(A86,s_02_2024!E:G,3,FALSE) -> 599 | G86: =F86/I86 -> 0.30459124 | H86: =E86+C86 -> 42 | I86: =F86+D86 -> 1966.57 | J86: =VLOOKUP(A86,v_02_2023!A:D,3,FALSE) -> 49 | K86: =VLOOKUP(A86,v_02_2023!A:D,4,FALSE) -> 2276.14 | L86: =H86-J86 -> -7 | M86: =I86-K86 -> -309.57 | N86: =M86/K86 -> -0.13600657
A87: B07P7L18T9 | B87: 40.102 | C87: 5 | D87: 77.51 | E87: 0 | F87: 0 | G87: =F87/I87 -> 0 | H87: =E87+C87 -> 5 | I87: =F87+D87 -> 77.51 | J87: =VLOOKUP(A87,v_02_2023!A:D,3,FALSE) -> 2 | K87: =VLOOKUP(A87,v_02_2023!A:D,4,FALSE) -> 25.54 | L87: =H87-J87 -> 3 | M87: =I87-K87 -> 51.97 | N87: =M87/K87 -> 2.0348473
A88: B07Q38Z7CK | B88: BC.060 | C88: 72 | D88: 1517.58 | E88: 0 | F88: 0 | G88: =F88/I88 -> 0 | H88: =E88+C88 -> 72 | I88: =F88+D88 -> 1517.58 | J88: =VLOOKUP(A88,v_02_2023!A:D,3,FALSE) -> 371 | K88: =VLOOKUP(A88,v_02_2023!A:D,4,FALSE) -> 7623.04 | L88: =H88-J88 -> -299 | M88: =I88-K88 -> -6105.46 | N88: =M88/K88 -> -0.80092194
A89: B07QX1RJRH | B89: 40.742 | C89: 6 | D89: 125.03 | E89: 0 | F89: 0 | G89: =F89/I89 -> 0 | H89: =E89+C89 -> 6 | I89: =F89+D89 -> 125.03 | J89: =VLOOKUP(A89,v_02_2023!A:D,3,FALSE) -> 3 | K89: =VLOOKUP(A89,v_02_2023!A:D,4,FALSE) -> 61.44 | L89: =H89-J89 -> 3 | M89: =I89-K89 -> 63.59 | N89: =M89/K89 -> 1.0349935
A90: B07R984VMS | B90: BI.505 | C90: 25 | D90: 206.18 | E90: 0 | F90: 0 | G90: =F90/I90 -> 0 | H90: =E90+C90 -> 25 | I90: =F90+D90 -> 206.18 | J90: =VLOOKUP(A90,v_02_2023!A:D,3,FALSE) -> 83 | K90: =VLOOKUP(A90,v_02_2023!A:D,4,FALSE) -> 682.51 | L90: =H90-J90 -> -58 | M90: =I90-K90 -> -476.33 | N90: =M90/K90 -> -0.69790919
A91: B07RN75ZFL | B91: 50.401 | C91: 10 | D91: 157.86 | E91: 0 | F91: 0 | G91: =F91/I91 -> 0 | H91: =E91+C91 -> 10 | I91: =F91+D91 -> 157.86 | J91: =VLOOKUP(A91,v_02_2023!A:D,3,FALSE) -> 5 | K91: =VLOOKUP(A91,v_02_2023!A:D,4,FALSE) -> 143.41 | L91: =H91-J91 -> 5 | M91: =I91-K91 -> 14.45 | N91: =M91/K91 -> 0.10076006
A92: B07RRBP1YR | B92: VE.502 | C92: 2 | D92: 134.53 | E92: 0 | F92: 0 | G92: =F92/I92 -> 0 | H92: =E92+C92 -> 2 | I92: =F92+D92 -> 134.53 | J92: =VLOOKUP(A92,v_02_2023!A:D,3,FALSE) -> 4 | K92: =VLOOKUP(A92,v_02_2023!A:D,4,FALSE) -> 395.46 | L92: =H92-J92 -> -2 | M92: =I92-K92 -> -260.93 | N92: =M92/K92 -> -0.65981389
A93: B07RRBS54G | B93: BP.620 | C93: 2 | D93: 71.35 | E93: 0 | F93: 0 | G93: =F93/I93 -> 0 | H93: =E93+C93 -> 2 | I93: =F93+D93 -> 71.35 | J93: =VLOOKUP(A93,v_02_2023!A:D,3,FALSE) -> 10 | K93: =VLOOKUP(A93,v_02_2023!A:D,4,FALSE) -> 584.64 | L93: =H93-J93 -> -8 | M93: =I93-K93 -> -513.29 | N93: =M93/K93 -> -0.87795909
A94: B07SSLRCT6 | B94: BP.304 | C94: 385 | D94: 5403.64 | E94: 0 | F94: 0 | G94: =F94/I94 -> 0 | H94: =E94+C94 -> 385 | I94: =F94+D94 -> 5403.64 | J94: =VLOOKUP(A94,v_02_2023!A:D,3,FALSE) -> 88 | K94: =VLOOKUP(A94,v_02_2023!A:D,4,FALSE) -> 1397.38 | L94: =H94-J94 -> 297 | M94: =I94-K94 -> 4006.26 | N94: =M94/K94 -> 2.8669796
A95: B07TJGZNPN | B95: BP.654 | C95: 1 | D95: 20.75 | E95: 0 | F95: 0 | G95: =F95/I95 -> 0 | H95: =E95+C95 -> 1 | I95: =F95+D95 -> 20.75 | J95: =VLOOKUP(A95,v_02_2023!A:D,3,FALSE) -> 18 | K95: =VLOOKUP(A95,v_02_2023!A:D,4,FALSE) -> 233.76 | L95: =H95-J95 -> -17 | M95: =I95-K95 -> -213.01 | N95: =M95/K95 -> -0.91123374
A96: B07TQVD94L | B96: BP.690 | C96: 64 | D96: 1720.31 | E96: =VLOOKUP(A96,s_02_2024!E:G,2,FALSE) -> 3 | F96: =VLOOKUP(A96,s_02_2024!E:G,3,FALSE) -> 124.7 | G96: =F96/I96 -> 0.06758771 | H96: =E96+C96 -> 67 | I96: =F96+D96 -> 1845.01 | J96: =VLOOKUP(A96,v_02_2023!A:D,3,FALSE) -> 88 | K96: =VLOOKUP(A96,v_02_2023!A:D,4,FALSE) -> 2170.61 | L96: =H96-J96 -> -21 | M96: =I96-K96 -> -325.6 | N96: =M96/K96 -> -0.15000392
A97: B07TSNB5WG | B97: BP.102 | C97: 0 | D97: 0 | E97: 0 | F97: 0 | H97: =E97+C97 -> 0 | I97: =F97+D97 -> 0 | J97: =VLOOKUP(A97,v_02_2023!A:D,3,FALSE) -> 756 | K97: =VLOOKUP(A97,v_02_2023!A:D,4,FALSE) -> 9423.25 | L97: =H97-J97 -> -756 | M97: =I97-K97 -> -9423.25 | N97: =M97/K97 -> -1
A98: B07TSNCJ5J | B98: BP.800 | C98: 53 | D98: 590.81 | E98: 0 | F98: 0 | G98: =F98/I98 -> 0 | H98: =E98+C98 -> 53 | I98: =F98+D98 -> 590.81 | J98: =VLOOKUP(A98,v_02_2023!A:D,3,FALSE) -> 60 | K98: =VLOOKUP(A98,v_02_2023!A:D,4,FALSE) -> 635.33 | L98: =H98-J98 -> -7 | M98: =I98-K98 -> -44.52 | N98: =M98/K98 -> -0.07007382
A99: B07TTJQDC2 | B99: 70.404 | C99: 7 | D99: 174.86 | E99: 0 | F99: 0 | G99: =F99/I99 -> 0 | H99: =E99+C99 -> 7 | I99: =F99+D99 -> 174.86 | J99: =VLOOKUP(A99,v_02_2023!A:D,3,FALSE) -> 4 | K99: =VLOOKUP(A99,v_02_2023!A:D,4,FALSE) -> 103.25 | L99: =H99-J99 -> 3 | M99: =I99-K99 -> 71.61 | N99: =M99/K99 -> 0.69355932
A100: B07TVSJDCL | B100: MD.500 | C100: 1 | D100: 24.41 | E100: =VLOOKUP(A100,s_02_2024!E:G,2,FALSE) -> 0 | F100: =VLOOKUP(A100,s_02_2024!E:G,3,FALSE) -> 13.03 | G100: =F100/I100 -> 0.3480235 | H100: =E100+C100 -> 1 | I100: =F100+D100 -> 37.44 | J100: =VLOOKUP(A100,v_02_2023!A:D,3,FALSE) -> 0 | K100: =VLOOKUP(A100,v_02_2023!A:D,4,FALSE) -> 0 | L100: =H100-J100 -> 1 | M100: =I100-K100 -> 37.44
...

Sheet IT
A1: ASIN | B1: SKU | C1: Ordini Vendor 24 | D1: Valori ordini Vendor 24 | E1: Ordini Seller 24 | F1: Valori ordini Seller 24 | G1: % seller / totale | H1: Ordini Complessivi 24 | I1: Valori ordini Complessivi 24 | J1: Ordini Vendor 23 | K1: Valori ordini Vendor 23 | L1: Differenza Ordini | M1: Differenza Valore | N1: Differenza Valore %
A2: B0050IHH4E | B2: 40.979 | C2: =VLOOKUP(A2,v_02_2024!F:I,3,FALSE) -> 311 | D2: =VLOOKUP(A2,v_02_2024!F:I,4,FALSE) -> 4876.26 | E2: =VLOOKUP(A2,s_02_2024!E:G,2,FALSE) -> 1 | F2: =VLOOKUP(A2,s_02_2024!E:G,3,FALSE) -> 19.9 | G2: =F2/I2 -> 0.0040644097 | H2: =E2+C2 -> 312 | I2: =F2+D2 -> 4896.16 | J2: =VLOOKUP(A2,v_02_2023!F:I,3,FALSE) -> 24 | K2: =VLOOKUP(A2,v_02_2023!F:I,4,FALSE) -> 312.72 | L2: =H2-J2 -> 288 | M2: =I2-K2 -> 4583.44 | N2: =M2/K2 -> 14.65669
A3: B00BH202XK | B3: 40.808A | C3: =VLOOKUP(A3,v_02_2024!F:I,3,FALSE) -> 1 | D3: =VLOOKUP(A3,v_02_2024!F:I,4,FALSE) -> 13.85 | E3: 0 | F3: 0 | G3: =F3/I3 -> 0 | H3: =E3+C3 -> 1 | I3: =F3+D3 -> 13.85 | J3: =VLOOKUP(A3,v_02_2023!F:I,3,FALSE) -> 2 | K3: =VLOOKUP(A3,v_02_2023!F:I,4,FALSE) -> 35.73 | L3: =H3-J3 -> -1 | M3: =I3-K3 -> -21.88 | N3: =M3/K3 -> -0.61237056
A4: B00EYDRS1I | B4: 90.349 | C4: =VLOOKUP(A4,v_02_2024!F:I,3,FALSE) -> 17 | D4: =VLOOKUP(A4,v_02_2024!F:I,4,FALSE) -> 102.19 | E4: 0 | F4: 0 | G4: =F4/I4 -> 0 | H4: =E4+C4 -> 17 | I4: =F4+D4 -> 102.19 | J4: =VLOOKUP(A4,v_02_2023!F:I,3,FALSE) -> 159 | K4: =VLOOKUP(A4,v_02_2023!F:I,4,FALSE) -> 878.28 | L4: =H4-J4 -> -142 | M4: =I4-K4 -> -776.09 | N4: =M4/K4 -> -0.88364758
A5: B00FAJUDU8 | B5: 40.967N | C5: 0 | D5: 0 | E5: =VLOOKUP(A5,s_02_2024!E:G,2,FALSE) -> 36 | F5: =VLOOKUP(A5,s_02_2024!E:G,3,FALSE) -> 1151.91 | G5: =F5/I5 -> 1 | H5: =E5+C5 -> 36 | I5: =F5+D5 -> 1151.91 | J5: =VLOOKUP(A5,v_02_2023!F:I,3,FALSE) -> 92 | K5: =VLOOKUP(A5,v_02_2023!F:I,4,FALSE) -> 1877.72 | L5: =H5-J5 -> -56 | M5: =I5-K5 -> -725.81 | N5: =M5/K5 -> -0.38653793
A6: B00FFBED98 | B6: 40.11 | C6: 0 | D6: 0 | E6: 0 | F6: 0 | H6: =E6+C6 -> 0 | I6: =F6+D6 -> 0 | J6: 0 | K6: 0 | L6: =H6-J6 -> 0 | M6: =I6-K6 -> 0
A7: B00FFBFVG2 | B7: 40.100 | C7: =VLOOKUP(A7,v_02_2024!F:I,3,FALSE) -> 0 | D7: =VLOOKUP(A7,v_02_2024!F:I,4,FALSE) -> 0 | E7: 0 | F7: 0 | H7: =E7+C7 -> 0 | I7: =F7+D7 -> 0 | J7: =VLOOKUP(A7,v_02_2023!F:I,3,FALSE) -> 3 | K7: =VLOOKUP(A7,v_02_2023!F:I,4,FALSE) -> 18.99 | L7: =H7-J7 -> -3 | M7: =I7-K7 -> -18.99 | N7: =M7/K7 -> -1
A8: B00FMZ2VW8 | B8: HK-HQ601C PINK | C8: 0 | D8: 0 | E8: 0 | F8: 0 | H8: =E8+C8 -> 0 | I8: =F8+D8 -> 0 | J8: 0 | K8: 0 | L8: =H8-J8 -> 0 | M8: =I8-K8 -> 0
A9: B00J7MNQFS | B9: 40.994 | C9: =VLOOKUP(A9,v_02_2024!F:I,3,FALSE) -> 3 | D9: =VLOOKUP(A9,v_02_2024!F:I,4,FALSE) -> 61.3 | E9: 0 | F9: 0 | G9: =F9/I9 -> 0 | H9: =E9+C9 -> 3 | I9: =F9+D9 -> 61.3 | J9: =VLOOKUP(A9,v_02_2023!F:I,3,FALSE) -> 3 | K9: =VLOOKUP(A9,v_02_2023!F:I,4,FALSE) -> 49.83 | L9: =H9-J9 -> 0 | M9: =I9-K9 -> 11.47 | N9: =M9/K9 -> 0.23018262
A10: B00L5GPWFG | B10: 40.120 | C10: =VLOOKUP(A10,v_02_2024!F:I,3,FALSE) -> 3 | D10: =VLOOKUP(A10,v_02_2024!F:I,4,FALSE) -> 73.53 | E10: 0 | F10: 0 | G10: =F10/I10 -> 0 | H10: =E10+C10 -> 3 | I10: =F10+D10 -> 73.53 | J10: =VLOOKUP(A10,v_02_2023!F:I,3,FALSE) -> 2 | K10: =VLOOKUP(A10,v_02_2023!F:I,4,FALSE) -> 49.02 | L10: =H10-J10 -> 1 | M10: =I10-K10 -> 24.51 | N10: =M10/K10 -> 0.5
A11: B00L5H5KUW | B11: 40.121 | C11: =VLOOKUP(A11,v_02_2024!F:I,3,FALSE) -> 424 | D11: =VLOOKUP(A11,v_02_2024!F:I,4,FALSE) -> 7577.95 | E11: 0 | F11: 0 | G11: =F11/I11 -> 0 | H11: =E11+C11 -> 424 | I11: =F11+D11 -> 7577.95 | J11: =VLOOKUP(A11,v_02_2023!F:I,3,FALSE) -> 202 | K11: =VLOOKUP(A11,v_02_2023!F:I,4,FALSE) -> 3294.62 | L11: =H11-J11 -> 222 | M11: =I11-K11 -> 4283.33 | N11: =M11/K11 -> 1.3000983
A12: B00NSNZSLM | B12: 90.602 | C12: =VLOOKUP(A12,v_02_2024!F:I,3,FALSE) -> 0 | D12: =VLOOKUP(A12,v_02_2024!F:I,4,FALSE) -> 0 | E12: =VLOOKUP(A12,s_02_2024!E:G,2,FALSE) -> 96 | F12: =VLOOKUP(A12,s_02_2024!E:G,3,FALSE) -> 2882.4 | G12: =F12/I12 -> 1 | H12: =E12+C12 -> 96 | I12: =F12+D12 -> 2882.4 | J12: =VLOOKUP(A12,v_02_2023!F:I,3,FALSE) -> 515 | K12: =VLOOKUP(A12,v_02_2023!F:I,4,FALSE) -> 10511.15 | L12: =H12-J12 -> -419 | M12: =I12-K12 -> -7628.75 | N12: =M12/K12 -> -0.72577691
A13: B00OKE4RTM | B13: 90.386 | C13: =VLOOKUP(A13,v_02_2024!F:I,3,FALSE) -> 3 | D13: =VLOOKUP(A13,v_02_2024!F:I,4,FALSE) -> 147.35 | E13: 0 | F13: 0 | G13: =F13/I13 -> 0 | H13: =E13+C13 -> 3 | I13: =F13+D13 -> 147.35 | J13: =VLOOKUP(A13,v_02_2023!F:I,3,FALSE) -> 1 | K13: =VLOOKUP(A13,v_02_2023!F:I,4,FALSE) -> 53.22 | L13: =H13-J13 -> 2 | M13: =I13-K13 -> 94.13 | N13: =M13/K13 -> 1.768696
A14: B00OLZPU5K | B14: 40.947 | C14: =VLOOKUP(A14,v_02_2024!F:I,3,FALSE) -> 1 | D14: =VLOOKUP(A14,v_02_2024!F:I,4,FALSE) -> 10.57 | E14: 0 | F14: 0 | G14: =F14/I14 -> 0 | H14: =E14+C14 -> 1 | I14: =F14+D14 -> 10.57 | J14: =VLOOKUP(A14,v_02_2023!F:I,3,FALSE) -> 3 | K14: =VLOOKUP(A14,v_02_2023!F:I,4,FALSE) -> 31.71 | L14: =H14-J14 -> -2 | M14: =I14-K14 -> -21.14 | N14: =M14/K14 -> -0.66666667
A15: B011LFVLW8 | B15: 90.620 | C15: =VLOOKUP(A15,v_02_2024!F:I,3,FALSE) -> 24 | D15: =VLOOKUP(A15,v_02_2024!F:I,4,FALSE) -> 784.8 | E15: 0 | F15: 0 | G15: =F15/I15 -> 0 | H15: =E15+C15 -> 24 | I15: =F15+D15 -> 784.8 | J15: =VLOOKUP(A15,v_02_2023!F:I,3,FALSE) -> 103 | K15: =VLOOKUP(A15,v_02_2023!F:I,4,FALSE) -> 2946.83 | L15: =H15-J15 -> -79 | M15: =I15-K15 -> -2162.03 | N15: =M15/K15 -> -0.73367992
A16: B011LH9V8M | B16: 40.958V | C16: =VLOOKUP(A16,v_02_2024!F:I,3,FALSE) -> 1 | D16: =VLOOKUP(A16,v_02_2024!F:I,4,FALSE) -> 6.73 | E16: 0 | F16: 0 | G16: =F16/I16 -> 0 | H16: =E16+C16 -> 1 | I16: =F16+D16 -> 6.73 | J16: 0 | K16: 0 | L16: =H16-J16 -> 1 | M16: =I16-K16 -> 6.73
A17: B015T5GR0C | B17: 40.760 | C17: 0 | D17: 0 | E17: 0 | F17: 0 | H17: =E17+C17 -> 0 | I17: =F17+D17 -> 0 | J17: 0 | K17: 0 | L17: =H17-J17 -> 0 | M17: =I17-K17 -> 0
A18: B016MWFVIU | B18: 40.761 | C18: =VLOOKUP(A18,v_02_2024!F:I,3,FALSE) -> 1 | D18: =VLOOKUP(A18,v_02_2024!F:I,4,FALSE) -> 16.31 | E18: 0 | F18: 0 | G18: =F18/I18 -> 0 | H18: =E18+C18 -> 1 | I18: =F18+D18 -> 16.31 | J18: 0 | K18: 0 | L18: =H18-J18 -> 1 | M18: =I18-K18 -> 16.31
A19: B017IUJA50 | B19: 90.920G | C19: =VLOOKUP(A19,v_02_2024!F:I,3,FALSE) -> 274 | D19: =VLOOKUP(A19,v_02_2024!F:I,4,FALSE) -> 4464.61 | E19: =VLOOKUP(A19,s_02_2024!E:G,2,FALSE) -> 7 | F19: =VLOOKUP(A19,s_02_2024!E:G,3,FALSE) -> 155.61 | G19: =F19/I19 -> 0.033680214 | H19: =E19+C19 -> 281 | I19: =F19+D19 -> 4620.22 | J19: =VLOOKUP(A19,v_02_2023!F:I,3,FALSE) -> 323 | K19: =VLOOKUP(A19,v_02_2023!F:I,4,FALSE) -> 5211.46 | L19: =H19-J19 -> -42 | M19: =I19-K19 -> -591.24 | N19: =M19/K19 -> -0.11344997
A20: B01CHW1L88 | B20: PE.001 | C20: =VLOOKUP(A20,v_02_2024!F:I,3,FALSE) -> 1 | D20: =VLOOKUP(A20,v_02_2024!F:I,4,FALSE) -> 9.54 | E20: 0 | F20: 0 | G20: =F20/I20 -> 0 | H20: =E20+C20 -> 1 | I20: =F20+D20 -> 9.54 | J20: 0 | K20: 0 | L20: =H20-J20 -> 1 | M20: =I20-K20 -> 9.54
A21: B01CHW1YD0 | B21: PE.140 | C21: 0 | D21: 0 | E21: 0 | F21: 0 | H21: =E21+C21 -> 0 | I21: =F21+D21 -> 0 | J21: 0 | K21: 0 | L21: =H21-J21 -> 0 | M21: =I21-K21 -> 0
A22: B01CHW20UQ | B22: PE.400 | C22: 0 | D22: 0 | E22: 0 | F22: 0 | H22: =E22+C22 -> 0 | I22: =F22+D22 -> 0 | J22: 0 | K22: 0 | L22: =H22-J22 -> 0 | M22: =I22-K22 -> 0
A23: B01CNX6UIM | B23: PE.300 | C23: 0 | D23: 0 | E23: 0 | F23: 0 | H23: =E23+C23 -> 0 | I23: =F23+D23 -> 0 | J23: 0 | K23: 0 | L23: =H23-J23 -> 0 | M23: =I23-K23 -> 0
A24: B01CNX6Z78 | B24: 90.820 | C24: 0 | D24: 0 | E24: 0 | F24: 0 | H24: =E24+C24 -> 0 | I24: =F24+D24 -> 0 | J24: 0 | K24: 0 | L24: =H24-J24 -> 0 | M24: =I24-K24 -> 0
A25: B01CNX704K | B25: 90.825 | C25: 0 | D25: 0 | E25: =VLOOKUP(A25,s_02_2024!E:G,2,FALSE) -> 5 | F25: =VLOOKUP(A25,s_02_2024!E:G,3,FALSE) -> 234.5 | G25: =F25/I25 -> 1 | H25: =E25+C25 -> 5 | I25: =F25+D25 -> 234.5 | J25: 0 | K25: 0 | L25: =H25-J25 -> 5 | M25: =I25-K25 -> 234.5
A26: B01CNX71NA | B26: 90.871 | C26: =VLOOKUP(A26,v_02_2024!F:I,3,FALSE) -> 5 | D26: =VLOOKUP(A26,v_02_2024!F:I,4,FALSE) -> 572.22 | E26: 0 | F26: 0 | G26: =F26/I26 -> 0 | H26: =E26+C26 -> 5 | I26: =F26+D26 -> 572.22 | J26: =VLOOKUP(A26,v_02_2023!F:I,3,FALSE) -> 4 | K26: =VLOOKUP(A26,v_02_2023!F:I,4,FALSE) -> 320.65 | L26: =H26-J26 -> 1 | M26: =I26-K26 -> 251.57 | N26: =M26/K26 -> 0.78456261
A27: B01CNXP36C | B27: 40.981N | C27: 0 | D27: 0 | E27: 0 | F27: 0 | H27: =E27+C27 -> 0 | I27: =F27+D27 -> 0 | J27: 0 | K27: 0 | L27: =H27-J27 -> 0 | M27: =I27-K27 -> 0
A28: B01HM47LF8 | B28: MD.004 | C28: =VLOOKUP(A28,v_02_2024!F:I,3,FALSE) -> 2 | D28: =VLOOKUP(A28,v_02_2024!F:I,4,FALSE) -> 6.98 | E28: 0 | F28: 0 | G28: =F28/I28 -> 0 | H28: =E28+C28 -> 2 | I28: =F28+D28 -> 6.98 | J28: =VLOOKUP(A28,v_02_2023!F:I,3,FALSE) -> 9 | K28: =VLOOKUP(A28,v_02_2023!F:I,4,FALSE) -> 30.95 | L28: =H28-J28 -> -7 | M28: =I28-K28 -> -23.97 | N28: =M28/K28 -> -0.77447496
A29: B01I497WWM | B29: 90.920R | C29: =VLOOKUP(A29,v_02_2024!F:I,3,FALSE) -> 2 | D29: =VLOOKUP(A29,v_02_2024!F:I,4,FALSE) -> 32.62 | E29: =VLOOKUP(A29,s_02_2024!E:G,2,FALSE) -> 1084 | F29: =VLOOKUP(A29,s_02_2024!E:G,3,FALSE) -> 21587.91 | G29: =F29/I29 -> 0.99849125 | H29: =E29+C29 -> 1086 | I29: =F29+D29 -> 21620.53 | J29: =VLOOKUP(A29,v_02_2023!F:I,3,FALSE) -> 2222 | K29: =VLOOKUP(A29,v_02_2023!F:I,4,FALSE) -> 30066.66 | L29: =H29-J29 -> -1136 | M29: =I29-K29 -> -8446.13 | N29: =M29/K29 -> -0.28091348
A30: B01IHGX2HQ | B30: MD.104 | C30: =VLOOKUP(A30,v_02_2024!F:I,3,FALSE) -> 13 | D30: =VLOOKUP(A30,v_02_2024!F:I,4,FALSE) -> 50.63 | E30: 0 | F30: 0 | G30: =F30/I30 -> 0 | H30: =E30+C30 -> 13 | I30: =F30+D30 -> 50.63 | J30: =VLOOKUP(A30,v_02_2023!F:I,3,FALSE) -> 2 | K30: =VLOOKUP(A30,v_02_2023!F:I,4,FALSE) -> 11.51 | L30: =H30-J30 -> 11 | M30: =I30-K30 -> 39.12 | N30: =M30/K30 -> 3.3987837
A31: B01II7S968 | B31: MD.217 | C31: =VLOOKUP(A31,v_02_2024!F:I,3,FALSE) -> 3 | D31: =VLOOKUP(A31,v_02_2024!F:I,4,FALSE) -> 18.15 | E31: 0 | F31: 0 | G31: =F31/I31 -> 0 | H31: =E31+C31 -> 3 | I31: =F31+D31 -> 18.15 | J31: 0 | K31: 0 | L31: =H31-J31 -> 3 | M31: =I31-K31 -> 18.15
A32: B01K6P6NT0 | B32: 40.400 | C32: 0 | D32: 0 | E32: 0 | F32: 0 | H32: =E32+C32 -> 0 | I32: =F32+D32 -> 0 | J32: 0 | K32: 0 | L32: =H32-J32 -> 0 | M32: =I32-K32 -> 0
A33: B01KMJ9OXW | B33: 90.590Y | C33: =VLOOKUP(A33,v_02_2024!F:I,3,FALSE) -> 0 | D33: =VLOOKUP(A33,v_02_2024!F:I,4,FALSE) -> 0 | E33: =VLOOKUP(A33,s_02_2024!E:G,2,FALSE) -> 285 | F33: =VLOOKUP(A33,s_02_2024!E:G,3,FALSE) -> 9936.02 | G33: =F33/I33 -> 1 | H33: =E33+C33 -> 285 | I33: =F33+D33 -> 9936.02 | J33: =VLOOKUP(A33,v_02_2023!F:I,3,FALSE) -> 327 | K33: =VLOOKUP(A33,v_02_2023!F:I,4,FALSE) -> 9421.49 | L33: =H33-J33 -> -42 | M33: =I33-K33 -> 514.53 | N33: =M33/K33 -> 0.054612381
A34: B01M4O6145 | B34: 90.071 | C34: =VLOOKUP(A34,v_02_2024!F:I,3,FALSE) -> 43 | D34: =VLOOKUP(A34,v_02_2024!F:I,4,FALSE) -> 877.63 | E34: 0 | F34: 0 | G34: =F34/I34 -> 0 | H34: =E34+C34 -> 43 | I34: =F34+D34 -> 877.63 | J34: =VLOOKUP(A34,v_02_2023!F:I,3,FALSE) -> 65 | K34: =VLOOKUP(A34,v_02_2023!F:I,4,FALSE) -> 1379.23 | L34: =H34-J34 -> -22 | M34: =I34-K34 -> -501.6 | N34: =M34/K34 -> -0.36368118
A35: B01MFA4H6K | B35: S304 | C35: 0 | D35: 0 | E35: 0 | F35: 0 | H35: =E35+C35 -> 0 | I35: =F35+D35 -> 0 | J35: 0 | K35: 0 | L35: =H35-J35 -> 0 | M35: =I35-K35 -> 0
A36: B01MTSEGF9 | B36: 50.700 | C36: =VLOOKUP(A36,v_02_2024!F:I,3,FALSE) -> 0 | D36: =VLOOKUP(A36,v_02_2024!F:I,4,FALSE) -> 0 | E36: =VLOOKUP(A36,s_02_2024!E:G,2,FALSE) -> 20 | F36: =VLOOKUP(A36,s_02_2024!E:G,3,FALSE) -> 898 | G36: =F36/I36 -> 1 | H36: =E36+C36 -> 20 | I36: =F36+D36 -> 898 | J36: =VLOOKUP(A36,v_02_2023!F:I,3,FALSE) -> 227 | K36: =VLOOKUP(A36,v_02_2023!F:I,4,FALSE) -> 6496.29 | L36: =H36-J36 -> -207 | M36: =I36-K36 -> -5598.29 | N36: =M36/K36 -> -0.86176725
A37: B01N12PI05 | B37: PE.301 | C37: 0 | D37: 0 | E37: 0 | F37: 0 | H37: =E37+C37 -> 0 | I37: =F37+D37 -> 0 | J37: 0 | K37: 0 | L37: =H37-J37 -> 0 | M37: =I37-K37 -> 0
A38: B01N4L0SUV | B38: 40.926 | C38: 0 | D38: 0 | E38: 0 | F38: 0 | H38: =E38+C38 -> 0 | I38: =F38+D38 -> 0 | J38: 0 | K38: 0 | L38: =H38-J38 -> 0 | M38: =I38-K38 -> 0
A39: B06W2JZMNV | B39: 90.200 | C39: 0 | D39: 0 | E39: 0 | F39: 0 | H39: =E39+C39 -> 0 | I39: =F39+D39 -> 0 | J39: 0 | K39: 0 | L39: =H39-J39 -> 0 | M39: =I39-K39 -> 0
A40: B06WGS8ZVG | B40: 90.131 | C40: 0 | D40: 0 | E40: 0 | F40: 0 | H40: =E40+C40 -> 0 | I40: =F40+D40 -> 0 | J40: =VLOOKUP(A40,v_02_2023!F:I,3,FALSE) -> 4 | K40: =VLOOKUP(A40,v_02_2023!F:I,4,FALSE) -> 43.35 | L40: =H40-J40 -> -4 | M40: =I40-K40 -> -43.35 | N40: =M40/K40 -> -1
A41: B06XPK3BTC | B41: 40.450GO | C41: =VLOOKUP(A41,v_02_2024!F:I,3,FALSE) -> 2 | D41: =VLOOKUP(A41,v_02_2024!F:I,4,FALSE) -> 29.04 | E41: 0 | F41: 0 | G41: =F41/I41 -> 0 | H41: =E41+C41 -> 2 | I41: =F41+D41 -> 29.04 | J41: =VLOOKUP(A41,v_02_2023!F:I,3,FALSE) -> 8 | K41: =VLOOKUP(A41,v_02_2023!F:I,4,FALSE) -> 122.46 | L41: =H41-J41 -> -6 | M41: =I41-K41 -> -93.42 | N41: =M41/K41 -> -0.76286134
A42: B06XPYSCGJ | B42: 40.939 | C42: =VLOOKUP(A42,v_02_2024!F:I,3,FALSE) -> 3 | D42: =VLOOKUP(A42,v_02_2024!F:I,4,FALSE) -> 11.67 | E42: 0 | F42: 0 | G42: =F42/I42 -> 0 | H42: =E42+C42 -> 3 | I42: =F42+D42 -> 11.67 | J42: =VLOOKUP(A42,v_02_2023!F:I,3,FALSE) -> 1 | K42: =VLOOKUP(A42,v_02_2023!F:I,4,FALSE) -> 6.75 | L42: =H42-J42 -> 2 | M42: =I42-K42 -> 4.92 | N42: =M42/K42 -> 0.72888889
A43: B06XQ25NLB | B43: 40.220 | C43: 0 | D43: 0 | E43: 0 | F43: 0 | H43: =E43+C43 -> 0 | I43: =F43+D43 -> 0 | J43: 0 | K43: 0 | L43: =H43-J43 -> 0 | M43: =I43-K43 -> 0
A44: B06Y17FS6D | B44: 90.550 | C44: =VLOOKUP(A44,v_02_2024!F:I,3,FALSE) -> 197 | D44: =VLOOKUP(A44,v_02_2024!F:I,4,FALSE) -> 5475.75 | E44: 0 | F44: 0 | G44: =F44/I44 -> 0 | H44: =E44+C44 -> 197 | I44: =F44+D44 -> 5475.75 | J44: =VLOOKUP(A44,v_02_2023!F:I,3,FALSE) -> 165 | K44: =VLOOKUP(A44,v_02_2023!F:I,4,FALSE) -> 4246.18 | L44: =H44-J44 -> 32 | M44: =I44-K44 -> 1229.57 | N44: =M44/K44 -> 0.28957086
A45: B06Y195DJN | B45: 90.882 | C45: 0 | D45: 0 | E45: =VLOOKUP(A45,s_02_2024!E:G,2,FALSE) -> 31 | F45: =VLOOKUP(A45,s_02_2024!E:G,3,FALSE) -> 1546.9 | G45: =F45/I45 -> 1 | H45: =E45+C45 -> 31 | I45: =F45+D45 -> 1546.9 | J45: 0 | K45: 0 | L45: =H45-J45 -> 31 | M45: =I45-K45 -> 1546.9
A46: B06Y1997YH | B46: 90.883 | C46: =VLOOKUP(A46,v_02_2024!F:I,3,FALSE) -> 30 | D46: =VLOOKUP(A46,v_02_2024!F:I,4,FALSE) -> 1743.72 | E46: 0 | F46: 0 | G46: =F46/I46 -> 0 | H46: =E46+C46 -> 30 | I46: =F46+D46 -> 1743.72 | J46: =VLOOKUP(A46,v_02_2023!F:I,3,FALSE) -> 61 | K46: =VLOOKUP(A46,v_02_2023!F:I,4,FALSE) -> 3495.3 | L46: =H46-J46 -> -31 | M46: =I46-K46 -> -1751.58 | N46: =M46/K46 -> -0.50112437
A47: B06Y1P6DPZ | B47: VE.112 | C47: 0 | D47: 0 | E47: 0 | F47: 0 | H47: =E47+C47 -> 0 | I47: =F47+D47 -> 0 | J47: 0 | K47: 0 | L47: =H47-J47 -> 0 | M47: =I47-K47 -> 0
A48: B073B57HQH | B48: 90.886 | C48: =VLOOKUP(A48,v_02_2024!F:I,3,FALSE) -> 0 | D48: =VLOOKUP(A48,v_02_2024!F:I,4,FALSE) -> 0 | E48: 0 | F48: 0 | H48: =E48+C48 -> 0 | I48: =F48+D48 -> 0 | J48: =VLOOKUP(A48,v_02_2023!F:I,3,FALSE) -> 8 | K48: =VLOOKUP(A48,v_02_2023!F:I,4,FALSE) -> 809.04 | L48: =H48-J48 -> -8 | M48: =I48-K48 -> -809.04 | N48: =M48/K48 -> -1
A49: B073B67PLQ | B49: 90.884 | C49: =VLOOKUP(A49,v_02_2024!F:I,3,FALSE) -> 21 | D49: =VLOOKUP(A49,v_02_2024!F:I,4,FALSE) -> 1715.37 | E49: 0 | F49: 0 | G49: =F49/I49 -> 0 | H49: =E49+C49 -> 21 | I49: =F49+D49 -> 1715.37 | J49: =VLOOKUP(A49,v_02_2023!F:I,3,FALSE) -> 43 | K49: =VLOOKUP(A49,v_02_2023!F:I,4,FALSE) -> 3168.67 | L49: =H49-J49 -> -22 | M49: =I49-K49 -> -1453.3 | N49: =M49/K49 -> -0.45864669
A50: B0757TJRR9 | B50: 40.500 | C50: =VLOOKUP(A50,v_02_2024!F:I,3,FALSE) -> 0 | D50: =VLOOKUP(A50,v_02_2024!F:I,4,FALSE) -> 0 | E50: =VLOOKUP(A50,s_02_2024!E:G,2,FALSE) -> 602 | F50: =VLOOKUP(A50,s_02_2024!E:G,3,FALSE) -> 19788.01 | G50: =F50/I50 -> 1 | H50: =E50+C50 -> 602 | I50: =F50+D50 -> 19788.01 | J50: =VLOOKUP(A50,v_02_2023!F:I,3,FALSE) -> 382 | K50: =VLOOKUP(A50,v_02_2023!F:I,4,FALSE) -> 10284.5 | L50: =H50-J50 -> 220 | M50: =I50-K50 -> 9503.51 | N50: =M50/K50 -> 0.92406145
A51: B075FX6RFP | B51: BC.040N | C51: 0 | D51: 0 | E51: =VLOOKUP(A51,s_02_2024!E:G,2,FALSE) -> 25 | F51: =VLOOKUP(A51,s_02_2024!E:G,3,FALSE) -> 950.5 | G51: =F51/I51 -> 1 | H51: =E51+C51 -> 25 | I51: =F51+D51 -> 950.5 | J51: 0 | K51: 0 | L51: =H51-J51 -> 25 | M51: =I51-K51 -> 950.5
A52: B075K5C2QG | B52: RI.201 | C52: =VLOOKUP(A52,v_02_2024!F:I,3,FALSE) -> 2 | D52: =VLOOKUP(A52,v_02_2024!F:I,4,FALSE) -> 39.33 | E52: 0 | F52: 0 | G52: =F52/I52 -> 0 | H52: =E52+C52 -> 2 | I52: =F52+D52 -> 39.33 | J52: =VLOOKUP(A52,v_02_2023!F:I,3,FALSE) -> -1 | K52: =VLOOKUP(A52,v_02_2023!F:I,4,FALSE) -> -14.75 | L52: =H52-J52 -> 3 | M52: =I52-K52 -> 54.08 | N52: =M52/K52 -> -3.6664407
A53: B075RF5S3N | B53: BC.160A | C53: =VLOOKUP(A53,v_02_2024!F:I,3,FALSE) -> 8 | D53: =VLOOKUP(A53,v_02_2024!F:I,4,FALSE) -> 187.22 | E53: 0 | F53: 0 | G53: =F53/I53 -> 0 | H53: =E53+C53 -> 8 | I53: =F53+D53 -> 187.22 | J53: =VLOOKUP(A53,v_02_2023!F:I,3,FALSE) -> 14 | K53: =VLOOKUP(A53,v_02_2023!F:I,4,FALSE) -> 332.32 | L53: =H53-J53 -> -6 | M53: =I53-K53 -> -145.1 | N53: =M53/K53 -> -0.43662735
A54: B075XR3T8V | B54: BT.600Y | C54: 0 | D54: 0 | E54: 0 | F54: 0 | H54: =E54+C54 -> 0 | I54: =F54+D54 -> 0 | J54: 0 | K54: 0 | L54: =H54-J54 -> 0 | M54: =I54-K54 -> 0
A55: B076D74TC7 | B55: BT.700Y | C55: 0 | D55: 0 | E55: =VLOOKUP(A55,s_02_2024!E:G,2,FALSE) -> 4 | F55: =VLOOKUP(A55,s_02_2024!E:G,3,FALSE) -> 147.96 | G55: =F55/I55 -> 1 | H55: =E55+C55 -> 4 | I55: =F55+D55 -> 147.96 | J55: 0 | K55: 0 | L55: =H55-J55 -> 4 | M55: =I55-K55 -> 147.96
A56: B076DC4VWG | B56: 40.501 | C56: =VLOOKUP(A56,v_02_2024!F:I,3,FALSE) -> 2 | D56: =VLOOKUP(A56,v_02_2024!F:I,4,FALSE) -> 49.02 | E56: 0 | F56: 0 | G56: =F56/I56 -> 0 | H56: =E56+C56 -> 2 | I56: =F56+D56 -> 49.02 | J56: =VLOOKUP(A56,v_02_2023!F:I,3,FALSE) -> 3 | K56: =VLOOKUP(A56,v_02_2023!F:I,4,FALSE) -> 54.5 | L56: =H56-J56 -> -1 | M56: =I56-K56 -> -5.48 | N56: =M56/K56 -> -0.10055046
A57: B076DCF8PV | B57: BB.102 | C57: =VLOOKUP(A57,v_02_2024!F:I,3,FALSE) -> 1 | D57: =VLOOKUP(A57,v_02_2024!F:I,4,FALSE) -> 20.41 | E57: 0 | F57: 0 | G57: =F57/I57 -> 0 | H57: =E57+C57 -> 1 | I57: =F57+D57 -> 20.41 | J57: 0 | K57: 0 | L57: =H57-J57 -> 1 | M57: =I57-K57 -> 20.41
A58: B076DCKSTJ | B58: BT.602H | C58: =VLOOKUP(A58,v_02_2024!F:I,3,FALSE) -> 4 | D58: =VLOOKUP(A58,v_02_2024!F:I,4,FALSE) -> 81.64 | E58: =VLOOKUP(A58,s_02_2024!E:G,2,FALSE) -> 144 | F58: =VLOOKUP(A58,s_02_2024!E:G,3,FALSE) -> 3615.6 | G58: =F58/I58 -> 0.97791866 | H58: =E58+C58 -> 148 | I58: =F58+D58 -> 3697.24 | J58: =VLOOKUP(A58,v_02_2023!F:I,3,FALSE) -> 277 | K58: =VLOOKUP(A58,v_02_2023!F:I,4,FALSE) -> 5653.57 | L58: =H58-J58 -> -129 | M58: =I58-K58 -> -1956.33 | N58: =M58/K58 -> -0.34603445
A59: B076DCL19C | B59: BP.720 | C59: =VLOOKUP(A59,v_02_2024!F:I,3,FALSE) -> 19 | D59: =VLOOKUP(A59,v_02_2024!F:I,4,FALSE) -> 910.1 | E59: 0 | F59: 0 | G59: =F59/I59 -> 0 | H59: =E59+C59 -> 19 | I59: =F59+D59 -> 910.1 | J59: =VLOOKUP(A59,v_02_2023!F:I,3,FALSE) -> 13 | K59: =VLOOKUP(A59,v_02_2023!F:I,4,FALSE) -> 744.9 | L59: =H59-J59 -> 6 | M59: =I59-K59 -> 165.2 | N59: =M59/K59 -> 0.22177473
A60: B076DCX3JH | B60: BB.103 | C60: 0 | D60: 0 | E60: 0 | F60: 0 | H60: =E60+C60 -> 0 | I60: =F60+D60 -> 0 | J60: 0 | K60: 0 | L60: =H60-J60 -> 0 | M60: =I60-K60 -> 0
A61: B076DD35DZ | B61: BC.002 | C61: 0 | D61: 0 | E61: 0 | F61: 0 | H61: =E61+C61 -> 0 | I61: =F61+D61 -> 0 | J61: 0 | K61: 0 | L61: =H61-J61 -> 0 | M61: =I61-K61 -> 0
A62: B076Q7BR6F | B62: BC.041N | C62: =VLOOKUP(A62,v_02_2024!F:I,3,FALSE) -> 14 | D62: =VLOOKUP(A62,v_02_2024!F:I,4,FALSE) -> 584.31 | E62: =VLOOKUP(A62,s_02_2024!E:G,2,FALSE) -> 21 | F62: =VLOOKUP(A62,s_02_2024!E:G,3,FALSE) -> 1029.9 | G62: =F62/I62 -> 0.63802108 | H62: =E62+C62 -> 35 | I62: =F62+D62 -> 1614.21 | J62: =VLOOKUP(A62,v_02_2023!F:I,3,FALSE) -> 132 | K62: =VLOOKUP(A62,v_02_2023!F:I,4,FALSE) -> 5435.2 | L62: =H62-J62 -> -97 | M62: =I62-K62 -> -3820.99 | N62: =M62/K62 -> -0.70300817
A63: B076QCMZX1 | B63: 40.821 | C63: =VLOOKUP(A63,v_02_2024!F:I,3,FALSE) -> 103 | D63: =VLOOKUP(A63,v_02_2024!F:I,4,FALSE) -> 1257.63 | E63: 0 | F63: 0 | G63: =F63/I63 -> 0 | H63: =E63+C63 -> 103 | I63: =F63+D63 -> 1257.63 | J63: 0 | K63: 0 | L63: =H63-J63 -> 103 | M63: =I63-K63 -> 1257.63
A64: B076QFRRZ5 | B64: 40.931 | C64: =VLOOKUP(A64,v_02_2024!F:I,3,FALSE) -> 57 | D64: =VLOOKUP(A64,v_02_2024!F:I,4,FALSE) -> 818.58 | E64: 0 | F64: 0 | G64: =F64/I64 -> 0 | H64: =E64+C64 -> 57 | I64: =F64+D64 -> 818.58 | J64: =VLOOKUP(A64,v_02_2023!F:I,3,FALSE) -> 149 | K64: =VLOOKUP(A64,v_02_2023!F:I,4,FALSE) -> 2062.9 | L64: =H64-J64 -> -92 | M64: =I64-K64 -> -1244.32 | N64: =M64/K64 -> -0.60318968
A65: B079SB5VJZ | B65: 50451 | C65: =VLOOKUP(A65,v_02_2024!F:I,3,FALSE) -> 13 | D65: =VLOOKUP(A65,v_02_2024!F:I,4,FALSE) -> 572.62 | E65: 0 | F65: 0 | G65: =F65/I65 -> 0 | H65: =E65+C65 -> 13 | I65: =F65+D65 -> 572.62 | J65: =VLOOKUP(A65,v_02_2023!F:I,3,FALSE) -> 337 | K65: =VLOOKUP(A65,v_02_2023!F:I,4,FALSE) -> 11019.9 | L65: =H65-J65 -> -324 | M65: =I65-K65 -> -10447.28 | N65: =M65/K65 -> -0.94803764
A66: B07B9CBD91 | B66: VE.550 | C66: 0 | D66: 0 | E66: 0 | F66: 0 | H66: =E66+C66 -> 0 | I66: =F66+D66 -> 0 | J66: 0 | K66: 0 | L66: =H66-J66 -> 0 | M66: =I66-K66 -> 0
A67: B07B9CPH62 | B67: BG.200Y | C67: =VLOOKUP(A67,v_02_2024!F:I,3,FALSE) -> 2 | D67: =VLOOKUP(A67,v_02_2024!F:I,4,FALSE) -> 98.2 | E67: 0 | F67: 0 | G67: =F67/I67 -> 0 | H67: =E67+C67 -> 2 | I67: =F67+D67 -> 98.2 | J67: =VLOOKUP(A67,v_02_2023!F:I,3,FALSE) -> 24 | K67: =VLOOKUP(A67,v_02_2023!F:I,4,FALSE) -> 1178.4 | L67: =H67-J67 -> -22 | M67: =I67-K67 -> -1080.2 | N67: =M67/K67 -> -0.91666667
A68: B07BB2DQ4V | B68: BT.150Y | C68: 0 | D68: 0 | E68: =VLOOKUP(A68,s_02_2024!E:G,2,FALSE) -> 12 | F68: =VLOOKUP(A68,s_02_2024!E:G,3,FALSE) -> 478.8 | G68: =F68/I68 -> 1 | H68: =E68+C68 -> 12 | I68: =F68+D68 -> 478.8 | J68: =VLOOKUP(A68,v_02_2023!F:I,3,FALSE) -> 13 | K68: =VLOOKUP(A68,v_02_2023!F:I,4,FALSE) -> 318.63 | L68: =H68-J68 -> -1 | M68: =I68-K68 -> 160.17 | N68: =M68/K68 -> 0.50268336
A69: B07BHCZR84 | B69: BA.200Y | C69: =VLOOKUP(A69,v_02_2024!F:I,3,FALSE) -> 47 | D69: =VLOOKUP(A69,v_02_2024!F:I,4,FALSE) -> 573.23 | E69: 0 | F69: 0 | G69: =F69/I69 -> 0 | H69: =E69+C69 -> 47 | I69: =F69+D69 -> 573.23 | J69: =VLOOKUP(A69,v_02_2023!F:I,3,FALSE) -> 2 | K69: =VLOOKUP(A69,v_02_2023!F:I,4,FALSE) -> 32.62 | L69: =H69-J69 -> 45 | M69: =I69-K69 -> 540.61 | N69: =M69/K69 -> 16.572961
A70: B07BHTW4WV | B70: VE.210 | C70: 0 | D70: 0 | E70: 0 | F70: 0 | H70: =E70+C70 -> 0 | I70: =F70+D70 -> 0 | J70: 0 | K70: 0 | L70: =H70-J70 -> 0 | M70: =I70-K70 -> 0
A71: B07CZ4WMB8 | B71: 40.330 | C71: 0 | D71: 0 | E71: 0 | F71: 0 | H71: =E71+C71 -> 0 | I71: =F71+D71 -> 0 | J71: 0 | K71: 0 | L71: =H71-J71 -> 0 | M71: =I71-K71 -> 0
A72: B07F187NFQ | B72: 50.900 | C72: =VLOOKUP(A72,v_02_2024!F:I,3,FALSE) -> 8 | D72: =VLOOKUP(A72,v_02_2024!F:I,4,FALSE) -> 29.05 | E72: 0 | F72: 0 | G72: =F72/I72 -> 0 | H72: =E72+C72 -> 8 | I72: =F72+D72 -> 29.05 | J72: 0 | K72: 0 | L72: =H72-J72 -> 8 | M72: =I72-K72 -> 29.05
A73: B07FN14FSN | B73: 50.160 | C73: 0 | D73: 0 | E73: 0 | F73: 0 | H73: =E73+C73 -> 0 | I73: =F73+D73 -> 0 | J73: 0 | K73: 0 | L73: =H73-J73 -> 0 | M73: =I73-K73 -> 0
A74: B07HFQH172 | B74: BC.250 | C74: 0 | D74: 0 | E74: 0 | F74: 0 | H74: =E74+C74 -> 0 | I74: =F74+D74 -> 0 | J74: 0 | K74: 0 | L74: =H74-J74 -> 0 | M74: =I74-K74 -> 0
A75: B07HHDSJHM | B75: BI.504 | C75: =VLOOKUP(A75,v_02_2024!F:I,3,FALSE) -> 0 | D75: =VLOOKUP(A75,v_02_2024!F:I,4,FALSE) -> 0 | E75: 0 | F75: 0 | H75: =E75+C75 -> 0 | I75: =F75+D75 -> 0 | J75: =VLOOKUP(A75,v_02_2023!F:I,3,FALSE) -> 1 | K75: =VLOOKUP(A75,v_02_2023!F:I,4,FALSE) -> 4.02 | L75: =H75-J75 -> -1 | M75: =I75-K75 -> -4.02 | N75: =M75/K75 -> -1
A76: B07HM7P6MP | B76: RI.080 | C76: =VLOOKUP(A76,v_02_2024!F:I,3,FALSE) -> 0 | D76: =VLOOKUP(A76,v_02_2024!F:I,4,FALSE) -> 0 | E76: =VLOOKUP(A76,s_02_2024!E:G,2,FALSE) -> 21 | F76: =VLOOKUP(A76,s_02_2024!E:G,3,FALSE) -> 607.9 | G76: =F76/I76 -> 1 | H76: =E76+C76 -> 21 | I76: =F76+D76 -> 607.9 | J76: =VLOOKUP(A76,v_02_2023!F:I,3,FALSE) -> 28 | K76: =VLOOKUP(A76,v_02_2023!F:I,4,FALSE) -> 674.22 | L76: =H76-J76 -> -7 | M76: =I76-K76 -> -66.32 | N76: =M76/K76 -> -0.098365519
A77: B07JGVMFY1 | B77: BP.581 | C77: =VLOOKUP(A77,v_02_2024!F:I,3,FALSE) -> 3 | D77: =VLOOKUP(A77,v_02_2024!F:I,4,FALSE) -> 44.01 | E77: 0 | F77: 0 | G77: =F77/I77 -> 0 | H77: =E77+C77 -> 3 | I77: =F77+D77 -> 44.01 | J77: =VLOOKUP(A77,v_02_2023!F:I,3,FALSE) -> 7 | K77: =VLOOKUP(A77,v_02_2023!F:I,4,FALSE) -> 107.31 | L77: =H77-J77 -> -4 | M77: =I77-K77 -> -63.3 | N77: =M77/K77 -> -0.58987979
A78: B07KYWNC7Z | B78: 40.405 | C78: =VLOOKUP(A78,v_02_2024!F:I,3,FALSE) -> 21 | D78: =VLOOKUP(A78,v_02_2024!F:I,4,FALSE) -> 464.25 | E78: 0 | F78: 0 | G78: =F78/I78 -> 0 | H78: =E78+C78 -> 21 | I78: =F78+D78 -> 464.25 | J78: =VLOOKUP(A78,v_02_2023!F:I,3,FALSE) -> 108 | K78: =VLOOKUP(A78,v_02_2023!F:I,4,FALSE) -> 2118.97 | L78: =H78-J78 -> -87 | M78: =I78-K78 -> -1654.72 | N78: =M78/K78 -> -0.78090771
A79: B07MC8ZVRM | B79: 40.452 | C79: 0 | D79: 0 | E79: 0 | F79: 0 | H79: =E79+C79 -> 0 | I79: =F79+D79 -> 0 | J79: 0 | K79: 0 | L79: =H79-J79 -> 0 | M79: =I79-K79 -> 0
A80: B07N4C3H3V | B80: 40.405 | C80: =VLOOKUP(A80,v_02_2024!F:I,3,FALSE) -> -15 | D80: =VLOOKUP(A80,v_02_2024!F:I,4,FALSE) -> -173.9 | E80: =VLOOKUP(A80,s_02_2024!E:G,2,FALSE) -> 191 | F80: =VLOOKUP(A80,s_02_2024!E:G,3,FALSE) -> 2840.52 | G80: =F80/I80 -> 1.0652136 | H80: =E80+C80 -> 176 | I80: =F80+D80 -> 2666.62 | J80: =VLOOKUP(A80,v_02_2023!F:I,3,FALSE) -> 50 | K80: =VLOOKUP(A80,v_02_2023!F:I,4,FALSE) -> 597.21 | L80: =H80-J80 -> 126 | M80: =I80-K80 -> 2069.41 | N80: =M80/K80 -> 3.4651295
A81: B07NNZSW1W | B81: BT.110 | C81: =VLOOKUP(A81,v_02_2024!F:I,3,FALSE) -> 4 | D81: =VLOOKUP(A81,v_02_2024!F:I,4,FALSE) -> 67.67 | E81: 0 | F81: 0 | G81: =F81/I81 -> 0 | H81: =E81+C81 -> 4 | I81: =F81+D81 -> 67.67 | J81: =VLOOKUP(A81,v_02_2023!F:I,3,FALSE) -> 3 | K81: =VLOOKUP(A81,v_02_2023!F:I,4,FALSE) -> 71.39 | L81: =H81-J81 -> 1 | M81: =I81-K81 -> -3.72 | N81: =M81/K81 -> -0.052108138
A82: B07NP6YY5W | B82: BP.200 | C82: 0 | D82: 0 | E82: 0 | F82: 0 | H82: =E82+C82 -> 0 | I82: =F82+D82 -> 0 | J82: 0 | K82: 0 | L82: =H82-J82 -> 0 | M82: =I82-K82 -> 0
A83: B07NQ1T7YK | B83: BP.101H | C83: =VLOOKUP(A83,v_02_2024!F:I,3,FALSE) -> 215 | D83: =VLOOKUP(A83,v_02_2024!F:I,4,FALSE) -> 2737.71 | E83: 0 | F83: 0 | G83: =F83/I83 -> 0 | H83: =E83+C83 -> 215 | I83: =F83+D83 -> 2737.71 | J83: =VLOOKUP(A83,v_02_2023!F:I,3,FALSE) -> 261 | K83: =VLOOKUP(A83,v_02_2023!F:I,4,FALSE) -> 3186.81 | L83: =H83-J83 -> -46 | M83: =I83-K83 -> -449.1 | N83: =M83/K83 -> -0.14092462
A84: B07NQ2VYGD | B84: BT.710Y | C84: 0 | D84: 0 | E84: =VLOOKUP(A84,s_02_2024!E:G,2,FALSE) -> 580 | F84: =VLOOKUP(A84,s_02_2024!E:G,3,FALSE) -> 17328.23 | G84: =F84/I84 -> 1 | H84: =E84+C84 -> 580 | I84: =F84+D84 -> 17328.23 | J84: 0 | K84: 0 | L84: =H84-J84 -> 580 | M84: =I84-K84 -> 17328.23
A85: B07NQC6S9V | B85: BT.651Y | C85: =VLOOKUP(A85,v_02_2024!F:I,3,FALSE) -> 9 | D85: =VLOOKUP(A85,v_02_2024!F:I,4,FALSE) -> 331.2 | E85: =VLOOKUP(A85,s_02_2024!E:G,2,FALSE) -> 9 | F85: =VLOOKUP(A85,s_02_2024!E:G,3,FALSE) -> 435.1 | G85: =F85/I85 -> 0.56779329 | H85: =E85+C85 -> 18 | I85: =F85+D85 -> 766.3 | J85: =VLOOKUP(A85,v_02_2023!F:I,3,FALSE) -> 28 | K85: =VLOOKUP(A85,v_02_2023!F:I,4,FALSE) -> 1331.46 | L85: =H85-J85 -> -10 | M85: =I85-K85 -> -565.16 | N85: =M85/K85 -> -0.42446638
A86: B07P7GGGQM | B86: BP.961 | C86: 0 | D86: 0 | E86: =VLOOKUP(A86,s_02_2024!E:G,2,FALSE) -> 10 | F86: =VLOOKUP(A86,s_02_2024!E:G,3,FALSE) -> 599 | G86: =F86/I86 -> 1 | H86: =E86+C86 -> 10 | I86: =F86+D86 -> 599 | J86: 0 | K86: 0 | L86: =H86-J86 -> 10 | M86: =I86-K86 -> 599
A87: B07P7L18T9 | B87: 40.102 | C87: =VLOOKUP(A87,v_02_2024!F:I,3,FALSE) -> 2 | D87: =VLOOKUP(A87,v_02_2024!F:I,4,FALSE) -> 29.58 | E87: 0 | F87: 0 | G87: =F87/I87 -> 0 | H87: =E87+C87 -> 2 | I87: =F87+D87 -> 29.58 | J87: 0 | K87: 0 | L87: =H87-J87 -> 2 | M87: =I87-K87 -> 29.58
A88: B07Q38Z7CK | B88: BC.060 | C88: =VLOOKUP(A88,v_02_2024!F:I,3,FALSE) -> 59 | D88: =VLOOKUP(A88,v_02_2024!F:I,4,FALSE) -> 1245.32 | E88: 0 | F88: 0 | G88: =F88/I88 -> 0 | H88: =E88+C88 -> 59 | I88: =F88+D88 -> 1245.32 | J88: =VLOOKUP(A88,v_02_2023!F:I,3,FALSE) -> 320 | K88: =VLOOKUP(A88,v_02_2023!F:I,4,FALSE) -> 6561.22 | L88: =H88-J88 -> -261 | M88: =I88-K88 -> -5315.9 | N88: =M88/K88 -> -0.81019993
A89: B07QX1RJRH | B89: 40.742 | C89: =VLOOKUP(A89,v_02_2024!F:I,3,FALSE) -> 4 | D89: =VLOOKUP(A89,v_02_2024!F:I,4,FALSE) -> 95.19 | E89: 0 | F89: 0 | G89: =F89/I89 -> 0 | H89: =E89+C89 -> 4 | I89: =F89+D89 -> 95.19 | J89: =VLOOKUP(A89,v_02_2023!F:I,3,FALSE) -> 2 | K89: =VLOOKUP(A89,v_02_2023!F:I,4,FALSE) -> 43.7 | L89: =H89-J89 -> 2 | M89: =I89-K89 -> 51.49 | N89: =M89/K89 -> 1.1782609
A90: B07R984VMS | B90: BI.505 | C90: 0 | D90: 0 | E90: 0 | F90: 0 | H90: =E90+C90 -> 0 | I90: =F90+D90 -> 0 | J90: 0 | K90: 0 | L90: =H90-J90 -> 0 | M90: =I90-K90 -> 0
A91: B07RN75ZFL | B91: 50.401 | C91: 0 | D91: 0 | E91: 0 | F91: 0 | H91: =E91+C91 -> 0 | I91: =F91+D91 -> 0 | J91: 0 | K91: 0 | L91: =H91-J91 -> 0 | M91: =I91-K91 -> 0
A92: B07RRBP1YR | B92: VE.502 | C92: 0 | D92: 0 | E92: 0 | F92: 0 | H92: =E92+C92 -> 0 | I92: =F92+D92 -> 0 | J92: =VLOOKUP(A92,v_02_2023!F:I,3,FALSE) -> 2 | K92: =VLOOKUP(A92,v_02_2023!F:I,4,FALSE) -> 162.3 | L92: =H92-J92 -> -2 | M92: =I92-K92 -> -162.3 | N92: =M92/K92 -> -1
A93: B07RRBS54G | B93: BP.620 | C93: 0 | D93: 0 | E93: 0 | F93: 0 | H93: =E93+C93 -> 0 | I93: =F93+D93 -> 0 | J93: 0 | K93: 0 | L93: =H93-J93 -> 0 | M93: =I93-K93 -> 0
A94: B07SSLRCT6 | B94: BP.304 | C94: =VLOOKUP(A94,v_02_2024!F:I,3,FALSE) -> 97 | D94: =VLOOKUP(A94,v_02_2024!F:I,4,FALSE) -> 1343.45 | E94: 0 | F94: 0 | G94: =F94/I94 -> 0 | H94: =E94+C94 -> 97 | I94: =F94+D94 -> 1343.45 | J94: =VLOOKUP(A94,v_02_2023!F:I,3,FALSE) -> 21 | K94: =VLOOKUP(A94,v_02_2023!F:I,4,FALSE) -> 342.51 | L94: =H94-J94 -> 76 | M94: =I94-K94 -> 1000.94 | N94: =M94/K94 -> 2.9223672
A95: B07TJGZNPN | B95: BP.654 | C95: 0 | D95: 0 | E95: 0 | F95: 0 | H95: =E95+C95 -> 0 | I95: =F95+D95 -> 0 | J95: =VLOOKUP(A95,v_02_2023!F:I,3,FALSE) -> 18 | K95: =VLOOKUP(A95,v_02_2023!F:I,4,FALSE) -> 233.76 | L95: =H95-J95 -> -18 | M95: =I95-K95 -> -233.76 | N95: =M95/K95 -> -1
A96: B07TQVD94L | B96: BP.690 | C96: =VLOOKUP(A96,v_02_2024!F:I,3,FALSE) -> 42 | D96: =VLOOKUP(A96,v_02_2024!F:I,4,FALSE) -> 1029.42 | E96: =VLOOKUP(A96,s_02_2024!E:G,2,FALSE) -> 3 | F96: =VLOOKUP(A96,s_02_2024!E:G,3,FALSE) -> 124.7 | G96: =F96/I96 -> 0.10804769 | H96: =E96+C96 -> 45 | I96: =F96+D96 -> 1154.12 | J96: =VLOOKUP(A96,v_02_2023!F:I,3,FALSE) -> 60 | K96: =VLOOKUP(A96,v_02_2023!F:I,4,FALSE) -> 1470.6 | L96: =H96-J96 -> -15 | M96: =I96-K96 -> -316.48 | N96: =M96/K96 -> -0.21520468
A97: B07TSNB5WG | B97: BP.102 | C97: =VLOOKUP(A97,v_02_2024!F:I,3,FALSE) -> 0 | D97: =VLOOKUP(A97,v_02_2024!F:I,4,FALSE) -> 0 | E97: 0 | F97: 0 | H97: =E97+C97 -> 0 | I97: =F97+D97 -> 0 | J97: =VLOOKUP(A97,v_02_2023!F:I,3,FALSE) -> 655 | K97: =VLOOKUP(A97,v_02_2023!F:I,4,FALSE) -> 7997.55 | L97: =H97-J97 -> -655 | M97: =I97-K97 -> -7997.55 | N97: =M97/K97 -> -1
A98: B07TSNCJ5J | B98: BP.800 | C98: =VLOOKUP(A98,v_02_2024!F:I,3,FALSE) -> 31 | D98: =VLOOKUP(A98,v_02_2024!F:I,4,FALSE) -> 339.39 | E98: 0 | F98: 0 | G98: =F98/I98 -> 0 | H98: =E98+C98 -> 31 | I98: =F98+D98 -> 339.39 | J98: =VLOOKUP(A98,v_02_2023!F:I,3,FALSE) -> 46 | K98: =VLOOKUP(A98,v_02_2023!F:I,4,FALSE) -> 516.88 | L98: =H98-J98 -> -15 | M98: =I98-K98 -> -177.49 | N98: =M98/K98 -> -0.34338725
A99: B07TTJQDC2 | B99: 70.404 | C99: 0 | D99: 0 | E99: 0 | F99: 0 | H99: =E99+C99 -> 0 | I99: =F99+D99 -> 0 | J99: 0 | K99: 0 | L99: =H99-J99 -> 0 | M99: =I99-K99 -> 0
A100: B07TVSJDCL | B100: MD.500 | C100: 0 | D100: 0 | E100: =VLOOKUP(A100,s_02_2024!E:G,2,FALSE) -> 0 | F100: =VLOOKUP(A100,s_02_2024!E:G,3,FALSE) -> 13.03 | G100: =F100/I100 -> 1 | H100: =E100+C100 -> 0 | I100: =F100+D100 -> 13.03 | J100: 0 | K100: 0 | L100: =H100-J100 -> 0 | M100: =I100-K100 -> 13.03
...
